Workbook

Sheet Summary
A1: Summary of Selected Results from Energy Transfer-related natural gas releases (2010-present)
A3: Number of Incidents | B3: =count('PHMSA Records'!A:A) -> 177 | E3: Impacts
A4: Start of Time Period | B4: 40179 | E4: Injuries | F4: =countif('PHMSA Records'!AG:AG, "YES") -> 2
A5: End of Time Period | B5: 45838 | E5: Deaths | F5: =countif('PHMSA Records'!Z:Z, "YES") -> 1
A6: Average Number of Days Between Incidents | B6: =(B5-B4)/B3 -> 31.971751 | E6: Ignition | F6: =countif('PHMSA Records'!AW:AW, "YES") -> 26
E7: Explosion | F7: =countif('PHMSA Records'!BB:BB, "YES") -> 8
A8: Total Volume (Unintentional Release) | E8: Total Property Damage | F8: =sum('PHMSA Records'!FW:FW) -> 100650634
A9: in thousand cubic feet (Mcf) | B9: =sum('PHMSA Records'!W:W) -> 6802170.1
A10: in million cubic feet (MMcf) | B10: =B9/1000 -> 6802.1701 | E10: Causes
A11: Total Volume (Intentional Release) | E11: Equipment Failure | F11: =countif('PHMSA Records'!IN:IN, "EQUIPMENT FAILURE") -> 54
A12: in thousand cubic feet (Mcf) | B12: =sum('PHMSA Records'!X:X) -> 700510.98 | E12: Corrosion | F12: =countif('PHMSA Records'!IN:IN, "CORROSION FAILURE") -> 52
A13: in million cubic feet (MMcf) | B13: =B12/1000 -> 700.51098 | E13: Material Failure of Pipe or Weld | F13: =countif('PHMSA Records'!IN:IN, "MATERIAL FAILURE OF PIPE OR WELD") -> 18
E14: Other Accident Cause | F14: =countif('PHMSA Records'!IN:IN, "OTHER INCIDENT CAUSE") -> 16
A15: Report Status | E15: Natural Force Damage | F15: =countif('PHMSA Records'!IN:IN, "NATURAL FORCE DAMAGE") -> 15
A16: Original | B16: =countif('PHMSA Records'!F:F, "ORIGINAL") -> 12 | E16: Excavation Damage | F16: =countif('PHMSA Records'!IN:IN, "EXCAVATION DAMAGE") -> 10
A17: Original Final | B17: =countif('PHMSA Records'!F:F, "ORIGINAL FINAL") -> 37 | E17: Incorrect Operation | F17: =countif('PHMSA Records'!IN:IN, "INCORRECT OPERATION") -> 8
A18: Supplemental | B18: =countif('PHMSA Records'!F:F, "SUPPLEMENTAL") -> 0 | E18: Other Outside Force Damage | F18: =countif('PHMSA Records'!IN:IN, "OTHER OUTSIDE FORCE DAMAGE") -> 4
A19: Supplemental Final | B19: =countif('PHMSA Records'!F:F, "SUPPLEMENTAL FINAL") -> 128

Sheet PHMSA Records
B1: REPORT_RECEIVED_DATE | C1: IYEAR | D1: REPORT_NUMBER | E1: SUPPLEMENTAL_NUMBER | F1: REPORT_TYPE | G1: OPERATOR_ID | H1: NAME | I1: OPERATOR_STREET_ADDRESS | J1: OPERATOR_CITY_NAME | K1: OPERATOR_STATE_ABBREVIATION | L1: OPERATOR_POSTAL_CODE | M1: LOCAL_DATETIME | N1: TIME_ZONE | O1: DAYLIGHT_SAVINGS_IND | P1: LOCATION_LATITUDE | Q1: LOCATION_LONGITUDE | R1: NRC_RPT_NUM | S1: NRC_RPT_DATETIME | T1: ADDITIONAL_NRC_REPORT_NUMBERS | U1: COMMODITY_RELEASED_TYPE | V1: COMMODITY_DETAILS | W1: UNINTENTIONAL_RELEASE | X1: INTENTIONAL_RELEASE | Y1: ACCOMPANYING_LIQUID | Z1: FATALITY_IND | AA1: NUM_EMP_FATALITIES | AB1: NUM_CONTR_FATALITIES | AC1: NUM_ER_FATALITIES | AD1: NUM_WORKER_FATALITIES | AE1: NUM_GP_FATALITIES | AF1: FATAL | AG1: INJURY_IND | AH1: NUM_EMP_INJURIES | AI1: NUM_CONTR_INJURIES | AJ1: NUM_ER_INJURIES | AK1: NUM_WORKER_INJURIES | AL1: NUM_GP_INJURIES | AM1: INJURE | AN1: STATUS_WHEN_IDENTIFIED | AO1: SHUTDOWN_DUE_ACCIDENT_IND | AP1: SHUTDOWN_EXPLAIN | AQ1: SHUTDOWN_DATETIME | AR1: RESTART_DATETIME | AS1: STILL_SHUTDOWN_IND | AT1: COMMUNICATION_STATE_FED_IND | AU1: PARTY_INITIATED_COMMUNICATION | AV1: INITIAL_RESPONDER_COM_DATETIME | AW1: IGNITE_IND | AX1: IGNITE_DATETIME | AY1: HOW_EXTINGUISHED | AZ1: HOW_EXTINGUISHED_OTHER_DETAIL | BA1: GAS_CONSUMED_BY_FIRE_IN_MCF | BB1: EXPLODE_IND | BC1: UPSTREAM_ACTION_TAKEN | BD1: UPSTREAM_OPRTNL_CNTRL_DETAIL | BE1: UPSTREAM_VALVE_CLOSE_DATETIME | BF1: DOWNSTREAM_ACTION_TAKEN | BG1: DOWNSTREAM_OPRTNL_CNTRL_DETAIL | BH1: DOWNSTREAM_VLV_CLOSE_DATETIME | BI1: NUM_PUB_EVACUATED | BJ1: INCIDENT_IDENTIFIED_DATETIME | BK1: ON_SITE_DATETIME | BL1: CONFIRMED_DISCOVERY_DATETIME | BM1: ON_OFF_SHORE | BN1: ONSHORE_STATE_ABBREVIATION | BO1: ONSHORE_POSTAL_CODE | BP1: ONSHORE_CITY_NAME | BQ1: ONSHORE_COUNTY_NAME | BR1: DESIGNATED_LOCATION | BS1: DESIGNATED_NAME | BT1: PIPE_FAC_NAME | BU1: SEGMENT_NAME | BV1: FEDERAL | BW1: LOCATION_TYPE | BX1: INCIDENT_AREA_TYPE | BY1: INCIDENT_AREA_SUBTYPE | BZ1: INCIDENT_AREA_DETAILS | CA1: DEPTH_OF_COVER | CB1: OTHER_UNDERGROUND_FACILITIES | CC1: CROSSING | CD1: BRIDGE_CROSSING_IND | CE1: BRIDGE_TYPE | CF1: RAILROAD_CROSSING_IND | CG1: RAILROAD_TYPE | CH1: ROAD_CROSSING_IND | CI1: ROAD_TYPE | CJ1: WATER_CROSSING_IND | CK1: WATER_TYPE | CL1: WATER_NAME | CM1: WATER_DEPTH | CN1: WATER_SUBTYPE | CO1: CROSSING_100_FEET | CP1: OFF_WATER_DEPTH | CQ1: OFF_ACCIDENT_ORIGIN | CR1: OFFSHORE_STATE_ABBREVIATION | CS1: OFF_INSTATE_AREA | CT1: OFF_INSTATE_BLOCK | CU1: OFFSHORE_COUNTY_NAME | CV1: OCS_TYPE | CW1: OFF_OCS_AREA | CX1: OFF_OCS_BLOCK | CY1: OFF_AREA_ACCIDENT_TYPE | CZ1: PIPE_FACILITY_TYPE | DA1: SYSTEM_PART_INVOLVED | DB1: ITEM_INVOLVED | DC1: PIPE_TYPE | DD1: PIPE_DIAMETER | DE1: PUDDLE_WELD_IND | DF1: PIPE_WALL_THICKNESS | DG1: PIPE_SMYS | DH1: PIPE_SPECIFICATION | DI1: PIPE_SEAM_TYPE | DJ1: PIPE_SEAM_DETAILS | DK1: PIPE_MANUFACTURER | DL1: PIPE_COATING_TYPE | DM1: PIPE_COATING_DETAILS | DN1: COATING_APPLIED_IND | DO1: PLASTIC_TYPE | DP1: PLASTIC_DETAILS | DQ1: PLASTIC_SDR | DR1: WT_PLASTIC | DS1: WT_PLASTIC_UNKNOWN_IND | DT1: MATERIAL_PE_PIPE_CODE | DU1: PLASTIC_PE_UNKNOWN_IND | DV1: WELD_SUBTYPE | DW1: WELD_DETAILS | DX1: DIFFERENT_GIRTH_WELD_IND | DY1: DIFF_GIRTH_WELD_WALL_THICKNESS | DZ1: DIFF_GIRTH_WELD_SMYS | EA1: DIFF_GIRTH_WELD_SPECIFICATION | EB1: DIFF_GIRTH_WELD_SEAM_TYPE | EC1: DIFF_GIRTH_WELD_SEAM_DETAIL | ED1: DIFF_GIRTH_WELD_MANUFACTURER | EE1: DIFF_GIRTH_WELD_COATING_TYPE | EF1: DIFF_GIRTH_WELD_COATING_DETAIL | EG1: DIFF_GIRTH_WELD_CTNG_APPLD_IND | EH1: VALVE_TYPE | EI1: VALVE_MAINLINE_TYPE | EJ1: VALVE_MAINLINE_DETAILS | EK1: VALVE_MANUFACTURER | EL1: TUBING_MATERIAL | EM1: TUBING_TYPE | EN1: ITEM_INVOLVED_DETAILS | EO1: INSTALLATION_YEAR | EP1: MANUFACTURED_YEAR | EQ1: MATERIAL_INVOLVED | ER1: MATERIAL_DETAILS | ES1: RELEASE_TYPE | ET1: PUNCTURE_AXIAL | EU1: PUNCTURE_CIRCUM | EV1: LEAK_TYPE | EW1: LEAK_TYPE_OTHER | EX1: RUPTURE_ORIENT | EY1: RUPTURE_DETAILS | EZ1: RUPTURE_LENGTH | FA1: RUPTURE_WIDTH | FB1: RELEASE_TYPE_DETAILS | FC1: CLASS_LOCATION_TYPE | FD1: COULD_BE_HCA | FE1: DETERMINATION_METHOD | FF1: PIR_RADIUS | FG1: NOT_FLAMMABLE_IND | FH1: HEAT_DAMAGE_IND | FI1: NON_HEAT_DAMAGE_IND | FJ1: HCA_FATALITIES_IND | FK1: FATAL_INJURE_CAUSE | FL1: DID_OCCUR_IN_MCA_IND | FM1: MCA_BUILDNG_HUMAN_OCCUPY_IND | FN1: MCA_PAVED_SURFACE_FREEWAY_IND | FO1: EST_COST_OPER_PAID | FP1: EST_COST_UNINTENTIONAL_RELEASE | FQ1: EST_COST_INTENTIONAL_RELEASE | FR1: EST_COST_PROP_DAMAGE | FS1: EST_COST_EMERGENCY | FT1: EST_COST_OTHER | FU1: EST_COST_OTHER_DETAILS | FV1: GAS_COST_IN_MCF | FW1: PRPTY | FX1: NUM_PERSONS_HOSP_NOT_OVNGHT | FY1: NUM_INJURED_TREATED_BY_EMT | FZ1: NUM_RESIDENT_BUILDING_AFFCTD | GA1: NUM_BUSINESS_BUILDING_AFFCTD | GB1: WILDLIFE_IMPACT_IND | GC1: FISH_AQUATIC_IMPACT_IND | GD1: BIRDS_IMPACT_IND | GE1: TERRESTRIAL_IMPACT_IND | GF1: ACCIDENT_PSIG | GG1: GAS_FLOW_IN_PIPE_IN_MCF | GH1: MOP_PSIG | GI1: MOP_CFR_SECTION | GJ1: MOP_CFR_SECTION_DETAILS | GK1: MAOP_ESTABLISHED_DATE | GL1: MAOP_REVERSAL_FLOW_IND | GM1: ACCIDENT_PRESSURE | GN1: PRESSURE_RESTRICTION_IND | GO1: EXCEED_RESTRICTION_IND | GP1: PHMSA_RESTRICTION_IND | GQ1: GAS_REQUIRED_ODORIZED_IND | GR1: GAS_ODORIZED_IND | GS1: UPSTREAM_VALVE_TYPE_IND | GT1: DOWNSTREAM_VALVE_TYPE_IND | GU1: LENGTH_SEGMENT_ISOLATED | GV1: INTERNAL_INSPECTION_IND | GW1: DIAMETER_CHANGE_IND | GX1: UNSUITABLE_MAINLINE_IND | GY1: TIGHT_MITERED_IND | GZ1: OTHER_RESTRICTIONS_IND | HA1: EXTRA_THICK_WALL_IND | HB1: OTHER_INSPECTION_IND | HC1: INTERNAL_INSPECTION_DETAILS | HD1: OPERATION_COMPLICATIONS_IND | HE1: EXCESSIVE_DEBRIS_IND | HF1: LOW_OP_PRESSURE_IND | HG1: LOW_FLOW_IND | HH1: INCOMPAT_COMMOD_IND | HI1: OTHER_COMPLICATIONS_IND | HJ1: INSPECT_COMP_DETAILS | HK1: PIPELINE_FUNCTION | HL1: SCADA_IN_PLACE_IND | HM1: SCADA_OPERATING_IND | HN1: SCADA_FUNCTIONAL_IND | HO1: SCADA_DETECTION_IND | HP1: SCADA_CONF_IND | HQ1: ACCIDENT_IDENTIFIER | HR1: ACCIDENT_DETAILS | HS1: OPERATOR_TYPE | HT1: INVESTIGATION_STATUS | HU1: INVESTIGATION_STATUS_DETAILS | HV1: INVEST_SCHEDULE_IND | HW1: INVEST_NO_SCHEDULE_IND | HX1: INVEST_NO_SCHEDULE_IND_DETAILS | HY1: INVEST_NO_CONTROL_ROOM_IND | HZ1: INVEST_NO_CONTROLLER_IND | IA1: INVEST_INCORRECT_ACTION_IND | IB1: INVEST_FATIGUE_IND | IC1: INVEST_INCORRECT_PROCEDURE_IND | ID1: INVEST_INCORRECT_CONTROL_IND | IE1: INVEST_MAINT_IND | IF1: INVEST_OTHER_IND | IG1: INVEST_OTHER_IND_DETAILS | IH1: EMPLOYEE_DRUG_TEST_IND | II1: CONTRACTOR_DRUG_TEST_IND | IJ1: NUM_EMPLOYEES_TESTED | IK1: NUM_EMPLOYEES_FAILED | IL1: NUM_CONTRACTORS_TESTED | IM1: NUM_CONTRACTORS_FAILED | IN1: CAUSE | IO1: CAUSE_DETAILS | IP1: INTERNAL_EXTERNAL | IQ1: VISUAL_EXAM_RESULTS | IR1: VISUAL_EXAM_DETAILS | IS1: GALVANIC_CORROSION_IND | IT1: ATMOSPHERE_CORROSION_IND | IU1: STRAY_CURRENT_CORROSION_IND | IV1: MICROBIOLOGICAL_CORROSION_IND | IW1: SELECTIVE_SEAM_CORROSION_IND | IX1: OTHER_CORROSION_IND | IY1: CORROSION_TYPE_DETAILS | IZ1: STRAY_CURRENT_TYPE | JA1: STRAY_CURRENT_DETAILS | JB1: FIELD_EXAM_BASIS_IND | JC1: METALLURGICAL_BASIS_IND | JD1: OTHER_BASIS_IND | JE1: CORROSION_BASIS_DETAILS | JF1: UNDERGROUND_LOCATION | JG1: UNDER_CATHODIC_PROTECTION_IND | JH1: CATHODIC_PRO_START_YEAR | JI1: SHIELDING_EVIDENT | JJ1: CATHODIC_SURVEY_TYPE | JK1: CP_ANNUAL_SURVEY_IND | JL1: CLOSE_INTERVAL_SURVEY_IND | JM1: OTHER_CP_SURVEY_IND | JN1: OTHER_CP_SURVEY_DETAILS | JO1: CP_ANNUAL_SURVEY_YEAR | JP1: CLOSE_INTERVAL_SURVEY_YEAR | JQ1: OTHER_CP_SURVEY_YEAR | JR1: EXTERNALLY_COATED | JS1: PRIOR_DAMAGE | JT1: INT_VISUAL_EXAM_RESULTS | JU1: INT_VISUAL_EXAM_DETAILS | JV1: INT_CORROSIVE_COMMODITY_IND | JW1: INT_WATER_ACID_IND | JX1: INT_MICROBIOLOGICAL_IND | JY1: INT_EROSION_IND | JZ1: INT_OTHER_CORROSION_IND | KA1: INT_CORROSION_TYPE_DETAILS | KB1: INT_FIELD_EXAM_BASIS_IND | KC1: INT_METALLURGICAL_BASIS_IND | KD1: INT_OTHER_BASIS_IND | KE1: INT_CORROSION_BASIS_DETAILS | KF1: INT_LOW_POINT_PIPE_LOC_IND | KG1: INT_ELBOW_LOC_IND | KH1: INT_DROP_OUT_LOC_IND | KI1: INT_DEAD_LEG_LOC_IND | KJ1: INT_OTHER_LOC_IND | KK1: CORROSION_LOCATION_DETAILS | KL1: CORROSION_INHIBITORS | KM1: CORROSION_LINING | KN1: CLEANING_DEWATERING | KO1: CORROSION_COUPONS | KP1: NATURAL_FORCE_TYPE | KQ1: EARTH_SUBTYPE | KR1: HEAVY_RAINS_SUBTYPE | KS1: LIGHTNING_SUBTYPE | KT1: TEMPERATURE_SUBTYPE | KU1: NF_OTHER_DETAILS | KV1: NF_EXTREME_WEATHER_IND | KW1: NF_HURRICANE_IND | KX1: NF_TROPICAL_STORM_IND | KY1: NF_TORNADO_IND | KZ1: NF_OTHER_IND | LA1: NF_EXTREME_WEATHER_DETAILS | LB1: EX_PARTY_TYPE | LC1: PRIOR_NOTIFICATION_IND | LD1: ONE_CALL_SYSTEM_IND | LE1: EXCAVATOR_IND | LF1: CONTRACTOR_IND | LG1: LANDOWNER_IND | LH1: STATE_LAW_EXEMPT_IND | LI1: STATE_LAW_EXEMPT_TYPE | LJ1: STATE_LAW_EXEMPT_DETAIL | LK1: STATE_LAW_EXEMPT_AUTHORITY | LL1: STATE_LAW_EXEMPT_CRITERIA | LM1: NOTIFY_CGA_DIRT | LN1: PUBLIC_ROW_IND | LO1: PUBLIC_SUBTYPE | LP1: PRIVATE_ROW_IND | LQ1: PRIVATE_SUBTYPE | LR1: PIPELINE_EASEMENT_ROW_IND | LS1: POWER_TRANSMISSION_ROW_IND | LT1: RAILROAD_ROW_IND | LU1: PUBLIC_UTIL_EASEMENT_ROW_IND | LV1: FEDERAL_LAND_ROW_IND | LW1: UNKNOWN_ROW_IND | LX1: JOINT_TRENCH_IND | LY1: CROSS_BORE_IND | LZ1: DEPTH_OF_GRADE | MA1: DEPTH_OF_GRADE_DETAIL | MB1: EXCAVATOR_TYPE | MC1: EXCAVATOR_EQUIPMENT | MD1: WORK_PERFORMED | ME1: ONE_CALL_NOTIFIED_IND | MF1: ONE_CALL_TICKET_NUM | MG1: ONE_CALL_CENTER_NAME | MH1: WHITE_LINED_IND | MI1: LOCATOR_TYPE | MJ1: VISIBLE_MARKS | MK1: SERVICE_INTERRUPTION | ML1: SERVICE_INTERRUPTION_HOURS | MM1: ROOT_CAUSE_CATEGORY | MN1: ROOT_CAUSE_TYPE | MO1: ROOT_CAUSE_TYPE_OTHER | MP1: OUTSIDE_FORCE_TYPE | MQ1: VEHICLE_SUBTYPE | MR1: OSF_HURRICANE_IND | MS1: OSF_TROPICAL_STORM_IND | MT1: OSF_TORNADO_IND | MU1: OSF_HEAVY_RAINS_IND | MV1: OSF_OTHER_WEATHER_IND | MW1: OSF_OTHER_WEATHER_DETAILS | MX1: INTENTIONAL_SUBTYPE | MY1: INTENTIONAL_DETAILS | MZ1: OSF_OTHER_DETAILS | NA1: DRIVER_ISSUED_CITATION_IND | NB1: CITATION_SPEED_IND | NC1: CITATION_RECKLESS_IND | ND1: CITATION_DUI_IND | NE1: CITATION_OTHER_IND | NF1: CITATION_OTHER_DETAIL | NG1: DRIVER_IN_CONTROL_IND | NH1: ESTIMATED_SPEED | NI1: ESTIMATED_SPEED_UNKNOWN_IND | NJ1: VEHICLE_TYPE | NK1: VEHICLE_TRAVEL_FROM | NL1: VEHICLE_TRAVEL_DISTANCE_FT | NM1: PROTECTIONS_INSTALLED_IND | NN1: PROTECTION_BOLLARDS_POST_IND | NO1: PROTECTION_BARRICADES_IND | NP1: PROTECTION_GUARD_RAILS_IND | NQ1: PROTECTION_OTHER_IND | NR1: PROTECTION_OTHER_DETAIL | NS1: PWJF_FAILURE_TYPE | NT1: FIELD_EXAM_IND | NU1: METALLURGICAL_IND | NV1: OTHER_ANALYSIS_IND | NW1: OTHER_ANALYSIS_DETAILS | NX1: STILL_UNDER_INVEST_IND | NY1: FATIGUE_VIBR_RELATED | NZ1: FAILURE_SUBTYPE | OA1: FATIGUE_VIBR_RELATED_OTHER | OB1: MECHANICAL_STRESS | OC1: OTHER_FACTOR | OD1: OTHER_FACTOR_DETAILS | OE1: STRESS_SUBTYPE | OF1: STRESS_DETAILS | OG1: ADDITIONAL_DENT_IND | OH1: ADDITIONAL_GOUGE_IND | OI1: ADDITIONAL_PIPE_BEND_IND | OJ1: ADDITIONAL_ARC_BURN_IND | OK1: ADDITIONAL_CRACK_IND | OL1: ADDITIONAL_LACK_FUSION_IND | OM1: ADDITIONAL_LAMINATION_IND | ON1: ADDITIONAL_BUCKLE_IND | OO1: ADDITIONAL_WRINKLE_IND | OP1: PWF_ADDITIONAL_MISALIGN_IND | OQ1: ADDITIONAL_BURNT_STEEL_IND | OR1: PWF_ADDITIONAL_OTHER_IND | OS1: ADDITIONAL_OTHER_DETAILS | OT1: POST_CONSTR_PRESSURE_TEST_VAL | OU1: EQ_FAILURE_TYPE | OV1: CONTROL_VALVE_IND | OW1: INSTRUMENTATION_IND | OX1: SCADA_IND | OY1: COMMUNICATIONS_IND | OZ1: BLOCK_VALVE_IND | PA1: CHECK_VALVE_IND | PB1: RELIEF_VALVE_IND | PC1: POWER_FAILURE_IND | PD1: STOPPLE_CONTROL_FITTING_IND | PE1: PRESSURE_REGULATOR_IND | PF1: ESD_SYSTEM_FAILURE_IND | PG1: OTHER_CONTROL_RELIEF_IND | PH1: OTHER_CONTROL_RELIEF_DETAILS | PI1: OTHER_COMPRESSOR_IND | PJ1: OTHER_COMPRESSOR_DETAILS | PK1: OTHER_STRIPPED_IND | PL1: OTHER_STRIPPED_DETAILS | PM1: OTHER_NON_THREADED_IND | PN1: OTHER_NON_THREADED_DETAILS | PO1: EQ_FAILURE_DETAILS | PP1: ADDITIONAL_VIBRATION_IND | PQ1: ADDITIONAL_OVERPRESSURE_IND | PR1: ADDITIONAL_SUPPORT_IND | PS1: ADDITIONAL_DEFECT_IND | PT1: ADDITIONAL_ELECTRICITY_IND | PU1: ADDITIONAL_INSTALLATION_IND | PV1: ADDITIONAL_IMPROPER_MNTNCE_IND | PW1: ADDITIONAL_MISMATCH_IND | PX1: ADDITIONAL_DISSIMILAR_IND | PY1: ADDITIONAL_BREAKDOWN_IND | PZ1: ADDITIONAL_VALVE_IND | QA1: ADDITIONAL_ALARM_IND | QB1: EQ_ADDITIONAL_MISALIGN_IND | QC1: EQ_ADDITIONAL_THERMAL_IND | QD1: ADDITIONAL_EROSION_WEAR_IND | QE1: EQ_ADDITIONAL_OTHER_IND | QF1: EQ_ADDITIONAL_OTHER_DETAILS | QG1: OPERATION_TYPE | QH1: OVERFLOW_OTHER_IND | QI1: OVERFLOW_OTHER_DETAILS | QJ1: OPERATION_DETAILS | QK1: RELATED_INADEQUATE_PROC_IND | QL1: RELATED_NO_PROC_IND | QM1: RELATED_FAILURE_FOLLOW_IND | QN1: RELATED_OTHER_IND | QO1: OPERATION_RELATED_DETAILS | QP1: CATEGORY_TYPE | QQ1: OPERATOR_QUALIFICATION_IND | QR1: QUALIFIED_INDIVIDUALS | QS1: OTHER_TYPE | QT1: MISC_DETAILS | QU1: UNKNOWN_SUBTYPE | QV1: INCIDENT_UNKNOWN_COMMENTS | QW1: COLLECTED_DATA_IND | QX1: AXIAL_MAGNETIC_FLX_LKG_IND | QY1: CIR_TRN_WAVE_MGN_FLX_LKG_IND | QZ1: ULTRASONIC_IND | RA1: GEOMETRY_DEFORMATION_IND | RB1: EMAT_IND | RC1: CPCM_IND | RD1: OTHER_TOOL_TECH_IND | RE1: AXIAL_RECENT_YEAR | RF1: AXIAL_RCNT_PROPUL_METHOD | RG1: AXIAL_RCNT_ATTUNED_DETECT | RH1: AXIAL_RCNT_ATND_DTCT_DTLS | RI1: AXIAL_RCNT_ATND_DTCT_METAL | RJ1: AXIAL_RCNT_ATT_DT_METAL_DTLS | RK1: AXIAL_PREVIOUS_YEAR | RL1: AXIAL_PREV_PROPUL_METHOD | RM1: AXIAL_PREV_ATTUNED_DETECT | RN1: AXIAL_PREV_ATND_DTCT_DTLS | RO1: AXIAL_PREV_ATND_DTCT_METAL | RP1: AXIAL_PREV_ATT_DT_METAL_DTLS | RQ1: CIRC_WAVE_RECENT_YEAR | RR1: CIRC_WV_RCNT_PROPUL_METHOD | RS1: CIRC_WV_RCNT_RESOLUTION | RT1: CIRC_WV_RCNT_RESOLUTION_DTLS | RU1: CIRC_WV_PREVIOUS_YEAR | RV1: CIRC_WV_PREV_PROPUL_METHOD | RW1: CIRC_WV_PREV_RESOLUTION | RX1: CIRC_WV_PREV_RESOLUTION_DTLS | RY1: ULTRASONIC_RECENT_YEAR | RZ1: ULTRASONIC_RCNT_PROPUL_METHOD | SA1: ULTRASONIC_RCNT_ATTUNED | SB1: ULTRA_RCNT_ATTUNEDD_DTLS | SC1: UTRA_RCNT_ATT_METL_RESOLUTION | SD1: UTRA_RCNT_ATT_METL_RES_DTLS | SE1: ULTR_PREVIOUS_YEAR | SF1: ULTRA_PREV_PROPUL_METHOD | SG1: ULTRA_PREV_ATTUNED | SH1: ULTRA_PREV_ATTUNED_DTLS | SI1: UTRA_PREV_ATT_METL_RESOLUTION | SJ1: UTRA_PREV_ATT_METL_RES_DTLS | SK1: GEOMETRY_RECENT_YEAR | SL1: GEOMETRY_RCNT_PROPUL_METHOD | SM1: GEOMETRY_RCNT_RESOLUTION | SN1: GEOMETRY_RCNT_RESOLUTION_DTLS | SO1: GEOMETRT_RCNT_MEASUR_CUPS | SP1: GEOMETRY_PREVIOUS_YEAR | SQ1: GEOMETRY_PREV_PROPUL_METHOD | SR1: GEOMETRY_PREV_RESOLUTION | SS1: GEOMETRY_PREV_RESOLUTION_DTLS | ST1: GEOMETRT_PREV_MEASUR_CUPS | SU1: EMAT_RECENT_YEAR | SV1: EMAT_RCNT_PROPUL_METHOD | SW1: EMAT_PREVIOUS_YEAR | SX1: EMAT_PREV_PROPUL_METHOD | SY1: CPCM_RECENT_YEAR | SZ1: CPCM_RCNT_PROPUL_METHOD | TA1: CPCM_PREVIOUS_YEAR | TB1: CPCM_PREV_PROPUL_METHOD | TC1: OTHER_TOOL | TD1: OTHER_RECENT_YEAR | TE1: OTHER_RCNT_PROPUL_METHOD | TF1: OTHER_PREVIOUS_YEAR | TG1: OTHER_PREV_PROPUL_METHOD | TH1: INSP_COMPL_BEFORE_DAMAGE_IND | TI1: HAS_HYDRTST_CONDUC_BEFORE_IND | TJ1: HYDRTST_MOST_RCNT_YEAR | TK1: HYDRTST_MOST_RCNT_PRESSURE | TL1: DIRECT_ASMNT_CONDUCTED | TM1: DIRECT_ASMNT_AT_PNT_ACCDNT_YR | TN1: DIRECT_ASMNT_PNT_NOT_IDNTF_YR | TO1: ASMNT_ECDA_RCNT_YEAR | TP1: ASMNT_ICDA_RCNT_YEAR | TQ1: ASMNT_SCCDA_RCNT_YEAR | TR1: ASMNT_CONFIRMATORY_RCNT_YEAR | TS1: ASMNT_OTHER_TYPE | TT1: ASMNT_OTHER_RCNT_YEAR | TU1: ASMNT_ECDA_RCNT_IND | TV1: ASMNT_ICDA_RCNT_IND | TW1: ASMNT_SCCDA_RCNT_IND | TX1: ASMNT_CONFIRMATORY_RCNT_IND | TY1: ASMNT_OTHER_RCNT_IND | TZ1: NON_DESTRUCTIVE_EXAM_IND | UA1: EXM_RADIOGRAPHY_RCNT_YEAR | UB1: EXM_WAVE_ULTRASONIC_RCNT_YEAR | UC1: EXM_HANDL_ULTRASONIC_RCNT_YEAR | UD1: EXM_WET_MGNT_PARTCL_RCNT_YEAR | UE1: EXM_DRY_MGNT_PARTCL_RCNT_YEAR | UF1: EXM_OTHER_TYPE | UG1: EXM_OTHER_RCNT_YEAR | UH1: EXM_RADIOGRAPHY_RCNT_IND | UI1: EXM_WAVE_ULTRASONIC_RCNT_IND | UJ1: EXM_HANDL_ULTRASONIC_RCNT_IND | UK1: EXM_WET_MGNT_PARTCL_RCNT_IND | UL1: EXM_DRY_MGNT_PARTCL_RCNT_IND | UM1: EXM_OTHER_RCNT_IND | UN1: EXTRNL_COR_GALVANIC_IND | UO1: EXTRNL_COR_ATMOSPHERIC_IND | UP1: EXTRNL_COR_STRAY_CURRENT_IND | UQ1: EXTRNL_COR_MICROBIOLOGIC_IND | UR1: EXTRNL_COR_SELECTIVE_SEAM_IND | US1: INTRNL_COR_CORROSIVE_CMDTY_IND | UT1: INTRNL_COR_WTR_DRPOUT_ACID_IND | UU1: INTRNL_COR_MICROBIOLOGIC_IND | UV1: INTRNL_COR_EROSION_IND | UW1: NF_EARTH_MOVEMENT_IND | UX1: NF_HEAVY_RAINS_IND | UY1: NF_LIGHTNING_IND | UZ1: NF_TEMPERATURE_IND | VA1: NF_HIGH_WINDS_IND | VB1: NF_VEGITATION_ROOT_IND | VC1: EXCVTN_DMG_OPERATOR_IND | VD1: EXCVTN_DMG_OP_CONTRACTOR_IND | VE1: EXCVTN_DMG_THIRD_PARTY_IND | VF1: EXCVTN_DMG_PREVIOUS_DAMAGE_IND | VG1: OSF_NEARBY_INDUSTRIAL_IND | VH1: OSF_VEHICLE_IND | VI1: OSF_BOAT_IND | VJ1: OSF_OTHER_MARITIME_IND | VK1: OSF_ELECTRICAL_ARCING_IND | VL1: OSF_PREVIOUS_MECHANICAL_IND | VM1: OSF_INTENTIONAL_IND | VN1: OSF_OTHER_UNDERGROUND_IND | VO1: PWF_DESIGN_IND | VP1: PWF_CONSTRUCTION_IND | VQ1: PWF_INSTALLATION_IND | VR1: PWF_FABRICATION_IND | VS1: PWF_MANUFACTURING_IND | VT1: PWF_ENV_STRESS_CORROSION_IND | VU1: PWF_ENV_SULFIDE_STRESS_IND | VV1: PWF_ENV_HYDROGEN_STRESS_IND | VW1: PWF_ENV_HARD_SPOT_IND | VX1: EQF_CONTROL_RELEAF_IND | VY1: EQF_COMPRESSOR_IND | VZ1: EQF_THREADED_COUPLING_IND | WA1: EQF_NON_THREADED_IND | WB1: EQF_DEFECTIVE_FITTING_IND | WC1: EQF_EQUIPMENT_BODY_IND | WD1: IO_DAMAGE_BY_OPERATOR_IND | WE1: IO_VALVE_POSITION_IND | WF1: IO_EQUIPMENT_OVERPRESSURE_IND | WG1: IO_NOT_INSTALLED_PROPERLY_IND | WH1: IO_WRONG_EQUIPMENT_IND | WI1: IO_INADEQUATE_PROCEDURE_IND | WJ1: IO_NO_PROCEDURE_IND | WK1: IO_FOLLOW_PROCEDURE_IND | WL1: PREPARER_NAME | WM1: PREPARER_TITLE | WN1: PREPARER_EMAIL | WO1: PREPARER_TELEPHONE | WP1: PREPARER_FAX | WQ1: LOCAL_CONTACT_NAME | WR1: LOCAL_CONTACT_EMAIL | WS1: LOCAL_CONTACT_TELEPHONE | WT1: AUTHORIZER_NAME | WU1: AUTHORIZER_TITLE | WV1: AUTHORIZER_TELEPHONE | WW1: AUTHORIZER_EMAIL | WX1: NARRATIVE
A2: 0 | B2: 45832 | C2: 2025 | D2: 20250073 | E2: 41071 | F2: ORIGINAL | G2: 32099 | H2: ENERGY TRANSFER COMPANY | I2: 1300 MAIN STREET | J2: HOUSTON | K2: TX | L2: 77002 | M2: 45805.849 | N2: CENTRAL | O2: NO | P2: 31.275848 | Q2: -101.69314 | R2: 1432147 | S2: 45806.577 | T2: 1432269 | U2: NATURAL GAS | W2: 39 | X2: 0 | Y2: 0 | Z2: NO | AF2: 0 | AG2: NO | AM2: 0 | AN2: NORMAL OPERATION, INCLUDES PAUSES DURING MAINTENANCE | AO2: YES | AQ2: 45805.849 | AR2: 45806.115 | AT2: YES | AU2: OPERATOR | AV2: 45805.854 | AW2: YES | AX2: 45805.849 | AY2: LOCAL/STATE/FEDERAL EMERGENCY RESPONDER | BA2: 39 | BB2: NO | BI2: 0 | BJ2: 45805.849 | BK2: 45805.861 | BL2: 45805.861 | BM2: ONSHORE | BN2: TX | BO2: 76932 | BP2: Not Within a Municipality | BQ2: REAGAN | BR2: NOT APPLICABLE | BT2: GARRISON DRAW COMPRESSOR STATION | BU2: 7406595 - SEQUITUR TO GARISON | BV2: NO | BW2: OPERATOR-CONTROLLED PROPERTY | BX2: ABOVEGROUND | BY2: TYPICAL ABOVEGROUND FACILITY PIPING OR APPURTENANCE | CC2: NO | CZ2: INTRASTATE | DA2: ONSHORE COMPRESSOR STATION EQUIPMENT AND PIPING | DB2: COMPRESSOR | EO2: 2024 | EP2: 2018 | EQ2: CARBON STEEL | ES2: LEAK | EV2: SEAL OR PACKING | FC2: CLASS 1 LOCATION | FD2: NO | FF2: 211 | FH2: NO | FI2: NO | FL2: NO | FO2: 0 | FP2: 139 | FQ2: 0 | FR2: 146000 | FS2: 5000 | FT2: 0 | FV2: 3.57 | FW2: 151139 | FX2: 0 | FY2: 0 | FZ2: 0 | GA2: 0 | GB2: NO | GF2: 30 | GG2: 3900 | GH2: 1440 | GI2: 192.619(A)(4) | GK2: 44285 | GL2: NO | GM2: PRESSURE DID NOT EXCEED MAOP | GN2: NO | GQ2: NO | HK2: TYPE C GATHERING | HL2: YES | HM2: YES | HN2: YES | HO2: YES | HP2: NO | HQ2: SCADA-BASED INFORMATION (SUCH AS ALARM(S), ALERT(S), EVENT(S), AND/OR VOLUME OR PACK CALCULATIONS) | HT2: NO, THE FACILITY WAS NOT MONITORED BY A CONTROLLER(S) AT THE TIME OF THE INCIDENT | IH2: NO | II2: NO | IN2: OTHER INCIDENT CAUSE | IO2: UNKNOWN | QS2: UNKNOWN | QU2: STILL UNDER INVESTIGATION, CAUSE OF INCIDENT TO BE DETERMINED* (*SUPPLEMENTAL REPORT REQUIRED) | WL2: TOBY PITTMAN | WN2: toby.pittman@energytransfer.com | WO2: 432-265-6810 | WQ2: TOBY PITTMAN | WR2: toby.pittman@energytransfer.com | WS2: 4322656810 | WT2: JUSTIN DAVIDSON | WV2: 7139895231 | WW2: justin.davidson@energytransfer.com | WX2: ON MAY 28, 2025, AT 8:22 P.M. AN ON-CALL PIPELINE TECH WITH ENERGY TRANSFER COMPANY (ETC) RECEIVED AN ALARM LOLO COMPRESSOR OIL INDICATING THAT THE COMPRESSOR, GARRISON DRAW UNIT 5 # 2777 USA COMPRESSOR WAS SHUT DOWN. AT ABOUT 8:30 P.M. WHILE ENROUTE TO THE COMPRESSOR STATION THE TECH WITNESSED A FIRE THAT WAS POSSIBLY LOCATED AT THE GARRISON DRAW COMPRESSOR STATION. THE TECH THEN NOTIFIED THE OPERATIONS SUPERVISOR, WHO THEN NOTIFIED THE FIRE DEPARTMENT. THEN THE TECH BEGAN SHUTTING IN METER RUN VALVES SENDING NATURAL GAS TO THE COMPRESSOR STATION. AT 8:40 P.M. THE PIPELINE TECH ARRIVED AT THE COMPRESSOR STATION AND CONFIRMED THE FIRE WAS ON ETC'S GARRISON DRAW UNIT 5. THE FIRE DEPARTMENT WAS ALREADY ON SCENE AT THAT TIME. THE PIPELINE TECH THEN ISOLATED GARRISON DRAW. THE FIRE WAS OUT AT 9:30 P.M. ON MAY 29, 2025, THE STATION WAS RETURNED TO SERVICE WITHOUT UNIT 5 AT 2:49 A.M. NRC NOTIFICATION WAS MADE AT 1:51 P.M. MAY 29, 2025. THE CAUSE OF THE FIRE IS STILL UNDER INVESTIGATION.
A3: 1 | B3: 45832 | C3: 2025 | D3: 20250072 | E3: 41069 | F3: ORIGINAL | G3: 39368 | H3: CRESTWOOD MIDSTREAM PARTNERS LP | I3: 1300 MAIN STREET | J3: HOUSTON | K3: TX | L3: 77002 | M3: 45802.326 | N3: CENTRAL | O3: NO | P3: 31.84378 | Q3: -103.75784 | R3: 1432147 | S3: 45802.61 | T3: 1432269 | U3: NATURAL GAS | W3: 15 | X3: 0 | Y3: 0 | Z3: NO | AF3: 0 | AG3: NO | AM3: 0 | AN3: NORMAL OPERATION, INCLUDES PAUSES DURING MAINTENANCE | AO3: YES | AQ3: 45802.332 | AR3: 45804.383 | AT3: YES | AU3: OPERATOR | AV3: 45802.342 | AW3: YES | AX3: 45802.331 | AY3: LOCAL/STATE/FEDERAL EMERGENCY RESPONDER | BA3: 15 | BB3: NO | BI3: 0 | BJ3: 45802.331 | BK3: 45802.364 | BL3: 45802.331 | BM3: ONSHORE | BN3: TX | BO3: 79754 | BP3: Not Within a Municipality | BQ3: LOVING | BR3: NOT APPLICABLE | BT3: WEST SLASH COMPRESSOR STATION | BU3: TX5052G BRANCH 55-9 | BV3: NO | BW3: OPERATOR-CONTROLLED PROPERTY | BX3: ABOVEGROUND | BY3: TYPICAL ABOVEGROUND FACILITY PIPING OR APPURTENANCE | CC3: NO | CZ3: INTRASTATE | DA3: ONSHORE COMPRESSOR STATION EQUIPMENT AND PIPING | DB3: COMPRESSOR | EO3: 2024 | EP3: 2018 | EQ3: CARBON STEEL | ES3: OTHER | FB3: UNDER INVESTIGATION | FC3: CLASS 1 LOCATION | FD3: NO | FF3: 211 | FH3: NO | FI3: NO | FL3: NO | FO3: 0 | FP3: 56 | FQ3: 0 | FR3: 146000 | FS3: 5000 | FT3: 0 | FV3: 3.71 | FW3: 151056 | FX3: 2 | FY3: 0 | FZ3: 0 | GA3: 0 | GB3: NO | GF3: 88 | GG3: 0 | GH3: 720 | GI3: 192.619(A)(4) | GK3: 45607 | GL3: NO | GM3: PRESSURE DID NOT EXCEED MAOP | GN3: NO | GQ3: NO | HK3: TYPE C GATHERING | HL3: YES | HM3: YES | HN3: YES | HO3: NO | HP3: NO | HQ3: LOCAL OPERATING PERSONNEL, INCLUDING CONTRACTORS | HS3: OPERATOR EMPLOYEE | HT3: NO, THE FACILITY WAS NOT MONITORED BY A CONTROLLER(S) AT THE TIME OF THE INCIDENT | IH3: NO | II3: YES | IL3: 1 | IM3: 0 | IN3: OTHER INCIDENT CAUSE | IO3: UNKNOWN | QS3: UNKNOWN | QU3: STILL UNDER INVESTIGATION, CAUSE OF INCIDENT TO BE DETERMINED* (*SUPPLEMENTAL REPORT REQUIRED) | WL3: TOBY PITTMAN | WN3: toby.pittman@energytransfer.com | WO3: 432-265-6810 | WQ3: TOBY PITTMAN | WR3: toby.pittman@energytransfer.com | WS3: 4322656810 | WT3: JUSTIN DAVIDSON | WV3: 7139895231 | WW3: justin.davidson@energytransfer.com | WX3: ON MAY 25, 2025, AT 7:57 A.M., WHILE MAINTENANCE WAS BEING PERFORMED BY AN ENERGY TRANSFER COMPANY (ETC) EMPLOYEE AND A CONTRACT EMPLOYEE, THE WEST SLASH UNIT 2 COMPRESSOR, CAUGHT FIRE. THE ETC EMPLOYEE NOTIFIED THE OPERATIONS MANAGER WHO THEN NOTIFIED EMERGENCY SERVICES. THE EMPLOYEE AND CONTRACT EMPLOYEE ACTIVATED THE EMERGENCY SHUT DOWN SYSTEM (ESD) SUCCESSFULLY SHUTTING DOWN THE COMPRESSOR STATION. BOTH THE ETC EMPLOYEE AND CONTRACT EMPLOYEE WERE INJURED WHEN THE FIRE IGNITED. WHEN EMERGENCY SERVICES ARRIVED AT THE LOCATION THE TWO INJURED RECEIVED MEDICAL ATTENTION AND THE FIRE WAS EXTINGUISHED. DUE TO THE EXTENT OF THE FIRE TO THE COMPRESSOR, THE COST OF REPAIRS ARE ESTIMATED TO EXCEED $145,400. THE CAUSE OF THE FIRE IS STILL UNDER INVESTIGATION.
A4: 3 | B4: 45812 | C4: 2025 | D4: 20250066 | E4: 40988 | F4: ORIGINAL FINAL | G4: 18152 | H4: SEA ROBIN PIPELINE CO | I4: 1300 MAIN STREET | J4: HOUSTON | K4: TX | L4: 77002 | M4: 45794.604 | N4: CENTRAL | O4: YES | P4: 28.246468 | Q4: -91.70387 | R4: 1421397 | S4: 45794.633 | T4: 1431515, 1431997 | U4: NATURAL GAS | W4: 1587069 | X4: 0 | Y4: 0 | Z4: NO | AF4: 0 | AG4: NO | AM4: 0 | AN4: NORMAL OPERATION, INCLUDES PAUSES DURING MAINTENANCE | AO4: YES | AQ4: 45794.609 | AR4: 45801.615 | AT4: YES | AU4: OPERATOR | AV4: 45794.633 | AW4: NO | BC4: VALVE CLOSURE | BE4: 45794.512 | BF4: VALVE CLOSURE | BH4: 45794.609 | BI4: 0 | BJ4: 45800.611 | BK4: 45794.512 | BL4: 45800.611 | BM4: OFFSHORE | BT4: SEA ROBIN | BU4: LINE 716-10-1 | CP4: 260 | CQ4: ON THE OUTER CONTINENTAL SHELF (OCS) | CV4: OCS-GULF OF AMERICA | CW4: EUGENE ISLAND | CX4: 330 | CY4: BELOW WATER, PIPE BURIED OR JETTED BELOW SEABED | CZ4: INTERSTATE | DA4: OFFSHORE PIPELINE, INCLUDING RISER AND RISER BEND | DB4: PIPE | DC4: PIPE BODY | DD4: 8.625 | DE4: NO | DF4: 0.41 | DG4: 24000 | DH4: API 5L X52 | DI4: OTHER | DJ4: UNKNOWN | DK4: UNKNOWN | DL4: OTHER | DM4: MASTEC & CONCRETE | DN4: YES | EO4: 1973 | EP4: 1973 | EQ4: CARBON STEEL | ES4: LEAK | EV4: PINHOLE | FC4: CLASS 1 LOCATION | FD4: NO | FF4: 215 | FH4: NO | FI4: NO | FL4: NO | FO4: 0 | FP4: 5523000 | FQ4: 0 | FR4: 350000 | FS4: 35000 | FT4: 0 | FV4: 3.48 | FW4: 5908000 | FX4: 0 | FY4: 0 | FZ4: 0 | GA4: 0 | GB4: NO | GF4: 900 | GG4: 3000 | GH4: 1306 | GI4: 192.619(A)(1) | GK4: 28126 | GL4: NO | GM4: PRESSURE DID NOT EXCEED MAOP | GN4: NO | GQ4: NO | GS4: MANUAL | GT4: MANUAL | GU4: 31680 | GV4: NO | GY4: YES | HD4: YES | HG4: YES | HK4: TRANSMISSION SYSTEM | HL4: YES | HM4: YES | HN4: YES | HO4: NO | HP4: NO | HQ4: OTHER | HR4: NOTIFIED BY PRODUCER | HT4: NO, THE OPERATOR DID NOT FIND THAT AN INVESTIGATION OF THE CONTROLLER(S) ACTIONS OR CONTROL ROOM ISSUES WAS NECESSARY DUE TO: (PROVIDE AN EXPLANATION FOR WHY THE OPERATOR DID NOT INVESTIGATE) | HU4: LEAK WAS TOO SMALL FOR SCADA TO DETECT | IH4: NO | II4: NO | IN4: CORROSION FAILURE | IO4: INTERNAL CORROSION | IP4: INTERNAL CORROSION | JT4: NOT CUT OPEN | JV4: YES | KB4: YES | KF4: YES | KL4: NO | KM4: NO | KN4: NO | KO4: NOT APPLICABLE - NOT MAINLINE PIPE | QW4: NO | TI4: NO | TL4: NO | TZ4: NO | WL4: PEGGY WEST | WM4: MANAGER DOT COMPLIANCE | WN4: peggy.west@energytransfer.com | WO4: 4093823918 | WT4: PEGGY WEST | WU4: MANAGER DOT COMPLIANCE | WV4: 4093823918 | WW4: peggy.west@energytransfer.com | WX4: AT APPROXIMATELY 1212 ON 05/17/25, OPERATIONS RECEIVED A NOTIFICATION FROM A 3RD PARTY REPORTING BUBBLES IN THE AREA NEAR THE SEA ROBIN 716-10-1 LATERAL IN EUGENE ISLAND 330 (EI 330). AN OVERFLIGHT WAS CONDUCTED TO VERIFY THE LOCATION OF THE BUBBLES AND WAS CONFIRMED AT APPROXIMATELY 1430 ON 05/17/25. NRC WAS CALLED REPORTING THE BUBBLES IN EI 331 (NRC#1431397, 48HR UPDATE#1431515). THE PIPELINE WAS ISOLATED ON 05/17/25 AT 1437. OVERFLIGHTS WERE CONDUCTED DAILY TO MONITOR THE AREA FOR ANY CHANGES AS WEATHER PERMITTED. DUE TO DSV AVAILABILITY, THE REPAIR CONTRACTOR WAS NOT ABLE TO DEPLOY UNTIL 5/11/25. THE LEAK WAS LOCATED AND A CLAMP WAS INSTALLED ON 5/24/25 AT 0650. THE PIPELINE WAS RETURNED TO SERVICE AT APPROXIMATELY 1346 ON 05/24/25. THE 48HR NRC NOTIFICATION WAS UPDATED ON 05/23/25 AT 1440 TO REFLECT THE CHANGE FROM UNKNOWN OWNER TO SEA ROBIN PIPELINE. (#1431997)
A5: 7 | B5: 45823 | C5: 2025 | D5: 20250070 | E5: 41024 | F5: ORIGINAL | G5: 32099 | H5: ENERGY TRANSFER COMPANY | I5: 1300 MAIN STREET | J5: HOUSTON | K5: TX | L5: 77002 | M5: 45786.812 | N5: CENTRAL | O5: YES | P5: 32.01374 | Q5: -100.76041 | R5: 1431278 | S5: 45793.542 | T5: 1431410 | U5: NATURAL GAS | W5: 192 | X5: 0 | Y5: 0 | Z5: NO | AF5: 0 | AG5: NO | AM5: 0 | AN5: NORMAL OPERATION, INCLUDES PAUSES DURING MAINTENANCE | AO5: YES | AQ5: 45786.812 | AS5: YES | AT5: NO | AW5: NO | BC5: VALVE CLOSURE | BE5: 45786.812 | BF5: VALVE CLOSURE | BH5: 45786.84 | BI5: 0 | BJ5: 45786.812 | BK5: 45786.812 | BL5: 45793.521 | BM5: ONSHORE | BN5: TX | BO5: 76949 | BP5: SILVER | BQ5: COKE | BR5: SURVEY STATION NO. | BS5: 49+96.5 | BT5: PERKINS 10'' HP TO FT CHADBOURNE | BU5: 210000 | BV5: NO | BW5: PIPELINE RIGHT-OF-WAY | BX5: UNDERGROUND | BY5: UNDER SOIL | CA5: 24 | CB5: YES | CC5: NO | CZ5: INTRASTATE | DA5: ONSHORE PIPELINE, INCLUDING VALVE SITES | DB5: PIPE | DC5: PIPE BODY | DD5: 10.75 | DE5: NO | DF5: 0.365 | DG5: 24000 | DH5: UNKNOWN | DI5: LONGITUDINAL ERW - UNKNOWN FREQUENCY | DK5: UNKNOWN | DL5: COAL TAR | DN5: UNKNOWN | EO5: 1965 | EP5: UNKNOWN | EQ5: CARBON STEEL | ES5: RUPTURE | EX5: CIRCUMFERENTIAL | EZ5: 10.8 | FA5: 10.8 | FC5: CLASS 1 LOCATION | FD5: NO | FF5: 198 | FH5: NO | FI5: NO | FL5: NO | FO5: 0 | FP5: 609 | FQ5: 0 | FR5: 236000 | FS5: 1000 | FT5: 0 | FV5: 3.17 | FW5: 237609 | FX5: 0 | FY5: 0 | FZ5: 0 | GA5: 0 | GB5: NO | GF5: 245 | GG5: 538 | GH5: 1440 | GI5: 192.619(A)(1) | GK5: 23743 | GL5: NO | GM5: PRESSURE DID NOT EXCEED MAOP | GN5: NO | GQ5: NO | GS5: MANUAL | GT5: MANUAL | GU5: 11299 | GV5: YES | HD5: NO | HK5: TYPE C GATHERING | HL5: NO | HQ5: LOCAL OPERATING PERSONNEL, INCLUDING CONTRACTORS | HS5: OPERATOR EMPLOYEE | HT5: NO, THE FACILITY WAS NOT MONITORED BY A CONTROLLER(S) AT THE TIME OF THE INCIDENT | IH5: NO | II5: NO | IN5: OTHER INCIDENT CAUSE | IO5: UNKNOWN | QS5: UNKNOWN | QU5: STILL UNDER INVESTIGATION, CAUSE OF INCIDENT TO BE DETERMINED* (*SUPPLEMENTAL REPORT REQUIRED) | WL5: CHRIS PALAFOX | WM5: SR. SPECIALIST DOT COMPLIANCE | WN5: christopher.palafox@energytransfer.com | WO5: 3259333577 | WT5: JUSTIN DAVIDSON | WU5: MANAGER DOT COMPLIANCE | WV5: 7139895231 | WW5: justin.davidson@energytransfer.com | WX5: ON MAY 9, 2025, AN INCIDENT OCCURRED ON THE 210000 - PERKINS 10" HP TO FT CHADBOURNE, 6.14 MILES SOUTHWEST OF SILVER, TEXAS IN COKE COUNTY. AT APPROXIMATELY 1930 THE LINE HAD A RELEASE. IT WAS DETERMINED TO BE A RUPTURE THAT OCCURRED DURING ROUTINE MAINTENANCE PIGGING OPERATIONS. ON MAY 16, 2025, AT 1230, IT WAS DETERMINED THE REPAIRS WOULD EXCEED THE $145,400.00 REPORTABLE DOLLAR CRITERIA AND THE NRC AND THE TXRRC WERE NOTIFIED. THE LINE SEPARATION IS STILL UNDER INVESTIGATION AND THE AFFECTED SECTION OF THE PIPE HAS BEEN SENT TO THE LAB FOR ANALYSIS. A SUPPLEMENTAL REPORT WILL BE SUBMITTED WHEN THE LAB ANALYSIS AND INVESTIGATION IS COMPLETE.
A6: 21 | B6: 45785 | C6: 2025 | D6: 20250049 | E6: 40859 | F6: ORIGINAL | G6: 19730 | H6: TRUNKLINE GAS CO | I6: 1300 MAIN STREET | J6: HOUSTON | K6: TX | L6: 77002 | M6: 45756.548 | N6: CENTRAL | O6: YES | P6: 30.59601 | Q6: -93.227044 | R6: 1428154 | S6: 45756.588 | T6: 1428308 | U6: NATURAL GAS | W6: 8620 | X6: 0 | Y6: 0 | Z6: NO | AF6: 0 | AG6: NO | AM6: 0 | AN6: NORMAL OPERATION, INCLUDES PAUSES DURING MAINTENANCE | AO6: YES | AQ6: 45756.548 | AR6: 45756.668 | AT6: YES | AU6: OPERATOR | AV6: 45756.562 | AW6: NO | BI6: 0 | BJ6: 45756.548 | BK6: 45756.548 | BL6: 45756.548 | BM6: ONSHORE | BN6: LA | BO6: 70652 | BP6: LONGVILLE | BQ6: BEAUREGARD | BR6: NOT APPLICABLE | BT6: LONGVILLE COMPRESSOR STATION | BU6: 100-3 36-INCH | BV6: NO | BW6: OPERATOR-CONTROLLED PROPERTY | BX6: ABOVEGROUND | BY6: TYPICAL ABOVEGROUND FACILITY PIPING OR APPURTENANCE | CC6: NO | CZ6: INTERSTATE | DA6: ONSHORE COMPRESSOR STATION EQUIPMENT AND PIPING | DB6: VALVE | EH6: MAINLINE | EI6: PLUG | EK6: NORDSTROM | EO6: UNKNOWN | EP6: UNKNOWN | EQ6: CARBON STEEL | ES6: LEAK | EV6: SEAL OR PACKING | FC6: CLASS 1 LOCATION | FD6: NO | FF6: 805 | FH6: NO | FI6: NO | FL6: NO | FO6: 0 | FP6: 32928 | FQ6: 0 | FR6: 0 | FS6: 0 | FT6: 0 | FV6: 3.82 | FW6: 32928 | FX6: 0 | FY6: 0 | FZ6: 0 | GA6: 0 | GB6: NO | GF6: 885 | GG6: 1259540 | GH6: 900 | GI6: 192.619(A)(1) | GK6: 39363 | GL6: NO | GM6: PRESSURE DID NOT EXCEED MAOP | GN6: NO | GQ6: NO | HK6: TRANSMISSION SYSTEM | HL6: YES | HM6: YES | HN6: YES | HO6: YES | HP6: YES | HQ6: LOCAL OPERATING PERSONNEL, INCLUDING CONTRACTORS | HS6: OPERATOR EMPLOYEE | HT6: YES, SPECIFY INVESTIGATION RESULT(S): (SELECT ALL THAT APPLY) | HZ6: YES | IH6: NO | II6: NO | IN6: EQUIPMENT FAILURE | IO6: MALFUNCTION OF CONTROL/RELIEF EQUIPMENT | OU6: MALFUNCTION OF CONTROL/RELIEF EQUIPMENT | OZ6: YES | QE6: YES | QF6: EQUIPMENT FAILURE STILL UNDER INVESTIGATION | WL6: PEGGY WEST | WM6: MANAGER DOT COMPLIANCE | WN6: peggy.west@energytransfer.com | WO6: 4092023088 | WT6: JUSTIN DAVIDSON | WU6: MANAGER DOT COMPLIANCE | WV6: 7139895231 | WW6: justin.davidson@energytransfer.com | WX6: ON 04/09/25 AT APPROXIMATELY 1309 PM, A VALVE CAP O-RING FAILED CAUSING THE ENGINE ROOM GAS DETECTION SYSTEM TO TRIGGER THE ESD SYSTEM. A 26'' PLUG VALVE WAS FOUND TO BE LEAKING BY AND ADDITIONAL VALVES WERE MANUALLY OPERATED TO ISOLATE THE STATION. UPON INVESTIGATION, IT WAS DETERMINED THE 26'' PLUG VALVE WAS FOUND IN THE CLOSED POSITION HOWEVER, THE VALVE DID NOT CLOSE ENTIRELY. THE VALVE WAS INSPECTED, GREASED, FUNCTION TESTED AND WAS STILL FOUND TO BE NOT FULLY ISOLATING. THE SECTION WAS ISOLATED AND TAKEN OUT OF SERVICE. VALVE WAS LOCKED OUT AND TAGGED OUT FOR FURTHER INVESTIGATION AND REPAIRS. THE REST OF THE STATION WAS PUT BACK IN SERVICE. NOTIFICATION WAS MADE TO THE NRC (#1428154) AT 1406 PM ON 04/09/25 AND THE 48 HOUR UPDATE (1428308) WAS MADE ON 04/11/25 AT 0908 AM.
A7: 24 | B7: 45785 | C7: 2025 | D7: 20250050 | E7: 40862 | F7: ORIGINAL | G7: 32099 | H7: ENERGY TRANSFER COMPANY | I7: 1300 MAIN STREET | J7: HOUSTON | K7: TX | L7: 77002 | M7: 45755.604 | N7: CENTRAL | O7: YES | P7: 28.83275 | Q7: -98.14965 | R7: 1428135 | S7: 45756.471 | T7: 1428310 | U7: NATURAL GAS | W7: 1800 | X7: 0 | Y7: 0 | Z7: NO | AF7: 0 | AG7: NO | AM7: 0 | AN7: NORMAL OPERATION, INCLUDES PAUSES DURING MAINTENANCE | AO7: YES | AQ7: 45755.625 | AR7: 45758.991 | AT7: YES | AU7: OPERATOR | AV7: 45755.617 | AW7: YES | AX7: 45755.604 | AY7: ALLOWED TO BURN OUT | BA7: 1800 | BB7: YES | BC7: VALVE CLOSURE | BE7: 45755.635 | BF7: VALVE CLOSURE | BH7: 45755.608 | BI7: 0 | BJ7: 45755.604 | BK7: 45755.604 | BL7: 45756.438 | BM7: ONSHORE | BN7: TX | BO7: 78113 | BP7: FALLS CITY | BQ7: ATASCOSA | BR7: NOT APPLICABLE | BT7: 88884002 DEHY TO COY CITY 10IN | BU7: 88884002 DEHY TO COY CITY 10IN | BV7: NO | BW7: OPERATOR-CONTROLLED PROPERTY | BX7: UNDERGROUND | BY7: UNDER SOIL | CA7: 48 | CB7: NO | CC7: NO | CZ7: INTRASTATE | DA7: ONSHORE PIPELINE, INCLUDING VALVE SITES | DB7: PIPE | DC7: PIPE SEAM | DD7: 10.75 | DF7: 0.25 | DG7: 52000 | DH7: API 5L PSL 2 | DI7: LONGITUDINAL ERW - HIGH FREQUENCY | DK7: UNKNOWN | DL7: ASPHALT | DN7: UNKNOWN | EO7: UNKNOWN | EP7: UNKNOWN | EQ7: CARBON STEEL | ES7: RUPTURE | EX7: LONGITUDINAL | EZ7: 213.6 | FA7: 33.7 | FC7: CLASS 1 LOCATION | FD7: NO | FF7: 251 | FH7: NO | FI7: NO | FL7: NO | FO7: 0 | FP7: 4500 | FQ7: 0 | FR7: 170000 | FS7: 4800 | FT7: 0 | FV7: 2.5 | FW7: 179300 | FX7: 0 | FY7: 0 | FZ7: 0 | GA7: 0 | GB7: NO | GF7: 900 | GG7: 1500 | GH7: 1024 | GI7: 192.619(A)(2) | GK7: 44490 | GL7: NO | GM7: PRESSURE DID NOT EXCEED MAOP | GN7: NO | GQ7: NO | GS7: MANUAL | GT7: MANUAL | GU7: 52915 | GV7: YES | HD7: YES | HG7: YES | HK7: TYPE C GATHERING | HL7: NO | HQ7: LOCAL OPERATING PERSONNEL, INCLUDING CONTRACTORS | HS7: OPERATOR EMPLOYEE | HT7: NO, THE FACILITY WAS NOT MONITORED BY A CONTROLLER(S) AT THE TIME OF THE INCIDENT | IH7: NO | II7: NO | IN7: OTHER INCIDENT CAUSE | IO7: UNKNOWN | QS7: UNKNOWN | QU7: STILL UNDER INVESTIGATION, CAUSE OF INCIDENT TO BE DETERMINED* (*SUPPLEMENTAL REPORT REQUIRED) | WL7: MIKE SMITH | WM7: SR. SPECIALIST DOT COMPLIANCE | WN7: mike.smith2@energytransfer.com | WO7: 8328944289 | WT7: JUSTIN DAVIDSON | WU7: MANAGER DOT COMPLIANCE | WV7: 7139895231 | WW7: justin.davidson@energytransfer.com | WX7: ON APRIL 8, 2025, ENERGY TRANSFER (ET) PERSONNEL DETECTED A FIRE WHILE ON ET SITE NEAR THE 97 DEHY TO COY CITY PIPELINE AT 14:30. OPERATIONS BEGAN TO TAKE PRECAUTIONARY MEASURES AND COMPLETELY ISOLATED THE LINE AT 15:15 AND THE FIRE WAS ALLOWED TO BURN OUT. ET PERSONNEL CONFIRMED DISCOVERY ON APRIL 9TH AT 10:30 AND DETERMINED THAT THE INCIDENT WOULD EXCEED THE COST REPORTING THRESHOLD. THE LINE HAS BEEN REPAIRED AND WAS RETURNED TO SERVICE AT 23:47 ON APRIL 11TH, 2025. THE CAUSE OF THE INCIDENT IS CURRENTLY UNKNOWN, AND THE INVESTIGATION IS UNDERWAY.
A8: 26 | B8: 45772 | C8: 2025 | D8: 20250044 | E8: 41049 | F8: SUPPLEMENTAL FINAL | G8: 32099 | H8: ENERGY TRANSFER COMPANY | I8: 1300 MAIN STREET | J8: HOUSTON | K8: TX | L8: 77002 | M8: 45743.499 | N8: CENTRAL | O8: YES | P8: 28.332579 | Q8: -99.611097 | R8: 1427041 | S8: 45743.842 | T8: 1427135 | U8: NATURAL GAS | W8: 22988 | X8: 799 | Y8: 0 | Z8: NO | AF8: 0 | AG8: NO | AM8: 0 | AN8: NORMAL OPERATION, INCLUDES PAUSES DURING MAINTENANCE | AO8: YES | AQ8: 45743.508 | AR8: 45746.05 | AT8: YES | AU8: OPERATOR | AV8: 45743.552 | AW8: NO | BC8: VALVE CLOSURE | BE8: 45743.508 | BF8: VALVE CLOSURE | BH8: 45743.503 | BI8: 15 | BJ8: 45743.502 | BK8: 45743.412 | BL8: 45743.808 | BM8: ONSHORE | BN8: TX | BO8: 78836 | BP8: CATARINA | BQ8: DIMMIT | BR8: NOT APPLICABLE | BT8: 20101161 RICH EAGLEFORD MAINLINE | BU8: 20101161 RICH EAGLEFORD MAINLINE | BV8: NO | BW8: OPERATOR-CONTROLLED PROPERTY | BX8: ABOVEGROUND | BY8: TYPICAL ABOVEGROUND FACILITY PIPING OR APPURTENANCE | CC8: NO | CZ8: INTRASTATE | DA8: ONSHORE PIPELINE, INCLUDING VALVE SITES | DB8: SCRAPER/PIG TRAP | EO8: 2012 | EP8: 2011 | EQ8: CARBON STEEL | ES8: OTHER | FB8: FROM OPENING OF BALL VALVE | FC8: CLASS 1 LOCATION | FD8: NO | FF8: 660 | FH8: NO | FI8: NO | FL8: NO | FO8: 12000 | FP8: 89193 | FQ8: 3100 | FR8: 873500 | FS8: 0 | FT8: 0 | FV8: 3.88 | FW8: 977793 | FX8: 0 | FY8: 0 | FZ8: 0 | GA8: 1 | GB8: NO | GF8: 1003 | GG8: 600000 | GH8: 1300 | GI8: 192.619(A)(2) | GK8: 40807 | GL8: NO | GM8: PRESSURE DID NOT EXCEED MAOP | GN8: NO | GQ8: NO | GS8: REMOTELY CONTROLLED | GT8: REMOTELY CONTROLLED | GU8: 550 | GV8: YES | HD8: NO | HK8: TYPE C GATHERING | HL8: YES | HM8: YES | HN8: YES | HO8: NO | HP8: NO | HQ8: LOCAL OPERATING PERSONNEL, INCLUDING CONTRACTORS | HS8: OPERATOR EMPLOYEE | HT8: NO, THE OPERATOR DID NOT FIND THAT AN INVESTIGATION OF THE CONTROLLER(S) ACTIONS OR CONTROL ROOM ISSUES WAS NECESSARY DUE TO: (PROVIDE AN EXPLANATION FOR WHY THE OPERATOR DID NOT INVESTIGATE) | HU8: CONTROLLER DID NOT CONTRIBUTE TO THE INCIDENT | IH8: NO | II8: NO | IN8: INCORRECT OPERATION | IO8: OTHER INCORRECT OPERATION | QG8: OTHER INCORRECT OPERATION | QJ8: FAILURE TO FOLLOW PROCEDURES | QM8: YES | QP8: ROUTINE MAINTENANCE | QQ8: YES | QR8: YES, THEY WERE QUALIFIED FOR THE TASK(S) | WL8: JOSEPH STOVER | WM8: SR. SPECIALIST DOT COMPLIANCE | WN8: joseph.stover@energytransfer.com | WO8: 8323241027 | WT8: JUSTIN DAVIDSON | WU8: MANAGER DOT COMPLIANCE | WV8: 7138820590 | WW8: justin.davidson@energytransfer.com | WX8: ON MARCH 27TH, 2025, 11:59 A.M., AN UNEXPECTED RELEASE OF NATURAL GAS WAS OBSERVED AT THE HOLLYWOOD AND VINE FACILITY. THE RELEASE CAME FROM THE LAUNCHER DOOR CLOSURE AND BLOWDOWN STACK OF THE LOADING BARREL. AN ETC EMPLOYEE WAS ONSITE AND WAS ABLE TO QUICKLY ENGAGE THE ASD SYSTEM ALLOWING THE SYSTEM TO BLOCK AND BLEED WITHIN FIVE MINUTES. DURING OUR INTERNAL INVESTIGATION IT WAS DETERMINED THAT THE EMPLOYEE LOADING THE SPHERE PIGS INTO THE LAUNCHER HAD FAILED TO SECURE THE PIG LAUNCHER DOOR CLOSURE ASSEMBLY WHICH RESULTED IN A GAS RELEASE DURING THE BARREL PURGING PROCESS.
A9: 31 | B9: 45763 | C9: 2025 | D9: 20250037 | E9: 40762 | F9: SUPPLEMENTAL FINAL | G9: 15105 | H9: PANHANDLE EASTERN PIPELINE CO | I9: 1300 MAIN STREET | J9: HOUSTON | K9: TX | L9: 77002 | M9: 45733.75 | N9: CENTRAL | O9: YES | P9: 38.798212 | Q9: -93.676357 | R9: 1426129 | S9: 45733.804 | T9: 1426260 | U9: NATURAL GAS | W9: 3037 | X9: 5793 | Y9: 0 | Z9: NO | AF9: 0 | AG9: NO | AM9: 0 | AN9: NORMAL OPERATION, INCLUDES PAUSES DURING MAINTENANCE | AO9: YES | AQ9: 45733.876 | AR9: 45738.64 | AT9: YES | AU9: OPERATOR | AV9: 45733.778 | AW9: NO | BC9: VALVE CLOSURE | BE9: 45733.803 | BF9: VALVE CLOSURE | BH9: 45733.8 | BI9: 0 | BJ9: 45733.769 | BK9: 45733.769 | BL9: 45733.769 | BM9: ONSHORE | BN9: MO | BO9: 64093 | BP9: WARRENSBURG | BQ9: JOHNSON | BT9: LOUISBURG 100 | BU9: LOUISBURG-41-04-001-1400 | BV9: NO | BW9: PIPELINE RIGHT-OF-WAY | BX9: UNDERGROUND | BY9: UNDER SOIL | CA9: 40 | CB9: NO | CC9: NO | CZ9: INTERSTATE | DA9: ONSHORE PIPELINE, INCLUDING VALVE SITES | DB9: WELD/FUSION, INCLUDING HEAT-AFFECTED ZONE | DD9: 22 | DF9: 0.312 | DG9: 30700 | DH9: EYS | DI9: LAP WELDED | DK9: NATIONAL TUBE SUPPLY COMPANY | DL9: COAL TAR | DN9: YES | DV9: PIPE GIRTH WELD | DX9: NO | EO9: 1931 | EP9: 1931 | EQ9: CARBON STEEL | ES9: LEAK | EV9: CRACK | FC9: CLASS 1 LOCATION | FD9: NO | FF9: 304 | FH9: NO | FI9: NO | FL9: NO | FO9: 1050 | FP9: 6912 | FQ9: 13184 | FR9: 55000 | FS9: 650 | FT9: 0 | FV9: 2.2758 | FW9: 76796 | FX9: 0 | FY9: 0 | FZ9: 0 | GA9: 0 | GB9: NO | GF9: 370 | GG9: 47000 | GH9: 400 | GI9: 192.619(A)(4) | GK9: 41778 | GL9: NO | GM9: PRESSURE DID NOT EXCEED MAOP | GN9: NO | GQ9: NO | GS9: MANUAL | GT9: MANUAL | GU9: 41676 | GV9: YES | HD9: YES | HG9: YES | HK9: TRANSMISSION SYSTEM | HL9: YES | HM9: YES | HN9: YES | HO9: NO | HP9: NO | HQ9: NOTIFICATION FROM PUBLIC | HT9: NO, THE OPERATOR DID NOT FIND THAT AN INVESTIGATION OF THE CONTROLLER(S) ACTIONS OR CONTROL ROOM ISSUES WAS NECESSARY DUE TO: (PROVIDE AN EXPLANATION FOR WHY THE OPERATOR DID NOT INVESTIGATE) | HU9: THE LINE WAS OPERATING APPROXIMATELY 30 PSIG BELOW MAOP AT THE TIME OF INCIDENT. | IH9: NO | II9: NO | IN9: MATERIAL FAILURE OF PIPE OR WELD | IO9: DESIGN-, CONSTRUCTION-, INSTALLATION-, OR FABRICATION-RELATED | NS9: DESIGN-, CONSTRUCTION-, INSTALLATION-, OR FABRICATION-RELATED | NT9: YES | OB9: YES | OK9: YES | OT9: 725 | QW9: YES | QX9: YES | RA9: YES | RE9: 2009 | RF9: FREE SWIMMING | RG9: METAL LOSS | RI9: HIGH RESOLUTION | RK9: 2001 | RL9: FREE SWIMMING | RM9: METAL LOSS | RO9: HIGH RESOLUTION | SK9: 2009 | SL9: FREE SWIMMING | SM9: HIGH RESOLUTION | SO9: NO CUPS | SP9: 2001 | SQ9: FREE SWIMMING | SR9: HIGH RESOLUTION | ST9: INSIDE ILI CUPS | TI9: YES | TJ9: 1953 | TK9: 725 | TL9: NO | TZ9: NO | VP9: YES | WL9: KORY TICE | WN9: kory.tice@energytransfer.com | WO9: 8066644029 | WQ9: KEVIN FERGUSON | WR9: kevin.ferguson@energytransfer.com | WS9: 9139061521 | WT9: SUSIE SJULIN | WV9: 4055575271 | WW9: susie.sjulin@energytransfer.com | WX9: AT APPROXIMATELY 18:16 ON 3/17/25, A LANDOWNER CALLED THE LOCAL REGULATORMAN ABOUT A HISSING SOUND NEAR ONE OF THE PANHANDLE EASTERN PIPELINES. THE REGULATORMAN CALLED THE OPERATIONS MANAGER AND WAS DISPATCHED TO THE SITE. THE OPERATIONS MANAGER THEN NOTIFIED GAS CONTROL OF THE POSSIBLE LEAK. THE REGULATORMAN ARRIVED ON SITE AT 18:28 AND CONFIRMED THE SOUND WAS IN FACT A LEAK. THE OPERATIONS MANAGER DISPATCHED EMPLOYEES TO THE UPSTREAM AND DOWNSTREAM BLOCK VALVES. DUE TO THE PROXIMITY TO A ROAD, THE REGULATORMAN CALLED 911 TO ASSIST WITH TRAFFIC CONTROL. THE BLOCK VALVES WERE CLOSED BY 19:17 AND THE LINE WAS BLOWN FLAT BY 21:01. THE LEAK WAS IDENTIFIED AS A CRACKED ACETYLENE WELD. THE WELD WAS CUT OUT AND NEW PIPE WAS INSTALLED. THE LINE WAS PURGED AND PLACED BACK IN SERVICE ON 3/22/25.
A10: 35 | B10: 45757 | C10: 2025 | D10: 20250036 | E10: 40741 | F10: ORIGINAL | G10: 32099 | H10: ENERGY TRANSFER COMPANY | I10: 1300 MAIN STREET | J10: HOUSTON | K10: TX | L10: 77002 | M10: 45723.403 | N10: CENTRAL | O10: NO | P10: 28.063611 | Q10: -99.596111 | R10: 1425566 | S10: 45727.595 | T10: 1425717 | U10: NATURAL GAS | W10: 45 | X10: 51.5 | Y10: 1 | Z10: NO | AF10: 0 | AG10: NO | AM10: 0 | AN10: NORMAL OPERATION, INCLUDES PAUSES DURING MAINTENANCE | AO10: YES | AQ10: 45723.489 | AS10: YES | AT10: NO | AW10: NO | BC10: VALVE CLOSURE | BE10: 45723.472 | BF10: VALVE CLOSURE | BH10: 45723.489 | BI10: 0 | BJ10: 45723.403 | BK10: 45723.417 | BL10: 45727.587 | BM10: ONSHORE | BN10: TX | BO10: 78836 | BP10: CATARINA | BQ10: WEBB | BR10: NOT APPLICABLE | BT10: GALVAN G13 LTS | BU10: GALVAN G13 LTS | BV10: NO | BW10: PIPELINE RIGHT-OF-WAY | BX10: UNDERGROUND | BY10: UNDER SOIL | CA10: 49 | CB10: NO | CC10: NO | CZ10: INTRASTATE | DA10: ONSHORE PIPELINE, INCLUDING VALVE SITES | DB10: PIPE | DC10: PIPE BODY | DD10: 12 | DE10: NO | DF10: 0.25 | DG10: 52000 | DH10: UNKNOWN | DI10: LONGITUDINAL ERW - HIGH FREQUENCY | DK10: UNKNOWN | DL10: EPOXY | DN10: NO | EO10: 2012 | EP10: UNKNOWN | EQ10: CARBON STEEL | ES10: LEAK | EV10: PINHOLE | FC10: CLASS 1 LOCATION | FD10: NO | FF10: 660 | FH10: NO | FI10: NO | FL10: NO | FO10: 10000 | FP10: 198 | FQ10: 226 | FR10: 144500 | FS10: 0 | FT10: 0 | FV10: 4.39 | FW10: 154924 | FX10: 0 | FY10: 0 | FZ10: 0 | GA10: 0 | GB10: NO | GF10: 60 | GG10: 200 | GH10: 1440 | GI10: 192.619(A)(1) | GK10: 41101 | GL10: NO | GM10: PRESSURE DID NOT EXCEED MAOP | GN10: NO | GQ10: NO | GS10: MANUAL | GT10: MANUAL | GU10: 16005 | GV10: YES | HD10: NO | HK10: TYPE C GATHERING | HL10: NO | HQ10: NOTIFICATION FROM PUBLIC | HT10: NO, THE FACILITY WAS NOT MONITORED BY A CONTROLLER(S) AT THE TIME OF THE INCIDENT | IH10: NO | II10: NO | IN10: OTHER INCIDENT CAUSE | IO10: UNKNOWN | QS10: UNKNOWN | QU10: STILL UNDER INVESTIGATION, CAUSE OF INCIDENT TO BE DETERMINED* (*SUPPLEMENTAL REPORT REQUIRED) | WL10: JOSEPH STOVER | WM10: SR. SPECIALIST DOT COMPLIANCE | WN10: joseph.stover@energytransfer.com | WO10: 8323241027 | WT10: JUSTIN DAVIDSON | WU10: MANAGER DOT COMPLIANCE | WV10: 7138820590 | WW10: justin.davidson@energytransfer.com | WX10: ENERGY TRANSFER (ET) PERSONNEL RECEIVED A CALL FROM THE LANDOWNER AT 9:40 AM ON MARCH 7TH, 2025, OF A POTENTIAL LEAK IN AN ET ROW. ET PERSONNEL ARRIVED ON SITE AT 10:00AM AND STARTED TAKING PRECAUTIONARY MEASURES AND ISOLATING THE LINE. THE LINE WAS ISOLATED AT 11:44 AM. IT WAS NOT CONFIRMED THAT THE LEAK WAS ON THE GALVAN G13 LTS UNTIL 14:05 ON MARCH 11TH, 2025, AND IT WAS PREDICTED TO EXCEED THE COST REPORTING THRESHOLD. THE INCIDENT INVESTIGATION IS STILL UNDERWAY, AND THE LINE IS CURRENTLY OUT OF SERVICE. REMEDIATION IS PENDING RESULTS OF THE INVESTIGATION.
A11: 44 | B11: 45728 | C11: 2025 | D11: 20250025 | E11: 40864 | F11: SUPPLEMENTAL FINAL | G11: 40285 | H11: GULF RUN TRANSMISSION, LLC | I11: 1300 MAIN STREET | J11: HOUSTON | K11: TX | L11: 77002 | M11: 45703.84 | N11: CENTRAL | O11: NO | P11: 32.290899 | Q11: -92.626194 | R11: 1423646 | S11: 45703.887 | T11: 1423735 | U11: NATURAL GAS | W11: 22000 | X11: 0 | Y11: 0 | Z11: NO | AF11: 0 | AG11: NO | AM11: 0 | AN11: NORMAL OPERATION, INCLUDES PAUSES DURING MAINTENANCE | AO11: YES | AQ11: 45703.877 | AR11: 45704.167 | AT11: NO | AW11: NO | BI11: 0 | BJ11: 45703.84 | BK11: 45703.874 | BL11: 45703.877 | BM11: ONSHORE | BN11: LA | BO11: 71251 | BP11: Not Within a Municipality | BQ11: JACKSON | BR11: NOT APPLICABLE | BT11: VERNON COMPRESSOR STATION | BU11: CP_PANOLA COMPRESSOR LS TO VERNON COMPRESSOR RS | BV11: NO | BW11: OPERATOR-CONTROLLED PROPERTY | BX11: ABOVEGROUND | BY11: TYPICAL ABOVEGROUND FACILITY PIPING OR APPURTENANCE | CC11: NO | CZ11: INTERSTATE | DA11: ONSHORE COMPRESSOR STATION EQUIPMENT AND PIPING | DB11: ESD SYSTEM, BUT EXCLUDING PRODUCT DRAIN LINES AND TUBING | EO11: 2007 | EP11: 2007 | EQ11: CARBON STEEL | ES11: OTHER | FB11: LACK OF ESD VALVE CLOSURE | FC11: CLASS 1 LOCATION | FD11: NO | FF11: 990 | FH11: NO | FI11: NO | FL11: NO | FO11: 0 | FP11: 102960 | FQ11: 0 | FR11: 0 | FS11: 0 | FT11: 0 | FV11: 4.68 | FW11: 102960 | FX11: 0 | FY11: 0 | FZ11: 0 | GA11: 0 | GB11: NO | GF11: 989 | GG11: 1400000 | GH11: 1168 | GI11: 192.619(A)(2) | GK11: 39187 | GL11: NO | GM11: PRESSURE DID NOT EXCEED MAOP | GN11: NO | GQ11: NO | HK11: TRANSMISSION SYSTEM | HL11: YES | HM11: YES | HN11: YES | HO11: YES | HP11: NO | HQ11: SCADA-BASED INFORMATION (SUCH AS ALARM(S), ALERT(S), EVENT(S), AND/OR VOLUME OR PACK CALCULATIONS) | HT11: NO, THE OPERATOR DID NOT FIND THAT AN INVESTIGATION OF THE CONTROLLER(S) ACTIONS OR CONTROL ROOM ISSUES WAS NECESSARY DUE TO: (PROVIDE AN EXPLANATION FOR WHY THE OPERATOR DID NOT INVESTIGATE) | HU11: CONTROLLER ACTIONS DID NOT CONTRIBUTE TO THE EVENT | IH11: NO | II11: NO | IN11: EQUIPMENT FAILURE | IO11: MALFUNCTION OF CONTROL/RELIEF EQUIPMENT | OU11: MALFUNCTION OF CONTROL/RELIEF EQUIPMENT | PG11: YES | PH11: IMPROPER PRESSURE SWITCH SET POINT | PU11: YES | QE11: YES | QF11: THE PRESSURE SWITCH THAT ACTUATES THE ESD BLOW DOWN VALVE WAS SET INCORRECTLY. | VX11: YES | WL11: RYAN HESS | WM11: COMPLIANCE | WN11: ryan.hess@energytransfer.com | WO11: 903-720-5473 | WQ11: BOB MIDDLETON | WR11: bob.middleton@energytransfer.com | WS11: 318-5607428 | WT11: SUSIE SJULIN | WU11: COMPLIANCE DIRECTOR | WV11: 405-557-5271 | WW11: susie.sjulin@energytransfer.com | WX11: ON 2/15/2025 THE VERNON COMPRESSOR STATION LOST COMMERCIAL POWER. IN ADDITION, THE EMERGENCY GENERATOR FAILED TO START, AND THE STATION BATTERY UPS SYSTEM FAILED TO SWITCH TO BATTERY BACKUP. THE UPS IS USED TO MAINTAIN POWER TO STATION NETWORKS, PLC'S, AND HMIS FOR SHORT PERIODS OF TIME UNTIL EITHER COMMERCIAL OR EMERGENCY GENERATOR POWER BECOMES AVAILABLE. WITH NO POWER, A NORMAL STOP COMMAND WAS ISSUED TO ALL THREE STATION TURBINES. THE TURBINES STOPPED, THE UNIT BLOWDOWN VALVES OPENED, AND THE FUEL SUPPLY VALVES CLOSED. THE STATION ESD BLOWDOWN VALVES ARE DESIGNED TO DEFAULT TO THE FAIL-OPEN POSITION AND MUST BE MANUALLY RESET. STATION BLOWDOWN VALVES WERE SET TO OPEN AT 55PSI. THE ESD PRESSURE DROPPED BELOW 50PSI, WHICH ACTIVATED THE VALVES, AND BEGAN RELIEVING THE STATION PRESSURE. TECHNICIANS ARRIVED ON LOCATION AND BLOCKED IN THE STATION DURING THE BLOWDOWN PROCESS, PRIOR TO A FULL STATION BLOWDOWN. CORRECTIVE ACTIONS TAKEN TO HAVE THE STATION BACK ONLINE BY 2/16/2025 AT 4:00AM. REMEDIAL ACTIONS TAKEN, SMALL LEAK WAS FOUND ON THE ESD SYSTEM. THE ESD PILOTS ON BLOWDOWN VALVES WERE RESET TO 30PSI AND THE SIDE GATE ESD PILOTS WERE REST TO 45PSI. ORIGINAL CONSTRUCTION DESIGN WAS CHANGED FROM UTILIZING ESD GAS AS PILOT PRESSURE TO POWER GAS. ALL REGULATORS WERE TESTED AND TRENDED TO ENSURE PROPER OPERATION. GENERATOR LOGIC ISSUES WERE IDENTIFIED AND CORRECTED, THEN MULTIPLE SIMULATED POWER LOSS SCENARIOS WERE RUN TO ENSURE THE GENERATOR TRANSFERRED PROPERLY AND CARRIED THE STATION LOAD.
A12: 50 | B12: 45800 | C12: 2025 | D12: 20250056 | E12: 40937 | F12: ORIGINAL | G12: 18152 | H12: SEA ROBIN PIPELINE CO | I12: 1300 MAIN STREET | J12: HOUSTON | K12: TX | L12: 77002 | M12: 45681.452 | N12: CENTRAL | O12: YES | P12: 28.615134 | Q12: -90.251182 | R12: 1421791 | S12: 45681.499 | T12: 1421896, 1429408 | U12: NATURAL GAS | W12: 5718 | X12: 2318 | Y12: 0 | Z12: NO | AF12: 0 | AG12: NO | AM12: 0 | AN12: NORMAL OPERATION, INCLUDES PAUSES DURING MAINTENANCE | AO12: YES | AQ12: 45681.542 | AS12: YES | AT12: YES | AU12: OPERATOR | AV12: 45681.499 | AW12: NO | BC12: VALVE CLOSURE | BE12: 45681.562 | BF12: VALVE CLOSURE | BH12: 45681.542 | BI12: 0 | BJ12: 45772.094 | BK12: 45681.542 | BL12: 45772.094 | BM12: OFFSHORE | BT12: SEA ROBIN | BU12: 319B-2400 | CP12: 156 | CQ12: ON THE OUTER CONTINENTAL SHELF (OCS) | CV12: OCS-GULF OF AMERICA | CW12: SOUTH TIMBALIER | CX12: 151 | CY12: BELOW WATER, PIPE BURIED OR JETTED BELOW SEABED | CZ12: INTERSTATE | DA12: OFFSHORE PIPELINE, INCLUDING RISER AND RISER BEND | DB12: PIPE | DC12: PIPE BODY | DD12: 20 | DE12: NO | DF12: 0.469 | DG12: 52000 | DH12: API 5L X52 | DI12: DSAW | DK12: KAISER STEEL | DL12: COAL TAR | DN12: NO | EO12: 1976 | EP12: 1976 | EQ12: CARBON STEEL | ES12: LEAK | EV12: PINHOLE | FC12: CLASS 1 LOCATION | FD12: NO | FF12: 482 | FH12: NO | FI12: NO | FL12: NO | FO12: 0 | FP12: 20528 | FQ12: 8322 | FR12: 2457394 | FS12: 107500 | FT12: 0 | FV12: 3.59 | FW12: 2593744 | FX12: 0 | FY12: 0 | FZ12: 0 | GA12: 0 | GB12: NO | GF12: 850 | GG12: 0 | GH12: 1200 | GI12: 192.619(A)(2) | GK12: 28126 | GL12: NO | GM12: PRESSURE DID NOT EXCEED MAOP | GN12: NO | GQ12: NO | GS12: MANUAL | GT12: MANUAL | GU12: 66105 | GV12: NO | GY12: YES | HD12: NO | HK12: TRANSMISSION SYSTEM | HL12: YES | HM12: YES | HN12: YES | HO12: NO | HP12: NO | HQ12: OTHER | HR12: NOTIFIED BY ARENA PLATFORM | HT12: NO, THE OPERATOR DID NOT FIND THAT AN INVESTIGATION OF THE CONTROLLER(S) ACTIONS OR CONTROL ROOM ISSUES WAS NECESSARY DUE TO: (PROVIDE AN EXPLANATION FOR WHY THE OPERATOR DID NOT INVESTIGATE) | HU12: LEAK WAS TOO SMALL FOR SCADA TO DETECT. | IH12: NO | II12: NO | IN12: OTHER INCIDENT CAUSE | IO12: UNKNOWN | QS12: UNKNOWN | QU12: STILL UNDER INVESTIGATION, CAUSE OF INCIDENT TO BE DETERMINED* (*SUPPLEMENTAL REPORT REQUIRED) | WL12: PEGGY WEST | WM12: MANAGER DOT COMPLIANCE | WN12: peggy.west@energytransfer.com | WO12: 4092023088 | WT12: PEGGY WEST | WU12: MANAGER DOT COMPLIANCE | WV12: 4092023088 | WW12: peggy.west@energytransfer.com | WX12: AT APPROXIMATELY 1051 ON 01/24/25, OPERATIONS RECEIVED A CALL FROM A 3RD PARTY REPORTING BUBBLES IN THE AREA NEAR THE SEA ROBIN 319B-2400 IN SOUTH TIMBALIER 151 (ST 151). NRC WAS CALLED REPORTING THE BUBBLES IN ST151 (NRC#1421791, 48HR UPDATE#1421896). AN OVERFLIGHT WAS CONDUCTED TO VERIFY THE LOCATION OF THE BUBBLES. PIPELINE WAS ISOLATED ON 01/24/25 AT 1330. OVERFLIGHTS WERE CONDUCTED DAILY TO MONITOR THE AREA FOR ANY CHANGES AS WEATHER PERMITTED. DUE TO WEATHER CONDITIONS, SEA STATES AND DSV AVAILABILITY, THE REPAIR CONTRACTOR WAS NOT ABLE TO DEPLOY UNTIL 4/24/25. DIVERS VERIFIED LEAK LOCATION ON 04/25/25 AT 0215 ON THE SEA ROBIN 319B-2400 PIPELINE. AN ATTEMPT WAS MADE TO REPAIR THE LEAK LOCATION. THE REPAIR WAS NOT COMPLETED DUE TO THE CLAMP NOT SEALING. A SPECIALIZED CLAMP IS ON ORDER. THE PIPELINE REMAINS ISOLATED UNTIL THE CLAMP CAN BE INSTALLED. THE 48HR NRC NOTIFICATION WAS UPDATED ON 04/25/25 AT 0859 TO REFLECT THE CHANGE FROM UNKNOWN OWNER TO SEA ROBIN PIPELINE. (#1429408)
A13: 51 | B13: 45702 | C13: 2025 | D13: 20250014 | E13: 40504 | F13: ORIGINAL FINAL | G13: 40285 | H13: GULF RUN TRANSMISSION, LLC | I13: 1300 MAIN STREET | J13: HOUSTON | K13: TX | L13: 77002 | M13: 45681.319 | N13: CENTRAL | O13: YES | P13: 32.290899 | Q13: -92.626194 | R13: 1421766 | S13: 45681.361 | T13: 1422317 | U13: NATURAL GAS | W13: 22000 | X13: 0 | Y13: 0 | Z13: NO | AF13: 0 | AG13: NO | AM13: 0 | AN13: NORMAL OPERATION, INCLUDES PAUSES DURING MAINTENANCE | AO13: YES | AQ13: 45681.309 | AR13: 45681.875 | AT13: YES | AU13: OPERATOR | AV13: 45681.3 | AW13: NO | BI13: 0 | BJ13: 45681.309 | BK13: 45681.306 | BL13: 45681.309 | BM13: ONSHORE | BN13: LA | BO13: 71251 | BP13: Not Within a Municipality | BQ13: JACKSON | BR13: NOT APPLICABLE | BT13: VERNON COMPRESSOR STATION | BU13: CP_PANOLA COMPRESSOR LS TO VERNON COMPRESSOR RS | BV13: NO | BW13: OPERATOR-CONTROLLED PROPERTY | BX13: ABOVEGROUND | BY13: TYPICAL ABOVEGROUND FACILITY PIPING OR APPURTENANCE | CC13: NO | CZ13: INTERSTATE | DA13: ONSHORE COMPRESSOR STATION EQUIPMENT AND PIPING | DB13: ESD SYSTEM, BUT EXCLUDING PRODUCT DRAIN LINES AND TUBING | EO13: 2007 | EP13: 2007 | EQ13: CARBON STEEL | ES13: OTHER | FB13: ESD VALVE FAILURE | FC13: CLASS 1 LOCATION | FD13: NO | FF13: 990 | FH13: NO | FI13: NO | FL13: NO | FO13: 0 | FP13: 84040 | FQ13: 0 | FR13: 15000 | FS13: 0 | FT13: 0 | FV13: 3.82 | FW13: 99040 | FX13: 0 | FY13: 0 | FZ13: 0 | GA13: 0 | GB13: NO | GF13: 900 | GG13: 1300000 | GH13: 1168 | GI13: 192.619(A)(2) | GK13: 39187 | GL13: NO | GM13: PRESSURE DID NOT EXCEED MAOP | GN13: NO | GQ13: NO | HK13: TRANSMISSION SYSTEM | HL13: YES | HM13: YES | HN13: YES | HO13: YES | HP13: YES | HQ13: LOCAL OPERATING PERSONNEL, INCLUDING CONTRACTORS | HS13: OPERATOR EMPLOYEE | HT13: NO, THE OPERATOR DID NOT FIND THAT AN INVESTIGATION OF THE CONTROLLER(S) ACTIONS OR CONTROL ROOM ISSUES WAS NECESSARY DUE TO: (PROVIDE AN EXPLANATION FOR WHY THE OPERATOR DID NOT INVESTIGATE) | HU13: CONTROLLER ACTIONS DID NOT CONTRIBUTE TO THE EVENT | IH13: NO | II13: NO | IN13: EQUIPMENT FAILURE | IO13: MALFUNCTION OF CONTROL/RELIEF EQUIPMENT | OU13: MALFUNCTION OF CONTROL/RELIEF EQUIPMENT | PF13: YES | QE13: YES | QF13: ESD VALVE FAILURE | VX13: YES | WL13: RYAN HESS | WM13: COMPLIANCE | WN13: ryan.hess@energytransfer.com | WO13: 903-720-5473 | WQ13: BOB MIDDLETON | WR13: bob.middleton@energytransfer.com | WS13: 318-5607428 | WT13: JIMMY CROSS | WU13: COMPLIANCE MANAGER | WV13: 405-576-8230 | WW13: jimmy.cross@energytransfer.com | WX13: A CONNECTION FAULT PRODUCED A FLAME DETECTOR INPUT FAILURE IN UNIT 3 BUILDING, WHICH CAUSED UNIT 3 TO SHUT DOWN AND ESD. UNIT 3 FUEL SUPPLY VALVE DID NOT CLOSE WHEN UNIT 3 BLOWDOWN VALVE OPENED. CAUSING A DRAIN ON STATION SYSTEM PRESSURE. THIS STATION HAS A PNEUMATIC/ELECTRICAL ESD. THE LOW ESD PRESSURE IS 55PSI. WHEN ESD FELL AT OR BELOW 55PSI THE STATION ESD.
A14: 57 | B14: 45694 | C14: 2025 | D14: 20250009 | E14: 40594 | F14: SUPPLEMENTAL FINAL | G14: 602 | H14: ENABLE GAS TRANSMISSION, LLC | I14: 1300 MAIN STREET | J14: HOUSTON | K14: TX | L14: 77002 | M14: 45675.819 | N14: CENTRAL | O14: NO | P14: 35.887232 | Q14: -95.406003 | R14: 1421380 | S14: 45675.858 | T14: 1421449 | U14: NATURAL GAS | W14: 49000 | X14: 0 | Y14: 0 | Z14: NO | AF14: 0 | AG14: NO | AM14: 0 | AN14: NORMAL OPERATION, INCLUDES PAUSES DURING MAINTENANCE | AO14: YES | AQ14: 45675.819 | AR14: 45675.896 | AT14: NO | AW14: NO | BI14: 0 | BJ14: 45675.792 | BK14: 45675.799 | BL14: 45675.819 | BM14: ONSHORE | BN14: OK | BO14: 74578 | BP14: WILBURTON | BQ14: LATIMER | BR14: NOT APPLICABLE | BT14: CHANDLER COMPRESSOR STATION | BU14: AD-EAST | BV14: NO | BW14: OPERATOR-CONTROLLED PROPERTY | BX14: ABOVEGROUND | BY14: TYPICAL ABOVEGROUND FACILITY PIPING OR APPURTENANCE | CC14: NO | CZ14: INTERSTATE | DA14: ONSHORE COMPRESSOR STATION EQUIPMENT AND PIPING | DB14: ESD SYSTEM, BUT EXCLUDING PRODUCT DRAIN LINES AND TUBING | EO14: 1973 | EP14: UNKNOWN | EQ14: CARBON STEEL | ES14: OTHER | FB14: PILOT OPERATOR FAILED ON AN ESD VENT VALVE RESULTING IN THE RELEASE OF THE NATURAL GAS. | FC14: CLASS 1 LOCATION | FD14: NO | FF14: 545 | FH14: NO | FI14: NO | FL14: NO | FO14: 0 | FP14: 159250 | FQ14: 0 | FR14: 775 | FS14: 690 | FT14: 0 | FV14: 3.25 | FW14: 160715 | FX14: 0 | FY14: 0 | FZ14: 0 | GA14: 0 | GB14: NO | GF14: 886 | GG14: 750000 | GH14: 1000 | GI14: 192.619(A)(1) | GK14: 26696 | GL14: NO | GM14: PRESSURE DID NOT EXCEED MAOP | GN14: NO | GQ14: NO | HK14: TRANSMISSION SYSTEM | HL14: YES | HM14: YES | HN14: YES | HO14: YES | HP14: YES | HQ14: SCADA-BASED INFORMATION (SUCH AS ALARM(S), ALERT(S), EVENT(S), AND/OR VOLUME OR PACK CALCULATIONS) | HT14: NO, THE OPERATOR DID NOT FIND THAT AN INVESTIGATION OF THE CONTROLLER(S) ACTIONS OR CONTROL ROOM ISSUES WAS NECESSARY DUE TO: (PROVIDE AN EXPLANATION FOR WHY THE OPERATOR DID NOT INVESTIGATE) | HU14: AFTER REVIEW OF THE INCIDENT, IT WAS DETERMINED THAT THE CONTROLLER ACTED IN ACCORDANCE WITH OUR POLICIES AND PROCEDURES. | IH14: NO | II14: NO | IN14: NATURAL FORCE DAMAGE | IO14: TEMPERATURE | KP14: TEMPERATURE | KT14: FROZEN COMPONENTS | KV14: YES | KZ14: YES | LA14: EXTREMELY COLD TEMPERATURES. | VX14: YES | WL14: JEFFREY OSBORN | WM14: SENIOR SPECIALIST - DOT COMPLIANCE | WN14: jeff.osborn@energytransfer.com | WO14: 4053807618 | WQ14: JEFFREY OSBORN | WR14: jeff.osborn@energytransfer.com | WS14: 4053807618 | WT14: JIMMY CROSS | WU14: SENIOR MANAGER - DOT COMPLIANCE | WV14: 4055768230 | WW14: jimmy.cross@energytransfer.com | WX14: SYSTEM CONTROL RECEIVED A RATE OF CHANGE ALARM AT 18:51 ON THE SUCTION PIPING AT CHANDLER COMPRESSOR STATION, ANOTHER ALARM AT 18:53 ON THE CHANDLER TO AC DOWNSTREAM AND ANOTHER ALARM AT 18:55 ON THE CHANDLER STATION SUCTION PIPING. A FIELD EMPLOYEE, WHO LIVES WITHIN MINUTES OF THE CHANDLER COMPRESSOR STATION, HEARD THE VENT AT THE STATION FROM HIS HOME. HE IMMEDIATELY CALLED SYSTEM CONTROL AT 19:00 TO LET THEM KNOW HE WAS IN ROUTE TO CHECK THIS OUT. AT 19:15, EMPLOYEE ARRIVED ON SITE TO CONFIRM WE HAD AN EVENT TAKING PLACE. EMPLOYEE HAD TO CALL FOR ADDITIONAL PERSONNEL, THAT WAS TRAINED ON THIS STATION, TO RESPOND TO ASSIST IN THE EVENT. IT WAS DETERMINED THAT AN O-RING ON THE SHAFT SEAL FAILED DURING THE BELOW FREEZING WEATHER, WHICH INCLUDED ICE AND SNOW, ON THE 8" PILOT OPERATOR ON THE STATION ESD VENT VALVE ON THE SUCTION HEADER OF THE STATION, CAUSING THE VALVE TO OPEN AND VENT GAS. VALVE WAS ISOLATED AT 19:40. PILOT OPERATOR WAS REPLACED, AND SYSTEM WAS PUT BACK IN SERVICE AT 21:30 THE SAME DAY. PART G REVISED TO G2 PER REQUEST BY MATHEWS/PHMSA.
A15: 59 | B15: 45804 | C15: 2025 | D15: 20250058 | E15: 40990 | F15: SUPPLEMENTAL FINAL | G15: 18152 | H15: SEA ROBIN PIPELINE CO | I15: 1300 MAIN STREET | J15: HOUSTON | K15: TX | L15: 77002 | M15: 45670.507 | N15: CENTRAL | O15: NO | P15: 28.243831 | Q15: -91.710811 | R15: 1421007 | S15: 45670.546 | T15: 1421083, 1430839 | U15: NATURAL GAS | W15: 793534 | X15: 0 | Y15: 0 | Z15: NO | AF15: 0 | AG15: NO | AM15: 0 | AN15: NORMAL OPERATION, INCLUDES PAUSES DURING MAINTENANCE | AO15: YES | AQ15: 45670.562 | AR15: 45791.594 | AT15: YES | AU15: OPERATOR | AV15: 45670.546 | AW15: NO | BC15: VALVE CLOSURE | BE15: 45670.559 | BF15: VALVE CLOSURE | BH15: 45670.562 | BI15: 0 | BJ15: 45788.792 | BK15: 45670.559 | BL15: 45788.792 | BM15: OFFSHORE | BT15: SEA ROBIN | BU15: LINE 716-10-1 | CP15: 260 | CQ15: ON THE OUTER CONTINENTAL SHELF (OCS) | CV15: OCS-GULF OF AMERICA | CW15: EUGENE ISLAND | CX15: 331 | CY15: BELOW WATER, PIPE BURIED OR JETTED BELOW SEABED | CZ15: INTERSTATE | DA15: OFFSHORE PIPELINE, INCLUDING RISER AND RISER BEND | DB15: PIPE | DC15: PIPE BODY | DD15: 8.625 | DE15: NO | DF15: 0.41 | DG15: 24000 | DH15: API 5L X52 | DI15: OTHER | DJ15: UNKNOWN | DK15: UNKNOWN | DL15: OTHER | DM15: MASTIC AND CONCRETE | DN15: YES | EO15: 1973 | EP15: 1973 | EQ15: CARBON STEEL | ES15: LEAK | EV15: PINHOLE | FC15: CLASS 1 LOCATION | FD15: NO | FF15: 215 | FH15: NO | FI15: NO | FL15: NO | FO15: 0 | FP15: 2848787 | FQ15: 0 | FR15: 350000 | FS15: 125000 | FT15: 0 | FV15: 3.59 | FW15: 3323787 | FX15: 0 | FY15: 0 | FZ15: 0 | GA15: 0 | GB15: NO | GF15: 840 | GG15: 3000 | GH15: 1306 | GI15: 192.619(A)(1) | GK15: 28126 | GL15: NO | GM15: PRESSURE DID NOT EXCEED MAOP | GN15: NO | GQ15: NO | GS15: MANUAL | GT15: MANUAL | GU15: 31680 | GV15: NO | GY15: YES | HD15: YES | HG15: YES | HK15: TRANSMISSION SYSTEM | HL15: YES | HM15: YES | HN15: YES | HO15: NO | HP15: NO | HQ15: LOCAL OPERATING PERSONNEL, INCLUDING CONTRACTORS | HS15: OPERATOR EMPLOYEE | HT15: NO, THE OPERATOR DID NOT FIND THAT AN INVESTIGATION OF THE CONTROLLER(S) ACTIONS OR CONTROL ROOM ISSUES WAS NECESSARY DUE TO: (PROVIDE AN EXPLANATION FOR WHY THE OPERATOR DID NOT INVESTIGATE) | HU15: LEAK WAS TOO SMALL FOR SCADA TO DETECT. | IH15: NO | II15: NO | IN15: CORROSION FAILURE | IO15: INTERNAL CORROSION | IP15: INTERNAL CORROSION | JT15: NOT CUT OPEN | JV15: YES | KB15: YES | KF15: YES | KL15: NO | KM15: NO | KN15: NO | KO15: YES | QW15: NO | TI15: NO | TL15: NO | TZ15: NO | WL15: PEGGY WEST | WM15: MANAGER DOT COMPLIANCE | WN15: peggy.west@energytransfer.com | WO15: 4092023088 | WT15: PEGGY WEST | WU15: MANAGER DOT COMPLIANCE | WV15: 4092023088 | WW15: peggy.west@energytransfer.com | WX15: AT APPROXIMATELY 1210 ON 01/13/25, OPERATIONS WAS CONDUCTING AN OVERFLIGHT TO VERIFY BUBBLES IN THE AREA NEAR THE SEA ROBIN 716-10-1 LATERAL IN EUGENE ISLAND 331 (EI 331) AND NOTICED ANOTHER LOCATION WITH BUBBLES. NRC WAS CALLED REPORTING THE SECOND SET OF BUBBLES. (NRC#1421007, 48HR UPDATE#1421083). THE PIPELINE WAS ISOLATED ON 01/13/25 AT 1330. OVERFLIGHTS WERE CONDUCTED DAILY TO MONITOR THE AREA FOR ANY CHANGES AS WEATHER PERMITTED. DUE TO POOR WEATHER CONDITIONS, SEA STATES AND DSV AVAILABILITY, THE REPAIR CONTRACTOR WAS NOT ABLE TO DEPLOY UNTIL 5/11/25. THE LEAK WAS LOCATED AND A CLAMP WAS INSTALLED ON 5/12/25 AT 1100. THE PIPELINE WAS RETURNED TO SERVICE AT APPROXIMATELY 1415 ON 05/14/25. THE 48HR NRC NOTIFICATION WAS UPDATED ON 05/11/25 AT 1955 TO REFLECT THE CHANGE FROM UNKNOWN OWNER TO SEA ROBIN PIPELINE. (#1430839) THE UNINTENTIONAL VOLUME WAS SPLIT BETWEEN TWO INCIDENTS FOR SEA ROBIN, BOTH OCCURRED 01/13/25 ON THE SAME PIPELINE. TOTAL VOLUME FOR BOTH INCIDENTS WAS 1,587,069 MCF.
A16: 60 | B16: 45804 | C16: 2025 | D16: 20250059 | E16: 40989 | F16: SUPPLEMENTAL FINAL | G16: 18152 | H16: SEA ROBIN PIPELINE CO | I16: 1300 MAIN STREET | J16: HOUSTON | K16: TX | L16: 77002 | M16: 45670.315 | N16: CENTRAL | O16: YES | P16: 28.245759 | Q16: -91.70579 | R16: 1420963 | S16: 45670.333 | T16: 1421082, 1430981 | U16: NATURAL GAS | W16: 793534 | X16: 0 | Y16: 0 | Z16: NO | AF16: 0 | AG16: NO | AM16: 0 | AN16: NORMAL OPERATION, INCLUDES PAUSES DURING MAINTENANCE | AO16: YES | AQ16: 45670.562 | AR16: 45791.594 | AT16: YES | AU16: OPERATOR | AV16: 45670.333 | AW16: NO | BC16: VALVE CLOSURE | BE16: 45670.559 | BF16: VALVE CLOSURE | BH16: 45670.562 | BI16: 0 | BJ16: 45790.547 | BK16: 45670.559 | BL16: 45790.547 | BM16: OFFSHORE | BT16: SEA ROBIN | BU16: LINE 716-10-1 | CP16: 260 | CQ16: ON THE OUTER CONTINENTAL SHELF (OCS) | CV16: OCS-GULF OF AMERICA | CW16: EUGENE ISLAND | CX16: 330 | CY16: BELOW WATER, PIPE BURIED OR JETTED BELOW SEABED | CZ16: INTERSTATE | DA16: OFFSHORE PIPELINE, INCLUDING RISER AND RISER BEND | DB16: PIPE | DC16: PIPE BODY | DD16: 8.625 | DE16: NO | DF16: 0.41 | DG16: 24000 | DH16: API 5L X52 | DI16: OTHER | DJ16: UNKNOWN | DK16: UNKNOWN | DL16: OTHER | DM16: MASTEC AND CONCRETE | DN16: YES | EO16: 1973 | EP16: 1973 | EQ16: CARBON STEEL | ES16: LEAK | EV16: PINHOLE | FC16: CLASS 1 LOCATION | FD16: NO | FF16: 215 | FH16: NO | FI16: NO | FL16: NO | FO16: 0 | FP16: 2848787 | FQ16: 0 | FR16: 350000 | FS16: 125000 | FT16: 0 | FV16: 3.59 | FW16: 3323787 | FX16: 0 | FY16: 0 | FZ16: 0 | GA16: 0 | GB16: NO | GF16: 840 | GG16: 3000 | GH16: 1306 | GI16: 192.619(A)(1) | GK16: 28126 | GL16: NO | GM16: PRESSURE DID NOT EXCEED MAOP | GN16: NO | GQ16: NO | GS16: MANUAL | GT16: MANUAL | GU16: 31680 | GV16: NO | GY16: YES | HD16: YES | HG16: YES | HK16: TRANSMISSION SYSTEM | HL16: YES | HM16: YES | HN16: YES | HO16: NO | HP16: NO | HQ16: OTHER | HR16: NOTIFIED BY PRODUCER | HT16: NO, THE OPERATOR DID NOT FIND THAT AN INVESTIGATION OF THE CONTROLLER(S) ACTIONS OR CONTROL ROOM ISSUES WAS NECESSARY DUE TO: (PROVIDE AN EXPLANATION FOR WHY THE OPERATOR DID NOT INVESTIGATE) | HU16: LEAK WAS TOO SMALL FOR SCADA TO DETECT. | IH16: NO | II16: NO | IN16: CORROSION FAILURE | IO16: INTERNAL CORROSION | IP16: INTERNAL CORROSION | JT16: NOT CUT OPEN | JV16: YES | KB16: YES | KF16: YES | KL16: NO | KM16: NO | KN16: NO | KO16: NO | QW16: NO | TI16: NO | TL16: NO | TZ16: NO | WL16: PEGGY WEST | WM16: MANAGER DOT COMPLIANCE | WN16: peggy.west@energytransfer.com | WO16: 4092023088 | WT16: PEGGY WEST | WU16: MANAGER DOT COMPLIANCE | WV16: 4092023088 | WW16: peggy.west@energytransfer.com | WX16: AT APPROXIMATELY 0733 ON 01/13/25, OPERATIONS RECEIVED A NOTIFICATION FROM A 3RD PARTY REPORTING BUBBLES IN THE AREA NEAR THE SEA ROBIN 716-10-1 LATERAL IN EUGENE ISLAND 330 (EI 330). AN OVERFLIGHT WAS CONDUCTED TO VERIFY THE LOCATION OF THE BUBBLES AND WAS CONFIRMED AT APPROXIMATELY 1210 ON 01/13/25. NRC WAS CALLED REPORTING THE BUBBLES IN EI 331 (NRC#1420963, 48HR UPDATE#1421082). THE PIPELINE WAS ISOLATED ON 01/13/25 AT 1330. OVERFLIGHTS WERE CONDUCTED DAILY TO MONITOR THE AREA FOR ANY CHANGES AS WEATHER PERMITTED. DUE TO POOR WEATHER CONDITIONS, SEA STATES AND DSV AVAILABILITY, THE REPAIR CONTRACTOR WAS NOT ABLE TO DEPLOY UNTIL 5/11/25. THE LEAK WAS LOCATED AND A CLAMP WAS INSTALLED ON 5/14/25 AT 0330. THE PIPELINE WAS RETURNED TO SERVICE AT APPROXIMATELY 1415 ON 05/14/25. THE 48HR NRC NOTIFICATION WAS UPDATED ON 05/13/25 AT 1440 TO REFLECT THE CHANGE FROM UNKNOWN OWNER TO SEA ROBIN PIPELINE. (#1430981) THE UNINTENTIONAL VOLUME WAS SPLIT BETWEEN TWO INCIDENTS FOR SEA ROBIN, BOTH OCCURRED 01/13/25 ON THE SAME PIPELINE. TOTAL VOLUME FOR BOTH INCIDENTS WAS 1,587,069 MCF.
A17: 65 | B17: 45681 | C17: 2024 | D17: 20250007 | E17: 40915 | F17: SUPPLEMENTAL FINAL | G17: 32099 | H17: ENERGY TRANSFER COMPANY | I17: 1300 MAIN STREET | J17: HOUSTON | K17: TX | L17: 77002 | M17: 45651.281 | N17: CENTRAL | O17: NO | P17: 32.32391 | Q17: -101.45735 | R17: 1419818 | S17: 45651.4 | T17: 1419912 | U17: NATURAL GAS | W17: 191 | X17: 0 | Y17: 0 | Z17: NO | AF17: 0 | AG17: NO | AM17: 0 | AN17: NORMAL OPERATION, INCLUDES PAUSES DURING MAINTENANCE | AO17: YES | AQ17: 45651.253 | AR17: 45651.542 | AT17: YES | AU17: OPERATOR | AV17: 45651.274 | AW17: YES | AX17: 45651.253 | AY17: ALLOWED TO BURN OUT | BA17: 191 | BB17: NO | BI17: 0 | BJ17: 45651.253 | BK17: 45651.281 | BL17: 45651.4 | BM17: ONSHORE | BN17: TX | BO17: 79720 | BP17: BIG SPRING | BQ17: HOWARD | BR17: NOT APPLICABLE | BT17: NORTH BIG SPRING COMPRESSOR STATION | BV17: NO | BW17: OPERATOR-CONTROLLED PROPERTY | BX17: ABOVEGROUND | BY17: OTHER | BZ17: COMPRESSOR | CC17: NO | CZ17: INTRASTATE | DA17: ONSHORE COMPRESSOR STATION EQUIPMENT AND PIPING | DB17: COMPRESSOR | EO17: 2022 | EP17: 2014 | EQ17: CARBON STEEL | ES17: LEAK | EV17: SEAL OR PACKING | FC17: CLASS 1 LOCATION | FD17: NO | FF17: 75 | FH17: NO | FI17: NO | FL17: NO | FO17: 0 | FP17: 754 | FQ17: 0 | FR17: 698000 | FS17: 2000 | FT17: 0 | FV17: 3.95 | FW17: 700754 | FX17: 0 | FY17: 0 | FZ17: 0 | GA17: 0 | GB17: NO | GF17: 1281 | GG17: 1991 | GH17: 1440 | GI17: 192.619(A)(1) | GK17: 41640 | GL17: NO | GM17: PRESSURE DID NOT EXCEED MAOP | GN17: NO | GQ17: NO | HK17: TYPE C GATHERING | HL17: YES | HM17: YES | HN17: YES | HO17: YES | HP17: YES | HQ17: SCADA-BASED INFORMATION (SUCH AS ALARM(S), ALERT(S), EVENT(S), AND/OR VOLUME OR PACK CALCULATIONS) | HT17: NO, THE OPERATOR DID NOT FIND THAT AN INVESTIGATION OF THE CONTROLLER(S) ACTIONS OR CONTROL ROOM ISSUES WAS NECESSARY DUE TO: (PROVIDE AN EXPLANATION FOR WHY THE OPERATOR DID NOT INVESTIGATE) | HU17: INVESTIGATION IDENTIFIED NO CONTROLLER ISSUES. CONTROLLER ACTIONS WERE CONSISTENT WITH COMPANY PROTOCOLS. | IH17: NO | II17: NO | IN17: EQUIPMENT FAILURE | IO17: COMPRESSOR OR COMPRESSOR-RELATED EQUIPMENT | OU17: COMPRESSOR OR COMPRESSOR-RELATED EQUIPMENT | PI17: SEAL FAILURE | PP17: YES | PR17: YES | WL17: CHRIS PALAFOX | WM17: SR. SPECIALIST DOT COMPLIANCE | WN17: christopher.palafox@energytransfer.com | WO17: 325-933-3577 | WQ17: CHRIS PALAFOX | WR17: christopher.palafox@energytransfer.com | WS17: 325-933-3577 | WT17: JUSTIN DAVIDSON | WU17: MANAGER DOT COMPLIANCE | WV17: 7138820590 | WW17: justin.davidson@energytransfer.com | WX17: ON DECEMBER 25, 2024, A FIRE OCCURRED AT THE NORTH BIG SPRING COMPRESSOR STATION, 6 MILES NORTHEAST OF BIG SPRING, TEXAS IN HOWARD COUNTY. AT APPROXIMATELY 0605 SCADA NOTIFIED OPERATIONS ABOUT AN ISSUE AT THE NORTH BIG SPRING COMPRESSOR STATION. 0645, IT WAS DISCOVERED THAT COMPRESSOR UNIT #6 WAS ON FIRE, ESD'D THE STATION AND CALLED THE LOCAL FIRE DEPARTMENT TO THE STATION. AT 0936, IT WAS DETERMINED THE REPAIRS AND DAMAGES WOULD EXCEED THE $145,400.00 REPORTABLE DOLLAR CRITERIA AND THE NRC AND THE TXRRC WAS NOTIFIED. LOCAL FIRE DEPARTMENT EXTINGUISHED THE FIRE. THIS IS A LEASED COMPRESSOR FROM A 3RD PARTY THE LEAK OF THE GAS AND THE CAUSE OF THE FIRE IS STILL UNDER INVESTIGATION. A SUPPLEMENTAL REPORT WILL BE SUBMITTED ONCE INVESTIGATION IS COMPLETE. **THE FINAL INVESTIGATION FOUND THAT COMPRESSOR CYLINDER #1 DISCHARGE FLANGE BOLTS WERE BROKEN AND THE GASKETED FLANGE CONNECTION FAILED WHICH RESULTED IN THE RELEASE OF GAS. COMPRESSOR CYLINDER #1 IS LOCATED WITHIN CLOSE PROXIMITY TO THE ENGINE AND ASSOCIATED EXHAUST COMPONENTS WHICH LIKELY RESULTED IN THE IGNITION OF THE GAS. ADDITIONAL FINDINGS INDICATED THAT UNIT #6 HAD EXPERIENCED SIGNIFICANT SEVERE VIBRATION. FINDINGS INCLUDE; MOVEMENT/SHIFTING OF COMPRESSOR SKID ON GRAVEL FOUNDATION, NUMEROUS FAILED, LOOSE, OR MISSING BOLTS/FASTENERS ON 1ST STAGE COMPRESSOR CYLINDER ASSEMBLIES AND CYLINDER SUPPORTS, LOOSE CROSS TIE BARS ON COMPRESSOR FRAME, FAILED THROUGH BOLTS ON DISCHARGE BOTTLE SUPPORTS, FAILED PROCESS PIPING CLAMP ON CYLINDER #2. THIS COMPRESSOR WAS PERMANENTLY REMOVED AND BYPASSED WITH NO REPLACEMENT. FACILITY STARTED BACK UP WITH UNIT #5 AT 1300 ON DECEMBER 25, 2024. TO PREVENT THIS FROM OCCURRING IN THE FUTURE, THE FOLLOWING WILL BE CONSIDERED: - VISUALLY INSPECT ENGINE MOUNTING HARDWARE FOR LOOSENESS OR ABNORMALITIES ON ALL ARCHROCK LEASED UNITS IN THE REGION AND REPORT ANY FINDINGS TO ARCHROCK FOR EVALUATION. ETC OPERATIONS - VERIFY PROPER TORQUE AND MOUNTING ON ARCHROCK LEASED AND MAINTAINED COMPRESSOR PACKAGES. ARCHROCK - ENSURE COMPRESSOR PACKAGE VIBRATION SHUTDOWNS ARE ADJUSTED PROPERLY AND FULLY FUNCTIONAL ON ARCHROCK LEASED AND MAINTAINED COMPRESSOR PACKAGES. ARCHROCK - AVOID OPERATING OR RESTARTING UNITS THAT HAVE EXPERIENCED CRITICAL SHUTDOWNS UNTIL A THOROUGH EVALUATION CAN BE PERFORMED BY A SUBJECT MATER EXPERT AND THE EQUIPMENT HAS BEEN DEEMED SAFE TO OPERATE. ETC OPERATIONS
A18: 104 | B18: 45518 | C18: 2024 | D18: 20240102 | E18: 40038 | F18: SUPPLEMENTAL FINAL | G18: 32099 | H18: ENERGY TRANSFER COMPANY | I18: 1300 MAIN STREET | J18: HOUSTON | K18: TX | L18: 77002 | M18: 45488.222 | N18: CENTRAL | O18: YES | P18: 31.382919 | Q18: -103.04852 | R18: 1404780 | S18: 45488.234 | T18: 1404966 | U18: NATURAL GAS | W18: 14550 | X18: 1880 | Y18: 0 | Z18: NO | AF18: 0 | AG18: NO | AM18: 0 | AN18: NORMAL OPERATION, INCLUDES PAUSES DURING MAINTENANCE | AO18: YES | AQ18: 45488.222 | AR18: 45538.417 | AT18: YES | AU18: OPERATOR | AV18: 45488.198 | AW18: YES | AX18: 45488.146 | AY18: ALLOWED TO BURN OUT | BA18: 14550 | BB18: NO | BC18: VALVE CLOSURE | BE18: 45488.198 | BF18: VALVE CLOSURE | BH18: 45488.222 | BI18: 0 | BJ18: 45488.146 | BK18: 45488.194 | BL18: 45488.222 | BM18: ONSHORE | BN18: TX | BO18: 79730 | BP18: COYANOSA | BQ18: PECOS | BR18: MILEPOST | BS18: 608 + 00 | BT18: K TO COYA 24 TX-PECOS_BLK OW,8 | BU18: K TO COYA 24 TX-PECOS_BLK OW,8 | BV18: NO | BW18: PIPELINE RIGHT-OF-WAY | BX18: UNDERGROUND | BY18: UNDER SOIL | CA18: 48 | CB18: NO | CC18: NO | CZ18: INTRASTATE | DA18: ONSHORE PIPELINE, INCLUDING VALVE SITES | DB18: PIPE | DC18: PIPE BODY | DD18: 24 | DE18: NO | DF18: 0.281 | DG18: 60000 | DH18: X-60 | DI18: DSAW | DK18: UNKNOWN | DL18: OTHER | DM18: WAX | DN18: UNKNOWN | EO18: 1965 | EP18: UNKNOWN | EQ18: CARBON STEEL | ES18: RUPTURE | EX18: LONGITUDINAL | EZ18: 600 | FA18: 24 | FC18: CLASS 1 LOCATION | FD18: NO | FF18: 561 | FH18: NO | FI18: NO | FL18: NO | FO18: 0 | FP18: 31137 | FQ18: 4023 | FR18: 189500 | FS18: 5000 | FT18: 0 | FV18: 2.14 | FW18: 229660 | FX18: 0 | FY18: 0 | FZ18: 0 | GA18: 0 | GB18: NO | GF18: 650 | GG18: 43.8 | GH18: 1024 | GI18: 192.619(A)(3) | GK18: 41613 | GL18: NO | GM18: PRESSURE DID NOT EXCEED MAOP | GN18: NO | GQ18: NO | GS18: MANUAL | GT18: MANUAL | GU18: 122285 | GV18: NO | HB18: YES | HC18: NO LAUNCHERS AND RECEIVERS | HD18: YES | HI18: YES | HJ18: NO LAUNCHERS AND RECEIVERS | HK18: TYPE C GATHERING | HL18: YES | HM18: YES | HN18: YES | HO18: YES | HP18: NO | HQ18: SCADA-BASED INFORMATION (SUCH AS ALARM(S), ALERT(S), EVENT(S), AND/OR VOLUME OR PACK CALCULATIONS) | HT18: NO, THE OPERATOR DID NOT FIND THAT AN INVESTIGATION OF THE CONTROLLER(S) ACTIONS OR CONTROL ROOM ISSUES WAS NECESSARY DUE TO: (PROVIDE AN EXPLANATION FOR WHY THE OPERATOR DID NOT INVESTIGATE) | HU18: THE INVESTIGATION IDENTIFIED NO CONTROLLER ISSUES. THE CONTROLLER ACTIONS WERE CONSISTENT WITH COMPANY PROTOCOLS. | IH18: NO | II18: NO | IN18: CORROSION FAILURE | IO18: EXTERNAL CORROSION | IP18: EXTERNAL CORROSION | IQ18: GENERAL CORROSION | IU18: YES | IV18: YES | IZ18: DIRECT CURRENT | JA18: ADJACENT PARALLEL PIPELINE | JC18: YES | JF18: YES | JG18: YES | JH18: 1981 | JI18: YES | JJ18: NO | JS18: NO | QW18: NO | TI18: YES | TJ18: 2024 | TK18: 1550 | TL18: Yes, and an investigative dig was cunducted at the point of the Accident | TM18: 2024 | TO18: 2023 | TP18: 2023 | TU18: YES | TV18: YES | TZ18: YES | UC18: 2023 | UJ18: YES | WL18: TOBY PITTMAN | WM18: SR. SPECIALIST DOT COMPLIANCE | WN18: toby.pittman@energytransfer.com | WO18: 432-423-2069 | WT18: JUSTIN DAVIDSON | WU18: MANAGER DOT COMPLIANCE | WV18: 713-989-5231 | WW18: justin.davidson@energytransfer.com | WX18: ON JULY 15, 2024, A RUPTURE OCCURRED ON ENERGY TRANSFER COMPANYS K TO COYA 24-INCH PIPELINE LOCATED APPROXIMATELY 15 MILES SOUTHWEST OF MONAHANS, TX. AT 3:30 A.M. SUPERVISORY CONTROL AND DATA ACQUISITION (SCADA) SYSTEM ALERTED THE COYANOSA GAS PLANT OPERATOR OF A LOSS OF PRESSURE. AT 4:40 A.M. THE PIPELINE OPERATOR ARRIVED ON LOCATION TO FIND LOCAL FIRST RESPONDERS WERE ALREADY ON SCENE BATTLING A FIRE. THE EMERGENCY PERSONNEL HAD BEEN NOTIFIED OF THE FIRE BY A THIRD PARTY. AT 5:20 A.M. THE AFFECTED PIPELINE WAS ISOLATED, AND THE FIRE HAD BURNED OUT, ENERGY TRANSFER PERSONNEL WERE ABLE TO CONFIRM THE DISCOVERY OF A RUPTURE ON THE K TO COYA 24. IT WAS DETERMINED THE REPAIRS AND DAMAGES WOULD EXCEED THE $145,400.00 REPORTABLE DOLLAR CRITERIA AND THE NRC AND THE TXRRC WERE NOTIFIED. THE LOCAL FIRE DEPARTMENT ALLOWED THE FIRE TO BURN ITSELF OUT. THE CAUSE OF THE RUPTURE IS STILL UNDER INVESTIGATION. THE CAUSE OF THE RUPTURE WAS IDENTIFIED AS EXTERNAL CORROSION OCCURRING ALONG THE 3:00 OCLOCK SIDE OF THE PIPE. THE THINNEST MEASURED REMAINING WALL THICKNESS WAS DETERMINED TO BE 0.020-INCH (7% OF THE NOMINAL WALL THICKNESS). OTHER AREAS OF CORROSION PRESENT ON THE PIPE MATERIAL PROVIDED APPEARED CONSISTENT WITH DC INTERFERENCE CURRENT CORROSION AND UNDER DEPOSIT CORROSION. PLAN TO PREVENT RECURRENCE, OPERATIONS WILL INSTALL MORE CP TEST STATIONS TO HELP LOCATE EXTERNAL CORROSION TROUBLE AREAS AND INSTALL MORE RECTIFIERS TO IMPRESS CURRENT EQUALLY OVER THE ENTIRETY OF THE PIPELINE. OPERATIONS WILL ALSO UTILIZE CORROSION COUPONS AND CHEMICAL INJECTION TO MONITOR AND MITIGATE ANY INTERNAL CORROSION.
A19: 110 | B19: 45505 | C19: 2024 | D19: 20240096 | E19: 40324 | F19: SUPPLEMENTAL FINAL | G19: 32099 | H19: ENERGY TRANSFER COMPANY | I19: 1300 MAIN STREET | J19: HOUSTON | K19: TX | L19: 77002 | M19: 45475.238 | N19: CENTRAL | O19: YES | P19: 31.274113 | Q19: -103.07155 | R19: 1403567 | S19: 45475.256 | T19: 1403750 | U19: NATURAL GAS | W19: 132 | X19: 0 | Y19: 0 | Z19: NO | AF19: 0 | AG19: NO | AM19: 0 | AN19: NORMAL OPERATION, INCLUDES PAUSES DURING MAINTENANCE | AO19: YES | AQ19: 45475.222 | AR19: 45478.438 | AT19: YES | AU19: OPERATOR | AV19: 45475.222 | AW19: YES | AX19: 45475.222 | AY19: LOCAL/STATE/FEDERAL EMERGENCY RESPONDER | BA19: 132 | BB19: NO | BI19: 0 | BJ19: 45475.222 | BK19: 45475.243 | BL19: 45475.222 | BM19: ONSHORE | BN19: TX | BO19: 79730 | BP19: COYANOSA | BQ19: PECOS | BR19: NOT APPLICABLE | BT19: OASIS WAHA COMPRESSOR STATION | BU19: OASIS WAHA COMPRESSOR STATION | BV19: NO | BW19: OPERATOR-CONTROLLED PROPERTY | BX19: ABOVEGROUND | BY19: OTHER | BZ19: COMPRESSOR UNIT | CC19: NO | CZ19: INTRASTATE | DA19: ONSHORE COMPRESSOR STATION EQUIPMENT AND PIPING | DB19: COMPRESSOR | EO19: 1962 | EP19: 1962 | EQ19: CARBON STEEL | ES19: OTHER | FB19: NO LEAK, COMPRESSOR FUEL GAS WAS CONSUMED BY FIRE | FC19: CLASS 1 LOCATION | FD19: NO | FF19: 75 | FH19: NO | FI19: NO | FL19: NO | FO19: 0 | FP19: 306 | FQ19: 0 | FR19: 1495000 | FS19: 5000 | FT19: 0 | FV19: 2.32 | FW19: 1500306 | FX19: 0 | FY19: 0 | FZ19: 0 | GA19: 0 | GB19: NO | GF19: 1026 | GG19: 512 | GH19: 1050 | GI19: 192.619(A)(1) | GK19: 22647 | GL19: NO | GM19: PRESSURE DID NOT EXCEED MAOP | GN19: NO | GQ19: NO | HK19: TRANSMISSION SYSTEM | HL19: YES | HM19: YES | HN19: YES | HO19: YES | HP19: YES | HQ19: SCADA-BASED INFORMATION (SUCH AS ALARM(S), ALERT(S), EVENT(S), AND/OR VOLUME OR PACK CALCULATIONS) | HT19: NO, THE OPERATOR DID NOT FIND THAT AN INVESTIGATION OF THE CONTROLLER(S) ACTIONS OR CONTROL ROOM ISSUES WAS NECESSARY DUE TO: (PROVIDE AN EXPLANATION FOR WHY THE OPERATOR DID NOT INVESTIGATE) | HU19: INVESTIGATION IDENTIFIED NO CONTROLLER ISSUES. CONTROLLER ACTIONS WERE CONSISTENT WITH COMPANY PROTOCOLS. | IH19: NO | II19: NO | IN19: EQUIPMENT FAILURE | IO19: COMPRESSOR OR COMPRESSOR-RELATED EQUIPMENT | OU19: COMPRESSOR OR COMPRESSOR-RELATED EQUIPMENT | PI19: OTHER | PJ19: BOLTS (SEE PART H NARRATIVE) | QE19: YES | QF19: FATIGUE | WL19: CHRIS PALAFOX | WM19: SR. SPECIALIST DOT COMPLIANCE | WN19: christopher.palafox@energytransfer.com | WO19: 325-933-3577 | WT19: JUSTIN DAVIDSON | WU19: MANAGER DOT COMPLIANCE | WV19: 713-882-0590 | WW19: justin.davidson@energytransfer.com | WX19: ON JULY 2, 2024, A FIRE OCCURRED AT THE OASIS WAHA COMPRESSOR STATION, 2.26 MILES NORTH OF COYANOSA, TEXAS IN PECOS COUNTY. AT APPROXIMATELY 0500 SCADA NOTIFIED OPERATIONS ABOUT A UNIT DOWN ON FIRE DETECTION. 0520, IT WAS DISCOVERED THAT COMPRESSOR UNITS 3 & 4 WERE ON FIRE, ESDD THE STATION AND CALLED THE LOCAL FIRE DEPARTMENT TO THE STATION. AT 0543, IT WAS DETERMINED THE REPAIRS AND DAMAGES WOULD EXCEED THE $145,400.00 REPORTABLE DOLLAR CRITERIA AND THE NRC AND THE TXRRC WAS NOTIFIED. LOCAL FIRE DEPARTMENT EXTINGUISHED THE FIRE. THE DAMAGED COMPRESSORS WERE BYPASSED, AND THE STATION WAS BACK ONLINE ON JULY 5. FUEL GAS AND LINE OIL FUELED THE FIRE. THE CAUSE OF THE FIRE IS STILL UNDER INVESTIGATION. A SUPPLEMENTAL REPORT WILL BE SUBMITTED ONCE INVESTIGATION IS COMPLETE. **DURING THE PHYSICAL INSPECTION THERE WERE ALSO FOUND TO BE BROKEN BOLTS GATHERED FOR ANALYSIS. THE COUPLING COVER BOLT, AS WELL AS A MISSING BOLT FROM THE TURBINE DRAIN FLANGE WERE FOUND ON THE SKID FLOOR. THESE BOLTS WERE ALSO SENT TO METALLURGIST ALSO AND WERE DETERMINED TO HAVE FAILED DUE TO FATIGUE. THE SHEARED BOLT AND STAINING ON THE DRAIN FLANGE SUGGEST A POSSIBLE ROOT CAUSE OF THE FIRE. THE FAILURE OF THE FLANGE AS AN OIL SEALING MECHANISM WOULD LEAD TO OIL DRAINING DIRECTLY ONTO THE EXHAUST BLANKET LEADING TO VAPORIZATION AND IGNITION OF THE OIL. THIS WAS AN ISOLATED INCIDENT. THE MITIGATION STEPS TO PREVENT THIS FROM OCCURRING IN THE FUTURE ARE AS FOLLOWED: -EVALUATE FIRE EYES/GAS DETECTOR PLACEMENT ON THESE PACKAGES. -CHANGE FASTENERS ON ENGINE SWINGS. -COORDINATE AN EVALUATION OF ALL UNITS TO CONFIRM NO MISSING/BROKEN FASTENERS, THIS IS NOW INCLUDED IN OUR 4000-HOUR PREVENTATIVE MAINTENANCE PLAN.
A20: 114 | B20: 45488 | C20: 2024 | D20: 20240090 | E20: 39834 | F20: SUPPLEMENTAL FINAL | G20: 32099 | H20: ENERGY TRANSFER COMPANY | I20: 1300 MAIN STREET | J20: HOUSTON | K20: TX | L20: 77002 | M20: 45459.083 | N20: CENTRAL | O20: YES | P20: 29.441306 | Q20: -95.292957 | R20: 1402033 | S20: 45459.337 | T20: 1402044 1402224 | U20: NATURAL GAS | W20: 3432 | X20: 3194 | Y20: 0 | Z20: NO | AF20: 0 | AG20: NO | AM20: 0 | AN20: NORMAL OPERATION, INCLUDES PAUSES DURING MAINTENANCE | AO20: YES | AQ20: 45459.544 | AR20: 45459.92 | AT20: YES | AU20: OPERATOR | AV20: 45459.276 | AW20: NO | BI20: 4 | BJ20: 45459.285 | BK20: 45459.285 | BL20: 45459.396 | BM20: ONSHORE | BN20: TX | BO20: 77511 | BP20: ALVIN | BQ20: BRAZORIA | BR20: NOT APPLICABLE | BT20: 3019 TEXAS CITY JUNCTION/TX CITY LOOP 18-INCH | BU20: COUNTY ROAD 190 FARM TAP (CENTERPOINT) | BV20: NO | BW20: PIPELINE RIGHT-OF-WAY | BX20: ABOVEGROUND | BY20: TYPICAL ABOVEGROUND FACILITY PIPING OR APPURTENANCE | CC20: NO | CZ20: INTRASTATE | DA20: ONSHORE REGULATOR/METERING STATION EQUIPMENT AND PIPING | DB20: PIPE | DC20: PIPE BODY | DD20: 2 | DE20: NO | DF20: 0.218 | DG20: 35000 | DH20: UNKNOWN | DI20: SEAMLESS | DK20: UNKNOWN | DL20: COAL TAR | DN20: UNKNOWN | EO20: 1952 | EP20: UNKNOWN | EQ20: CARBON STEEL | ES20: OTHER | FB20: AN ABOVE-GRADE -DISTRIBUTION LATERAL- (CENTERPOINT) OFF LINE 3019 (ETC PIPELINE) WAS STRUCK AS A RESULT OF A VEHICLE ACCIDENT. THE ABOVE-GRADE DISTRIBUTION CONNECTION WAS SHEARED OFF AT GRADE LEVEL, RESULTING IN NATURAL GAS BLOWING INTO THE ATMOSPHERE FROM ETCS TRANSMISSION PIPELINE. | FC20: CLASS 1 LOCATION | FD20: NO | FF20: 307 | FH20: NO | FI20: NO | FL20: NO | FO20: 1000 | FP20: 7894 | FQ20: 7346 | FR20: 89000 | FS20: 19500 | FT20: 0 | FV20: 2.3 | FW20: 124740 | FX20: 0 | FY20: 0 | FZ20: 0 | GA20: 0 | GB20: NO | GF20: 532 | GG20: 10 | GH20: 545 | GI20: 192.619(A)(1) | GK20: 42145 | GL20: NO | GM20: PRESSURE DID NOT EXCEED MAOP | GN20: NO | GQ20: NO | HK20: TRANSMISSION SYSTEM | HL20: YES | HM20: YES | HN20: YES | HO20: NO | HP20: NO | HQ20: OTHER | HR20: CENTERPOINT GAS COMPANY | HT20: NO, THE OPERATOR DID NOT FIND THAT AN INVESTIGATION OF THE CONTROLLER(S) ACTIONS OR CONTROL ROOM ISSUES WAS NECESSARY DUE TO: (PROVIDE AN EXPLANATION FOR WHY THE OPERATOR DID NOT INVESTIGATE) | HU20: THIS EVENT DID NOT GENERATE ALARMS AS GAS LEAKAGE VENTED TO THE ATMOSPHERE VIA 1-INCH PIPING AT THE CENTERPOINT TAP CONNECTION. ETC'S UPSTREAM OVERPRESSURE DEVICES ADJUSTED FLOW, INCREASING GAS FLOW AND MAINTAINING FLOW RATES AND PRESSURE, AND DID NOT EXCEED SET POINTS THAT WOULD HAVE GENERATED ALARMS. (THE LEAK AND FLOW RATE WAS INSUFFICIENT TO CREATE ALARMS.) | IH20: NO | II20: NO | IN20: OTHER OUTSIDE FORCE DAMAGE | IO20: DAMAGE BY CAR, TRUCK, OR OTHER MOTORIZED VEHICLE/EQUIPMENT NOT ENGAGED IN EXCAVATION | MP20: DAMAGE BY CAR, TRUCK, OR OTHER MOTORIZED VEHICLE/EQUIPMENT NOT ENGAGED IN EXCAVATION | MQ20: THIRD PARTY | NA20: UNKNOWN | NG20: NO | NI20: YES | NJ20: PASSENGER CAR | NK20: ROADWAY | NL20: 20 | NM20: YES | NN20: YES | WL20: MIKE SMITH | WM20: SR. SPECIALIST DOT COMPLIANCE | WN20: mike.smith2@energytransfer.com | WO20: 832-894-4289 | WT20: JUSTIN DAVIDSON | WU20: MANAGER DOT COMPLIANCE | WV20: 7138820590 | WW20: justin.davidson@energytransfer.com | WX20: ON JUNE 16, 2024, AT APPROXIMATELY 6:00 AM, CENTERPOINT NOTIFIED ENERGY TRANSFER (ET) OF A PIPELINE LEAK ON THE RIGHT-OF-WAY LOCATED AT 29.441306 -95.292957. NOTE: CENTERPOINT WAS AWARE OF THE LEAK AS EARLY AS 2:00 AM ON JUNE 16, 2024. ON JUNE 16, 2024, AT 6:37 A.M., ET OPERATION CREWS RESPONDED TO THE EMERGENCY, ASSESSED THE EVENT, AND SUCCESSFULLY ISOLATED THE PIPELINE BY 9:56 A.M. THE BLOWDOWN WAS COMPLETED AT 1:04 PM, JUNE 16, 2024. ON JUNE 16, 2024, CREWS MOVED IN AND BEGAN EXCAVATING PIPELINE 3019, 18-INCH MAINLINE, AND 2-INCH TAP AT 5:20 PM. OPERATIONS CLOSED THE BURIED 2-INCH TAP VALVE THAT SERVICED THE CENTERPOINT FARM TAP. ON JUNE 18, 2024, AT 7:15 AM, ET MADE 48-HOUR FOLLOW-UP NOTIFICATIONS TO THE NRC. GAS LOST: 3.432 MMCF WAS UNINTENTIONAL, AND 3.194 MMCF WAS FROM BLOWDOWN. SUPPLEMENTAL: AT APPROXIMATELY 2:00 A.M. ON JUNE 16, 2024, AN INDIVIDUAL WAS TRAVELING AT A HIGH RATE OF SPEED ON COUNTY ROAD 190. THE INDIVIDUAL LOST CONTROL OF THE VEHICLE, LEFT THE ROAD, AND PLUNGED INTO THE CENTER POINT DISTRIBUTION FARM TAP SERVICED BY ENERGY TRANSFER COMPANY (ETC). AS A RESULT OF THE VEHICLE INCIDENT, THE FARM TAP WAS FRAGMENTED AT GROUND LEVEL, RESULTING IN A RELEASE OF NATURAL GAS FROM ETCS TRANSMISSION PIPELINE. ETC EXPOSED LINE 3019 AND REPLACED THE EXISTING RISER WITH A NEW 2-INCH RISER TO SUPPLY THE CENTER POINT DISTRIBUTION FARM TAP. THE WORK WAS COMPLETED ON JULY 18, 2024, IN CONJUNCTION WITH A SCHEDULED ENCROACHMENT PROJECT.
A21: 120 | B21: 45464 | C21: 2024 | D21: 20240083 | E21: 39707 | F21: ORIGINAL FINAL | G21: 5304 | H21: FLORIDA GAS TRANSMISSION CO | I21: 1300 MAIN STREET | J21: HOUSTON | K21: TX | L21: 77002 | M21: 45443.758 | N21: EASTERN | O21: YES | P21: 28.04385 | Q21: -82.30102 | R21: 1400505 | S21: 45443.842 | T21: 1400709 | U21: NATURAL GAS | W21: 56734 | X21: 0 | Y21: 0 | Z21: NO | AF21: 0 | AG21: NO | AM21: 0 | AN21: NORMAL OPERATION, INCLUDES PAUSES DURING MAINTENANCE | AO21: YES | AQ21: 45443.758 | AR21: 45443.847 | AW21: NO | BI21: 0 | BJ21: 45443.778 | BK21: 45443.814 | BL21: 45443.814 | BM21: ONSHORE | BN21: FL | BO21: 33592 | BP21: THONOTOSASSA | BQ21: HILLSBOROUGH | BR21: NOT APPLICABLE | BT21: COMPRESSOR STATION 27 THONOTOSASSA | BU21: 12-INCH BLOWDOWN DISCHARGE HEADER | BV21: NO | BW21: OPERATOR-CONTROLLED PROPERTY | BX21: ABOVEGROUND | BY21: TYPICAL ABOVEGROUND FACILITY PIPING OR APPURTENANCE | CC21: NO | CZ21: INTERSTATE | DA21: ONSHORE COMPRESSOR STATION EQUIPMENT AND PIPING | DB21: VALVE | EH21: AUXILIARY OR OTHER VALVE | EO21: 2011 | EP21: 2011 | EQ21: CARBON STEEL | ES21: OTHER | FB21: STATION DISCHARGE HEADER BLOWDOWN INADVERTENTLY OPENED. | FC21: CLASS 1 LOCATION | FD21: NO | FF21: 1065 | FH21: NO | FI21: NO | FL21: NO | FO21: 0 | FP21: 156019 | FQ21: 0 | FR21: 200 | FS21: 0 | FT21: 0 | FV21: 2.75 | FW21: 156219 | FX21: 0 | FY21: 0 | FZ21: 0 | GA21: 0 | GB21: NO | GF21: 1100 | GG21: 940000 | GH21: 1333 | GI21: 192.619(A)(2) | GK21: 40634 | GL21: NO | GM21: PRESSURE DID NOT EXCEED MAOP | GN21: NO | GQ21: YES | GR21: YES | HK21: TRANSMISSION SYSTEM | HL21: YES | HM21: YES | HN21: YES | HO21: NO | HP21: NO | HQ21: NOTIFICATION FROM EMERGENCY RESPONDER | HT21: NO, THE OPERATOR DID NOT FIND THAT AN INVESTIGATION OF THE CONTROLLER(S) ACTIONS OR CONTROL ROOM ISSUES WAS NECESSARY DUE TO: (PROVIDE AN EXPLANATION FOR WHY THE OPERATOR DID NOT INVESTIGATE) | HU21: THE INVESTIGATION DID NOT IDENTIFY CONTROLLER ACTION AS A CONTRIBUTING FACTOR. | IH21: NO | II21: NO | IN21: INCORRECT OPERATION | IO21: VALVE LEFT OR PLACED IN WRONG POSITION, BUT NOT RESULTING IN AN OVERPRESSURE | QG21: VALVE LEFT OR PLACED IN WRONG POSITION, BUT NOT RESULTING IN AN OVERPRESSURE | QN21: YES | QO21: NO INDICATORS ON THREE-WAY BALL VALVE TO DIFFERENTIATE BLOCKED, BLOCKED AND VENTED, OR OPEN. | QP21: ROUTINE MAINTENANCE | QQ21: YES | QR21: YES, THEY WERE QUALIFIED FOR THE TASK(S) | WL21: TODD NARDOZZI | WM21: DIRECTOR - DOT COMPLIANCE | WN21: todd.nardozzi@energytransfer.com | WO21: 713-989-7126 | WT21: TODD NARDOZZI | WU21: DIRECTOR - DOT COMPLIANCE | WV21: 713-989-7126 | WW21: todd.nardozzi@energytransfer.com | WX21: ON 05/31/2024 AT 18:12, THE 12-INCH STATION DISCHARGE HEADER BLOWDOWN INADVERTENTLY OPENED RESULTING IN GAS BLOWING AT APPROXIMATELY 1100 PSI FOR 78 MINUTES. A LOCAL EMERGENCY RESPONDER NOTIFIED THE CONTROL CENTER IN HOUSTON, TX. CONTROL CENTER CALLED LOCAL OPERATIONS MANAGEMENT AND AN FGT EMPLOYEE WAS DISPATCHED TO COMPRESSOR STATION 27 THONOTOSASSA AND FOUND THE DISCHARGE BLOWDOWN OPEN. THE EMPLOYEE IMMEDIATELY CLOSED THE MANUAL BLOCK VALVE JUST DOWNSTREAM OF THE AUTOMATIC VALVE. UPON FURTHER INVESTIGATION, THE EMPLOYEE FOUND A THREE-WAY VALVE ON THE ESD LINE IN THE CLOSED POSITION. SEALS IN THE OPERATOR ON THE DISCHARGE BLOWDOWN VALVE HAD BEEN REPLACED ON THE PREVIOUS DAY. THERE ARE TWO VALVES INLINE ON THE ESD SENSING FEED LINE. THE CAUSE OF THE INCIDENT WAS DUE TO A VALVE LEFT OR PLACED IN WRONG POSITION, BUT NOT RESULTING IN AN OVERPRESSURE. REPLACING 3-WAY-SWITCHING VALVE WITH A MANUAL BLOCK VALVE IN LINE WITH A MANUAL BLEED BETWEEN THE TWO BLOCK VALVES TO PREVENT POTENTIAL REOCCURRENCE.
A22: 125 | B22: 45446 | C22: 2024 | D22: 20240072 | E22: 39630 | F22: ORIGINAL FINAL | G22: 26330 | H22: ENABLE OKLAHOMA INTRASTATE TRANSMISSION, LLC | I22: 1300 MAIN STREET | J22: HOUSTON | K22: TX | L22: 77002 | M22: 45431.622 | N22: CENTRAL | O22: YES | P22: 36.282556 | Q22: -95.661771 | R22: 1399401 | S22: 45431.641 | T22: 1399561 | U22: NATURAL GAS | W22: 8475 | X22: 0 | Y22: 0 | Z22: NO | AF22: 0 | AG22: NO | AM22: 0 | AN22: NORMAL OPERATION, INCLUDES PAUSES DURING MAINTENANCE | AO22: NO | AP22: UNIT 427 WAS ISOLATED AND BLOWN DOWN AND UNIT 428 WAS PUT ONLINE IN ITS PLACE. | AT22: NO | AW22: NO | BI22: 0 | BJ22: 45431.569 | BK22: 45431.569 | BL22: 45431.622 | BM22: ONSHORE | BN22: OK | BO22: 74019 | BP22: CLAREMORE | BQ22: ROGERS | BR22: NOT APPLICABLE | BT22: CLAREMORE COMPRESSOR STATION | BU22: LINE 4 | BV22: NO | BW22: OPERATOR-CONTROLLED PROPERTY | BX22: ABOVEGROUND | BY22: TYPICAL ABOVEGROUND FACILITY PIPING OR APPURTENANCE | CC22: NO | CZ22: INTRASTATE | DA22: ONSHORE COMPRESSOR STATION EQUIPMENT AND PIPING | DB22: COMPRESSOR | EO22: UNKNOWN | EP22: UNKNOWN | EQ22: CARBON STEEL | ES22: OTHER | FB22: TUBING ON A RELIEF VALVE FAILED CAUSING THE DISCHARGE RELIEF VALVE ON UNIT 427 TO VENT OUTSIDE TO THE YARD SILENCER. | FC22: CLASS 1 LOCATION | FD22: NO | FF22: 431 | FH22: NO | FI22: NO | FL22: NO | FO22: 0 | FP22: 22035 | FQ22: 0 | FR22: 220 | FS22: 0 | FT22: 0 | FV22: 2.6 | FW22: 22255 | FX22: 0 | FY22: 0 | FZ22: 0 | GA22: 0 | GB22: NO | GF22: 400 | GG22: 150000 | GH22: 1000 | GI22: 192.619(A)(2) | GK22: 35916 | GL22: BI-DIRECTIONAL | GM22: PRESSURE DID NOT EXCEED MAOP | GN22: NO | GQ22: YES | GR22: YES | HK22: TRANSMISSION SYSTEM | HL22: NO | HQ22: NOTIFICATION FROM PUBLIC | HT22: NO, THE OPERATOR DID NOT FIND THAT AN INVESTIGATION OF THE CONTROLLER(S) ACTIONS OR CONTROL ROOM ISSUES WAS NECESSARY DUE TO: (PROVIDE AN EXPLANATION FOR WHY THE OPERATOR DID NOT INVESTIGATE) | HU22: NO ACTIONS BY THE CONTROLLER WERE INVOLVED IN THIS INCIDENT RESULTING IN NO INVESTIGATION OF THE CONTROLLERS' ACTION. THE PRESSURES NEVER MET AN ALARM STATUS SO THAT THE CONTROLLER WOULD NOT HAVE BEEN NOTIFIED. THE FIRST SIGN OF A PROBLEM, TO THE CONTROLLER, WAS A PHONE CALL FROM THE PUBLIC. | IH22: NO | II22: NO | IN22: EQUIPMENT FAILURE | IO22: DEFECTIVE OR LOOSE TUBING OR FITTING | OU22: DEFECTIVE OR LOOSE TUBING OR FITTING | PP22: YES | WB22: YES | WL22: JEFFREY OSBORN | WM22: SENIOR SPECIALIST - DOT COMPLIANCE | WN22: jeff.osborn@energytransfer.com | WO22: 4053807618 | WP22: 4053797281 | WQ22: JEFFREY OSBORN | WR22: jeff.osborn@energytransfer.com | WS22: 4053807618 | WT22: JIMMY CROSS | WU22: SENIOR MANAGER - DOT COMPLIANCE | WV22: 4055576823 | WW22: jimmy.cross@energytransfer.com | WX22: 5/19/24 13:04, OPERATOR RECEIVED A REPORT OF GAS VENTING AT CLAREMORE COMPRESSOR STATION. TECHNICIAN WAS DISPATCHED TO THE STATION TO INVESTIGATE REPORT. ON 5/19/24 AT 13:40, TECHNICIAN ARRIVAL AT THE STATION. TECHNICIAN IDENTIFIED UNIT 427 DISCHARGE RELIEF VALVE VENTING INTO THE YARD SILENCER. AT 14:00, TECHNICIAN NOTIFIED SYSTEM CONTROL OF THE INCIDENT. TECHNICIAN ENTERS THE BUILDING AND TAKES UNIT 427 OFFLINE AND ISOLATED THE UNIT. 14:07, TECHNICIAN NOTIFIED SYSTEM CONTROL OF THE PROBLEM AND INSTRUCTED THEM TO START UP UNIT 428 AND PUT IT ONLINE TO REPLACE UNIT 427. UPON INVESTIGATION OF THE FAILURE, TECHNICIAN IDENTIFIED A TUBING SENSING LINE, THAT WENT TO THE UNIT RELIEF VALVE, HAD FAILED RESULTING IN THE CAUSE OF THE RELIEF VALVE VENTING. AT 14:20, TECHNICIAN STARTED GATHERING DATA TO DETERMINE THE AMOUNT OF GAS LOSS THAT WAS VENTED DURING THIS INCIDENT. AT 14:55, IT WAS DETERMINED THAT THE GAS LOSS FOR THE INCIDENT WAS 8,475 MSCF MAKING THIS A REPORTABLE INCIDENT. AT 15:03, DOT COMPLIANCE WAS NOTIFIED OF THE REPORTABLE INCIDENT. AT 15:23, NOTIFICATION WAS MADE TO THE NATIONAL RESPONSE CENTER (INCIDENT REPORT # 1399561). ON 05/20/24 AT 08:00, TUBING LINE WAS REPLACED (WITH A HIGH-PRESSURE FLEX STEEL LINE TO PREVENT INCIDENT FROM RECURRING AGAIN IN THE FUTURE), RELIEF VALVE WAS RETESTED AND PUT BACK IN SERVICE.
A23: 129 | B23: 45449 | C23: 2024 | D23: 20240079 | E23: 39651 | F23: ORIGINAL FINAL | G23: 602 | H23: ENABLE GAS TRANSMISSION, LLC | I23: 1300 MAIN STREET | J23: HOUSTON | K23: TX | L23: 77002 | M23: 45421.568 | N23: CENTRAL | O23: YES | P23: 33.49613 | Q23: -92.91935 | R23: 1398499 | S23: 45421.583 | T23: 1398644 | U23: NATURAL GAS | W23: 13000 | X23: 1758 | Y23: 0 | Z23: NO | AF23: 0 | AG23: NO | AM23: 0 | AN23: NORMAL OPERATION, INCLUDES PAUSES DURING MAINTENANCE | AO23: YES | AQ23: 45422.017 | AR23: 45422.696 | AT23: NO | AW23: NO | BC23: VALVE CLOSURE | BE23: 45422.021 | BF23: VALVE CLOSURE | BH23: 45422.022 | BI23: 0 | BJ23: 45421.568 | BK23: 45421.568 | BL23: 45421.568 | BM23: ONSHORE | BN23: AR | BO23: 71701 | BP23: Not Within a Municipality | BQ23: OUACHITA | BR23: NOT APPLICABLE | BT23: SM-23 | BU23: SM-23 | BV23: NO | BW23: PIPELINE RIGHT-OF-WAY | BX23: UNDERGROUND | BY23: UNDER SOIL | CA23: 36 | CB23: NO | CC23: NO | CZ23: INTERSTATE | DA23: ONSHORE PIPELINE, INCLUDING VALVE SITES | DB23: PIPE | DC23: PIPE BODY | DD23: 20 | DE23: NO | DF23: 0.25 | DG23: 46000 | DH23: API 5L | DI23: LONGITUDINAL ERW - UNKNOWN FREQUENCY | DK23: UNKNOWN | DL23: COAL TAR | DN23: NO | EO23: 1967 | EP23: UNKNOWN | EQ23: CARBON STEEL | ES23: MECHANICAL PUNCTURE | ET23: 3.6 | EU23: 1.2 | FC23: CLASS 1 LOCATION | FD23: NO | FF23: 390 | FH23: NO | FI23: NO | FL23: NO | FO23: 0 | FP23: 26390 | FQ23: 3569 | FR23: 95055 | FS23: 20353 | FT23: 0 | FV23: 2.03 | FW23: 145367 | FX23: 0 | FY23: 0 | FZ23: 0 | GA23: 0 | GB23: NO | GF23: 550 | GG23: 10 | GH23: 800 | GI23: 192.619(A)(2) | GK23: 24473 | GL23: NO | GM23: PRESSURE DID NOT EXCEED MAOP | GN23: NO | GQ23: YES | GR23: YES | GS23: MANUAL | GT23: MANUAL | GU23: 32736 | GV23: YES | HD23: NO | HK23: TRANSMISSION SYSTEM | HL23: NO | HQ23: NOTIFICATION FROM THIRD PARTY THAT CAUSED THE INCIDENT | HT23: NO, THE OPERATOR DID NOT FIND THAT AN INVESTIGATION OF THE CONTROLLER(S) ACTIONS OR CONTROL ROOM ISSUES WAS NECESSARY DUE TO: (PROVIDE AN EXPLANATION FOR WHY THE OPERATOR DID NOT INVESTIGATE) | HU23: NO SCADA ON THIS PARTICULAR PIPELINE SEGMENT. INCIDENT WAS CALLED IN BY THIRD PARTY. | IH23: NO | II23: NO | IN23: EXCAVATION DAMAGE | IO23: EXCAVATION DAMAGE BY THIRD PARTY | LB23: EXCAVATION DAMAGE BY THIRD PARTY | LC23: NO | LH23: NO | LM23: YES | LR23: YES | LX23: NO | LY23: NO | LZ23: 18î ñ 36î | MB23: CONTRACTOR | MC23: BULLDOZER | MD23: GRADING | ME23: NO | MI23: UNKNOWN/OTHER | MJ23: NO | MK23: YES | ML23: 24 | MM23: NOTIFICATION ISSUE | MN23: NO NOTIFICATION MADE TO THE ONE-CALL CENTER/811 | WL23: DANIEL ANTOINE | WM23: SR. DOT SPECIALIST | WN23: daniel.antoine@energytransfer.com | WO23: 501-351-8513 | WQ23: MATT GREENE | WR23: matthew.greene@energytransfer.com | WS23: 870-703-0482 | WT23: SUSIE SJULIN | WU23: DIRECTOR REGULATORY COMPLIANCE | WV23: 405-557-5271 | WW23: susie.sjulin@energytransfer.com | WX23: ON THURSDAY, MAY 9TH AT APPROXIMATELY 1:25PM CENTRAL TIME, EMMET OPERATIONS RECEIVED A CALL FROM A THIRD PARTY ABOUT A POSSIBLE LINE STRIKE WITH A GAS RELEASE. AT 1:38PM, OPERATIONS PERSONNEL CONFIRMED THAT A THIRD PARTY HAD STRUCK LINE SM-23 WITH A BULLDOZER CAUSING A GAS RELEASE. NO ONE WAS INJURED AND THE GAS DID NOT IGNITE. AN OPERATIONS TECHNICIAN REMAINED ON SITE TO MONITOR THE RELEASE WHILE ONE TECHNICIAN WENT TO THE UPSTREAM VALVE SITE AND ANOTHER TECHNICIAN MOBILIZED TO THE DOWNSTREAM VALVE SITE. PRESSURE AT THE TIME OF THE STRIKE WAS 550PSIG; PRESSURE WAS LOWERED TO 350PSIG AND MONITORED. THE DECISION TO MONITOR PRESSURE WAS MADE TO AVOID SIGNIFICANT OUTAGES TO RESIDENTIAL CUSTOMERS. ONCE CUSTOMER NOTIFICATIONS WERE FINALIZED, THE PIPELINE WAS SHUNT IN AND BLOWN DOWN. A TYPE B SLEEVE WAS INSTALLED OVER THE DEFECT AND THE PIPELINE WAS PURGED AND RETURNED TO SERVICE ON FRIDAY MAY 10TH AT APPROXIMATELY 4:40PM CENTRAL TIME. THE PIPELINE WAS STRUCK BY A THIRD PARTY LOGGING COMPANY. THE CONTRACTORS WORKING FOR THE LOGGING COMPANY DID NOT COMPLETE A ONE CALL AND WERE NOT AUTHORIZED TO PERFORM WORK ON THE SM-23 RIGHT OF WAY.
A24: 135 | B24: 45441 | C24: 2024 | D24: 20240070 | E24: 39996 | F24: SUPPLEMENTAL FINAL | G24: 19730 | H24: TRUNKLINE GAS CO | I24: 1300 MAIN STREET | J24: HOUSTON | K24: TX | L24: 77002 | M24: 45412.744 | N24: CENTRAL | O24: YES | P24: 30.59601 | Q24: -93.227044 | R24: 1397797 | S24: 45413.687 | T24: 1397850 | U24: NATURAL GAS | W24: 67680 | X24: 0 | Y24: 0 | Z24: NO | AF24: 0 | AG24: NO | AM24: 0 | AN24: NORMAL OPERATION, INCLUDES PAUSES DURING MAINTENANCE | AO24: YES | AQ24: 45412.774 | AR24: 45412.917 | AT24: YES | AU24: OPERATOR | AV24: 45412.771 | AW24: NO | BI24: 0 | BJ24: 45412.744 | BK24: 45412.753 | BL24: 45412.753 | BM24: ONSHORE | BN24: LA | BO24: 70652 | BP24: LONGVILLE | BQ24: BEAUREGARD | BR24: NOT APPLICABLE | BT24: LONGVILLE COMPRESSOR STATION | BU24: 100-2 36-INCH | BV24: NO | BW24: OPERATOR-CONTROLLED PROPERTY | BX24: ABOVEGROUND | BY24: TYPICAL ABOVEGROUND FACILITY PIPING OR APPURTENANCE | CC24: NO | CZ24: INTERSTATE | DA24: ONSHORE COMPRESSOR STATION EQUIPMENT AND PIPING | DB24: VALVE | EH24: MAINLINE | EI24: PLUG | EK24: UNKNOWN | EO24: UNKNOWN | EP24: UNKNOWN | EQ24: CARBON STEEL | ES24: OTHER | FB24: MAINLINE FIRE GATE VALVE FAILED TO SEAL CLOSED | FC24: CLASS 1 LOCATION | FD24: NO | FF24: 805 | FH24: NO | FI24: NO | FL24: NO | FO24: 0 | FP24: 98813 | FQ24: 0 | FR24: 1000 | FS24: 0 | FT24: 0 | FV24: 1.46 | FW24: 99813 | FX24: 0 | FY24: 0 | FZ24: 0 | GA24: 0 | GB24: NO | GF24: 785 | GG24: 1200000 | GH24: 1050 | GI24: 192.619(A)(1) | GK24: 39363 | GL24: NO | GM24: PRESSURE DID NOT EXCEED MAOP | GN24: NO | GQ24: NO | HK24: TRANSMISSION SYSTEM | HL24: YES | HM24: YES | HN24: YES | HO24: YES | HP24: YES | HQ24: SCADA-BASED INFORMATION (SUCH AS ALARM(S), ALERT(S), EVENT(S), AND/OR VOLUME OR PACK CALCULATIONS) | HT24: YES, SPECIFY INVESTIGATION RESULT(S): (SELECT ALL THAT APPLY) | HZ24: YES | IH24: NO | II24: NO | IN24: EQUIPMENT FAILURE | IO24: MALFUNCTION OF CONTROL/RELIEF EQUIPMENT | OU24: MALFUNCTION OF CONTROL/RELIEF EQUIPMENT | OZ24: YES | QE24: YES | QF24: FAULTY WIRE ON GAS DETECTION SYSTEM | WL24: PEGGY WEST | WM24: LEAD SPECIALIST DOT COMPLIANCE | WN24: peggy.west@energytransfer.com | WO24: 409-202-3088 | WT24: JUSTIN DAVIDSON | WU24: MANAGER - DOT COMPLIANCE | WV24: 713-989-5231 | WW24: justin.davidson@energytransfer.com | WX24: ON APRIL 30, 2024 AT APPROXIMATELY 5:52 PM, GAS CONTROL RECEIVED AN ALARM AND DISPATCHED ETE PERSONNEL TO THE LONGVILLE COMPRESSOR STATION. ETE FOUND THE ESD SYSTEM HAD BEEN SET OFF AND THE STATION WAS BLOWING GAS. MAIN FIRE GATE VALVE DID NOT SEAL OFF AND CONTINUED TO BLOW GAS FOR AN ADDITIONAL FORTY-THREE MINUTES UNTIL EMPLOYEES DETERMINED WHICH FIRE GATE VALVE WAS CAUSING THE STATION NOT TO BLOW DOWN. IT WAS DETERMINED THAT THE ESD SYSTEM WAS TRIGGERED BY A FAULTY WIRE CAUSED THE GAS DETECTION SYSTEM TO THE SOUTH GAS DETECTOR ON 4509 TO INDICATE A FALSE READING WITH UP TO 50% LEL AND OVER RANGE. AFTER FURTHER INVESTIGATION, IT WAS DETERMINED AT 4:15 PM ON MAY 1, 2024 APPROXIMATELY 67.68 MMSCF OF NATURAL GAS WAS RELEASED TO THE ATMOSPHERE. MAIN FIRE GATE PLUG VALVE WAS DISASSEMBLED, INSPECTED, REASSEMBLED AND GREASED, TESTED FOR FUNCTIONALITY AND SEALING OFF AGAINST POSITIVE PRESSURE. EQUIPMENT WAS RETURNED TO SERVICE. SUPPLEMENTAL/FINAL -UPDATED TIME IN A4 & A16A -UPDATED C3 TO VALVE
A25: 142 | B25: 45428 | C25: 2024 | D25: 20240058 | E25: 39560 | F25: ORIGINAL | G25: 40069 | H25: STINGRAY PIPELINE COMPANY, LLC | I25: 1300 MAIN STREET | J25: HOUSTON | K25: TX | L25: 77002 | M25: 45402.646 | N25: CENTRAL | O25: YES | P25: 28.321389 | Q25: -93.253611 | R25: 1396923 | S25: 45402.682 | T25: 1397013 | U25: NATURAL GAS | W25: 0 | X25: 1290 | Y25: 0 | Z25: NO | AF25: 0 | AG25: NO | AM25: 0 | AN25: IDLE | AT25: YES | AU25: OPERATOR | AV25: 45402.646 | AW25: NO | BC25: VALVE CLOSURE | BE25: 44619.708 | BF25: VALVE CLOSURE | BH25: 44790.365 | BI25: 0 | BJ25: 45402.646 | BK25: 45402.646 | BL25: 45402.646 | BM25: OFFSHORE | BT25: STINGRAY PIPELINE | BU25: LINE 1004C-100 30-INCH (3394) | CP25: 185 | CQ25: ON THE OUTER CONTINENTAL SHELF (OCS) | CV25: OCS-GULF OF MEXICO | CW25: WEST CAMERON | CX25: 538 | CY25: BELOW WATER, PIPE BURIED OR JETTED BELOW SEABED | CZ25: INTERSTATE | DA25: OFFSHORE PIPELINE, INCLUDING RISER AND RISER BEND | DB25: PIPE | DC25: PIPE BODY | DD25: 30 | DE25: NO | DF25: 0.562 | DG25: 60000 | DH25: X-60 | DI25: DSAW | DK25: U.S. STEEL | DL25: OTHER | DM25: CONCRETE | DN25: UNKNOWN | EO25: 1975 | EP25: 1975 | EQ25: CARBON STEEL | ES25: LEAK | EV25: PINHOLE | FC25: CLASS 1 LOCATION | FD25: NO | FF25: 717 | FH25: NO | FI25: NO | FL25: NO | FO25: 0 | FP25: 0 | FQ25: 1871 | FR25: 750000 | FS25: 0 | FT25: 0 | FV25: 1.45 | FW25: 751871 | FX25: 0 | FY25: 0 | FZ25: 0 | GA25: 0 | GB25: NO | GF25: 155 | GG25: 0 | GH25: 1200 | GI25: 192.619(A)(1) | GK25: 27456 | GL25: NO | GM25: PRESSURE DID NOT EXCEED MAOP | GN25: NO | GQ25: NO | GS25: MANUAL | GT25: MANUAL | GU25: 318991 | GV25: YES | HD25: YES | HI25: YES | HJ25: LAUNCHER IS SUBSEA | HK25: OFFSHORE GATHERING | HL25: YES | HM25: YES | HN25: YES | HO25: NO | HP25: NO | HQ25: LOCAL OPERATING PERSONNEL, INCLUDING CONTRACTORS | HS25: CONTRACTOR WORKING FOR THE OPERATOR | HT25: NO, THE OPERATOR DID NOT FIND THAT AN INVESTIGATION OF THE CONTROLLER(S) ACTIONS OR CONTROL ROOM ISSUES WAS NECESSARY DUE TO: (PROVIDE AN EXPLANATION FOR WHY THE OPERATOR DID NOT INVESTIGATE) | HU25: INCIDENT DUE TO A SMALL PINHOLE AND WAS TOO SMALL FOR SCADA TO DETECT | IH25: NO | II25: NO | IN25: OTHER INCIDENT CAUSE | IO25: UNKNOWN | QS25: UNKNOWN | QU25: STILL UNDER INVESTIGATION, CAUSE OF INCIDENT TO BE DETERMINED* (*SUPPLEMENTAL REPORT REQUIRED) | WL25: PEGGY WEST | WM25: SENIOR SPECIALIST - DOT COMPLIANCE | WN25: peggy.west@energytransfer.com | WO25: 409-202-3088 | WT25: JUSTIN DAVIDSON | WU25: MANAGER - DOT COMPLIANCE | WV25: 713-989-5231 | WW25: justin.davidson@energytransfer.com | WX25: ON 4/20/24 AT APPROXIMATELY 15:30 WHILE ADDING PRESSURE TO THE PIPELINE IN ORDER TO LOCATE A LEAK POINT FROM 02/02/24, A SHEEN WAS SPOTTED IN WC 538 BY THE OVERFLIGHT. OVERFLIGHTS ARE BEING CONDUCTED DAILY AND CURRENTLY THERE IS NO SHEEN OR BUBBLES BEING RELEASED. THE FOLLOWING INFORMATION WAS GIVEN TO BRYAN LETHCOE, ANTHONY WRIGHT AND GERY BAUMAN FOR THE FOUR SHEENS FOUND DURING THE REPAIR OF LEAK 7: -LEAK 7 DISCOVERED IN FEBRUARY -LINE PRESSURE WAS LOWERED FROM 125-150PSIG TO BELOW BOTTOM PRESSURE TO STOP LEAK -DSV DEPLOYMENT WAS DELAYED DUE TO OTHER COMMITMENTS AND WEATHER CONDITIONS -ONCE DSV WAS AVAILABLE LINE PRESSURE WAS INCREASED IN ORDER TO LOCATE LEAK 7 -2X DAILY OVERFLIGHTS NOTED SEPARATE SHEENS AND AREA OF SURFACE BUBBLES AFTER PRESSURE WAS INCREASED. --3 SHEENS --1 AREA OF BUBBLES -DSV CREW POSITIVELY IDENTIFIED LEAK 7 -PRESSURE WAS PULLED DOWN BELOW 70PSIG TO STOP OTHER 4 LEAKS --THESE 4 ADDITIONAL LEAKS HAVE NOT BEEN POSITIVELY LOCATED --SHEENS ARE SHRINKING --OVERFLIGHTS CONTINUE -CLAMP INSTALLED ON LEAK 7 -LEAKS ARE BEING EVALUATED AND FUTURE USE OF LINE TO BE DETERMINED -PRESSURE IS CURRENTLY BE MAINTAINED BELOW 50 PSI
A26: 143 | B26: 45428 | C26: 2024 | D26: 20240057 | E26: 39559 | F26: ORIGINAL | G26: 40069 | H26: STINGRAY PIPELINE COMPANY, LLC | I26: 1300 MAIN STREET | J26: HOUSTON | K26: TX | L26: 77002 | M26: 45402.646 | N26: CENTRAL | O26: YES | P26: 28.308333 | Q26: -93.271389 | R26: 1396924 | S26: 45402.685 | T26: 1397015 | U26: NATURAL GAS | W26: 0 | X26: 1290 | Y26: 0 | Z26: NO | AF26: 0 | AG26: NO | AM26: 0 | AN26: IDLE | AT26: YES | AU26: OPERATOR | AV26: 45402.646 | AW26: NO | BC26: VALVE CLOSURE | BE26: 44619.708 | BF26: VALVE CLOSURE | BH26: 44790.365 | BI26: 0 | BJ26: 45402.646 | BK26: 45402.646 | BL26: 45402.646 | BM26: OFFSHORE | BT26: STINGRAY PIPELINE | BU26: LINE 1004C-100 30-INCH (3394) | CP26: 185 | CQ26: ON THE OUTER CONTINENTAL SHELF (OCS) | CV26: OCS-GULF OF MEXICO | CW26: WEST CAMERON | CX26: 550 | CY26: BELOW WATER, PIPE BURIED OR JETTED BELOW SEABED | CZ26: INTERSTATE | DA26: OFFSHORE PIPELINE, INCLUDING RISER AND RISER BEND | DB26: PIPE | DC26: PIPE BODY | DD26: 30 | DE26: NO | DF26: 0.562 | DG26: 60000 | DH26: X-60 | DI26: DSAW | DK26: U.S. STEEL | DL26: OTHER | DM26: CONCRETE | DN26: UNKNOWN | EO26: 1975 | EP26: 1975 | EQ26: CARBON STEEL | ES26: LEAK | EV26: PINHOLE | FC26: CLASS 1 LOCATION | FD26: NO | FF26: 717 | FH26: NO | FI26: NO | FL26: NO | FO26: 0 | FP26: 0 | FQ26: 1871 | FR26: 750000 | FS26: 0 | FT26: 0 | FV26: 1.45 | FW26: 751871 | FX26: 0 | FY26: 0 | FZ26: 0 | GA26: 0 | GB26: NO | GF26: 155 | GG26: 0 | GH26: 1200 | GI26: 192.619(A)(1) | GK26: 27456 | GL26: NO | GM26: PRESSURE DID NOT EXCEED MAOP | GN26: NO | GQ26: NO | GS26: MANUAL | GT26: MANUAL | GU26: 318991 | GV26: YES | HD26: YES | HI26: YES | HJ26: LAUNCHER IS SUBSEA | HK26: OFFSHORE GATHERING | HL26: YES | HM26: YES | HN26: YES | HO26: NO | HP26: NO | HQ26: LOCAL OPERATING PERSONNEL, INCLUDING CONTRACTORS | HS26: CONTRACTOR WORKING FOR THE OPERATOR | HT26: NO, THE OPERATOR DID NOT FIND THAT AN INVESTIGATION OF THE CONTROLLER(S) ACTIONS OR CONTROL ROOM ISSUES WAS NECESSARY DUE TO: (PROVIDE AN EXPLANATION FOR WHY THE OPERATOR DID NOT INVESTIGATE) | HU26: INCIDENT DUE TO A SMALL PINHOLE AND WAS TOO SMALL FOR SCADA TO DETECT | IH26: NO | II26: NO | IN26: OTHER INCIDENT CAUSE | IO26: UNKNOWN | QS26: UNKNOWN | QU26: STILL UNDER INVESTIGATION, CAUSE OF INCIDENT TO BE DETERMINED* (*SUPPLEMENTAL REPORT REQUIRED) | WL26: PEGGY WEST | WN26: peggy.west@energytransfer.com | WO26: 409-202-3088 | WT26: JUSTIN DAVIDSON | WU26: MANAGER - DOT COMPLIANCE | WV26: 713-989-5231 | WW26: justin.davidson@energytransfer.com | WX26: ON 4/20/24 AT APPROXIMATELY 15:30 WHILE ADDING PRESSURE TO THE PIPELINE IN ORDER TO LOCATE A LEAK POINT FROM 02/02/24, A SHEEN WAS SPOTTED IN WC 550 BY THE OVERFLIGHT. OVERFLIGHTS ARE BEING CONDUCTED DAILY AND CURRENTLY THERE IS NO SHEEN OR BUBBLES BEING RELEASED. THE FOLLOWING INFORMATION WAS GIVEN TO BRYAN LETHCOE, ANTHONY WRIGHT AND GERY BAUMAN FOR THE FOUR SHEENS FOUND DURING THE REPAIR OF LEAK 7: -LEAK 7 DISCOVERED IN FEBRUARY -LINE PRESSURE WAS LOWERED FROM 125-150PSIG TO BELOW BOTTOM PRESSURE TO STOP LEAK -DSV DEPLOYMENT WAS DELAYED DUE TO OTHER COMMITMENTS AND WEATHER CONDITIONS -ONCE DSV WAS AVAILABLE LINE PRESSURE WAS INCREASED IN ORDER TO LOCATE LEAK 7 -2X DAILY OVERFLIGHTS NOTED SEPARATE SHEENS AND AREA OF SURFACE BUBBLES AFTER PRESSURE WAS INCREASED. --3 SHEENS --1 AREA OF BUBBLES -DSV CREW POSITIVELY IDENTIFIED LEAK 7 -PRESSURE WAS PULLED DOWN BELOW 70PSIG TO STOP OTHER 4 LEAKS --THESE 4 ADDITIONAL LEAKS HAVE NOT BEEN POSITIVELY LOCATED --SHEENS ARE SHRINKING --OVERFLIGHTS CONTINUE -CLAMP INSTALLED ON LEAK 7 -LEAKS ARE BEING EVALUATED AND FUTURE USE OF LINE TO BE DETERMINED -PRESSURE IS CURRENTLY BE MAINTAINED BELOW 50 PSI
A27: 144 | B27: 45428 | C27: 2024 | D27: 20240060 | E27: 39562 | F27: ORIGINAL | G27: 40069 | H27: STINGRAY PIPELINE COMPANY, LLC | I27: 1300 MAIN STREET | J27: HOUSTON | K27: TX | L27: 77002 | M27: 45402.393 | N27: CENTRAL | O27: YES | P27: 28.293056 | Q27: -93.314444 | R27: 1396895 | S27: 45402.429 | T27: 1397012 | U27: NATURAL GAS | W27: 0 | X27: 1290 | Y27: 0.53 | Z27: NO | AF27: 0 | AG27: NO | AM27: 0 | AN27: IDLE | AT27: YES | AU27: OPERATOR | AV27: 45402.393 | AW27: NO | BC27: VALVE CLOSURE | BE27: 44619.708 | BF27: VALVE CLOSURE | BH27: 44790.365 | BI27: 0 | BJ27: 45402.393 | BK27: 45402.393 | BL27: 45402.393 | BM27: OFFSHORE | BT27: STINGRAY PIPELINE | BU27: LINE 1004C-100 30-INCH | CP27: 185 | CQ27: ON THE OUTER CONTINENTAL SHELF (OCS) | CV27: OCS-GULF OF MEXICO | CW27: WEST CAMERON | CX27: 550 | CY27: BELOW WATER, PIPE BURIED OR JETTED BELOW SEABED | CZ27: INTERSTATE | DA27: OFFSHORE PIPELINE, INCLUDING RISER AND RISER BEND | DB27: PIPE | DC27: PIPE BODY | DD27: 30 | DE27: NO | DF27: 0.562 | DG27: 60000 | DH27: X-60 | DI27: DSAW | DK27: U.S. STEEL | DL27: OTHER | DM27: CONCRETE | DN27: UNKNOWN | EO27: 1975 | EP27: 1975 | EQ27: CARBON STEEL | ES27: LEAK | EV27: PINHOLE | FC27: CLASS 1 LOCATION | FD27: NO | FF27: 717 | FH27: NO | FI27: NO | FL27: NO | FO27: 0 | FP27: 0 | FQ27: 0 | FR27: 750000 | FS27: 0 | FT27: 0 | FV27: 1.45 | FW27: 750000 | FX27: 0 | FY27: 0 | FZ27: 0 | GA27: 0 | GB27: NO | GF27: 155 | GG27: 0 | GH27: 1200 | GI27: 192.619(A)(1) | GK27: 27456 | GL27: NO | GM27: PRESSURE DID NOT EXCEED MAOP | GN27: NO | GQ27: NO | GS27: MANUAL | GT27: MANUAL | GU27: 318991 | GV27: YES | HD27: YES | HI27: YES | HJ27: LAUNCHER IS SUBSEA | HK27: OFFSHORE GATHERING | HL27: YES | HM27: YES | HN27: YES | HO27: NO | HP27: NO | HQ27: LOCAL OPERATING PERSONNEL, INCLUDING CONTRACTORS | HS27: CONTRACTOR WORKING FOR THE OPERATOR | HT27: NO, THE OPERATOR DID NOT FIND THAT AN INVESTIGATION OF THE CONTROLLER(S) ACTIONS OR CONTROL ROOM ISSUES WAS NECESSARY DUE TO: (PROVIDE AN EXPLANATION FOR WHY THE OPERATOR DID NOT INVESTIGATE) | HU27: INCIDENT DUE TO A SMALL PINHOLE AND WAS TOO SMALL FOR SCADA TO DETECT | IH27: NO | II27: NO | IN27: OTHER INCIDENT CAUSE | IO27: UNKNOWN | QS27: UNKNOWN | QU27: STILL UNDER INVESTIGATION, CAUSE OF INCIDENT TO BE DETERMINED* (*SUPPLEMENTAL REPORT REQUIRED) | WL27: PEGGY WEST | WM27: SENIOR SPECIALIST - DOT COMPLIANCE | WN27: peggy.west@energytransfer.com | WO27: 409-202-3088 | WT27: JUSTIN DAVIDSON | WU27: MANAGER - DOT COMPLIANCE | WV27: 713-989-5231 | WW27: justin.davidson@energytransfer.com | WX27: ON 4/20/24 AT APPROXIMATELY 09:26 WHILE ADDING PRESSURE TO THE PIPELINE IN ORDER TO LOCATE A LEAK POINT FROM 02/02/24, A SHEEN WAS SPOTTED IN WC 550 BY THE OVERFLIGHT. OVERFLIGHTS ARE BEING CONDUCTED DAILY AND CURRENTLY THERE IS NO SHEEN OR BUBBLES BEING RELEASED. THE FOLLOWING INFORMATION WAS GIVEN TO BRYAN LETHCOE, ANTHONY WRIGHT AND GERY BAUMAN FOR THE FOUR SHEENS FOUND DURING THE REPAIR OF LEAK 7: -LEAK 7 DISCOVERED IN FEBRUARY -LINE PRESSURE WAS LOWERED FROM 125-150PSIG TO BELOW BOTTOM PRESSURE TO STOP LEAK -DSV DEPLOYMENT WAS DELAYED DUE TO OTHER COMMITMENTS AND WEATHER CONDITIONS -ONCE DSV WAS AVAILABLE LINE PRESSURE WAS INCREASED IN ORDER TO LOCATE LEAK 7 -2X DAILY OVERFLIGHTS NOTED SEPARATE SHEENS AND AREA OF SURFACE BUBBLES AFTER PRESSURE WAS INCREASED. --3 SHEENS --1 AREA OF BUBBLES -DSV CREW POSITIVELY IDENTIFIED LEAK 7 -PRESSURE WAS PULLED DOWN BELOW 70PSIG TO STOP OTHER 4 LEAKS --THESE 4 ADDITIONAL LEAKS HAVE NOT BEEN POSITIVELY LOCATED --SHEENS ARE SHRINKING --OVERFLIGHTS CONTINUE -CLAMP INSTALLED ON LEAK 7 -LEAKS ARE BEING EVALUATED AND FUTURE USE OF LINE TO BE DETERMINED -PRESSURE IS CURRENTLY BE MAINTAINED BELOW 50 PSI
A28: 145 | B28: 45428 | C28: 2024 | D28: 20240059 | E28: 39561 | F28: ORIGINAL | G28: 40069 | H28: STINGRAY PIPELINE COMPANY, LLC | I28: 1300 MAIN STREET | J28: HOUSTON | K28: TX | L28: 77002 | M28: 45401.746 | N28: CENTRAL | O28: YES | P28: 28.226389 | Q28: -93.354167 | R28: 1396880 | S28: 45401.778 | T28: 1397010 | U28: NATURAL GAS | W28: 0 | X28: 1290 | Y28: 0.17 | Z28: NO | AF28: 0 | AG28: NO | AM28: 0 | AN28: IDLE | AT28: YES | AU28: OPERATOR | AV28: 45401.746 | AW28: NO | BC28: VALVE CLOSURE | BE28: 44619.708 | BF28: VALVE CLOSURE | BH28: 44790.365 | BI28: 0 | BJ28: 45401.746 | BK28: 45401.746 | BL28: 45401.746 | BM28: OFFSHORE | BT28: STINGRAY PIPELINE | BU28: LINE 1004C-100 30-INCH (3394) | CP28: 185 | CQ28: ON THE OUTER CONTINENTAL SHELF (OCS) | CV28: OCS-GULF OF MEXICO | CW28: WEST CAMERON | CX28: 564 | CY28: BELOW WATER, PIPE BURIED OR JETTED BELOW SEABED | CZ28: INTERSTATE | DA28: OFFSHORE PIPELINE, INCLUDING RISER AND RISER BEND | DB28: PIPE | DC28: PIPE BODY | DD28: 30 | DE28: NO | DF28: 0.562 | DG28: 60000 | DH28: X-60 | DI28: DSAW | DK28: U.S. STEEL | DL28: OTHER | DM28: CONCRETE | DN28: UNKNOWN | EO28: 1975 | EP28: 1975 | EQ28: CARBON STEEL | ES28: LEAK | EV28: PINHOLE | FC28: CLASS 1 LOCATION | FD28: NO | FF28: 717 | FH28: NO | FI28: NO | FL28: NO | FO28: 0 | FP28: 0 | FQ28: 2025 | FR28: 750000 | FS28: 0 | FT28: 0 | FV28: 1.57 | FW28: 752025 | FX28: 0 | FY28: 0 | FZ28: 0 | GA28: 0 | GB28: NO | GF28: 160 | GG28: 0 | GH28: 1200 | GI28: 192.619(A)(1) | GK28: 27456 | GL28: NO | GM28: PRESSURE DID NOT EXCEED MAOP | GN28: NO | GQ28: NO | GS28: MANUAL | GT28: MANUAL | GU28: 318991 | GV28: YES | HD28: YES | HI28: YES | HJ28: LAUNCHER IS SUBSEA | HK28: OFFSHORE GATHERING | HL28: YES | HM28: YES | HN28: YES | HO28: NO | HP28: NO | HQ28: LOCAL OPERATING PERSONNEL, INCLUDING CONTRACTORS | HS28: CONTRACTOR WORKING FOR THE OPERATOR | HT28: NO, THE OPERATOR DID NOT FIND THAT AN INVESTIGATION OF THE CONTROLLER(S) ACTIONS OR CONTROL ROOM ISSUES WAS NECESSARY DUE TO: (PROVIDE AN EXPLANATION FOR WHY THE OPERATOR DID NOT INVESTIGATE) | HU28: INCIDENT DUE TO A SMALL PINHOLE AND WAS TOO SMALL FOR SCADA TO DETECT | IH28: NO | II28: NO | IN28: OTHER INCIDENT CAUSE | IO28: UNKNOWN | QS28: UNKNOWN | QU28: STILL UNDER INVESTIGATION, CAUSE OF INCIDENT TO BE DETERMINED* (*SUPPLEMENTAL REPORT REQUIRED) | WL28: PEGGY WEST | WM28: SENIOR SPECIALIST - DOT COMPLIANCE | WN28: peggy.west@energytransfer.com | WO28: 409-202-3088 | WT28: JUSTIN DAVIDSON | WU28: MANAGER - DOT COMPLIANCE | WV28: 713-989-5231 | WW28: justin.davidson@energytransfer.com | WX28: ON 4/19/24 AT APPROXIMATELY 17:54 WHILE ADDING PRESSURE TO THE PIPELINE IN ORDER TO LOCATE A LEAK POINT FROM 02/02/24, A SHEEN WAS SPOTTED IN WC 564 NEAR THE ORIGINAL COORDINATES OF THE LEAK BY THE OVERFLIGHT. SONAR WAS USED TO SCAN THE AREA BUT WAS UNABLE TO SEE THE SOURCE USING THAT TECHNOLOGY. THE SHEEN WAS LOCATED APPROXIMATELY ONE MILE FROM THE LOCATION WHERE THE DSV WAS WORKING TO LOCATE A LEAK. OVERFLIGHTS ARE BEING CONDUCTED DAILY AND CURRENTLY THERE IS NO SHEEN OR BUBBLES BEING RELEASED. THE FOLLOWING INFORMATION WAS GIVEN TO BRYAN LETHCOE, ANTHONY WRIGHT AND GERY BAUMAN FOR THE FOUR SHEENS FOUND DURING THE REPAIR OF LEAK 7: -LEAK 7 DISCOVERED IN FEBRUARY -LINE PRESSURE WAS LOWERED FROM 125-150PSIG TO BELOW BOTTOM PRESSURE TO STOP LEAK -DSV DEPLOYMENT WAS DELAYED DUE TO OTHER COMMITMENTS AND WEATHER CONDITIONS -ONCE DSV WAS AVAILABLE LINE PRESSURE WAS INCREASED IN ORDER TO LOCATE LEAK 7 -2X DAILY OVERFLIGHTS NOTED SEPARATE SHEENS AND AREA OF SURFACE BUBBLES AFTER PRESSURE WAS INCREASED. --3 SHEENS --1 AREA OF BUBBLES -DSV CREW POSITIVELY IDENTIFIED LEAK 7 -PRESSURE WAS PULLED DOWN BELOW 70PSIG TO STOP OTHER 4 LEAKS --THESE 4 ADDITIONAL LEAKS HAVE NOT BEEN POSITIVELY LOCATED --SHEENS ARE SHRINKING --OVERFLIGHTS CONTINUE -CLAMP INSTALLED ON LEAK 7 -LEAKS ARE BEING EVALUATED AND FUTURE USE OF LINE TO BE DETERMINED -PRESSURE IS CURRENTLY BE MAINTAINED BELOW 50 PSI
A29: 146 | B29: 45429 | C29: 2024 | D29: 20240062 | E29: 39877 | F29: SUPPLEMENTAL FINAL | G29: 32099 | H29: ENERGY TRANSFER COMPANY | I29: 1300 MAIN STREET | J29: HOUSTON | K29: TX | L29: 77002 | M29: 45399.5 | N29: CENTRAL | O29: YES | P29: 28.122918 | Q29: -99.967259 | R29: 1396678 | S29: 45399.623 | T29: 1396848 | U29: NATURAL GAS | W29: 22 | X29: 121.4 | Y29: 850 | Z29: NO | AF29: 0 | AG29: NO | AM29: 0 | AN29: NORMAL OPERATION, INCLUDES PAUSES DURING MAINTENANCE | AO29: YES | AQ29: 45399.585 | AR29: 45411.746 | AT29: NO | AW29: NO | BC29: VALVE CLOSURE | BE29: 45399.556 | BF29: VALVE CLOSURE | BH29: 45399.523 | BI29: 0 | BJ29: 45399.5 | BK29: 45399.503 | BL29: 45399.615 | BM29: ONSHORE | BN29: TX | BO29: 78045 | BP29: LAREDO | BQ29: WEBB | BR29: NOT APPLICABLE | BT29: SME L 11 NORTH 12-INCH | BU29: SME L 11 NORTH 12-INCH | BV29: NO | BW29: PIPELINE RIGHT-OF-WAY | BX29: UNDERGROUND | BY29: UNDER SOIL | CA29: 72 | CB29: NO | CC29: NO | CZ29: INTRASTATE | DA29: ONSHORE PIPELINE, INCLUDING VALVE SITES | DB29: PIPE | DC29: PIPE BODY | DD29: 12 | DE29: NO | DF29: 0.25 | DG29: 52000 | DH29: API 5L | DI29: LONGITUDINAL ERW - HIGH FREQUENCY | DK29: CALIFORNIA STEEL INDUSTRIES | DL29: EPOXY | DN29: UNKNOWN | EO29: 2011 | EP29: 2011 | EQ29: CARBON STEEL | ES29: LEAK | EV29: PINHOLE | FC29: CLASS 1 LOCATION | FD29: NO | FF29: 660 | FH29: NO | FI29: NO | FL29: NO | FO29: 20000 | FP29: 37 | FQ29: 204 | FR29: 130200 | FS29: 0 | FT29: 0 | FV29: 1.68 | FW29: 150441 | FX29: 0 | FY29: 0 | FZ29: 0 | GA29: 0 | GB29: NO | GF29: 280 | GG29: 6045 | GH29: 1440 | GI29: 192.619(A)(2) | GK29: 40827 | GL29: NO | GM29: PRESSURE DID NOT EXCEED MAOP | GN29: NO | GQ29: NO | GS29: MANUAL | GT29: MANUAL | GU29: 14784 | GV29: YES | HD29: NO | HK29: TYPE C GATHERING | HL29: NO | HQ29: OTHER | HR29: NOTIFICATION FROM PRODUCER SM ENERGY | HT29: NO, THE FACILITY WAS NOT MONITORED BY A CONTROLLER(S) AT THE TIME OF THE INCIDENT | IH29: NO | II29: NO | IN29: CORROSION FAILURE | IO29: INTERNAL CORROSION | IP29: INTERNAL CORROSION | JT29: LOCALIZED PITTING | JZ29: YES | KA29: THE COMBINATION OF LOW FLOW, SIDERITE, AND IRON SULFIDE | KC29: YES | KF29: YES | KL29: NO | KM29: NO | KN29: NO | KO29: YES | QW29: NO | TI29: NO | TL29: NO | TZ29: NO | WL29: JOSEPH STOVER | WM29: SENIOR SPECIALIST - DOT COMPLIANCE | WN29: joseph.stover@energytransfer.com | WO29: 713-398-7715 | WT29: JUSTIN DAVIDSON | WU29: MANAGER - DOT COMPLIANCE | WV29: 713-989-5231 | WW29: justin.davidson@energytransfer.com | WX29: ON APRIL 17TH 2024, AT APPROXIMATELY 12:00 ENERGY TRANSFER RECEIVED A NOTIFICATION FROM THE PRODUCER SM ENERGY, OF A POSSIBLE LEAK IN THE AREA. ET PERSONNEL PROCEEDED WITH ISOLATING THE LINE AND AT 14:03 THE VALVES WERE LOCKED OUT. AT APPROXIMATELY 14:45, ENERGY TRANSFER PERSONNEL CONFIRMED A LEAK ON THE SME L11 12-INCH PIPELINE (28.122918, -99.967259) AND PROCEEDED WITH BLOWING DOWN THE LINE. THIS IS A 12-INCH TYPE C GAS GATHERING LINE IN A RURAL AREA LOCATED IN WEBB COUNTY NEAR LAREDO, TX AN ESTIMATED 22 MCF OF UNINTENTIONAL GAS WAS RELEASED. IT WAS DETERMINED UPON CONFIRMED DISCOVERY THAT THIS INCIDENT WOULD BE REPORTABLE DUE TO THE ESTIMATE OF PROPERTY DAMAGE AND REPAIR COST. THIS INCIDENT WAS REPORTED TO THE NRC ON APRIL 17TH 2024, AT 2:57PM THE LINE WAS EXCAVATED AND A COUPON (36-INCHES LONG: 0.250-INCH WT) WAS SENT INTO ADV INTEGRITY FOR 3RD PARTY ANALYSIS. FAILURE WAS FOUND TO BE AT THE 6 OCLOCK POSITION; PIT WAS MEASURED TO BE 0.5 INCHES IN DIAMETER. SEDIMENT WAS FOUND, REMOVED, AND ANALYZED AT THE 6 OCLOCK POSITION OF THE PIPE. THE FINDINGS SHOWED THE SEDIMENT HAD PRESENCE OF SIDERITE. AFTER REVIEWING OPERATIONAL AND HISTORICAL RECORDS ALONG WITH A LAB ANALYSIS WE HAVE CONCLUDED THAT THE COMBINATION OF SIDERITE, SAND, IRON SULFIDE, AND OTHER DEBRIS LED TO UNDER DEPOSIT CORROSION AND TO AN EVENTUAL FAILURE. OUR EFFORTS TO MITIGATE THIS ISSUE IS TO MODIFY OUR MAINTENANCE PLAN BY INCORPORATING CHEMICAL TREATMENT FOR IRON SULFIDE AND SOLID DEPOSITS ALONG WITH OUR ROUTINE MAINTENANCE AND PIGGING
A30: 149 | B30: 45426 | C30: 2024 | D30: 20240055 | E30: 39876 | F30: SUPPLEMENTAL FINAL | G30: 32099 | H30: ENERGY TRANSFER COMPANY | I30: 1300 MAIN STREET | J30: HOUSTON | K30: TX | L30: 77002 | M30: 45396.404 | N30: CENTRAL | O30: YES | P30: 28.069722 | Q30: -99.934444 | R30: 1396451 | S30: 45397.419 | T30: 1396630 | U30: NATURAL GAS | W30: 17 | X30: 5.5 | Y30: 185 | Z30: NO | AF30: 0 | AG30: NO | AM30: 0 | AN30: NORMAL OPERATION, INCLUDES PAUSES DURING MAINTENANCE | AO30: YES | AQ30: 45396.466 | AR30: 45399.439 | AT30: NO | AW30: NO | BC30: VALVE CLOSURE | BE30: 45396.466 | BF30: VALVE CLOSURE | BH30: 45396.466 | BI30: 0 | BJ30: 45396.404 | BK30: 45396.458 | BL30: 45397.375 | BM30: ONSHORE | BN30: TX | BO30: 78045 | BP30: LAREDO | BQ30: WEBB | BR30: NOT APPLICABLE | BT30: BRISCOE R SA 21H, 22H, 23H | BU30: BRISCOE R SA 21H, 22H, 23H | BV30: NO | BW30: PIPELINE RIGHT-OF-WAY | BX30: UNDERGROUND | BY30: UNDER SOIL | CA30: 42 | CB30: NO | CC30: NO | CZ30: INTRASTATE | DA30: ONSHORE PIPELINE, INCLUDING VALVE SITES | DB30: PIPE | DC30: PIPE BODY | DD30: 10 | DE30: NO | DF30: 0.25 | DG30: 52000 | DH30: API 5L | DI30: LONGITUDINAL ERW - HIGH FREQUENCY | DK30: HYUNDAI | DL30: EPOXY | DN30: NO | EO30: 2016 | EP30: 2014 | EQ30: CARBON STEEL | ES30: LEAK | EV30: PINHOLE | FC30: CLASS 1 LOCATION | FD30: NO | FF30: 660 | FH30: NO | FI30: NO | FL30: NO | FO30: 40000 | FP30: 29 | FQ30: 9 | FR30: 156000 | FS30: 0 | FT30: 0 | FV30: 1.68 | FW30: 196038 | FX30: 0 | FY30: 0 | FZ30: 0 | GA30: 0 | GB30: NO | GF30: 138 | GG30: 3000 | GH30: 1440 | GI30: 192.619(A)(2) | GK30: 42492 | GL30: NO | GM30: PRESSURE DID NOT EXCEED MAOP | GN30: NO | GQ30: NO | GS30: MANUAL | GT30: MANUAL | GU30: 1035 | GV30: NO | GX30: YES | HD30: NO | HK30: TYPE C GATHERING | HL30: NO | HQ30: OTHER | HR30: NOTIFICATION FROM PRODUCER SM ENERGY | HT30: NO, THE FACILITY WAS NOT MONITORED BY A CONTROLLER(S) AT THE TIME OF THE INCIDENT | IH30: NO | II30: NO | IN30: CORROSION FAILURE | IO30: INTERNAL CORROSION | IP30: INTERNAL CORROSION | JT30: LOCALIZED PITTING | JZ30: YES | KA30: THE COMBINATION OF LOW FLOW, SIDERITE, AND IRON SULFIDE | KC30: YES | KF30: YES | KL30: YES | KM30: NO | KN30: NOT APPLICABLE - NOT MAINLINE PIPE | KO30: NOT APPLICABLE - NOT MAINLINE PIPE | QW30: NO | TI30: NO | TL30: NO | TZ30: NO | WL30: JOSEPH STOVER | WM30: SENIOR SPECIALIST - DOT COMPLIANCE | WN30: joseph.stover@energytransfer.com | WO30: 713-398-7715 | WT30: JUSTIN DAVIDSON | WU30: MANAGER - DOT COMPLIANCE | WV30: 713-989-5231 | WW30: justin.davidson@energytransfer.com | WX30: ON APRIL 14, 2024, AT 9:43AM ENERGY TRANSFER RECEIVED A NOTIFICATION FROM THE PRODUCER SM ENERGY OF A POSSIBLE LEAK IN THE AREA. ET PERSONNEL ARRIVED ON SITE TO INVESTIGATE AT 11:00AM. AT 11:11AM ET PERSONNEL SHUT IN THE BRISCOE R 21H. THIS IS A 10-INCH TYPE C GAS GATHERING LINE IN A RURAL AREA LOCATED IN WEBB COUNTY NEAR LAREDO, TX. AFTER THE LINE WAS EXCAVATED AND EXPOSED, ET WAS ABLE CONFIRM DISCOVERY ON APRIL 15, 2024 AT 9:00AM. THE LOCATION OF THE LEAK WAS DISCOVERED AT 28.069722, - 99.934444. UPON CONFIRMED DISCOVERY IT WAS DETERMINED THAT THIS INCIDENT WOULD BE REPORTABLE DUE TO THE ESTIMATE OF PROPERTY DAMAGE AND REPAIR COST. THIS INCIDENT WAS REPORTED TO THE NRC ON APRIL 15, 2024, AT 10:04AM AN ESTIMATED 22.5 MCF OF GAS WAS UNINTENTIONALLY RELEASED. THE LINE WAS EXCAVATED, AND COUPONS WERE SENT TO ADV INTEGRITY FOR 3RD PARTY ANALYSIS. FAILURES WERE FOUND TO BE AT THE 6 OCLOCK POSITION; TWO OF THE PITS MEASURED ABOUT 1/4-INCH IN DIAMETER, WHILE THE OTHER PIT MEASURED 1/8-INCH IN DIAMETER. SEDIMENT WAS FOUND, REMOVED, AND ANALYZED AT THE 6 OCLOCK POSITION OF THE PIPELINE. THE FINDINGS SHOWED THE SEDIMENT HAD PRESENCE OF SIDERITE. AFTER REVIEWING OPERATIONAL AND HISTORICAL RECORDS ALONG WITH A LAB ANALYSIS WE HAVE CONCLUDED THAT THE COMBINATION OF SIDERITE, SAND, IRON SULFIDE, AND OTHER DEBRIS LED TO UNDER DEPOSIT CORROSION AND TO AN EVENTUAL FAILURE. THIS LINE IS CURRENTLY NON-PIGGABLE . OUR EFFORTS TO MITIGATE THIS ISSUE IS TO MODIFY OUR QUARTERLY MAINTENANCE PLAN BY INCORPORATING CHEMICAL TREATMENT FOR IRON SULFIDE AND SOLID DEPOSITS.
A31: 150 | B31: 45414 | C31: 2024 | D31: 20240052 | E31: 39720 | F31: SUPPLEMENTAL FINAL | G31: 32099 | H31: ENERGY TRANSFER COMPANY | I31: 1300 MAIN STREET | J31: HOUSTON | K31: TX | L31: 77002 | M31: 45388.497 | N31: CENTRAL | O31: YES | P31: 31.67124 | Q31: -95.15346 | R31: 1395761 | S31: 45388.533 | T31: 1395868 | U31: NATURAL GAS | W31: 4723 | X31: 299 | Y31: 0 | Z31: NO | AF31: 0 | AG31: NO | AM31: 0 | AN31: NORMAL OPERATION, INCLUDES PAUSES DURING MAINTENANCE | AO31: YES | AQ31: 45388.521 | AR31: 45390.417 | AT31: NO | AW31: NO | BC31: VALVE CLOSURE | BE31: 45388.521 | BF31: VALVE CLOSURE | BH31: 45388.51 | BI31: 0 | BJ31: 45387.49 | BK31: 45388.383 | BL31: 45388.497 | BM31: ONSHORE | BN31: TX | BO31: 75925 | BP31: ALTO | BQ31: CHEROKEE | BR31: SURVEY STATION NO. | BS31: 7048.6 | BT31: 20101162 VANTEX_MARATHON 8IN TIEIN | BU31: 20101162 VANTEX_MARATHON 8IN TIEIN | BV31: NO | BW31: PIPELINE RIGHT-OF-WAY | BX31: UNDERGROUND | BY31: UNDER SOIL | CA31: 48 | CB31: NO | CC31: YES | CJ31: YES | CK31: UNCASED | CL31: UNNAMED CREEK | CM31: UNKNOWN | CN31: BELOW WATER, PIPE BURIED BELOW BOTTOM (NOT IN BORED/DRILLED CROSSING) | CO31: NO | CZ31: INTRASTATE | DA31: ONSHORE PIPELINE, INCLUDING VALVE SITES | DB31: PIPE | DC31: PIPE SEAM | DD31: 8 | DF31: 0.188 | DG31: 42000 | DH31: API 5L | DI31: LONGITUDINAL ERW - HIGH FREQUENCY | DK31: TEXTUBE CO | DL31: COAL TAR | DN31: UNKNOWN | EO31: 1998 | EP31: 1998 | EQ31: CARBON STEEL | ES31: LEAK | EV31: PINHOLE | FC31: CLASS 1 LOCATION | FD31: NO | FF31: 141 | FH31: NO | FI31: NO | FL31: NO | FO31: 0 | FP31: 9540 | FQ31: 604 | FR31: 27901 | FS31: 0 | FT31: 0 | FV31: 2.02 | FW31: 38045 | FX31: 0 | FY31: 0 | FZ31: 0 | GA31: 0 | GB31: NO | GF31: 618 | GG31: 2500 | GH31: 1318 | GI31: 192.619(A)(2) | GK31: 36088 | GL31: NO | GM31: PRESSURE DID NOT EXCEED MAOP | GN31: NO | GQ31: NO | GS31: MANUAL | GT31: MANUAL | GU31: 17424 | GV31: NO | HB31: YES | HC31: NO LAUNCHERS/RECEIVERS | HD31: NO | HK31: TRANSMISSION SYSTEM | HL31: NO | HQ31: LOCAL OPERATING PERSONNEL, INCLUDING CONTRACTORS | HS31: OPERATOR EMPLOYEE | HT31: NO, THE FACILITY WAS NOT MONITORED BY A CONTROLLER(S) AT THE TIME OF THE INCIDENT | IH31: NO | II31: NO | IN31: CORROSION FAILURE | IO31: INTERNAL CORROSION | IP31: INTERNAL CORROSION | JT31: GENERAL CORROSION | JX31: YES | KB31: YES | KC31: YES | KF31: YES | KL31: NO | KM31: NO | KN31: NO | KO31: YES | QW31: NO | TI31: NO | TL31: NO | TZ31: NO | WL31: SLADE BEARD | WM31: SENIOR SPECIALIST-DOT COMPLIANCE | WN31: slade.beard@energytransfer.com | WO31: 430-258-1223 | WT31: JUSTIN DAVIDSON | WU31: MANAGER - DOT COMPLIANCE | WV31: 713-989-5231 | WW31: justin.davidson@energytransfer.com | WX31: ON APRIL 5, 2024, AT APPROXIMATELY 11:45AM, ENERGY TRANSFER DETECTED A LEAK IN THE RIGHT OF WAY OF A GATHERING LINE LOCATED AT 31.67124, -95.15346. AT THIS POINT, THE GATHERING LINE WAS ISOLATED, AND PRODUCERS WERE NOTIFIED TO SHUT IN. ON APRIL 6, 2024, AT 9:12AM CREWS ARRIVED ON SEEN TO BEGIN EXCAVATION ON SITE ONLY TO DISCOVER THERE WAS NO LEAK PRESENT ON THE GATHERING LINE. ON APRIL 6, 2024, AT 11:55AM THE LEAK WAS CONFIRMED TO BE ON A TRANSMISSION LINE IN THE SAME RIGHT OF WAY CORRIDOR, 20101162 VANTEX MARATHON 8IN. BY 12:30PM THE LINE WAS ISOLATED AT THE UPSTREAM AND DOWNSTREAM VALVES. AN ESTIMATED 4723 MCF OF UNINTENTIONAL GAS WAS LOST, AS WELL AS 299 MCF FROM BLOWDOWN. ON APRIL 6, 2024, AT 12:48PM THE NATIONAL RESPONSE CENTER(NRC) WAS NOTIFIED.
A32: 151 | B32: 45414 | C32: 2024 | D32: 20240053 | E32: 40760 | F32: SUPPLEMENTAL FINAL | G32: 15105 | H32: PANHANDLE EASTERN PIPELINE CO | I32: 1300 MAIN STREET | J32: HOUSTON | K32: TX | L32: 77002 | M32: 45387.552 | N32: CENTRAL | O32: YES | P32: 38.300435 | Q32: -96.130344 | R32: 1395700 | S32: 45387.698 | T32: 1395822 | U32: NATURAL GAS | W32: 3540 | X32: 10068 | Y32: 0 | Z32: NO | AF32: 0 | AG32: NO | AM32: 0 | AN32: NORMAL OPERATION, INCLUDES PAUSES DURING MAINTENANCE | AO32: YES | AQ32: 45387.575 | AR32: 45393.368 | AT32: YES | AU32: OPERATOR | AV32: 45387.574 | AW32: NO | BC32: VALVE CLOSURE | BE32: 45387.558 | BF32: VALVE CLOSURE | BH32: 45387.575 | BI32: 0 | BJ32: 45387.552 | BK32: 45387.552 | BL32: 45387.552 | BM32: ONSHORE | BN32: KS | BO32: 66854 | BP32: Not Within a Municipality | BQ32: LYON | BR32: MILEPOST | BS32: MP 3.46 | BT32: OPLE 300 | BU32: OLPE - 41-03-003-1200 | BV32: NO | BW32: PIPELINE RIGHT-OF-WAY | BX32: UNDERGROUND | BY32: UNDER SOIL | CA32: 56 | CB32: NO | CC32: NO | CZ32: INTERSTATE | DA32: ONSHORE PIPELINE, INCLUDING VALVE SITES | DB32: WELD/FUSION, INCLUDING HEAT-AFFECTED ZONE | DD32: 26 | DF32: 0.312 | DG32: 52000 | DH32: API-5LX | DI32: SEAMLESS | DK32: U.S. STEEL | DL32: COAL TAR | DN32: YES | DV32: PIPE GIRTH WELD | DX32: NO | EO32: 1949 | EP32: 1949 | EQ32: CARBON STEEL | ES32: LEAK | EV32: CRACK | FC32: CLASS 1 LOCATION | FD32: NO | FF32: 538 | FH32: NO | FI32: NO | FL32: NO | FO32: 0 | FP32: 9735 | FQ32: 27687 | FR32: 64000 | FS32: 0 | FT32: 0 | FV32: 2.75 | FW32: 101422 | FX32: 0 | FY32: 0 | FZ32: 0 | GA32: 0 | GB32: NO | GF32: 747 | GG32: 265000 | GH32: 900 | GI32: 192.619(A)(1) | GK32: 43290 | GL32: NO | GM32: PRESSURE DID NOT EXCEED MAOP | GN32: NO | GQ32: NO | GS32: MANUAL | GT32: MANUAL | GU32: 49203 | GV32: YES | HD32: NO | HK32: TRANSMISSION SYSTEM | HL32: YES | HM32: YES | HN32: YES | HO32: NO | HP32: NO | HQ32: NOTIFICATION FROM PUBLIC | HT32: NO, THE OPERATOR DID NOT FIND THAT AN INVESTIGATION OF THE CONTROLLER(S) ACTIONS OR CONTROL ROOM ISSUES WAS NECESSARY DUE TO: (PROVIDE AN EXPLANATION FOR WHY THE OPERATOR DID NOT INVESTIGATE) | HU32: NORMAL FLOWS AND OPERATIONS. | IH32: NO | II32: NO | IN32: MATERIAL FAILURE OF PIPE OR WELD | IO32: DESIGN-, CONSTRUCTION-, INSTALLATION-, OR FABRICATION-RELATED | NS32: DESIGN-, CONSTRUCTION-, INSTALLATION-, OR FABRICATION-RELATED | NT32: YES | NU32: YES | OB32: YES | OK32: YES | OT32: 1164 | QW32: YES | QX32: YES | RA32: YES | RE32: 2020 | RF32: FREE SWIMMING | RG32: METAL LOSS | RI32: HIGH RESOLUTION | RK32: 2013 | RL32: FREE SWIMMING | RM32: METAL LOSS | RO32: HIGH RESOLUTION | SK32: 2020 | SL32: FREE SWIMMING | SM32: HIGH RESOLUTION | SO32: NO CUPS | SP32: 2013 | SQ32: FREE SWIMMING | SR32: HIGH RESOLUTION | ST32: NO CUPS | TI32: YES | TJ32: 2024 | TK32: 1134 | TL32: NO | TZ32: NO | VP32: YES | WL32: KORY TICE | WM32: DOT COMPLIANCE SPECIALIST | WN32: kory.tice@energytransfer.com | WO32: 8066644029 | WQ32: KEVIN FERGUSON | WR32: kevin.ferguson@energytransfer.com | WS32: 9139061521 | WT32: SUSIE SJULIN | WU32: DIRECTOR DOT COMPLIANCE | WV32: 4055575271 | WW32: susie.sjulin@energytransfer.com | WX32: AT 12:54PM PEPL EMPLOYEE RECEIVED CALL FROM A LANDOWNER THAT HE COULD HEAR A LEAK AND SEE VAPOR EAST OF ROAD N AND SOUTH OF 100 RD. AT 1:00PM NOTIFIED EMPLOYEES AT OLPE STATION TO GO TO LOCATION AND CONFIRM LEAK AND LOCATION. AT 1:15PM THE LOCATION AND LEAK WERE CONFIRMED AND BELIEVED TO BE THE 300L. AT 1:17PM SENT AN EMPLOYEE TO PROTECT LEAK SITE AND TWO EMPLOYEES TO 300L WEST RIVER HEADER FOR ISOLATION. AT 1:23PM STATION VALVE 554-3 WAS CLOSED. AT 1:45PM A GAUGE WAS PLACED ON 554-3 DSBO 642PSI TO CONFIRM THE 300L WAS LEAKING BY PRESSURE DROP. AT 1:47PM CALLED LYON COUNTY DISPATCH AND INFORMED OF THE SITUATION AND LOCATION, WAS ASKED IF ASSISTANCE WAS NEEDED, INFORMED THEM THAT NO ASSISTANCE WAS NEEDED AT THE TIME. AT 1:48PM WEST RIVER HEADER VALVE 326W WAS CLOSED, AND AT 1:55PM 516 W-1W WAS OPENED. AT 2:10PM THE STATION PRESSURE WAS AT 569 PSI. AT 2:17PM VALVE 516W-2W WAS OPENED. AT 2:20PM STATION PRESSURE WAS AT 545 PSI. AT 2:28PM STARTED BLOWDOWN. AT 2:38PM 2 GATE 300-400 CROSSOVER VALVE 302-E OPENED. AT 2:39PM 2 GATE 300-400 CROSSOVER VALVE 402-E OPENED. AT 3:19PM ISOLATED SECTION WAS BLOWN FLAT. ON 4/11/2024 PIPE WAS EXPOSED, AND LEAK IDENTIFIED AS A CRACKED WELD. A 44-FOOT PIPE SEGMENT WAS CUT OUT AND REPLACED. A SPECIMEN WAS SENT TO THE LAB FOR EVALUATION AND DETERMINATION OF CAUSE. THE LAB REPORT WAS COMPLETED ON 11/1/2024 AND FOUND THAT THE LEAK WAS CAUSED BY A COMBINATION OF A PREEXISTING DELAYED HYDROGEN CRACK ON THE INTERNAL PIPE SURFACE AT THE TOE OF THE GIRTH WELD, THE PRESENCE OF A CONCENTRATED AXIAL STRESS AT THE BOTTOM OF THE PIPE, AND THE EXCEEDANCE OF THE GIRTH WELD'S TENSILE STRAIN CAPACITY. THE CRACK MEASURED 34 INCHES LONG CIRCUMFERENTIALLY ALONG THE BOTTOM SIDE OF THE GIRTH WELD.
A33: 167 | B33: 45379 | C33: 2024 | D33: 20240038 | E33: 39593 | F33: SUPPLEMENTAL FINAL | G33: 32099 | H33: ENERGY TRANSFER COMPANY | I33: 1300 MAIN STREET | J33: HOUSTON | K33: TX | L33: 77002 | M33: 45349.709 | N33: CENTRAL | O33: NO | P33: 29.719593 | Q33: -96.093968 | R33: 1392517 | S33: 45349.722 | T33: 1392700 | U33: NATURAL GAS | W33: 1585 | X33: 12.038 | Y33: 0 | Z33: NO | AF33: 0 | AG33: NO | AM33: 0 | AN33: NORMAL OPERATION, INCLUDES PAUSES DURING MAINTENANCE | AO33: YES | AQ33: 45350.042 | AR33: 45351.672 | AT33: NO | AW33: NO | BC33: VALVE CLOSURE | BE33: 45349.728 | BF33: VALVE CLOSURE | BH33: 45349.757 | BI33: 0 | BJ33: 45349.69 | BK33: 45349.705 | BL33: 45349.722 | BM33: ONSHORE | BN33: TX | BO33: 77474 | BP33: SEALY | BQ33: AUSTIN | BR33: SURVEY STATION NO. | BS33: 2716+55 | BT33: OLD OCEAN 24-INCH | BU33: 9054 LINE O AMOCO PLANT BELLVILLE OLD OCEAN | BV33: NO | BW33: PIPELINE RIGHT-OF-WAY | BX33: UNDERGROUND | BY33: UNDER SOIL | CA33: 42 | CB33: NO | CC33: NO | CZ33: INTRASTATE | DA33: ONSHORE PIPELINE, INCLUDING VALVE SITES | DB33: PIPE | DC33: PIPE BODY | DD33: 24 | DE33: NO | DF33: 0.312 | DG33: 52000 | DH33: API 5L | DI33: FLASH WELDED | DK33: A.O. SMITH | DL33: OTHER | DM33: KRAFT PAPER WRAP | DN33: NO | EO33: 1960 | EP33: 1960 | EQ33: CARBON STEEL | ES33: MECHANICAL PUNCTURE | ET33: 2 | EU33: 0.1 | FC33: CLASS 1 LOCATION | FD33: NO | FF33: 499 | FH33: NO | FI33: NO | FL33: NO | FO33: 0 | FP33: 2869 | FQ33: 22 | FR33: 153000 | FS33: 0 | FT33: 0 | FV33: 1.81 | FW33: 155891 | FX33: 0 | FY33: 0 | FZ33: 0 | GA33: 0 | GB33: NO | GF33: 730 | GG33: 170000 | GH33: 811 | GI33: 192.619(A)(1) | GK33: 43160 | GL33: NO | GM33: PRESSURE DID NOT EXCEED MAOP | GN33: NO | GQ33: NO | GS33: MANUAL | GT33: MANUAL | GU33: 80784 | GV33: YES | HD33: NO | HK33: TRANSMISSION SYSTEM | HL33: YES | HM33: YES | HN33: YES | HO33: YES | HP33: YES | HQ33: NOTIFICATION FROM THIRD PARTY THAT CAUSED THE INCIDENT | HT33: NO, THE OPERATOR DID NOT FIND THAT AN INVESTIGATION OF THE CONTROLLER(S) ACTIONS OR CONTROL ROOM ISSUES WAS NECESSARY DUE TO: (PROVIDE AN EXPLANATION FOR WHY THE OPERATOR DID NOT INVESTIGATE) | HU33: LINE STRIKE BY 3RD PARTY DAMAGE | IH33: NO | II33: NO | IN33: EXCAVATION DAMAGE | IO33: EXCAVATION DAMAGE BY THIRD PARTY | LB33: EXCAVATION DAMAGE BY THIRD PARTY | LC33: NO | LH33: NO | LM33: NO | LR33: YES | LX33: NO | LY33: NO | LZ33: MEASURED DEPTH FROM GRADE | MA33: 42 | MB33: CONTRACTOR | MC33: UNKNOWN/OTHER | MD33: FENCING | ME33: NO | MI33: UNKNOWN/OTHER | MJ33: UNKNOWN/OTHER | MK33: YES | ML33: 47 | MM33: NOTIFICATION ISSUE | MN33: NO NOTIFICATION MADE TO THE ONE-CALL CENTER/811 | WL33: JOE STOVER | WM33: SR. SPECIALIST - DOT COMPLIANCE | WN33: joseph.stover@energytransfer.com | WO33: 713-989-7715 | WT33: JUSTIN DAVIDSON | WU33: MANAGER - DOT COMPLIANCE | WV33: 713-989-5231 | WW33: justin.davidson@energytransfer.com | WX33: A THIRD-PARTY CONTRACTOR BUILDING A FENCE FOR A LANDOWNER FAILED TO MAKE A ONE CALL AND STRUCK THE SOUTH OOPL 24 INCH WITH A SKID STEER POST DRIVER CRACKING THE PIPE CAUSING A GAS LEAK. THE LANDOWNER CALLED THE NUMBER ON THE LINE MARKER ADJACENT TO THE FENCE CONSTRUCTION AND NOTIFIED OUR GAS CONTROL OF THE LEAK. ET GAS CONTROL NOTIFIED OPERATIONS AND THE LEAK WAS LOCATED AND THE AREA WAS SECURED. THE PIPE SEGMENT WAS THEN ISOLATED, AND A CONTROLLED BLOWDOWN WAS COMPLETED. THE AREA WAS DEEMED SAFE FOR ENTRY. ET CONSTRUCTION THEN EXCAVATED AND REPAIRED THE PIPE BY MEANS OF PIPE REPLACEMENT. AFTER REPAIRS WERE MADE THE PIPELINE WAS PUT BACK INTO SERVICE.
A34: 168 | B34: 45373 | C34: 2024 | D34: 20240036 | E34: 39464 | F34: SUPPLEMENTAL FINAL | G34: 18152 | H34: SEA ROBIN PIPELINE CO | I34: 1300 MAIN STREET | J34: HOUSTON | K34: TX | L34: 77002 | M34: 45346.66 | N34: CENTRAL | O34: NO | P34: 28.347136 | Q34: -91.591434 | R34: 1392308 | S34: 45346.676 | T34: 1392385 | U34: NATURAL GAS | W34: 0 | X34: 77000 | Y34: 0 | Z34: NO | AF34: 0 | AG34: NO | AM34: 0 | AN34: NORMAL OPERATION, INCLUDES PAUSES DURING MAINTENANCE | AO34: YES | AQ34: 45343.387 | AR34: 45396.977 | AT34: YES | AU34: LOCAL/STATE/FEDERAL EMERGENCY RESPONDER | AV34: 45337.748 | AW34: NO | BC34: VALVE CLOSURE | BE34: 45347.438 | BF34: VALVE CLOSURE | BH34: 45347.104 | BI34: 0 | BJ34: 45337.66 | BK34: 45346.49 | BL34: 45346.66 | BM34: OFFSHORE | BT34: SEA ROBIN EI BLOCK 295 | BU34: 3330 LINE 709 | CP34: 220 | CQ34: ON THE OUTER CONTINENTAL SHELF (OCS) | CV34: OCS-GULF OF MEXICO | CW34: EUGENE ISLAND | CX34: 295 | CY34: BELOW WATER, PIPE ON OR ABOVE SEABED | CZ34: INTERSTATE | DA34: OFFSHORE PIPELINE, INCLUDING RISER AND RISER BEND | DB34: PIPE | DC34: PIPE BODY | DD34: 24 | DE34: NO | DF34: 0.5 | DG34: 60000 | DH34: API 5L X-52 | DI34: SINGLE SAW | DK34: UNKNOWN | DL34: OTHER | DM34: CONCRETE | DN34: UNKNOWN | EO34: 1972 | EP34: 1972 | EQ34: CARBON STEEL | ES34: LEAK | EV34: PINHOLE | FC34: CLASS 1 LOCATION | FD34: NO | FF34: 598 | FH34: NO | FI34: NO | FL34: NO | FO34: 0 | FP34: 0 | FQ34: 117040 | FR34: 879487 | FS34: 0 | FT34: 0 | FV34: 1.52 | FW34: 996527 | FX34: 0 | FY34: 0 | FZ34: 0 | GA34: 0 | GB34: NO | GF34: 880 | GG34: 22000 | GH34: 1306 | GI34: 192.619(A)(1) | GK34: 28126 | GL34: NO | GM34: PRESSURE DID NOT EXCEED MAOP | GN34: NO | GQ34: NO | GS34: MANUAL | GT34: MANUAL | GU34: 248160 | GV34: NO | GY34: YES | HD34: YES | HI34: YES | HJ34: OFFSHORE LOCATION MULTIPLE DIAMETER PIPE | HK34: TRANSMISSION SYSTEM | HL34: YES | HM34: YES | HN34: YES | HO34: NO | HP34: NO | HQ34: OTHER | HR34: BSEE | HT34: NO, THE OPERATOR DID NOT FIND THAT AN INVESTIGATION OF THE CONTROLLER(S) ACTIONS OR CONTROL ROOM ISSUES WAS NECESSARY DUE TO: (PROVIDE AN EXPLANATION FOR WHY THE OPERATOR DID NOT INVESTIGATE) | HU34: INCIDENT DUE TO A SMALL PINHOLE AND WAS TOO SMALL FOR SCADA TO DETECT | IH34: NO | II34: NO | IN34: CORROSION FAILURE | IO34: INTERNAL CORROSION | IP34: INTERNAL CORROSION | JT34: NOT CUT OPEN | JW34: YES | JX34: YES | KB34: YES | KF34: YES | KL34: YES | KM34: NO | KN34: YES | KO34: YES | QW34: NO | TI34: NO | TL34: NO | TZ34: NO | WL34: PEGGY WEST | WM34: SR. ANALYST - DOT COMPLIANCE | WN34: peggy.west@energytransfer.com | WO34: 409-202-3088 | WT34: JUSTIN DAVIDSON | WU34: MANAGER DOT COMPLIANCE | WV34: 713-989-5231 | WW34: justin.davidson@energytransfer.com | WX34: ON FEBRUARY 15, 2024 AT APPROXIMATELY 17:57, ET WAS NOTIFIED BY BSEE OF A POSSIBLE LEAK IN EUGENE ISLAND BLOCK 295. ET PERSONNEL PLOTTED THE COORDINATES AND DETERMINED THE BUBBLES WERE APPROXIMATELY 1000 FEET FROM OUR NEAREST PIPELINE AND WITHIN 100 FEET OF A PRODUCER'S LINE. DUE TO POOR WEATHER CONDITIONS AND CONTRACTOR AVAILABILITY, WE COULD NOT COMPLETE THE INVESTIGATION UNTIL FEBRUARY 24, 2024. AT THAT TIME, ET PERSONNEL AND THE PRODUCER PERFORMED A JOINT INVESTIGATION TO SEE WHICH LINE THE LEAK WAS LOCATED ON. IT WAS DETERMINED THE LEAK WAS COMING FROM LINE 709 (SEG# 3330). PRODUCTION WAS SHUT-IN AND PIPELINE WAS ISOLATED. ET PERSONNEL DEPRESSURIZED THE PIPELINE. WE ARE CURRENTLY WAITING FOR DSV AVAILABILITY TO MAKE REPAIRS. DUE TO DSV AVAILABILITY AND WEATHER CONDITIONS, THE REPAIR CONTRACTOR WAS NOT ABLE TO MAKE REPAIRS UNTIL APRIL 13, 2024. THE DSV CONTRACTOR WAS ABLE TO LOCATE THE LEAK AND INSTALL A CLAMP AT APPROXIMATELY 21:06. ET PERSONNEL CHECKED FOR LEAKS AND STARTED EQUALIZING ON APRIL 14, 2024 AT APPROXIMATELY 23:27. THE CAUSE OF THE LEAK WAS DETERMINED TO BE INTERNAL CORROSION DUE TO A PINHOLE AT THE 6 OCLOCK POSITION.
A35: 171 | B35: 45369 | C35: 2024 | D35: 20240035 | E35: 39592 | F35: SUPPLEMENTAL FINAL | G35: 32099 | H35: ENERGY TRANSFER COMPANY | I35: 1300 MAIN STREET | J35: HOUSTON | K35: TX | L35: 77002 | M35: 45336.646 | N35: CENTRAL | O35: NO | P35: 28.135952 | Q35: -99.964216 | R35: 1391581 | S35: 45336.74 | T35: 1391728 | U35: NATURAL GAS | W35: 27.8 | X35: 87.8 | Y35: 25 | Z35: NO | AF35: 0 | AG35: NO | AM35: 0 | AN35: NORMAL OPERATION, INCLUDES PAUSES DURING MAINTENANCE | AO35: YES | AQ35: 45336.764 | AR35: 45345.833 | AT35: NO | AW35: NO | BC35: VALVE CLOSURE | BE35: 45336.736 | BF35: VALVE CLOSURE | BH35: 45336.764 | BI35: 0 | BJ35: 45336.646 | BK35: 45336.681 | BL35: 45336.703 | BM35: ONSHORE | BN35: TX | BO35: 78045 | BP35: LAREDO | BQ35: WEBB | BR35: NOT APPLICABLE | BT35: SME L11 NORTH 12-INCH | BU35: SME L11 NORTH 12-INCH | BV35: NO | BW35: PIPELINE RIGHT-OF-WAY | BX35: UNDERGROUND | BY35: UNDER SOIL | CA35: 72 | CB35: NO | CC35: NO | CZ35: INTRASTATE | DA35: ONSHORE PIPELINE, INCLUDING VALVE SITES | DB35: PIPE | DC35: PIPE BODY | DD35: 12 | DE35: NO | DF35: 0.25 | DG35: 52000 | DH35: API 5L | DI35: LONGITUDINAL ERW - HIGH FREQUENCY | DK35: CALIFORNIA STEEL INDUSTRIES | DL35: EPOXY | DN35: NO | EO35: 2011 | EP35: 2011 | EQ35: CARBON STEEL | ES35: LEAK | EV35: PINHOLE | FC35: CLASS 1 LOCATION | FD35: NO | FF35: 660 | FH35: NO | FI35: NO | FL35: NO | FO35: 40000 | FP35: 44 | FQ35: 138 | FR35: 150000 | FS35: 0 | FT35: 0 | FV35: 1.57 | FW35: 190182 | FX35: 0 | FY35: 0 | FZ35: 0 | GA35: 0 | GB35: NO | GF35: 80 | GG35: 5141 | GH35: 1440 | GI35: 192.619(A)(2) | GK35: 40827 | GL35: NO | GM35: PRESSURE DID NOT EXCEED MAOP | GN35: NO | GQ35: NO | GS35: MANUAL | GT35: MANUAL | GU35: 14784 | GV35: YES | HD35: NO | HK35: TYPE C GATHERING | HL35: NO | HQ35: OTHER | HR35: NOTIFICATION FROM PRODUCER | HT35: NO, THE FACILITY WAS NOT MONITORED BY A CONTROLLER(S) AT THE TIME OF THE INCIDENT | IH35: NO | II35: NO | IN35: CORROSION FAILURE | IO35: INTERNAL CORROSION | IP35: INTERNAL CORROSION | JT35: OTHER | JU35: MIXED MECHANISMS OF INTERNAL CORROSION | JV35: YES | KB35: YES | KF35: YES | KL35: NO | KM35: NO | KN35: NO | KO35: YES | QW35: NO | TI35: NO | TL35: NO | TZ35: NO | WL35: JOE STOVER | WM35: SR. SPECIALIST - DOT COMPLIANCE | WN35: joseph.stover@energytransfer.com | WO35: 713-989-7715 | WT35: JUSTIN DAVIDSON | WU35: MANAGER - DOT COMPLIANCE | WV35: 713-989-5231 | WW35: justin.davidson@energytransfer.com | WX35: ON FEBRUARY 14, 2024 AT APPROXIMATELY 4:53 PM, ENERGY TRANSFER PERSONNEL CONFIRMED A LEAK ON THE SME L11 12IN PIPELINE (28.135952, - 99.964216). THIS IS A 12IN TYPE C GAS GATHERING LINE IN A RURAL AREA LOCATED IN WEBB COUNTY NEAR LAREDO, TX. OPERATIONS PROCEEDED WITH LINE ISOLATION AND UPSTREAM AND DOWNSTREAM VALVES WERE LOCKED OUT AND TAGGED OUT BY 6:20 PM. INVESTIGATION REVEALED THAT THE APPARENT CAUSE OF THE INCIDENT WAS DUE TO INTERNAL CORROSION (MIC). AN ESTIMATED 27.80 MCF OF UNINTENTIONAL GAS WAS RELEASED AND AN ESTIMATED 25 BBLS OF ACCOMPANYING LIQUID (FULL WELLSTREAM MIXTURE OF CONDENSATE AND WATER) WAS RELEASED. AT THE TIME, THIS INCIDENT DID NOT MEET REPORTING CRITERIA, BUT AFTER FURTHER CALCULATIONS AND INVESTIGATING, IT WAS DETERMINED THAT THE PROPERTY DAMAGE AND REPAIR COST WAS GOING TO EXCEED THE REPORTING CRITERIA. ON FEBRUARY 14, 2023, THIS INCIDENT WAS REPORTED TO THE NATIONAL RESPONSE CENTER (NRC) AT 5:46 PM.
A36: 176 | B36: 45350 | C36: 2024 | D36: 20240025 | E36: 39487 | F36: SUPPLEMENTAL FINAL | G36: 40069 | H36: STINGRAY PIPELINE COMPANY, LLC | I36: 1300 MAIN STREET | J36: HOUSTON | K36: TX | L36: 77002 | M36: 45324.354 | N36: CENTRAL | O36: NO | P36: 28.314722 | Q36: -93.252778 | R36: 1390590 | S36: 45324.374 | T36: 1390720 | U36: NATURAL GAS | W36: 0 | X36: 6442 | Y36: 0.03 | Z36: NO | AF36: 0 | AG36: NO | AM36: 0 | AN36: IDLE | AW36: NO | BC36: VALVE CLOSURE | BE36: 44619.708 | BF36: VALVE CLOSURE | BH36: 44790.365 | BI36: 0 | BJ36: 45323.927 | BK36: 45324.354 | BL36: 45324.354 | BM36: OFFSHORE | BT36: STINGRAY PIPELINE | BU36: LINE 1004C-100 30-INCH | CP36: 185 | CQ36: ON THE OUTER CONTINENTAL SHELF (OCS) | CV36: OCS-GULF OF MEXICO | CW36: WEST CAMERON | CX36: 551 | CY36: BELOW WATER, PIPE BURIED OR JETTED BELOW SEABED | CZ36: INTERSTATE | DA36: OFFSHORE PIPELINE, INCLUDING RISER AND RISER BEND | DB36: PIPE | DC36: PIPE BODY | DD36: 30 | DE36: NO | DF36: 0.562 | DG36: 60000 | DH36: X-60 | DI36: DSAW | DK36: U.S. STEEL | DL36: OTHER | DM36: CONCRETE | DN36: UNKNOWN | EO36: 1975 | EP36: 1975 | EQ36: CARBON STEEL | ES36: LEAK | EV36: PINHOLE | FC36: CLASS 1 LOCATION | FD36: NO | FF36: 717 | FH36: NO | FI36: NO | FL36: NO | FO36: 0 | FP36: 0 | FQ36: 13754 | FR36: 870721 | FS36: 0 | FT36: 0 | FV36: 2.135 | FW36: 884475 | FX36: 0 | FY36: 0 | FZ36: 0 | GA36: 0 | GB36: NO | GF36: 100 | GG36: 0 | GH36: 1200 | GI36: 192.619(A)(1) | GK36: 27456 | GL36: NO | GM36: PRESSURE DID NOT EXCEED MAOP | GN36: NO | GQ36: NO | GS36: MANUAL | GT36: MANUAL | GU36: 318991 | GV36: YES | HD36: YES | HI36: YES | HJ36: LAUNCHER IS SUBSEA | HK36: OFFSHORE GATHERING | HL36: YES | HM36: YES | HN36: YES | HO36: NO | HP36: NO | HQ36: NOTIFICATION FROM EMERGENCY RESPONDER | HT36: NO, THE OPERATOR DID NOT FIND THAT AN INVESTIGATION OF THE CONTROLLER(S) ACTIONS OR CONTROL ROOM ISSUES WAS NECESSARY DUE TO: (PROVIDE AN EXPLANATION FOR WHY THE OPERATOR DID NOT INVESTIGATE) | HU36: INCIDENT DUE TO A SMALL PINHOLE AND WAS TOO SMALL FOR SCADA TO DETECT | IH36: NO | II36: NO | IN36: CORROSION FAILURE | IO36: INTERNAL CORROSION | IP36: INTERNAL CORROSION | JT36: NOT CUT OPEN | JW36: YES | JX36: YES | KB36: YES | KF36: YES | KL36: NO | KM36: NO | KN36: NO | KO36: YES | QW36: NO | TI36: NO | TL36: NO | TZ36: NO | WL36: PEGGY WEST | WM36: SR. SPECIALIST DOT COMPLIANCE | WN36: peggy.west@energytransfer.com | WO36: 409-202-3088 | WT36: JUSTIN DAVIDSON | WU36: MANAGER DOT COMPLIANCE | WV36: 713-989-5231 | WW36: justin.davidson@energytransfer.com | WX36: ON 2/1/2024 AT APPROXIMATELY 22:15, MSU PORT ARTHUR CALLED ABOUT A SHEEN IN WC 551 NEAR THE STINGRAY PIPELINE. THE LINE WAS ALREADY SHUT IN AND PIPELINE VALVES REMAINED CLOSED. ON 2/2/2024 A SCHEDULED OVERFLIGHT CONFIRMED THE LEAK TO ON THE STINGRAY 1004C-100 30-INCH LINE. A SUPPLEMENTAL REPORT WILL BE SUBMITTED ONCE A CAUSE HAS BEEN DETERMINED. UPDATE 04/23/24: ' LEAK 7 DISCOVERED ON 2/2/24 ' LINE PRESSURE WAS LOWERED FROM 125-150PSIG TO BELOW BOTTOM PRESSURE TO STOP LEAK ' DSV DEPLOYMENT WAS DELAYED DUE TO OTHER COMMITMENTS AND WEATHER CONDITIONS ' ONCE DSV WAS AVAILABLE LINE PRESSURE WAS INCREASED IN ORDER TO LOCATE LEAK 7 ' 2X DAILY OVERFLIGHTS NOTED SEPARATE SHEENS AND AREA OF SURFACE BUBBLES AFTER PRESSURE WAS INCREASED. O 3 SHEENS O 1 AREA OF BUBBLES ' DSV CREW POSITIVELY IDENTIFIED LEAK 7 ' PRESSURE WAS PULLED DOWN BELOW 60 PSIG TO STOP OTHER 4 LEAKS O THESE 4 ADDITIONAL LEAKS HAVE NOT BEEN POSITIVELY LOCATED O SHEENS ARE SHRINKING O OVERFLIGHTS CONTINUE ' CLAMP CURRENTLY BEING INSTALLED ON LEAK 7 ' AFTER LEAK 7 REPAIR IS COMPLETE ADDITIONAL LEAKS WILL BE EVALUATED AND FUTURE USE OF LINE TO BE DETERMINED ' PRESSURE WILL CONTINUE TO BE MAINTAINED BELOW BOTTOM PRESSURE UPDATE 04/24/24: ' DSV COMPLETED INSTALLATION OF FIRST CLAMP AT 00:38 ' LEAK WAS DUE TO INTERNAL CORROSION ' TOTAL VOLUME RELEASED SINCE START OF INCIDENT 7.9 BBLS
A37: 182 | B37: 45338 | C37: 2024 | D37: 20240019 | E37: 39204 | F37: ORIGINAL | G37: 32099 | H37: ENERGY TRANSFER COMPANY | I37: 1300 MAIN STREET | J37: HOUSTON | K37: TX | L37: 77002 | M37: 45316.671 | N37: CENTRAL | O37: NO | P37: 32.911481 | Q37: -93.362856 | R37: 1389955 | S37: 45316.733 | T37: 1390036 | U37: NATURAL GAS | W37: 502.32 | X37: 0 | Y37: 0.5 | Z37: NO | AF37: 0 | AG37: NO | AM37: 0 | AN37: NORMAL OPERATION, INCLUDES PAUSES DURING MAINTENANCE | AO37: YES | AQ37: 45316.691 | AS37: YES | AT37: YES | AU37: OPERATOR | AV37: 45316.691 | AW37: NO | BC37: VALVE CLOSURE | BE37: 45316.688 | BF37: VALVE CLOSURE | BH37: 45316.691 | BI37: 0 | BJ37: 45316.671 | BK37: 45316.684 | BL37: 45316.684 | BM37: ONSHORE | BN37: LA | BO37: 71071 | BP37: SAREPTA | BQ37: WEBSTER | BR37: SURVEY STATION NO. | BS37: 261+22 | BT37: TEPPCO 8INCH | BU37: MIN-3-1-3 | BV37: NO | BW37: PIPELINE RIGHT-OF-WAY | BX37: UNDERGROUND | BY37: UNDER SOIL | CA37: 6 | CB37: NO | CC37: NO | CZ37: INTRASTATE | DA37: ONSHORE PIPELINE, INCLUDING VALVE SITES | DB37: PIPE | DC37: PIPE BODY | DD37: 8 | DE37: NO | DF37: 0.322 | DG37: 24000 | DH37: UNKNOWN | DI37: LONGITUDINAL ERW - UNKNOWN FREQUENCY | DK37: UNKNOWN | DL37: COAL TAR | DN37: NO | EO37: UNKNOWN | EP37: UNKNOWN | EQ37: CARBON STEEL | ES37: RUPTURE | EX37: LONGITUDINAL | EZ37: 36 | FA37: 14 | FC37: CLASS 1 LOCATION | FD37: NO | FF37: 171 | FH37: NO | FI37: NO | FL37: NO | FO37: 0 | FP37: 1093 | FQ37: 0 | FR37: 227148 | FS37: 0 | FT37: 0 | FV37: 2.175 | FW37: 228241 | FX37: 0 | FY37: 0 | FZ37: 0 | GA37: 0 | GB37: NO | GF37: 360 | GG37: 12000 | GH37: 692 | GI37: 192.619(A)(2) | GK37: 37029 | GL37: NO | GM37: PRESSURE DID NOT EXCEED MAOP | GN37: NO | GQ37: NO | GS37: MANUAL | GT37: MANUAL | GU37: 11018 | GV37: YES | HD37: NO | HK37: TYPE C GATHERING | HL37: NO | HQ37: NOTIFICATION FROM PUBLIC | HT37: NO, THE FACILITY WAS NOT MONITORED BY A CONTROLLER(S) AT THE TIME OF THE INCIDENT | IH37: NO | II37: NO | IN37: CORROSION FAILURE | IO37: INTERNAL CORROSION | IP37: INTERNAL CORROSION | JT37: GENERAL CORROSION | JV37: YES | JW37: YES | JX37: YES | KB37: YES | KF37: YES | KL37: YES | KM37: NO | KN37: YES | KO37: YES | QW37: NO | TI37: YES | TJ37: 2001 | TK37: 816 | TL37: NO | TZ37: NO | WL37: PEGGY WEST | WM37: SR. SPECIALIST DOT COMPLIANCE | WN37: peggy.west@energytransfer.com | WO37: 409-202-3088 | WT37: JUSTIN DAVIDSON | WU37: MANAGER DOT COMPLIANCE | WV37: 713-380-3283 | WW37: justin.davidson@energytransfer.com | WX37: AT 16:06 ON 1/25/24, AN ETC FIELD OPERATIONS MANAGER WAS NOTIFIED OF A POSSIBLE LEAK NEAR FIRE TOWER ROAD, EAST OF SAREPTA, LA. THE ETC MANAGER DISPATCHED FIELD OPERATIONS PERSONNEL FOR EMERGENCY RESPONSE. AT APPROXIMATELY 16:25, IT WAS CONFIRMED THAT IT WAS A PIPELINE RUPTURE. AT APPROXIMATELY 16:35, THE LINE WAS ISOLATED AND DE-PRESSURIZED. CLEARED BY THE VOLUNTEER FIRE DEPARTMENT RESPONDERS WERE ON THE SCENE AND FIRE TOWER ROAD WAS SHUT DOWN FOR APPROXIMATELY 15 MINUTES AT WHICH TIME THE FIRE DEPARTMENT CLEARED THE SCENE. THE EMERGENCY ISOLATION VALVES WERE LOCKED AND TAGGED OUT. ON 1/26/24, AS EXTRA PRECAUTION, ETC FIELD OPERATIONS ISOLATED AND BLEW DOWN ON BOTH SIDES OF THE SECTION THAT WAS BLOCKED IN FOR THE LEAK. THESE SECTIONS WERE BLOWN DOWN TO APPROXIMATELY 5 PSIG. THE PIPELINE IS SHUT-IN AND WAITING FOR REPAIRS.
A38: 183 | B38: 45344 | C38: 2024 | D38: 20240022 | E38: 39722 | F38: SUPPLEMENTAL FINAL | G38: 32099 | H38: ENERGY TRANSFER COMPANY | I38: 1300 MAIN STREET | J38: HOUSTON | K38: TX | L38: 77002 | M38: 45315.146 | N38: CENTRAL | O38: NO | P38: 28.018098 | Q38: -99.724361 | R38: 1389762 | S38: 45315.154 | T38: 1389954 | U38: NATURAL GAS | W38: 257000 | X38: 0 | Y38: 0 | Z38: NO | AF38: 0 | AG38: NO | AM38: 0 | AN38: NORMAL OPERATION, INCLUDES PAUSES DURING MAINTENANCE | AO38: YES | AQ38: 45315.115 | AR38: 45315.278 | AT38: YES | AU38: OPERATOR | AV38: 45315.124 | AW38: YES | AX38: 45315.067 | AY38: ALLOWED TO BURN OUT | BA38: 257.04 | BB38: NO | BI38: 0 | BJ38: 45315.067 | BK38: 45315.113 | BL38: 45315.146 | BM38: ONSHORE | BN38: TX | BO38: 78041 | BP38: LAREDO | BQ38: WEBB | BR38: NOT APPLICABLE | BT38: GALVAN G5LT CDP COMPRESSOR STATION | BU38: GALVAN G5LT CDP COMPRESSOR STATION | BV38: NO | BW38: OPERATOR-CONTROLLED PROPERTY | BX38: ABOVEGROUND | BY38: TYPICAL ABOVEGROUND FACILITY PIPING OR APPURTENANCE | CC38: NO | CZ38: INTRASTATE | DA38: ONSHORE COMPRESSOR STATION EQUIPMENT AND PIPING | DB38: COMPRESSOR | EO38: 2015 | EP38: 2015 | EQ38: MATERIAL OTHER THAN CARBON STEEL OR PLASTIC | ER38: MILD STEEL ENGINE CASTING | ES38: LEAK | EV38: CONNECTION FAILURE | FC38: CLASS 1 LOCATION | FD38: NO | FF38: 226 | FH38: NO | FI38: NO | FL38: NO | FO38: 0 | FP38: 625 | FQ38: 0 | FR38: 700000 | FS38: 0 | FT38: 0 | FV38: 2.43 | FW38: 700625 | FX38: 0 | FY38: 0 | FZ38: 0 | GA38: 0 | GB38: NO | GF38: 120 | GG38: 1810 | GH38: 1440 | GI38: 192.619(A)(1) | GK38: 42186 | GL38: NO | GM38: PRESSURE DID NOT EXCEED MAOP | GN38: NO | GQ38: NO | HK38: TYPE C GATHERING | HL38: YES | HM38: YES | HN38: YES | HO38: YES | HP38: NO | HQ38: SCADA-BASED INFORMATION (SUCH AS ALARM(S), ALERT(S), EVENT(S), AND/OR VOLUME OR PACK CALCULATIONS) | HT38: NO, THE OPERATOR DID NOT FIND THAT AN INVESTIGATION OF THE CONTROLLER(S) ACTIONS OR CONTROL ROOM ISSUES WAS NECESSARY DUE TO: (PROVIDE AN EXPLANATION FOR WHY THE OPERATOR DID NOT INVESTIGATE) | HU38: INVESTIGATION IDENTIFIED NO CONTROLLER ISSUES. CONTROLLER ACTIONS WERE CONSISTENT WITH COMPANY PROTOCOL. | IH38: NO | II38: NO | IN38: EQUIPMENT FAILURE | IO38: THREADED CONNECTION/COUPLING FAILURE | OU38: THREADED CONNECTION/COUPLING FAILURE | PK38: THREADED FITTING | QE38: YES | QF38: REFERENCE NARRATIVE IN PART H | WL38: JUSTIN DAVIDSON | WM38: MANAGER DOT COMPLIANCE | WN38: justin.davidson@energytransfer.com | WO38: 713-989-5231 | WT38: JUSTIN DAVIDSON | WU38: MANAGER DOT COMPLIANCE | WV38: 713-989-5231 | WW38: justin.davidson@energytransfer.com | WX38: ON JANUARY 24, 2024, AT APPROXIMATELY 01:57, ENERGY TRANSFER (ET) PERSONNEL WERE NOTIFIED BY GAS CONTROL OF A COMPRESSOR SHUT DOWN AT THE GALVAN G5L CDP COMPRESSOR STATION. THIS STATION IS TIED TO THE G5LTS-8 LINE, WHICH IS A TYPE C GAS GATHERING LINE LOCATED IN WEBB COUNTY. ET PERSONNEL ARRIVED ON SITE AT 02:43 AND NOTICED THAT A UNIT WAS ON FIRE. ET PERSONNEL IMMEDIATELY INITIATED AN EMERGENCY AREA SHUT DOWN BY CLOSING THE FUEL LINE SUCTION HEADER VALVE AND DISCHARGE VALVE AT 02:45, WHICH ALLOWED THE FIRE TO BURN OUT. DAMAGE WAS LIMITED TO THE INDIVIDUAL ENGINE. THE UNIT WITH THE DAMAGED ENGINE WAS ISOLATED FROM THE COMMON HEADER, WHICH ALSO HAS 3 OTHER UNITS CONNECTED TO IT. THE FACILITY WAS STARTED UP AND PUT BACK IN SERVICE ON JANUARY 24TH AT APPROXIMATELY 06:41 ON JANUARY 24TH. THE DAMAGED ENGINE HAS BEEN ASSESSED AND A REPLACEMENT ENGINE HAS BEEN ORDERED. INVESTIGATION REVEALED THAT THE MOST APPARENT CAUSE OF THE INCIDENT WAS THE STARTER/FUEL GAS SUPPLY DEVELOPED A LEAK AT OR NEAR THE VICINITY OF THE SEALCO VALVE. THE START/FUEL GAS LEAKAGE FOUND AN IGNITION SOURCE. THE HIGH HEAT CAUSED THE SEALCO VALVE TO LOSE ITS INTEGRITY AND SEPARATE INTO PIECES. THIS ALLOWED THE 120# OF FUEL GAS TO FUEL THE FIRE.
A39: 189 | B39: 45324 | C39: 2024 | D39: 20240013 | E39: 39144 | F39: ORIGINAL FINAL | G39: 19730 | H39: TRUNKLINE GAS CO | I39: 1300 MAIN STREET | J39: HOUSTON | K39: TX | L39: 77002 | M39: 45302.125 | N39: CENTRAL | O39: NO | P39: 31.600806 | Q39: -92.430758 | R39: 1388743 | S39: 45302.632 | T39: 1388792 | U39: NATURAL GAS | W39: 15000 | X39: 0 | Y39: 0 | Z39: NO | AF39: 0 | AG39: NO | AM39: 0 | AN39: NORMAL OPERATION, INCLUDES PAUSES DURING MAINTENANCE | AO39: NO | AP39: ONLY ONE COMPRESSOR SHUTDOWN | AT39: YES | AU39: OPERATOR | AV39: 45302.146 | AW39: NO | BI39: 0 | BJ39: 45302.125 | BK39: 45302.146 | BL39: 45302.125 | BM39: ONSHORE | BN39: LA | BO39: 71467 | BP39: POLLOCK | BQ39: GRANT | BR39: NOT APPLICABLE | BT39: POLLOCK COMPRESSOR STATION | BU39: 100-3 24-INCH | BV39: NO | BW39: OPERATOR-CONTROLLED PROPERTY | BX39: ABOVEGROUND | BY39: TYPICAL ABOVEGROUND FACILITY PIPING OR APPURTENANCE | CC39: NO | CZ39: INTERSTATE | DA39: ONSHORE COMPRESSOR STATION EQUIPMENT AND PIPING | DB39: COMPRESSOR | EO39: UNKNOWN | EP39: UNKNOWN | EQ39: CARBON STEEL | ES39: OTHER | FB39: RELIEF VALVE LIFTED | FC39: CLASS 1 LOCATION | FD39: NO | FF39: 745 | FH39: NO | FI39: NO | FL39: NO | FO39: 0 | FP39: 44400 | FQ39: 0 | FR39: 1000 | FS39: 0 | FT39: 0 | FV39: 2.96 | FW39: 45400 | FX39: 0 | FY39: 0 | FZ39: 0 | GA39: 0 | GB39: NO | GF39: 876 | GG39: 502000 | GH39: 900 | GI39: 192.619(C) | GK39: 25748 | GL39: NO | GM39: PRESSURE DID NOT EXCEED MAOP | GN39: NO | GQ39: NO | HK39: TRANSMISSION SYSTEM | HL39: YES | HM39: YES | HN39: YES | HO39: YES | HP39: YES | HQ39: SCADA-BASED INFORMATION (SUCH AS ALARM(S), ALERT(S), EVENT(S), AND/OR VOLUME OR PACK CALCULATIONS) | HT39: NO, THE OPERATOR DID NOT FIND THAT AN INVESTIGATION OF THE CONTROLLER(S) ACTIONS OR CONTROL ROOM ISSUES WAS NECESSARY DUE TO: (PROVIDE AN EXPLANATION FOR WHY THE OPERATOR DID NOT INVESTIGATE) | HU39: A REVIEW OF THE ACCIDENT DETERMINED THAT THERE WERE NO CONTROL ROOM ACTIONS THAT CONTRIBUTED TO THE EVENT. | IH39: NO | II39: NO | IN39: EQUIPMENT FAILURE | IO39: MALFUNCTION OF CONTROL/RELIEF EQUIPMENT | OU39: MALFUNCTION OF CONTROL/RELIEF EQUIPMENT | PB39: YES | QE39: YES | QF39: AGE RELATED | WL39: PEGGY WEST | WM39: SR. SPECIALIST DOT COMPLIANCE | WN39: peggy.west@energytransfer.com | WO39: 409-202-3088 | WT39: JUSTIN DAVIDSON | WU39: MANAGER DOT COMPLIANCE | WV39: 713-380-3283 | WW39: justin.davidson@energytransfer.com | WX39: ON 01/11/24 AT APPROXIMATELY 03:00, AN OVERPRESSURE PROTECTION VALVE FAILED AT POLLOCK COMPRESSOR STATION ALLOWING THE UNIT BLOWDOWN VALVE TO OPEN. THE UNIT WAS SHUTDOWN CAUSING THE RELIEF VALVE TO STOP BLOWING GAS. AFTER FURTHER INVESTIGATION, IT WAS DETERMINED AT 15:10 THAT APPROXIMATELY 15 MMSCF OF NATURAL GAS WAS RELEASE TO THE ATMOSPHERE. PILOT/RV WERE FUNCTIONALLY TESTED. DURING FUNCTION TESTING, THE DEVICE WOULD LIFT EARLY AND AT INCONSISTENT PRESSURES. PILOT/RV WAS REPLACED, AND FUNCTION TESTED. UNIT WAS RETURNED TO SERVICE.
A40: 222 | B40: 45232 | C40: 2023 | D40: 20230099 | E40: 39400 | F40: SUPPLEMENTAL FINAL | G40: 602 | H40: ENABLE GAS TRANSMISSION, LLC | I40: 1300 MAIN STREET | J40: HOUSTON | K40: TX | L40: 77002 | M40: 45203.739 | N40: CENTRAL | O40: YES | P40: 34.682625 | Q40: -93.111507 | R40: 1380909 | S40: 45203.739 | T40: 1381352 | U40: NATURAL GAS | W40: 99860 | X40: 0 | Y40: 0 | Z40: NO | AF40: 0 | AG40: NO | AM40: 0 | AN40: NORMAL OPERATION, INCLUDES PAUSES DURING MAINTENANCE | AO40: YES | AQ40: 45203.771 | AR40: 45379.806 | AT40: YES | AU40: LOCAL/STATE/FEDERAL EMERGENCY RESPONDER | AV40: 45203.715 | AW40: YES | AX40: 45203.697 | AY40: ALLOWED TO BURN OUT | BA40: 99860 | BB40: NO | BC40: VALVE CLOSURE | BE40: 45203.771 | BF40: VALVE CLOSURE | BH40: 45203.73 | BI40: 2 | BJ40: 45203.728 | BK40: 45203.728 | BL40: 45203.728 | BM40: ONSHORE | BN40: AR | BO40: 71949 | BP40: Not Within a Municipality | BQ40: GARLAND | BR40: NOT APPLICABLE | BT40: BT-1-AN AT JESSIEVILLE JUNCTION | BU40: BT-1-AN | BV40: NO | BW40: OPERATOR-CONTROLLED PROPERTY | BX40: UNDERGROUND | BY40: UNDER SOIL | CA40: 48 | CB40: NO | CC40: NO | CZ40: INTERSTATE | DA40: ONSHORE PIPELINE, INCLUDING VALVE SITES | DB40: PIPE | DC40: PIPE BODY | DD40: 24 | DE40: NO | DF40: 0.281 | DG40: 60000 | DH40: API-5L | DI40: DSAW | DK40: A.O. SMITH/US STEEL | DL40: COAL TAR | DN40: NO | EO40: 1967 | EP40: UNKNOWN | EQ40: CARBON STEEL | ES40: RUPTURE | EX40: LONGITUDINAL | EZ40: 538 | FA40: 30 | FC40: CLASS 1 LOCATION | FD40: NO | FF40: 524 | FH40: YES | FI40: NO | FL40: NO | FO40: 60345 | FP40: 300379 | FQ40: 0 | FR40: 10000000 | FS40: 75000 | FT40: 0 | FV40: 3.008 | FW40: 10435724 | FX40: 0 | FY40: 0 | FZ40: 10 | GA40: 4 | GB40: NO | GF40: 980 | GG40: 220000 | GH40: 1000 | GI40: 192.619(A)(1) | GK40: 24749 | GL40: NO | GM40: PRESSURE DID NOT EXCEED MAOP | GN40: NO | GQ40: NO | GS40: MANUAL | GT40: MANUAL | GU40: 153120 | GV40: YES | HD40: NO | HK40: TRANSMISSION SYSTEM | HL40: YES | HM40: YES | HN40: YES | HO40: YES | HP40: YES | HQ40: NOTIFICATION FROM PUBLIC | HT40: YES, SPECIFY INVESTIGATION RESULT(S): (SELECT ALL THAT APPLY) | HV40: YES | HY40: YES | HZ40: YES | IH40: NO | II40: NO | IN40: MATERIAL FAILURE OF PIPE OR WELD | IO40: ENVIRONMENTAL CRACKING-RELATED | NS40: ENVIRONMENTAL CRACKING-RELATED | NU40: YES | OE40: STRESS CORROSION CRACKING | OT40: 1415 | QW40: YES | QX40: YES | RA40: YES | RE40: 2023 | RF40: FREE SWIMMING | RG40: METAL LOSS | RI40: HIGH RESOLUTION | RK40: 2013 | RL40: FREE SWIMMING | RM40: METAL LOSS | RO40: HIGH RESOLUTION | SK40: 2023 | SL40: FREE SWIMMING | SM40: HIGH RESOLUTION | SO40: NO CUPS | SP40: 2013 | SQ40: FREE SWIMMING | SR40: STANDARD RESOLUTION | ST40: INSIDE ILI CUPS | TI40: NO | TL40: NO | TZ40: NO | UN40: YES | WL40: DANIEL ANTOINE | WM40: SR. DOT SPECIALIST | WN40: daniel.antoine@energytransfer.com | WO40: 501-351-8513 | WQ40: DANIEL ANTOINE | WR40: daniel.antoine@energytransfer.com | WS40: 501-351-8513 | WT40: SUSIE SJULIN | WU40: DIRECTOR REGULATORY COMPLIANCE | WV40: 405-557-5271 | WW40: susie.sjulin@energytransfer.com | WX40: ON 10/04/2023 AT APPROXIMATELY 443PM, BT-1-AN, A NATURAL GAS TRANSMISSION PIPELINE, RUPTURED AND IGNITED AT JESSIEVILLE JUNCTION. -443PM: SYSTEM CONTROL WAS NOTIFIED BY A CALLER FROM THE GENERAL PUBLIC AT 443PM -445PM: THE LEAD GAS CONTROLLER BEGAN NOTIFYING OPS PERSONNEL AT 445PM OF A POSSIBLE FAILURE AT JESSIEVILLE JUNCTION. -447PM: THE LEAD GAS CONTROLLER RECEIVED A RATE OF CHANGE ALARM INDICATING A RAPID LOSS OF LINE PRESSURE. -529PM: OPS PERSONNEL ARRIVED ON SITE AND CONFIRMED THAT A PIPELINE HAD FAILED AT JESSIEVILLE JUNCTION. -531PM: OPS PERSONNEL ISOLATED THE DOWNSTREAM VALVE 16" BT-1-AS VALVE AT HWY 88. -544PM: NRC NOTIFICATION WAS MADE (NRC# 1380909); 48HR NRC UPDATE (NRC# 1381352) -615PM: DETERMINATION WAS MADE THAT ABOVE GROUND PIPING FOR BT-1-AN 24", BT-1 16", BT-1-AS 16", AND BT-1 30" WERE AFFECTED AT JESSIEVILLE JUNCTION. -630PM: OPS PERSONNEL ISOLATED THE UPSTREAM VALVES FOR BT-1 16" AND BT-1-AN 24" AT DRY FORK MLV OPS PERSONNEL MANNED THE VALVES AT DRY FORK AND HWY 88 WHILE ADDITIONAL TECHNICIANS STAYED ONSITE AT JESSIEVILLE JUNCTION THROUGHOUT THE NIGHT TO MONITOR THE FLAME AS IT BURNED OUT. THREE PEOPLE WERE EVACUATED FROM A HOME APPROXIMATELY 645' FROM THE FAILURE SITE ON 10/04/2023; THEY WERE EVACUATED AT THE TIME OF INCIDENT AND ABLE TO RETURN TO THE HOME AT APPROXIMATELY 730PM THAT EVENING. 10/05/2023 -744AM: THE FIRE AT THE FAILURE SITE WAS CONFIRMED TO BE COMPLETELY EXTINGUISHED. -800AM: OPS PERSONNEL INITIATED THE OPERATION OF AIR MOVERS -1255PM: FAILURE SITE WAS CLEARED FOR ACCESS AND PERSONNEL FROM AID AND THE SW REGION WERE ABLE TO BEGIN THEIR INVESTIGATION 10/07/2023 -THE SUSPECTED ORIGIN FAILURE PIECE (BT-1-AN) WAS LOADED ON A TRUCK TO BE SHIPPED TO ADV INTEGRITY LAB IN MAGNOLIA, TX -CONTRACT CREW BEGAN EXCAVATING BT-1-AN, BT-1 16", BT-1 30", AND BT-1-AS 16" TO THE APPROPRIATE LOCATION ON EACH SEGMENT TO CUT AND CAP. THE METALLURGICAL TESTING RESULTS FOR THE ORIGIN PIECE OF PIPE ARE PENDING AND A SUPPLEMENTAL REPORT WILL BE FILED. ON 10/13/2023, ENERGY TRANSFER RECEIVED A CORRECTIVE ACTION ORDER (4-2023-007 CAO EGT) DEFINING THE REQUIREMENTS TO RETURN BT-1-AN, BT-1 16", BT-1 30", AND BT-1-AS TO SERVICE FROM DRY FORK MLV TO HWY 88 GATE VALVE. THE SEGMENTS REMAIN ISOLATED AND OUT OF SERVICE AT THE OF THIS FILING. CUSTOMER IMPACT -THERE ARE 12 TOTAL TAPS AND 1 TOWN BORDER OUT OF SERVICE DUE TO THE ISOLATED SEGMENT FROM DRY FORK MLV TO HWY 88 GATE VALVE BEING OUT OF SERVICE. -8 DOMESTIC STYLE TAPS AND 4 RURAL EXTENSION U-SHAPE TAPS -HOT SPRINGS #2 TOWN BORDER -THE LOCAL DISTRIBUTION COMPANY IN THE AREA HAS 244 CUSTOMERS AFFECTED WITH THE ISOLATED SEGMENTS FROM DRY FORK MLV TO HWY 88 GATE VALVE OUT OF SERVICE. *SUPPLEMENTAL REPORT UPDATES* PART C - ADDITIONAL FACILITY INFORMATION WAS UPDATED: -3C: SMYS IS 60,000 -3F: PIPE MANUFACTURER IS A.O. SMITH/ US STEEL -C6: TYPE OF RELEASE IS LONGITUDINAL AND APPROX. SIZE OF RELEASE IS 30.0IN X 538IN PART G - APPARENT CAUSE WAS UPDATED: -G5 - "MATERIAL FAILURE OF PIPE OR WELD" WAS SELECTED AS THE APPARENT CAUSE. -DETERMINED BY METALLURGICAL ANALYSIS. -ENVIRONMENTAL CRACKING-RELATED "STRESS CORROSION CRACKING". -POST CONSTRUCTION PT PRESSURE WAS ADDED PART J - INTEGRITY INSPECTIONS -UPDATED WITH MOST RECENT AND PREVIOUS TOOL RUN INFORMATION. UPDATED SUPPLEMENTAL AND FINAL REPORT WITH DATE AND TIME THAT FLOW WAS ESTABLISHED ON BT-1-AN. THE PIPELINE WAS OFFICIALLY RESTARTED ON 3-28-2024 AT 19:20.
A41: 225 | B41: 45217 | C41: 2023 | D41: 20230096 | E41: 38766 | F41: SUPPLEMENTAL FINAL | G41: 32099 | H41: ENERGY TRANSFER COMPANY | I41: 1300 MAIN STREET | J41: HOUSTON | K41: TX | L41: 77002 | M41: 45188.333 | N41: CENTRAL | O41: YES | P41: 31.389161 | Q41: -102.99995 | R41: 1379671 | S41: 45189.895 | T41: 1379829 | U41: NATURAL GAS | W41: 5500 | X41: 0 | Y41: 70 | Z41: NO | AF41: 0 | AG41: NO | AM41: 0 | AN41: NORMAL OPERATION, INCLUDES PAUSES DURING MAINTENANCE | AO41: YES | AQ41: 45188.333 | AR41: 45222.125 | AT41: NO | AW41: NO | BC41: VALVE CLOSURE | BE41: 45188.365 | BF41: VALVE CLOSURE | BH41: 45188.375 | BI41: 0 | BJ41: 45188.333 | BK41: 45188.333 | BM41: ONSHORE | BN41: TX | BO41: 79777 | BP41: PYOTE | BQ41: WARD | BR41: NOT APPLICABLE | BT41: 88885654 WT APOLLO 6008442-WA 12IN | BU41: HOWE 12IN | BV41: NO | BW41: PIPELINE RIGHT-OF-WAY | BX41: UNDERGROUND | BY41: UNDER SOIL | CA41: 60 | CB41: YES | CC41: NO | CZ41: INTRASTATE | DA41: ONSHORE PIPELINE, INCLUDING VALVE SITES | DB41: PIPE | DC41: PIPE BODY | DD41: 12 | DE41: NO | DF41: 0.281 | DG41: 35000 | DH41: UNKNOWN | DI41: LONGITUDINAL ERW - UNKNOWN FREQUENCY | DK41: UNKNOWN | DL41: COAL TAR | DN41: UNKNOWN | EO41: 1974 | EP41: UNKNOWN | EQ41: CARBON STEEL | ES41: RUPTURE | EX41: LONGITUDINAL | EZ41: 12 | FA41: 180 | FC41: CLASS 1 LOCATION | FD41: NO | FF41: 257 | FH41: NO | FI41: NO | FL41: NO | FO41: 0 | FP41: 14740 | FQ41: 0 | FR41: 998000 | FS41: 2000 | FT41: 0 | FV41: 2.68 | FW41: 1014740 | FX41: 0 | FY41: 0 | FZ41: 0 | GA41: 0 | GB41: NO | GF41: 1048 | GG41: 22.5 | GH41: 1100 | GI41: 192.619(A)(1) | GK41: 27030 | GL41: NO | GM41: PRESSURE DID NOT EXCEED MAOP | GN41: NO | GQ41: NO | GS41: MANUAL | GT41: MANUAL | GU41: 42179 | GV41: NO | HB41: YES | HC41: NEEDING UPGRADE LAUNCHER AND RECEIVERS | HD41: YES | HI41: YES | HJ41: NEEDING UPGRADE LAUNCHER AND RECEIVERS | HK41: TYPE C GATHERING | HL41: YES | HM41: YES | HN41: YES | HO41: NO | HP41: NO | HQ41: CONTROLLER | HS41: OPERATOR EMPLOYEE | HT41: NO, THE OPERATOR DID NOT FIND THAT AN INVESTIGATION OF THE CONTROLLER(S) ACTIONS OR CONTROL ROOM ISSUES WAS NECESSARY DUE TO: (PROVIDE AN EXPLANATION FOR WHY THE OPERATOR DID NOT INVESTIGATE) | HU41: A REVIEW OF THE ACCIDENT DETERMINED THAT THERE WERE NO CONTROL ROOM ACTIONS THAT CONTRIBUTED TO THE EVENT | IH41: NO | II41: NO | IN41: CORROSION FAILURE | IO41: INTERNAL CORROSION | IP41: INTERNAL CORROSION | JT41: GENERAL CORROSION | JX41: YES | KC41: YES | KJ41: YES | KK41: TOP QUARTER OF PIPE | KL41: YES | KM41: NO | KN41: YES | KO41: NO | QW41: NO | TI41: NO | TL41: NO | TZ41: NO | WL41: CHRISTOPHER PALAFOX | WM41: SR. SPECIALIST DOT COMPLIANCE | WN41: christopher.palafox@energytransfer.com | WO41: 325-933-3577 | WT41: SUSIE SJULIN | WU41: DIRECTOR - DOT COMPLIANCE | WV41: 405-557-5271 | WW41: susie.sjulin@energytransfer.com | WX41: ON SEPTEMBER 19, 2023 AT APPROXIMATELY 0800, THE CONTROL CENTER RECEIVED A CALL FROM A THIRD PARTY ABOUT A POTENTIAL LEAK ON THE 88885654 WT APOLLO 6008442-WA 12IN (HOWE 12IN), LOCATED 12 MILES SOUTH SOUTHWEST OF PYOTE, TEXAS. THE CONTROLLER NOTIFIED OPERATIONS AND AT APPROXIMATELY 0900 THE PIPELINE WAS BLOCKED AND ISOLATED BY OPERATIONS. ONCE ONSITE, OPERATIONS CONFIRMED THE PIPELINE HAD RUPTURED. APPROXIMATELY 5.5 MMCF OF NATURAL GAS WAS RELEASED. AT 0730 THE WAHA GAS PLANT HAD AN OUTAGE THUS CAUSING THE PIPELINE TO PRESSURE UP. THE CAUSE OF THE RUPTURE IS STILL UNDER INVESTIGATION. THE RUPTURED PORTION OF THE PIPE WAS CUT OUT AND SENT TO THE LAB FOR ANALYSIS. A SUPPLEMENTAL REPORT WILL BE SUBMITTED ONCE THE INVESTIGATION IS COMPLETE, AND THE RESULTS ARE IN FROM THE LAB. OCTOBER 23, 2023 AT APPROXIMATELY 0300, THE PIPELINE WAS PUT BACK INTO SERVICE. THE CONCLUSION OF THE LAB REPORT REVEALED THAT THE CORROSION WAS PRIMARILY CAUSED BY THE PRESENCE OF HYDROGEN SULFIDE (H2S). TO PREVENT THIS FROM OCCURRING IN THE FUTURE, COUPONS WERE INSTALLED ON THE PIPELINE, THIS PIPELINE WILL BE PUT ON A WEEKLY PIGGING SCHEDULE AND INHIBITORS WILL CONTINUE TO BE INJECTED INTO THE PIPELINE. AN ILI RUN WILL BE BUDGETED FOR 2025.
A42: 233 | B42: 45174 | C42: 2023 | D42: 20230084 | E42: 38638 | F42: SUPPLEMENTAL FINAL | G42: 602 | H42: ENABLE GAS TRANSMISSION, LLC | I42: 1300 MAIN STREET | J42: HOUSTON | K42: TX | L42: 77002 | M42: 45154.478 | N42: CENTRAL | O42: YES | P42: 33.469058 | Q42: -94.316272 | R42: 1376361 | S42: 45154.519 | T42: 1376542 | U42: NATURAL GAS | W42: 28 | X42: 0.36 | Y42: 0 | Z42: NO | AF42: 0 | AG42: NO | AM42: 0 | AN42: NORMAL OPERATION, INCLUDES PAUSES DURING MAINTENANCE | AO42: NO | AP42: WE INSTALLED A STOPPLE FITTING AND THE LINE REMAINED IN-SERVICE. | AT42: NO | AW42: NO | BC42: OPERATIONAL CONTROL | BD42: WE LOWERED THE LINE PRESSURE TO 180PSI. | BF42: OPERATIONAL CONTROL | BG42: WE LOWERED THE LINE PRESSURE TO 180PSI. | BI42: 0 | BJ42: 45154.478 | BK42: 45154.478 | BM42: ONSHORE | BN42: TX | BO42: 75561 | BP42: HOOKS | BQ42: BOWIE | BR42: SURVEY STATION NO. | BS42: 909+14 | BT42: CM-14 | BU42: CM-14 TO CM-20 | BV42: NO | BW42: PIPELINE RIGHT-OF-WAY | BX42: UNDERGROUND | BY42: UNDER SOIL | CA42: 32 | CB42: NO | CC42: NO | CZ42: INTERSTATE | DA42: ONSHORE PIPELINE, INCLUDING VALVE SITES | DB42: WELD/FUSION, INCLUDING HEAT-AFFECTED ZONE | DV42: FILLET WELD | EO42: UNKNOWN | EP42: UNKNOWN | EQ42: CARBON STEEL | ES42: LEAK | EV42: CRACK | FC42: CLASS 1 LOCATION | FD42: NO | FF42: 660 | FH42: NO | FI42: NO | FL42: NO | FO42: 0 | FP42: 66 | FQ42: 1 | FR42: 205000 | FS42: 0 | FT42: 0 | FV42: 2.34 | FW42: 205067 | FX42: 0 | FY42: 0 | FZ42: 0 | GA42: 0 | GB42: NO | GF42: 230 | GG42: 824 | GH42: 250 | GI42: 192.619(A)(2) | GK42: 41981 | GL42: NO | GM42: PRESSURE DID NOT EXCEED MAOP | GN42: NO | GQ42: YES | GR42: YES | GU42: 27000 | GV42: NO | GW42: YES | HD42: YES | HF42: YES | HK42: TRANSMISSION SYSTEM | HL42: YES | HM42: YES | HN42: YES | HO42: NO | HP42: NO | HQ42: GROUND PATROL BY OPERATOR OR ITS CONTRACTOR | HS42: OPERATOR EMPLOYEE | HT42: NO, THE OPERATOR DID NOT FIND THAT AN INVESTIGATION OF THE CONTROLLER(S) ACTIONS OR CONTROL ROOM ISSUES WAS NECESSARY DUE TO: (PROVIDE AN EXPLANATION FOR WHY THE OPERATOR DID NOT INVESTIGATE) | HU42: THE LEAK WAS VERY MINOR. OPERATIONS PERSONNEL FOUND THE LEAK DURING LINE PATROL DUE TO THE ODORANT. | IH42: NO | II42: NO | IN42: MATERIAL FAILURE OF PIPE OR WELD | IO42: DESIGN-, CONSTRUCTION-, INSTALLATION-, OR FABRICATION-RELATED | NS42: DESIGN-, CONSTRUCTION-, INSTALLATION-, OR FABRICATION-RELATED | NT42: YES | OC42: YES | OD42: NO INVESTIGATION WAS PERFORMED ON THE WELD, SO CAUSE IS UNKNOWN. | OK42: YES | OT42: UNKNOWN | QW42: NO | TI42: NO | TL42: NO | TZ42: NO | VQ42: YES | WL42: JOSH ALEXANDER | WN42: charles.alexander@energytransfer.com | WT42: JIMMY CROSS | WV42: 405.576.8230 | WW42: jimmy.cross@energytransfer.com | WX42: THIS LEAK WAS CAUSED BY A CRACK IN A WELD ON A PREVIOUSLY INSTALLED FITTING. WE ARE UNSURE OF THE INSTALLATION DATE OF THE FITTING. OUR INVENTORY MAPS SHOW A DATE OF 1951 BUT THE INSTALLATION DATE IS NOT ON THE MAP. WE WERE ABLE TO INSTALL 3-WAY STOPPLE FITTING TO MAKE THE REPAIR. WE REPLACED 40' OF PIPE AND ONE 2" VALVE. THE LEAKING SECTION WAS REMOVED FROM THE PIPE.
A43: 246 | B43: 45149 | C43: 2023 | D43: 20230071 | E43: 38388 | F43: ORIGINAL FINAL | G43: 32099 | H43: ENERGY TRANSFER COMPANY | I43: 1300 MAIN STREET | J43: HOUSTON | K43: TX | L43: 77002 | M43: 45124.59 | N43: CENTRAL | O43: YES | P43: 32.64945 | Q43: -92.790518 | R43: 1373350 | S43: 45124.613 | T43: 1373494 | U43: NATURAL GAS | W43: 10 | X43: 0 | Y43: 0 | Z43: NO | AF43: 0 | AG43: NO | AM43: 0 | AN43: NORMAL OPERATION, INCLUDES PAUSES DURING MAINTENANCE | AO43: YES | AQ43: 45123.913 | AR43: 45126.344 | AT43: YES | AU43: OPERATOR | AV43: 45123.926 | AW43: YES | AX43: 45123.903 | AY43: ALLOWED TO BURN OUT | BA43: 10 | BB43: NO | BI43: 0 | BJ43: 45123.903 | BK43: 45123.903 | BM43: ONSHORE | BN43: LA | BO43: 71235 | BP43: DUBACH | BQ43: LINCOLN | BR43: NOT APPLICABLE | BT43: SALEM COMPRESSOR STATION | BU43: SALEM COMPRESSOR STATION | BV43: NO | BW43: OPERATOR-CONTROLLED PROPERTY | BX43: BELOWGROUND STORAGE OR ABOVEGROUND STORAGE VESSEL, INCLUDING ATTACHED APPURTENANCE | CC43: NO | CZ43: INTRASTATE | DA43: ONSHORE COMPRESSOR STATION EQUIPMENT AND PIPING | DB43: COMPRESSOR | EO43: UNKNOWN | EP43: UNKNOWN | EQ43: MATERIAL OTHER THAN CARBON STEEL OR PLASTIC | ER43: STEEL ENG CASTING, COVERS, ELEC COMP | ES43: OTHER | FB43: FIRE ON COMPRESSOR FRAME | FC43: CLASS 1 LOCATION | FD43: NO | FF43: 294 | FH43: NO | FI43: NO | FL43: NO | FO43: 0 | FP43: 23 | FQ43: 0 | FR43: 350000 | FS43: 0 | FT43: 0 | FV43: 2.25 | FW43: 350023 | FX43: 0 | FY43: 0 | FZ43: 0 | GA43: 0 | GB43: NO | GF43: 75 | GG43: 3.8 | GH43: 1038 | GI43: 192.619(A)(2) | GK43: 44883 | GL43: NO | GM43: PRESSURE DID NOT EXCEED MAOP | GN43: NO | GQ43: NO | HK43: TYPE C GATHERING | HL43: YES | HM43: YES | HN43: YES | HO43: NO | HP43: NO | HQ43: LOCAL OPERATING PERSONNEL, INCLUDING CONTRACTORS | HS43: OPERATOR EMPLOYEE | HT43: NO, THE OPERATOR DID NOT FIND THAT AN INVESTIGATION OF THE CONTROLLER(S) ACTIONS OR CONTROL ROOM ISSUES WAS NECESSARY DUE TO: (PROVIDE AN EXPLANATION FOR WHY THE OPERATOR DID NOT INVESTIGATE) | HU43: NO INVESTIGATION DUE TO LIGHTNING STRIKE CAUSE FIRE | IH43: NO | II43: NO | IN43: NATURAL FORCE DAMAGE | IO43: LIGHTNING | KP43: LIGHTNING | KS43: DIRECT HIT | KV43: NO | WL43: PEGGY WEST | WM43: SR. REGULATORY ANALYST | WN43: peggy.west@energytransfer.com | WO43: 409-202-3088 | WT43: SUSIE SJULIN | WU43: DIRECTOR - REGULATORY COMPLIANCE | WV43: 405-557-5271 | WW43: susie.sjulin@energytransfer.com | WX43: AT APPROXIMATELY 21:40 ON 07/16/23, ETE EMPLOYEE ARRIVED AT SALEM COMPRESSOR STATION TO PLACE COMPRESSOR UNIT #3 ONLINE DUE TO THE SEVERE STORM CAUSING WIDESPREAD POWER OUTAGES. THE ETE EMPLOYEE FOUND UNIT #3 ON FIRE. STATION WAS ISOLATED AT 21:55. FIRE WAS EXTINGUISHED AT APPROXIMATELY 22:13. DUE TO SAFETY AND FATIGUE OF THE EMPLOYEES BEING ONSITE OVERNIGHT TO EXTINGUISH FIRE AND TO ISOLATE EQUIPMENT, AN INVESTIGATION WAS NOT CONDUCTED UNTIL LATER IN THE MORNING OF 7/17/23. IT WAS DETERMINED AT APPROXIMATELY 14:09 ON 7/17/23 THAT THE DAMAGE TO THE COMPRESSOR WAS OVER THE PROPERTY DAMAGE THRESHOLD AMOUNT. THE NRC WAS NOTIFIED (#1373350) AT 14:43 ON 7/17/23 AND THE 48-HOUR NOTIFICATION (#1373494) WAS REPORTED ON 7/19/23 AT APPROXIMATELY 08:49. THE STATION WAS PUT BACK ONLINE AT APPROXIMATELY 08:15 ON 07/19/23.
A44: 253 | B44: 45133 | C44: 2023 | D44: 20230069 | E44: 39180 | F44: SUPPLEMENTAL FINAL | G44: 32436 | H44: MIDCONTINENT EXPRESS PIPELINE LLC | I44: 1001 LOUISIANA ST | J44: HOUSTON | K44: TX | L44: 77002 | M44: 45104.503 | N44: CENTRAL | O44: NO | P44: 33.055595 | Q44: -94.186392 | R44: 1371415 | S44: 45104.581 | T44: 1371647 | U44: NATURAL GAS | W44: 50086.93 | X44: 1150 | Y44: 0 | Z44: NO | AF44: 0 | AG44: NO | AM44: 0 | AN44: NORMAL OPERATION, INCLUDES PAUSES DURING MAINTENANCE | AO44: YES | AQ44: 45104.492 | AR44: 45105.034 | AT44: NO | AW44: NO | BI44: 0 | BJ44: 45104.5 | BK44: 45104.517 | BL44: 45104.537 | BM44: ONSHORE | BN44: TX | BO44: 75551 | BP44: ATLANTA | BQ44: CASS | BR44: NOT APPLICABLE | BT44: MEP 2 COMPRESSOR STATION | BU44: GOV 1003; BDV 1005 | BV44: NO | BW44: OPERATOR-CONTROLLED PROPERTY | BX44: ABOVEGROUND | BY44: TYPICAL ABOVEGROUND FACILITY PIPING OR APPURTENANCE | CC44: NO | CZ44: INTERSTATE | DA44: ONSHORE COMPRESSOR STATION EQUIPMENT AND PIPING | DB44: ESD SYSTEM, BUT EXCLUDING PRODUCT DRAIN LINES AND TUBING | EO44: 2010 | EP44: 2009 | EQ44: CARBON STEEL | ES44: LEAK | EV44: CONNECTION FAILURE | FC44: CLASS 2 LOCATION | FD44: NO | FF44: 1115 | FH44: NO | FI44: NO | FL44: NO | FO44: 0 | FP44: 105183 | FQ44: 2415 | FR44: 4000 | FS44: 1800 | FT44: 0 | FV44: 2.1 | FW44: 113398 | FX44: 0 | FY44: 0 | FZ44: 0 | GA44: 0 | GB44: NO | GF44: 1191 | GG44: 1200000 | GH44: 1480 | GI44: 192.619(A)(2) | GK44: 39906 | GL44: NO | GM44: PRESSURE DID NOT EXCEED MAOP | GN44: NO | GQ44: NO | HK44: TRANSMISSION SYSTEM | HL44: YES | HM44: YES | HN44: YES | HO44: NO | HP44: YES | HQ44: NOTIFICATION FROM PUBLIC | HT44: YES, SPECIFY INVESTIGATION RESULT(S): (SELECT ALL THAT APPLY) | IF44: YES | IG44: THE STATION ISOLATION VALVES ARE INTERLOCKED WITH THE STATION BLOWDOWN VALVES. HOWEVER, TWO FAILURES ON THE INTERLOCKING SYSTEM RESULTED IN BOTH THE DISCHARGE HEADER BLOWDOWN VALVE AND THE DISCHARGE HEADER ISOLATION VALVE TO REMAIN OPEN. | IH44: NO | II44: NO | IN44: EQUIPMENT FAILURE | IO44: MALFUNCTION OF CONTROL/RELIEF EQUIPMENT | OU44: MALFUNCTION OF CONTROL/RELIEF EQUIPMENT | OZ44: YES | PF44: YES | PT44: YES | WL44: RONALD BARNES II | WM44: ENGINEER - CODES AND STANDARDS | WN44: ronald_barnes@kindermorgan.com | WO44: 7134202324 | WT44: JAIME HERNANDEZ | WU44: DIRECTOR - ENGINEERING CODES AND STANDARDS | WV44: 713-369-9443 | WW44: jaime_hernandez@kindermorgan.com | WX44: ON 06/27/2023 AT 12:00 PM, MIDCONTINENT EXPRESS PIPELINE (MEP) HAD A REPORTABLE GAS RELEASE THAT OCCURRED AT THE MEP 2 COMPRESSOR STATION WHEN THE ESD SYSTEM WAS ACTIVATED AND THE DISCHARGE SIDE OF THE ESD SYSTEM DID NOT OPERATE AS DESIGNED. THE ESD WAS ACTIVATED AS A RESULT OF LOSS OF UPS POWER SUPPLY. THE USE OF THE UPS POWER WAS INITIATED BY A TRIPPED ELECTRICAL BREAKER THAT WAS CAUSED BY AN ELECTRICALLY SHORTED AIR COMPRESSOR. THE ESD BLOCK VALVE THAT IS HELD CLOSED BY AN ENERGIZED SOLENOID, WHEN SUPPLIED BY COMMERCIAL OR UPS POWER. WHEN UPS BATTERIES WERE DRAINED, THE STATION LOST CONTROL POWER TO THE STATION COMPUTERS, PLCS AND UNIT HMIS. THE LOSS OF COMMERCIAL POWER DUE TO TRIPPED BREAKER AND THE LOSS OF UPS POWER ALLOWED THE ESD VALVE TO OPEN CAUSING THE STATION TO BLOWDOWN THROUGH A FULLY PNEUMATIC SYSTEM. WHEN RESPONSE PERSONNEL ARRIVED THEY FOUND THE STATION DISCHARGE SIDE GATE AND DISCHARGE BLOWDOWN VENT VALVE IN AN OPEN POSITION WHICH LED TO THE 50,086.93 MCF RELEASE OF NATURAL GAS. THE ESD SYSTEM BY DESIGN HAS AN INTERLOCK PROCESS SO THAT THE BLOWDOWN VALVES WILL NOT OPEN UNLESS THE ASSOCIATED STATION SIDE GATE VALVES CLOSE. THIS IS ACCOMPLISHED THROUGH A SERIES OF TRIGGER VALVES. THE SUCTION SIDE OF THE STATION WORKED AS DESIGNED DURING THE ESD. HOWEVER, THE DISCHARGE SIDE EXPERIENCED FAILURES IN TWO SHAFER TRIGGER VALVES WHICH ALLOWED THE BLOWDOWN VENT VALVE TO OPEN WITH THE DISCHARGE SIDE GATE OPEN. THE INVESTIGATION FOUND EXCESSIVE CORROSION/RUST WITHIN THE INTERNAL WORKINGS OF THE TWO SHAFER VALVES. THE SHAFER TRIGGER VALVES WERE REPLACED, THE TRIPPED BREAKER WAS RESET, THE SHORTED AIR COMPRESSOR WAS REMOVED FROM SERVICE UNTIL THE MOTOR WAS REPLACED, THE DISCHARGE SIDE GATE AND EDS DISCHARGE BLOWDOWN VALVE WERE RETURN TO THEIR NORMAL STATE AND THE STATION WAS PLACED BACK ONLINE.
A45: 256 | B45: 45121 | C45: 2023 | D45: 20230064 | E45: 38543 | F45: SUPPLEMENTAL FINAL | G45: 32099 | H45: ENERGY TRANSFER COMPANY | I45: 1300 MAIN STREET | J45: HOUSTON | K45: TX | L45: 77002 | M45: 45092.844 | N45: MOUNTAIN | O45: YES | P45: 32.026001 | Q45: -104.11779 | R45: 1370222 | S45: 45092.88 | T45: 1370381 | U45: NATURAL GAS | W45: 1 | X45: 0 | Y45: 0 | Z45: NO | AF45: 0 | AG45: NO | AM45: 0 | AN45: NORMAL OPERATION, INCLUDES PAUSES DURING MAINTENANCE | AO45: YES | AQ45: 45092.844 | AR45: 45093.625 | AT45: YES | AU45: OPERATOR | AV45: 45092.844 | AW45: YES | AX45: 45092.844 | AY45: ALLOWED TO BURN OUT | BA45: 1 | BB45: NO | BI45: 0 | BJ45: 45092.844 | BK45: 45092.844 | BM45: ONSHORE | BN45: NM | BO45: 88263 | BP45: MALAGA | BQ45: EDDY | BR45: MILEPOST | BS45: 000+00 | BT45: AVALON COMPRESSOR STATION | BU45: UNIT #5 | BV45: NO | BW45: OPERATOR-CONTROLLED PROPERTY | BX45: ABOVEGROUND | BY45: OTHER | BZ45: COMPRESSOR | CC45: NO | CZ45: INTRASTATE | DA45: ONSHORE COMPRESSOR STATION EQUIPMENT AND PIPING | DB45: COMPRESSOR | EO45: 2021 | EP45: UNKNOWN | EQ45: CARBON STEEL | ES45: LEAK | EV45: OTHER | FC45: CLASS 1 LOCATION | FD45: NO | FF45: 660 | FH45: NO | FI45: NO | FL45: NO | FO45: 0 | FP45: 4 | FQ45: 0 | FR45: 695000 | FS45: 5000 | FT45: 0 | FV45: 4.26 | FW45: 700004 | FX45: 0 | FY45: 0 | FZ45: 0 | GA45: 0 | GB45: NO | GF45: 1050 | GG45: 7000 | GH45: 1380 | GI45: 192.619(A)(1) | GK45: 44340 | GL45: NO | GM45: PRESSURE DID NOT EXCEED MAOP | GN45: NO | GQ45: NO | HK45: TYPE C GATHERING | HL45: YES | HM45: YES | HN45: YES | HO45: YES | HP45: NO | HQ45: LOCAL OPERATING PERSONNEL, INCLUDING CONTRACTORS | HS45: OPERATOR EMPLOYEE | HT45: NO, THE OPERATOR DID NOT FIND THAT AN INVESTIGATION OF THE CONTROLLER(S) ACTIONS OR CONTROL ROOM ISSUES WAS NECESSARY DUE TO: (PROVIDE AN EXPLANATION FOR WHY THE OPERATOR DID NOT INVESTIGATE) | HU45: A REVIEW OF THE ACCIDENT DETERMINED THAT THERE WERE NO CONTROL ROOM ACTIONS THAT CONTRIBUTED TO THE EVENT | IH45: NO | II45: NO | IN45: INCORRECT OPERATION | IO45: VALVE LEFT OR PLACED IN WRONG POSITION, BUT NOT RESULTING IN AN OVERPRESSURE | QG45: VALVE LEFT OR PLACED IN WRONG POSITION, BUT NOT RESULTING IN AN OVERPRESSURE | QL45: YES | QP45: ROUTINE MAINTENANCE | QQ45: NO | WL45: CHRISTOPHER PALAFOX | WM45: SPECIALIST REGULATORY COMPLIANCE | WN45: christopher.palafox@energytransfer.com | WO45: 832-537-5207 | WT45: SUSIE SJULIN | WU45: DIRECTOR - REGULATORY COMPLIANCE | WV45: 405-557-5271 | WW45: susie.sjulin@energytransfer.com | WX45: ON JUNE 15, 2023, AT APPROXIMATELY 20:15 LOCAL TIME, A FIRE OCCURRED AT THE AVALON COMPRESSOR STATION ON UNIT #5, 14 MILES SOUTH OF MALAGA, NEW MEXICO IN EDDY COUNTY. OPERATIONS CAME UPON THE BURNING COMPRESSOR, ESDD THE STATION AND CALLED THE LOCAL FIRE DEPARTMENT TO THE STATION. A DECISION WAS MADE TO LET THE FIRE BURN ITSELF OUT. AT 21:00 MOUNTAIN TIME, IT WAS DETERMINED THE REPAIRS AND DAMAGES WOULD EXCEED THE $123,900.00 REPORTABLE DOLLAR CRITERIA AND THE NRC AND THE NMPRC WAS NOTIFIED. ON JUNE 16, 2023, AT APPROXIMATELY 15:00, UNIT #5 WAS ISOLATED AND THE STATION WAS PUT BACK ONLINE BY USING THE OTHER COMPRESSORS. THE UNINTENTIONAL GAS LOSS WAS CALCULATED AT 1.0 MCF. THE CAUSE OF THE FIRE IS STILL UNDER INVESTIGATION. A SUPPLEMENTAL REPORT WILL BE SUBMITTED ONCE INVESTIGATION IS COMPLETE. **THE INVESTIGATION FOUND THAT CONDENSATE FROM THE COMPRESSOR THROW #4 INLET SCRUBBER LEAKED ONTO THE ENGINE-COMPRESSOR SKID THRU A PARTIALLY OPEN (TWO TURNS OPEN) NEEDLE VALVE ATTACHED TO THE TOP OF A LIQUID DRAIN LINE CHECK VALVE. THE CONDENSATE VAPORS FOUND AN IGNITION SOURCE (ENGINE EXHAUST) AND IGNITED THE CONDENSATE. TO PREVENT THIS FROM OCCURRING IN THE FUTURE, ALL OPENED-ENDED VALVES/LINES ON THESE PARTICULAR SYSTEMS ARE TO BE PLUGGED. ALSO, RECOMMEND LIQUID DUMP LINE CHECK VALVE REPLACEMENT.
A46: 266 | B46: 45085 | C46: 2023 | D46: 20230054 | E46: 38149 | F46: ORIGINAL FINAL | G46: 31202 | H46: ENABLE MIDSTREAM PARTNERS, LP | I46: 1300 MAIN STREET | J46: HOUSTON | K46: TX | L46: 77002 | M46: 45057.681 | N46: CENTRAL | O46: YES | P46: 35.160292 | Q46: -94.325093 | R46: 1367017 | S46: 45057.681 | T46: 1367226 1367294 | U46: NATURAL GAS | W46: 100 | X46: 31 | Y46: 0 | Z46: NO | AF46: 0 | AG46: NO | AM46: 0 | AN46: NORMAL OPERATION, INCLUDES PAUSES DURING MAINTENANCE | AO46: YES | AQ46: 45057.999 | AR46: 45061.688 | AT46: NO | AW46: YES | AX46: 45057.585 | AY46: OPERATOR/CONTRACTOR | BA46: 100 | BB46: NO | BC46: VALVE CLOSURE | BE46: 45057.601 | BF46: VALVE CLOSURE | BH46: 45057.601 | BI46: 0 | BJ46: 45057.585 | BK46: 45057.585 | BM46: ONSHORE | BN46: AR | BO46: 72936 | BP46: Not Within a Municipality | BQ46: SEBASTIAN | BR46: NOT APPLICABLE | BT46: O-470 | BU46: O-470 PLUNKETT COMP TO EGT LINE O | BV46: NO | BW46: PIPELINE RIGHT-OF-WAY | BX46: UNDERGROUND | BY46: UNDER SOIL | CA46: 36 | CB46: NO | CC46: NO | CZ46: INTRASTATE | DA46: ONSHORE PIPELINE, INCLUDING VALVE SITES | DB46: PIPE | DC46: PIPE BODY | DD46: 4 | DE46: NO | DF46: 0.156 | DG46: 35000 | DH46: UNKNOWN | DI46: OTHER | DJ46: UNKNOWN | DK46: UNKNOWN | DL46: OTHER | DM46: UNKNOWN | DN46: UNKNOWN | EO46: 1970 | EP46: UNKNOWN | EQ46: CARBON STEEL | ES46: LEAK | EV46: PINHOLE | FC46: CLASS 1 LOCATION | FD46: NO | FF46: 93 | FH46: NO | FI46: NO | FL46: NO | FO46: 0 | FP46: 207 | FQ46: 64 | FR46: 40000 | FS46: 0 | FT46: 0 | FV46: 2.07 | FW46: 40271 | FX46: 0 | FY46: 0 | FZ46: 0 | GA46: 0 | GB46: NO | GF46: 730 | GG46: 300 | GH46: 900 | GI46: 192.619(A)(2) | GK46: 41256 | GL46: NO | GM46: PRESSURE DID NOT EXCEED MAOP | GN46: NO | GQ46: NO | GS46: MANUAL | GT46: MANUAL | GU46: 7633 | GV46: NO | HB46: YES | HC46: NO RESTRICTIONS THAT WOULD LIMIT TOOL ACCOMMODATION. LAUNCHER AND RECEIVER WILL BE INSTALLED. | HD46: NO | HK46: TRANSMISSION SYSTEM | HL46: NO | HQ46: GROUND PATROL BY OPERATOR OR ITS CONTRACTOR | HS46: OPERATOR EMPLOYEE | HT46: NO, THE OPERATOR DID NOT FIND THAT AN INVESTIGATION OF THE CONTROLLER(S) ACTIONS OR CONTROL ROOM ISSUES WAS NECESSARY DUE TO: (PROVIDE AN EXPLANATION FOR WHY THE OPERATOR DID NOT INVESTIGATE) | HU46: THIS PIPELINE IS NOT MONITORED BY SCADA. | IH46: NO | II46: NO | IN46: CORROSION FAILURE | IO46: EXTERNAL CORROSION | IP46: EXTERNAL CORROSION | IQ46: LOCALIZED PITTING | IX46: YES | IY46: PITTING | JB46: YES | JF46: YES | JG46: YES | JH46: 1970 | JI46: NO | JJ46: NO | JS46: YES | QW46: NO | TI46: NO | TL46: NO | TZ46: NO | UY46: YES | WL46: DANIEL ANTOINE | WM46: SR. DOT SPECIALIST | WN46: daniel.antoine@energytransfer.com | WO46: 501-351-8513 | WQ46: DANNY BRADLEY | WR46: daniel.bradley@energytransfer.com | WS46: 479-648-2320 | WT46: SUSIE SJULIN | WU46: DIRECTOR REGULATORY COMPLIANCE | WV46: 405-557-5271 | WW46: susie.sjulin@energytransfer.com | WX46: A POSSIBLE LEAK/FIRE WAS DISCOVERED ON 5/11/2023 AT 14:03 BY OPERATIONS TECHNICIANS CONDUCTING ANNUAL LINE PATROLS ON LINE O-470. TECHNICIANS WERE CHANGING OUT SIGN MARKERS IN THE O-470 ROW WHEN THEY FELT HEAT COMING FROM UNDERNEATH THE ROCKS THAT COVERED PIPELINE IN THE ROW. TECHNICIANS IMMEDIATELY BACKED AWAY FROM THE LOCATION. TECHNICIANS WENT TO BOTH THE UPSTREAM AND DOWNSTREAM VALVE LOCATIONS TO BEGIN ISOLATING THE PIPELINE. OPERATIONS TECHNICIANS NOTIFIED THE OPS MANAGER AT 15:45, WHO THEN NOTIFIED THE OPS DIRECTOR OF THE SITUATION. A CONFERENCE CALL WAS CONDUCTED (BEGINNING AT 16:00) TO DEVELOP A PLAN TO ISOLATE AND REMEDIATE THE SECTION OF PIPE WITH THE LEAK. THE NRC (#1367017) WAS NOTIFIED AT 16:21 ON 5/11/2023. A 48HR NRC NOTIFICATION WAS PLACED AT 12:48 ON 5/14/2023. A FINAL NRC NOTIFICATION WAS PLACED AT 11:29 ON 5/15/2023; THIS UPDATE WAS TO CLARIFY THAT THE PIPELINE INVOLVED IN THIS LEAK INCIDENT WAS A TRANSMISSION PIPELINE. A PLAN WAS PUT IN PLACE TO LOWER PRESSURE FROM 728PSIG (THE PRESSURE AT TIME OF DISCOVERY) TO 200PSIG, IN AN EFFORT TO KEEP ANY POTENTIAL FLAME BURNING UNTIL THE EXACT LOCATION OF THE LEAK COULD BE DETERMINED. OPS TECHNICIANS BEGAN BLOWING DOWN THE PIPELINE AT 17:34 AND GOT THE LINE PRESSURE DOWN TO 600PSIG BY 18:11 WHILE CONTRACTORS MOBILIZED TO THE SITE. CONTRACTORS UTILIZED A TRACKHOE WITH AN EXTENDED BOOM TO PULL ROCKS AWAY FROM THE LEAK LOCATION...AS ROCKS WERE PULLED AWAY, THE FLAME/FIRE WAS VISIBLE; AS CONTRACTORS WERE WORKING THE PIPELINE WAS BROUGHT DOWN TO 200PSIG. THE FIRE WAS EXTINGUISHED JUST BEFORE 24:00 ON 5/11/2023. AIR MOVERS WERE THEN UTILIZED TO COMPLETE THE BLOW DOWN. THE CAUSE OF THE LEAK WAS IDENTIFIED AS EXTERNAL CORROSION (PITTING) AND THE FIRE/FLAME WAS LIKELY IGNITED BY A LIGHTNING STRIKE ON 5/11/2023. A 41' SEGMENT OF PIPE WAS SPOOLED IN TO REMEDIATE THE LEAK LOCATION. THE PIPELINE WAS BROUGHT BACK IN TO SERVICE ON 5/15/2023 AT 16:30. NO BUILDINGS INTENDED FOR HUMAN OCCUPANCY WERE WITHIN 220 YARDS OF THE SEGMENT AND NO DOMESTIC CUSTOMERS WERE IMPACTED BY THE OUTAGE.
A47: 283 | B47: 45030 | C47: 2023 | D47: 20230034 | E47: 38145 | F47: SUPPLEMENTAL FINAL | G47: 32099 | H47: ENERGY TRANSFER COMPANY | I47: 1300 MAIN STREET | J47: HOUSTON | K47: TX | L47: 77002 | M47: 45000.635 | N47: CENTRAL | O47: YES | P47: 28.069311 | Q47: -99.923707 | R47: 1362685 | S47: 45005.724 | T47: 1362815 | U47: NATURAL GAS | W47: 15.12 | X47: 1.67 | Y47: 20 | Z47: NO | AF47: 0 | AG47: NO | AM47: 0 | AN47: NORMAL OPERATION, INCLUDES PAUSES DURING MAINTENANCE | AO47: YES | AQ47: 45000.639 | AR47: 45044.646 | AT47: NO | AW47: NO | BC47: VALVE CLOSURE | BE47: 45000.637 | BF47: VALVE CLOSURE | BH47: 45000.639 | BI47: 0 | BJ47: 45000.635 | BK47: 45000.635 | BM47: ONSHORE | BN47: TX | BO47: 78045 | BP47: LAREDO | BQ47: WEBB | BR47: MILEPOST | BS47: 0+00 | BT47: B3LTE SUCTION TX-WEBB-A | BU47: B3LTE SUCTION TX-WEBB-A | BV47: NO | BW47: OPERATOR-CONTROLLED PROPERTY | BX47: UNDERGROUND | BY47: UNDER SOIL | CA47: 72 | CB47: NO | CC47: NO | CZ47: INTRASTATE | DA47: ONSHORE PIPELINE, INCLUDING VALVE SITES | DB47: PIPE | DC47: PIPE BODY | DD47: 12 | DE47: NO | DF47: 0.25 | DG47: 60000 | DH47: UNKNOWN | DI47: LONGITUDINAL ERW - HIGH FREQUENCY | DK47: UNKNOWN | DL47: EPOXY | DN47: YES | EO47: 2012 | EP47: 2012 | EQ47: CARBON STEEL | ES47: LEAK | EV47: PINHOLE | FC47: CLASS 1 LOCATION | FD47: NO | FF47: 157 | FH47: NO | FI47: NO | FL47: NO | FO47: 200000 | FP47: 35 | FQ47: 4 | FR47: 150000 | FS47: 68 | FT47: 0 | FV47: 2.31 | FW47: 350107 | FX47: 0 | FY47: 0 | FZ47: 0 | GA47: 0 | GB47: NO | GF47: 75 | GG47: 350 | GH47: 1440 | GI47: 192.619(A)(2) | GK47: 40967 | GL47: NO | GM47: PRESSURE DID NOT EXCEED MAOP | GN47: NO | GQ47: NO | GS47: MANUAL | GT47: MANUAL | GU47: 268 | GV47: NO | GZ47: YES | HD47: YES | HI47: YES | HJ47: NO TRAPS AVAILABLE ON STATION PIPING | HK47: TYPE C GATHERING | HL47: NO | HQ47: GROUND PATROL BY OPERATOR OR ITS CONTRACTOR | HS47: OPERATOR EMPLOYEE | HT47: NO, THE OPERATOR DID NOT FIND THAT AN INVESTIGATION OF THE CONTROLLER(S) ACTIONS OR CONTROL ROOM ISSUES WAS NECESSARY DUE TO: (PROVIDE AN EXPLANATION FOR WHY THE OPERATOR DID NOT INVESTIGATE) | HU47: INVESTIGATION IDENTIFIED NO CONTROLLER ISSUES. CONTROLLER ACTIONS WERE CONSISTENT WITH COMPANY PROTOCOL. | IH47: NO | II47: NO | IN47: CORROSION FAILURE | IO47: INTERNAL CORROSION | IP47: INTERNAL CORROSION | JT47: OTHER | JU47: MIXED MECHANISMS OF INTERNAL CORROSION | JX47: YES | KB47: YES | KD47: YES | KE47: NDE | KF47: YES | KL47: NO | KM47: NO | KN47: NOT APPLICABLE - NOT MAINLINE PIPE | KO47: YES | QW47: NO | TI47: NO | TL47: Yes, and an investigative dig was cunducted at the point of the Accident | TM47: 2023 | TP47: 2023 | TV47: YES | TZ47: NO | WL47: TIMOTHY BUNAG | WM47: SR. ENGINEER - REGULATORY COMPLIANCE | WN47: timothy.bunag@energytransfer.com | WO47: 832-294-5324 | WT47: CHRIS KRESTA | WU47: MANAGER - REGULATORY COMPLIANCE | WV47: 713-989-7077 | WW47: chris.kresta@energytransfer.com | WX47: ON MARCH 15, 2023 AT APPROXIMATELY 3:10 PM, ENERGY TRANSFER PERSONNEL IDENTIFIED A LEAK IN THE B3LTE FACILITY (28.069311 -99.923707) ON THE B3LTE SUCTION WEBB A PIPELINE. THIS IS A 12-INCH TYPE C GAS GATHERING LINE IN A RURAL AREA LOCATED IN WEBB COUNTY NEAR LAREDO, TX. OPERATIONS PROCEEDED WITH LINE ISOLATION AND UPSTREAM AND DOWNSTREAM VALVES WERE LOCKED OUT AND TAGGED OUT BY 3:20 PM. PIPE REPLACEMENT WAS MADE ON APRIL 26, 2023 AT 5:32 PM. LINE WAS PUT BACK IN SERVICE AS OF 3:30 PM ON APRIL 28, 2023. INVESTIGATION REVEALED THAT THE APPARENT CAUSE OF THE INCIDENT WAS DUE TO INTERNAL CORROSION (MIC). TO PREVENT REOCCURRENCE, ENERGY TRANSFER COMPANY WILL WORK WITH SM ENERGY (PRODUCER) TO REVIEW GAS ANALYSIS AND MAKE ADJUSTMENTS AS NEEDED TO ENSURE BIOCIDE TREATMENT IS ADEQUATE. AT THE TIME OF THE INCIDENT, REPORTING CRITERIA WAS NOT MET. AFTER FURTHER CALCULATIONS AND INVESTIGATING, IT WAS DETERMINED THAT THE PROPERTY DAMAGE AND REPAIR COST WAS GOING TO EXCEED THE $129,300 REPORTING CRITERIA. ON MARCH 20, 2023, THIS INCIDENT WAS TELEPHONICALLY REPORTED TO THE NATIONAL RESPONSE CENTER (NRC) AT 5:22 PM. A COURTESY CALL WAS ALSO MADE TO THE TEXAS RAILROAD COMMISSION AT 5:30 PM. PHMSA AID / CURTIS HUFF REQUESTED WE UPDATE A4 TO MATCH THE TIME IN A13, BUT WE DECLINED TO MAKE THAT CHANGE BECAUSE IT WOULD BE INACCURATE. HERE, THE FAILURE WAS IDENTIFIED (A13) FIVE DAYS BEFORE THE INCIDENT BECAME REPORTABLE (A4). UPON IDENTIFICATION OF THE FAILURE, IT WAS REASONABLE TO BELIEVE IT WAS NOT REPORTABLE AS THE PROPERTY DAMAGE REPORTING THRESHOLD WOULD NOT BE EXCEEDED FOR THIS PINHOLE LEAK. IT WAS NOT UNTIL 5 DAYS LATER THAT IT WAS DETERMINED THAT LIQUIDS RELEASED WITH THE GAS LEFT COMPANY PROPERTY AND AT THE RESULTING INCREASE IN THE REPAIR COST ESTIMATES THEN WERE DETERMINED TO FAR EXCEED WHAT WAS EXPECTED, CAUSING REPORTABILITY TO BE TRIGGERED AT THAT TIME. AFTER SUBMITTING THE FINAL REPORT, AID/HUFF AGAIN CAME BACK AND REQUIRED THAT A4'S DATE BE CHANGED, AND HE QUOTED THE INSTRUCTIONS FOR THE FORM FOR TYPE R GATHERING INSTEAD OF TYPE C AS IS PRESENT HERE. BECAUSE AID WILL NOT ALLOW US TO CLOSE THE REPORT WITHOUT MAKING THE CHANGE, A4 WAS UPDATED AS REQUIRED BY AID TO REFLECT THE SAME TIME AS A13.
A48: 287 | B48: 45012 | C48: 2023 | D48: 20230029 | E48: 38131 | F48: SUPPLEMENTAL FINAL | G48: 32099 | H48: ENERGY TRANSFER COMPANY | I48: 1300 MAIN STREET | J48: HOUSTON | K48: TX | L48: 77002 | M48: 44988.619 | N48: CENTRAL | O48: NO | P48: 31.655385 | Q48: -102.0573 | R48: 1361380 | S48: 44988.701 | T48: 1361508 | U48: NATURAL GAS | W48: 3690 | X48: 0 | Y48: 0 | Z48: NO | AF48: 0 | AG48: NO | AM48: 0 | AN48: ROUTINE SHUTDOWN | AT48: NO | AW48: NO | BC48: VALVE CLOSURE | BE48: 44988.583 | BF48: VALVE CLOSURE | BH48: 44988.583 | BI48: 0 | BJ48: 44988.619 | BK48: 44988.619 | BM48: ONSHORE | BN48: TX | BO48: 79765 | BP48: ODESSA | BQ48: MIDLAND | BR48: MILEPOST | BS48: 0+00 | BT48: ATHLON DISCHARGE 12IN PH1,2 PIG LAUNCHER DOOR | BU48: 20150013 | BV48: NO | BW48: OPERATOR-CONTROLLED PROPERTY | BX48: ABOVEGROUND | BY48: TYPICAL ABOVEGROUND FACILITY PIPING OR APPURTENANCE | CC48: NO | CZ48: INTRASTATE | DA48: ONSHORE PIPELINE, INCLUDING VALVE SITES | DB48: VALVE | EH48: MAINLINE | EI48: BALL | EK48: UNKNOWN | EO48: 2015 | EP48: UNKNOWN | EQ48: CARBON STEEL | ES48: LEAK | EV48: SEAL OR PACKING | FC48: CLASS 1 LOCATION | FD48: NO | FF48: 353 | FH48: NO | FI48: NO | FL48: NO | FO48: 0 | FP48: 9815 | FQ48: 0 | FR48: 109000 | FS48: 1000 | FT48: 0 | FV48: 2.66 | FW48: 119815 | FX48: 0 | FY48: 0 | FZ48: 0 | GA48: 0 | GB48: NO | GF48: 1000 | GG48: 61000 | GH48: 1440 | GI48: 192.619(A)(2) | GK48: 42125 | GL48: NO | GM48: PRESSURE DID NOT EXCEED MAOP | GN48: NO | GQ48: NO | GS48: MANUAL | GT48: MANUAL | GU48: 30096 | GV48: YES | HD48: NO | HK48: TYPE C GATHERING | HL48: YES | HM48: YES | HN48: YES | HO48: NO | HP48: NO | HQ48: LOCAL OPERATING PERSONNEL, INCLUDING CONTRACTORS | HS48: OPERATOR EMPLOYEE | HT48: NO, THE OPERATOR DID NOT FIND THAT AN INVESTIGATION OF THE CONTROLLER(S) ACTIONS OR CONTROL ROOM ISSUES WAS NECESSARY DUE TO: (PROVIDE AN EXPLANATION FOR WHY THE OPERATOR DID NOT INVESTIGATE) | HU48: INVESTIGATION IDENTIFIED NO CONTROLLER ISSUES. CONTROLLER ACTIONS WERE CONSISTENT WITH COMPANY PROTOCOLS. | IH48: NO | II48: NO | IN48: EQUIPMENT FAILURE | IO48: OTHER EQUIPMENT FAILURE | OU48: OTHER EQUIPMENT FAILURE | PO48: MAIN LINE SUPPLY GAS VALVE | PZ48: YES | WL48: CHRISTOPHER PALAFOX | WM48: SPECIALIST REGULATORY COMPLIANCE | WN48: christopher.palafox@energytransfer.com | WO48: 713-989-4464 | WT48: CHRIS KRESTA | WU48: MANAGER - REGULATORY COMPLIANCE | WV48: 7139897077 | WW48: chris.kresta@energytransfer.com | WX48: ON MARCH 3, 2023 AT APPROXIMATELY 14:52, A NATURAL GAS RELEASE OCCURRED AT THE 20150013 ATHLON DISCHARGE 12-INCH PIG LAUNCHER SITE LOCATED 23 MILES SOUTHEAST OF ODESSA, TX IN MIDLAND COUNTY. WHILE PREPARING TO LAUNCH A CLEANING PIG, THE OPERATOR MOVED ALL VALVES INVOLVED TO THEIR PROPER POSITIONS AS PER SOP. THE OPERATOR VISUALLY AND AUDIBLY WITNESSED THE PIG TRAP BLOW DOWN. ONCE THE PIG TRAP WAS COMPLETELY BLOWN DOWN THE OPERATOR BEGAN TO OPEN THE PIG TRAP DOOR AS PER SOP. THE OPERATOR WALKED AWAY FROM THE PIG TRAP DOOR TO RETRIEVE THE CLEANING PIG FROM HIS TRUCK AND HEARD A HISSING SOUND COMING FROM THE PIG TRAP. THE HISSING SOUND WAS GROWING LOUDER AND THE OPERATOR REMOVED HIMSELF FROM THE AREA TO BE SAFE. THAT IS WHEN THE GAS PRESSURE CAUSED THE PIG TRAP DOOR TO OPEN CAUSING THE RELEASE OF GAS FROM THE 16-INCH PIG TRAP DOOR. AT APPROXIMATELY 16:35, IT WAS CALCULATED AND CONFIRMED THAT THE UNINTENTIONAL GAS LOSS WAS AT 3.69 MMCF, WHICH EXCEEDED THE 3 MMCF REPORTING CRITERIA AND THE NRC WAS NOTIFIED AT 16:49. THE BETTIS ACTUATOR AND VERSE VALVE WERE REMOVED AND SENT FOR INSPECTION AND REPAIRS. A NEW MANUAL GEAR OPERATOR WAS INSTALLED AND AT 14:00 ON 04MAR THE PIPELINE WAS PUT BACK INTO SERVICE. **JUNE 1, 2023, IT WAS DETERMINED THAT THE 1-INCH MAIN LINE SUPPLY GAS BALL VALVE WAS LEAKING BY AND LIKELY RE-SUPPLIED THE ACTUATOR ASSEMBLY WITH ENOUGH PRESSURE TO ACTUATE THE VALVE OPEN ALLOWING GAS TO RE-ENTER THE PIG LAUNCHING BARREL THUS CAUSING THE UNINTENTIONAL GAS RELEASE. THE LEAKING 1-INCH BALL VALVE WAS REPLACED WITH A NEW ONE. THIS WAS AN ISOLATED INCIDENT AND TO PREVENT THIS FROM OCCURRING IN THE FUTURE AND THIS SITE, THE ACTUATORS WERE REMOVED AND REPLACED WITH MANUAL GEAR OPERATORS. THE SITE SPECIFIC PIGGING PROCEDURES HAVE BEEN UPDATED TO INCLUDE AREAS WITH ACTUATORS TO LOCK OUT THE SUPPLY SOURCE BLOWDOWN VALVE IN THE OPEN POSITION IN CASE THERE IS A LEAKING VALVE AND TO PREVENT GAS FROM RE-ENTERING THE PIG LAUNCHER BARREL.
