Workbook

Sheet Summary
A1: Summary of Selected Results from Energy Transfer-related hazardous liquids spills (2018-present)
A3: Number of Incidents | B3: =COUNT('PHMSA records'!A:A) -> 300 | E3: Impacts
A4: Start of Time Period | B4: 43101 | E4: Injuries | F4: =COUNTIF('PHMSA records'!AG:AG, "YES") -> 2
A5: End of Time Period | B5: 45838 | E5: Deaths | F5: =COUNTIF('PHMSA records'!Z:Z, "YES") -> 1
A6: Average Number of Days Between Incidents | B6: =(B5-B4)/B3 -> 9.1233333 | E6: Ignition | F6: =COUNTIF('PHMSA records'!BH:BH, "YES") -> 10
E7: Explosion | F7: =COUNTIF('PHMSA records'!BM:BM, "YES") -> 2
A8: Total Volume (Unintentional Release) | E8: Wildlife | F8: =COUNTIF('PHMSA records'!FY:FY, "YES") -> 6
A9: in barrels | B9: =SUM('PHMSA records'!W:W) -> 91290.14 | E9: Soil Contamination | F9: =COUNTIF('PHMSA records'!GC:GC, "YES") -> 246
A10: in gallons | B10: =B9*42 -> 3834185.9 | E10: Water Contamination | F10: =COUNTIF('PHMSA records'!GK:GK, "YES") -> 25
A11: in Olympic-sized swimming pools | B11: =B10/660000 -> 5.8093725 | E11: Groundwater Contamination | F11: =COUNTIF('PHMSA records'!GN:GN, "YES") -> 7
E12: Drinking Water Contamination | F12: =COUNTIF('PHMSA records'!GO:GO, "YES") -> 1
A13: Totals by Product | B13: # incidents | C13: Total Volume | E13: High-Consequence Area | F13: =COUNTIF('PHMSA records'!GU:GU, "YES") -> 129
A14: Crude Oil | B14: =COUNTIF('PHMSA records'!R:R, "CRUDE OIL") -> 249 | C14: =SUMIF('PHMSA records'!R:R, "CRUDE OIL", 'PHMSA records'!W:W) -> 31859.72 | E14: High-Population Area | F14: =COUNTIF('PHMSA records'!GX:GX, "YES") -> 96
A15: Refined Petroleum Products | B15: =COUNTIF('PHMSA records'!R:R, "REFINED AND/OR PETROLEUM PRODUCT (NON-HVL) WHICH IS A LIQUID AT AMBIENT CONDITIONS") -> 30 | C15: =SUMIF('PHMSA records'!R:R, "REFINED AND/OR PETROLEUM PRODUCT (NON-HVL) WHICH IS A LIQUID AT AMBIENT CONDITIONS", 'PHMSA records'!W:W) -> 6837.59 | E15: Total Property Damage | F15: =SUM('PHMSA records'!HM:HM) -> 96458844
A16: HVLs | B16: =COUNTIF('PHMSA records'!R:R, "HVL OR OTHER FLAMMABLE OR TOXIC FLUID WHICH IS A GAS AT AMBIENT CONDITIONS") -> 21 | C16: =SUMIF('PHMSA records'!R:R, "HVL OR OTHER FLAMMABLE OR TOXIC FLUID WHICH IS A GAS AT AMBIENT CONDITIONS", 'PHMSA records'!W:W) -> 52592.83
E17: Causes
A18: Report Status | E18: Equipment Failure | F18: =COUNTIF('PHMSA records'!JX:JX, "EQUIPMENT FAILURE") -> 109
A19: Original | B19: =COUNTIF('PHMSA records'!F:F, "ORIGINAL") -> 19 | E19: Corrosion | F19: =COUNTIF('PHMSA records'!JX:JX, "CORROSION FAILURE") -> 101
A20: Original Final | B20: =COUNTIF('PHMSA records'!F:F, "ORIGINAL FINAL") -> 145 | E20: Incorrect Operation | F20: =COUNTIF('PHMSA records'!JX:JX, "INCORRECT OPERATION") -> 34
A21: Supplemental | B21: =COUNTIF('PHMSA records'!F:F, "SUPPLEMENTAL") -> 5 | E21: Other Accident Cause | F21: =COUNTIF('PHMSA records'!JX:JX, "OTHER ACCIDENT CAUSE") -> 17
A22: Supplemental Final | B22: =COUNTIF('PHMSA records'!F:F, "SUPPLEMENTAL FINAL") -> 131 | E22: Material Failure of Pipe or Weld | F22: =COUNTIF('PHMSA records'!JX:JX, "MATERIAL FAILURE OF PIPE OR WELD") -> 15
E23: Excavation Damage | F23: =COUNTIF('PHMSA records'!JX:JX, "EXCAVATION DAMAGE") -> 9
E24: Natural Force Damage | F24: =COUNTIF('PHMSA records'!JX:JX, "NATURAL FORCE DAMAGE") -> 8
E25: Other Outside Force Damage | F25: =COUNTIF('PHMSA records'!JX:JX, "OTHER OUTSIDE FORCE DAMAGE") -> 7

Sheet PHMSA records
B1: REPORT_RECEIVED_DATE | C1: IYEAR | D1: REPORT_NUMBER | E1: SUPPLEMENTAL_NUMBER | F1: REPORT_TYPE | G1: OPERATOR_ID | H1: NAME | I1: OPERATOR_STREET_ADDRESS | J1: OPERATOR_CITY_NAME | K1: OPERATOR_STATE_ABBREVIATION | L1: OPERATOR_POSTAL_CODE | M1: LOCAL_DATETIME | N1: TIME_ZONE | O1: DAYLIGHT_SAVINGS_IND | P1: LOCATION_LATITUDE | Q1: LOCATION_LONGITUDE | R1: COMMODITY_RELEASED_TYPE | S1: COMMODITY_SUBTYPE | T1: COMMODITY_DETAILS | U1: BLEND_DETAILS | V1: BIO_DIESEL_DETAILS | W1: UNINTENTIONAL_RELEASE_BBLS | X1: INTENTIONAL_RELEASE_BBLS | Y1: RECOVERED_BBLS | Z1: FATALITY_IND | AA1: NUM_EMP_FATALITIES | AB1: NUM_CONTR_FATALITIES | AC1: NUM_ER_FATALITIES | AD1: NUM_WORKER_FATALITIES | AE1: NUM_GP_FATALITIES | AF1: FATAL | AG1: INJURY_IND | AH1: NUM_EMP_INJURIES | AI1: NUM_CONTR_INJURIES | AJ1: NUM_ER_INJURIES | AK1: NUM_WORKER_INJURIES | AL1: NUM_GP_INJURIES | AM1: INJURE | AN1: ACCIDENT_IDENTIFIER | AO1: ACCIDENT_DETAILS | AP1: OPERATOR_TYPE | AQ1: INCIDENT_IDENTIFIED_DATETIME | AR1: SYSTEM_PART_INVOLVED | AS1: ON_OFF_SHORE | AT1: STATUS_WHEN_IDENTIFIED | AU1: SHUTDOWN_DUE_ACCIDENT_IND | AV1: SHUTDOWN_EXPLAIN | AW1: SHUTDOWN_DATETIME | AX1: RESTART_DATETIME | AY1: STILL_SHUTDOWN_IND | AZ1: COMMUNICATION_STATE_FED_IND | BA1: PARTY_INITIATED_COMMUNICATION | BB1: INITIAL_RESPONDER_COM_DATETIME | BC1: ON_SITE_DATETIME | BD1: CONFIRMED_DISCOVERY_DATETIME | BE1: NRC_RPT_DATETIME | BF1: NRC_RPT_NUM | BG1: ADDITIONAL_NRC_REPORT_NUMBERS | BH1: IGNITE_IND | BI1: IGNITE_DATETIME | BJ1: HOW_EXTINGUISHED | BK1: HOW_EXTINGUISHED_OTHER_DETAIL | BL1: CONSUMED_BY_FIRE_IN_BARRELS | BM1: EXPLODE_IND | BN1: UPSTREAM_ACTION_TAKEN | BO1: UPSTREAM_OPRTNL_CNTRL_DETAIL | BP1: UPSTREAM_VALVE_CLOSE_DATETIME | BQ1: UPSTREAM_VALVE_TYPE_IND | BR1: DOWNSTREAM_ACTION_TAKEN | BS1: DOWNSTREAM_OPRTNL_CNTRL_DETAIL | BT1: DOWNSTREAM_VLV_CLOSE_DATETIME | BU1: DOWNSTREAM_VALVE_TYPE_IND | BV1: NOTIFY_QUALIFIED_INDIV_IND | BW1: QUALIFIED_INDIV_NOTIF_DATETIME | BX1: OIL_SPILL_REMOVAL_ORG_IND | BY1: OSRO_ACTIVATED_DATETIME | BZ1: OSRO_ARRIVED_ON_SITE_DT | CA1: NUM_PUB_EVACUATED | CB1: PIPE_FAC_NAME | CC1: SEGMENT_NAME | CD1: ONSHORE_STATE_ABBREVIATION | CE1: ONSHORE_POSTAL_CODE | CF1: ONSHORE_CITY_NAME | CG1: ONSHORE_COUNTY_NAME | CH1: DESIGNATED_LOCATION | CI1: DESIGNATED_NAME | CJ1: FEDERAL | CK1: LOCATION_TYPE | CL1: INCIDENT_AREA_TYPE | CM1: INCIDENT_AREA_SUBTYPE | CN1: INCIDENT_AREA_DETAILS | CO1: DEPTH_OF_COVER | CP1: CROSSING | CQ1: BRIDGE_CROSSING_IND | CR1: BRIDGE_TYPE | CS1: RAILROAD_CROSSING_IND | CT1: RAILROAD_TYPE | CU1: ROAD_CROSSING_IND | CV1: ROAD_TYPE | CW1: WATER_CROSSING_IND | CX1: WATER_TYPE | CY1: WATER_NAME | CZ1: WATER_DEPTH | DA1: WATER_SUBTYPE | DB1: CROSSING_100_FEET | DC1: OFF_WATER_DEPTH | DD1: OFF_ACCIDENT_ORIGIN | DE1: OFFSHORE_STATE_ABBREVIATION | DF1: OFF_INSTATE_AREA | DG1: OFF_INSTATE_BLOCK | DH1: OFFSHORE_COUNTY_NAME | DI1: OCS_TYPE | DJ1: OFF_OCS_AREA | DK1: OFF_OCS_BLOCK | DL1: OFF_AREA_ACCIDENT_TYPE | DM1: PIPE_FACILITY_TYPE | DN1: ITEM_INVOLVED | DO1: PIPE_TYPE | DP1: PUDDLE_WELD_IND | DQ1: PIPE_DIAMETER | DR1: PIPE_WALL_THICKNESS | DS1: PIPE_SMYS | DT1: PIPE_SPECIFICATION | DU1: PIPE_SEAM_TYPE | DV1: PIPE_SEAM_DETAILS | DW1: PIPE_MANUFACTURER | DX1: PIPE_COATING_TYPE | DY1: PIPE_COATING_DETAILS | DZ1: COATING_APPLIED_IND | EA1: WELD_SUBTYPE | EB1: WELD_DETAILS | EC1: DIFFERENT_GIRTH_WELD_IND | ED1: DIFF_GIRTH_WELD_WALL_THICKNESS | EE1: DIFF_GIRTH_WELD_SMYS | EF1: DIFF_GIRTH_WELD_SPECIFICATION | EG1: DIFF_GIRTH_WELD_SEAM_TYPE | EH1: DIFF_GIRTH_WELD_SEAM_DETAIL | EI1: DIFF_GIRTH_WELD_MANUFACTURER | EJ1: DIFF_GIRTH_WELD_COATING_TYPE | EK1: DIFF_GIRTH_WELD_COATING_DETAIL | EL1: DIFF_GIRTH_WELD_CTNG_APPLD_IND | EM1: VALVE_TYPE | EN1: VALVE_MAINLINE_TYPE | EO1: VALVE_MAINLINE_DETAILS | EP1: VALVE_MANUFACTURER | EQ1: PUMP_TYPE | ER1: PUMP_TYPE_DETAILS | ES1: PUMP_SERVICE_TYPE | ET1: PUMP_SERVICE_TYPE_DETAILS | EU1: TUBING_MATERIAL | EV1: TUBING_TYPE | EW1: TANK_VESSEL_SUBTYPE | EX1: TANK_VESSEL_DETAILS | EY1: TANK_TYPE | EZ1: TANK_MAX_PRESSURE | FA1: TANK_SET_POINT_RELIEF_DEVICE | FB1: TANK_RELIEF_VALVE_ACTVTD_IND | FC1: TANK_MOP_EXCEEDED_IND | FD1: SAFE_FILL_LEVEL | FE1: SAFE_FILL_LEVEL_EXCEEDED_IND | FF1: API_STD_OUT_OF_SERVICE_YEAR | FG1: API_STD_OUT_OF_SRVC_NONE_IND | FH1: API_STD_IN_SERVICE_YEAR | FI1: API_STD_NO_IN_SERVICE_IND | FJ1: ITEM_INVOLVED_DETAILS | FK1: INSTALLATION_YEAR | FL1: MANUFACTURED_YEAR | FM1: MATERIAL_INVOLVED | FN1: MATERIAL_DETAILS | FO1: RELEASE_TYPE | FP1: PUNCTURE_AXIAL | FQ1: PUNCTURE_CIRCUM | FR1: LEAK_TYPE | FS1: LEAK_TYPE_OTHER | FT1: RUPTURE_ORIENT | FU1: RUPTURE_DETAILS | FV1: RUPTURE_WIDTH | FW1: RUPTURE_LENGTH | FX1: RELEASE_TYPE_DETAILS | FY1: WILDLIFE_IMPACT_IND | FZ1: FISH_AQUATIC_IMPACT_IND | GA1: BIRDS_IMPACT_IND | GB1: TERRESTRIAL_IMPACT_IND | GC1: SOIL_CONTAMINATION | GD1: LONG_TERM_ASSESSMENT | GE1: REMEDIATION_IND | GF1: SURFACE_WATER_REMED_IND | GG1: GROUNDWATER_REMED_IND | GH1: SOIL_REMED_IND | GI1: VEGETATION_REMED_IND | GJ1: WILDLIFE_REMED_IND | GK1: WATER_CONTAM_IND | GL1: OCEAN_SEAWATER_IND | GM1: SURFACE_CONTAM_IND | GN1: GROUNDWATER_CONTAM_IND | GO1: DRINKING_WATER_CONTAM_IND | GP1: PRIVATE_WELL_CONTAM_IND | GQ1: PUBLIC_WATER_CONTAM_IND | GR1: AMOUNT_RELEASED | GS1: REL_WATER_NAME | GT1: COULD_BE_HCA | GU1: COMMODITY_REACHED_HCA | GV1: COMMERCIALLY_NAV_IND | GW1: COMMERCIALLY_NAV_YES_NO | GX1: HIGH_POP_IND | GY1: HIGH_POP_YES_NO | GZ1: OTHER_POP_IND | HA1: OTHER_POP_YES_NO | HB1: USA_DRINKING_IND | HC1: USA_DRINKING_YES_NO | HD1: USA_ECOLOGICAL_IND | HE1: USA_ECOLOGICAL_YES_NO | HF1: EST_COST_OPER_PAID | HG1: EST_COST_GAS_RELEASED | HH1: EST_COST_PROP_DAMAGE | HI1: EST_COST_EMERGENCY | HJ1: EST_COST_ENVIRONMENTAL | HK1: EST_COST_OTHER | HL1: EST_COST_OTHER_DETAILS | HM1: PRPTY | HN1: NUM_PERSONS_HOSP_NOT_OVNGHT | HO1: NUM_INJURED_TREATED_BY_EMT | HP1: NUM_RESIDENT_BUILDING_AFFCTD | HQ1: NUM_BUSINESS_BUILDING_AFFCTD | HR1: ACCIDENT_PSIG | HS1: MOP_PSIG | HT1: MOP_CFR_SECTION | HU1: MOP_CFR_SECTION_DETAILS | HV1: MAOP_ESTABLISHED_DATE | HW1: MAOP_REVERSAL_FLOW_IND | HX1: SURGE_ANALYSIS_DATE | HY1: ACCIDENT_PRESSURE | HZ1: PRESSURE_RESTRICTION_IND | IA1: EXCEED_RESTRICTION_IND | IB1: PHMSA_RESTRICTION_IND | IC1: LENGTH_SEGMENT_ISOLATED | ID1: INTERNAL_INSPECTION_IND | IE1: DIAMETER_CHANGE_IND | IF1: UNSUITABLE_MAINLINE_IND | IG1: TIGHT_MITERED_IND | IH1: OTHER_RESTRICTIONS_IND | II1: EXTRA_THICK_WALL_IND | IJ1: OTHER_INSPECTION_IND | IK1: INTERNAL_INSPECTION_DETAILS | IL1: OPERATION_COMPLICATIONS_IND | IM1: EXCESSIVE_DEBRIS_IND | IN1: LOW_OP_PRESSURE_IND | IO1: LOW_FLOW_IND | IP1: INCOMPAT_COMMOD_IND | IQ1: OTHER_COMPLICATIONS_IND | IR1: INSPECT_COMP_DETAILS | IS1: PIPELINE_FUNCTION | IT1: SCADA_IN_PLACE_IND | IU1: SCADA_OPERATING_IND | IV1: SCADA_FUNCTIONAL_IND | IW1: SCADA_DETECTION_IND | IX1: SCADA_CONF_IND | IY1: CPM_IN_PLACE_IND | IZ1: CPM_OPERATING_IND | JA1: CPM_FUNCTIONAL_IND | JB1: CPM_DETECTION_IND | JC1: CPM_CONF_IND | JD1: INVESTIGATION_STATUS | JE1: INVESTIGATION_STATUS_DETAILS | JF1: INVEST_SCHEDULE_IND | JG1: INVEST_NO_SCHEDULE_IND | JH1: INVEST_NO_SCHEDULE_IND_DETAILS | JI1: INVEST_NO_CONTROL_ROOM_IND | JJ1: INVEST_NO_CONTROLLER_IND | JK1: INVEST_INCORRECT_ACTION_IND | JL1: INVEST_FATIGUE_IND | JM1: INVEST_INCORRECT_PROCEDURE_IND | JN1: INVEST_INCORRECT_CONTROL_IND | JO1: INVEST_MAINT_IND | JP1: INVEST_OTHER_IND | JQ1: INVEST_OTHER_IND_DETAILS | JR1: EMPLOYEE_DRUG_TEST_IND | JS1: CONTRACTOR_DRUG_TEST_IND | JT1: NUM_EMPLOYEES_TESTED | JU1: NUM_EMPLOYEES_FAILED | JV1: NUM_CONTRACTORS_TESTED | JW1: NUM_CONTRACTORS_FAILED | JX1: CAUSE | JY1: CAUSE_DETAILS | JZ1: INTERNAL_EXTERNAL | KA1: VISUAL_EXAM_RESULTS | KB1: VISUAL_EXAM_DETAILS | KC1: GALVANIC_CORROSION_IND | KD1: ATMOSPHERE_CORROSION_IND | KE1: STRAY_CURRENT_CORROSION_IND | KF1: MICROBIOLOGICAL_CORROSION_IND | KG1: SELECTIVE_SEAM_CORROSION_IND | KH1: OTHER_CORROSION_IND | KI1: CORROSION_TYPE_DETAILS | KJ1: STRAY_CURRENT_TYPE | KK1: STRAY_CURRENT_DETAILS | KL1: FIELD_EXAM_BASIS_IND | KM1: METALLURGICAL_BASIS_IND | KN1: OTHER_BASIS_IND | KO1: CORROSION_BASIS_DETAILS | KP1: UNDERGROUND_LOCATION | KQ1: UNDER_CATHODIC_PROTECTION_IND | KR1: CATHODIC_PRO_START_YEAR | KS1: SHIELDING_EVIDENT | KT1: CATHODIC_SURVEY_TYPE | KU1: CP_ANNUAL_SURVEY_IND | KV1: CLOSE_INTERVAL_SURVEY_IND | KW1: OTHER_CP_SURVEY_IND | KX1: CP_ANNUAL_SURVEY_YEAR | KY1: CLOSE_INTERVAL_SURVEY_YEAR | KZ1: OTHER_CP_SURVEY_YEAR | LA1: OTHER_CP_SURVEY_DETAILS | LB1: EXTERNALLY_COATED | LC1: PRIOR_DAMAGE | LD1: INT_VISUAL_EXAM_RESULTS | LE1: INT_VISUAL_EXAM_DETAILS | LF1: INT_CORROSIVE_COMMODITY_IND | LG1: INT_WATER_ACID_IND | LH1: INT_MICROBIOLOGICAL_IND | LI1: INT_EROSION_IND | LJ1: INT_OTHER_CORROSION_IND | LK1: INT_CORROSION_TYPE_DETAILS | LL1: INT_FIELD_EXAM_BASIS_IND | LM1: INT_METALLURGICAL_BASIS_IND | LN1: INT_OTHER_BASIS_IND | LO1: INT_CORROSION_BASIS_DETAILS | LP1: INT_LOW_POINT_PIPE_LOC_IND | LQ1: INT_ELBOW_LOC_IND | LR1: INT_DEAD_LEG_LOC_IND | LS1: INT_OTHER_LOC_IND | LT1: CORROSION_LOCATION_DETAILS | LU1: CORROSION_INHIBITORS | LV1: CORROSION_LINING | LW1: CLEANING_DEWATERING | LX1: CORROSION_COUPONS | LY1: NATURAL_FORCE_TYPE | LZ1: EARTH_SUBTYPE | MA1: HEAVY_RAINS_SUBTYPE | MB1: LIGHTNING_SUBTYPE | MC1: TEMPERATURE_SUBTYPE | MD1: NF_OTHER_DETAILS | ME1: NF_EXTREME_WEATHER_IND | MF1: NF_HURRICANE_IND | MG1: NF_TROPICAL_STORM_IND | MH1: NF_TORNADO_IND | MI1: NF_OTHER_IND | MJ1: NF_EXTREME_WEATHER_DETAILS | MK1: EX_PARTY_TYPE | ML1: PRIOR_NOTIFICATION_IND | MM1: ONE_CALL_SYSTEM_IND | MN1: EXCAVATOR_IND | MO1: CONTRACTOR_IND | MP1: LANDOWNER_IND | MQ1: STATE_LAW_EXEMPT_IND | MR1: STATE_LAW_EXEMPT_TYPE | MS1: STATE_LAW_EXEMPT_DETAIL | MT1: STATE_LAW_EXEMPT_AUTHORITY | MU1: STATE_LAW_EXEMPT_CRITERIA | MV1: NOTIFY_CGA_DIRT | MW1: PUBLIC_ROW_IND | MX1: PUBLIC_SUBTYPE | MY1: PRIVATE_ROW_IND | MZ1: PRIVATE_SUBTYPE | NA1: PIPELINE_EASEMENT_ROW_IND | NB1: POWER_TRANSMISSION_ROW_IND | NC1: RAILROAD_ROW_IND | ND1: PUBLIC_UTIL_EASEMENT_ROW_IND | NE1: FEDERAL_LAND_ROW_IND | NF1: UNKNOWN_ROW_IND | NG1: JOINT_TRENCH_IND | NH1: CROSS_BORE_IND | NI1: DEPTH_OF_GRADE | NJ1: DEPTH_OF_GRADE_DETAIL | NK1: EXCAVATOR_TYPE | NL1: EXCAVATOR_EQUIPMENT | NM1: WORK_PERFORMED | NN1: ONE_CALL_NOTIFIED_IND | NO1: ONE_CALL_TICKET_NUM | NP1: ONE_CALL_CENTER_NAME | NQ1: WHITE_LINED_IND | NR1: LOCATOR_TYPE | NS1: VISIBLE_MARKS | NT1: SERVICE_INTERRUPTION | NU1: SERVICE_INTERRUPTION_HOURS | NV1: ROOT_CAUSE_CATEGORY | NW1: ROOT_CAUSE_TYPE | NX1: ROOT_CAUSE_TYPE_OTHER | NY1: OUTSIDE_FORCE_TYPE | NZ1: VEHICLE_SUBTYPE | OA1: OSF_HURRICANE_IND | OB1: OSF_TROPICAL_STORM_IND | OC1: OSF_TORNADO_IND | OD1: OSF_HEAVY_RAINS_IND | OE1: OSF_OTHER_WEATHER_IND | OF1: OSF_OTHER_WEATHER_DETAILS | OG1: INTENTIONAL_SUBTYPE | OH1: INTENTIONAL_DETAILS | OI1: OSF_OTHER_DETAILS | OJ1: DRIVER_ISSUED_CITATION_IND | OK1: CITATION_SPEED_IND | OL1: CITATION_RECKLESS_IND | OM1: CITATION_DUI_IND | ON1: CITATION_OTHER_IND | OO1: CITATION_OTHER_DETAIL | OP1: DRIVER_IN_CONTROL_IND | OQ1: ESTIMATED_SPEED | OR1: ESTIMATED_SPEED_UNKNOWN_IND | OS1: VEHICLE_TYPE | OT1: VEHICLE_TRAVEL_FROM | OU1: VEHICLE_TRAVEL_DISTANCE_FT | OV1: PROTECTIONS_INSTALLED_IND | OW1: PROTECTION_BOLLARDS_POST_IND | OX1: PROTECTION_BARRICADES_IND | OY1: PROTECTION_GUARD_RAILS_IND | OZ1: PROTECTION_OTHER_IND | PA1: PROTECTION_OTHER_DETAIL | PB1: FIELD_EXAM_IND | PC1: METALLURGICAL_IND | PD1: OTHER_ANALYSIS_IND | PE1: OTHER_ANALYSIS_DETAILS | PF1: STILL_UNDER_INVEST_IND | PG1: FAILURE_TYPE | PH1: FATIGUE_VIBR_RELATED | PI1: FAILURE_SUBTYPE | PJ1: FATIGUE_VIBR_RELATED_OTHER | PK1: MECHANICAL_STRESS | PL1: OTHER_FACTOR | PM1: OTHER_FACTOR_DETAILS | PN1: STRESS_SUBTYPE | PO1: STRESS_DETAILS | PP1: ADDITIONAL_DENT_IND | PQ1: ADDITIONAL_GOUGE_IND | PR1: ADDITIONAL_PIPE_BEND_IND | PS1: ADDITIONAL_ARC_BURN_IND | PT1: ADDITIONAL_CRACK_IND | PU1: ADDITIONAL_LACK_FUSION_IND | PV1: ADDITIONAL_LAMINATION_IND | PW1: ADDITIONAL_BUCKLE_IND | PX1: ADDITIONAL_WRINKLE_IND | PY1: PWF_ADDL_MISALIGNMENT_IND | PZ1: ADDITIONAL_BURNT_STEEL_IND | QA1: PWF_ADDITIONAL_OTHER_IND | QB1: EQ_FAILURE_TYPE | QC1: CONTROL_VALVE_IND | QD1: INSTRUMENTATION_IND | QE1: SCADA_IND | QF1: COMMUNICATIONS_IND | QG1: BLOCK_VALVE_IND | QH1: CHECK_VALVE_IND | QI1: RELIEF_VALVE_IND | QJ1: POWER_FAILURE_IND | QK1: STOPPLE_CONTROL_FITTING_IND | QL1: ESD_SYSTEM_FAILURE_IND | QM1: OTHER_CONTROL_RELIEF_IND | QN1: OTHER_CONTROL_RELIEF_DETAILS | QO1: OTHER_PUMP_IND | QP1: OTHER_PUMP_DETAILS | QQ1: OTHER_STRIPPED_IND | QR1: OTHER_STRIPPED_DETAILS | QS1: OTHER_NON_THREADED_IND | QT1: OTHER_NON_THREADED_DETAILS | QU1: FAILURE_DETAILS | QV1: ADDITIONAL_VIBRATION_IND | QW1: ADDITIONAL_OVERPRESSURE_IND | QX1: ADDITIONAL_SUPPORT_IND | QY1: ADDITIONAL_DEFECT_IND | QZ1: ADDITIONAL_ELECTRICITY_IND | RA1: ADDITIONAL_INSTALLATION_IND | RB1: ADDITIONAL_IMPROPER_MNTNCE_IND | RC1: ADDITIONAL_MISMATCH_IND | RD1: ADDITIONAL_DISSIMILAR_IND | RE1: ADDITIONAL_BREAKDOWN_IND | RF1: ADDITIONAL_VALVE_IND | RG1: ADDITIONAL_ALARM_IND | RH1: IEF_ADDL_MISALIGNMENT_IND | RI1: ADDITIONAL_THERMAL_IND | RJ1: ADDITIONAL_EROSION_WEAR_IND | RK1: EQ_ADDITIONAL_OTHER_IND | RL1: EQ_ADDITIONAL_OTHER_DETAILS | RM1: OPERATION_TYPE | RN1: OVERFLOW_OTHER_IND | RO1: OVERFLOW_OTHER_DETAILS | RP1: OPERATION_DETAILS | RQ1: RELATED_INADEQUATE_PROC_IND | RR1: RELATED_NO_PROC_IND | RS1: RELATED_FAILURE_FOLLOW_IND | RT1: RELATED_OTHER_IND | RU1: OPERATION_RELATED_DETAILS | RV1: CATEGORY_TYPE | RW1: OPERATOR_QUALIFICATION_IND | RX1: QUALIFIED_INDIVIDUALS | RY1: OTHER_TYPE | RZ1: MISC_DETAILS | SA1: UNKNOWN_SUBTYPE | SB1: INCIDENT_UNKNOWN_COMMENTS | SC1: COLLECTED_DATA_IND | SD1: AXIAL_MAGNETIC_FLX_LKG_IND | SE1: CIR_TRN_WAVE_MGN_FLX_LKG_IND | SF1: ULTRASONIC_IND | SG1: GEOMETRY_DEFORMATION_IND | SH1: EMAT_IND | SI1: CPCM_IND | SJ1: OTHER_TOOL_TECH_IND | SK1: AXIAL_RECENT_YEAR | SL1: AXIAL_RCNT_PROPUL_METHOD | SM1: AXIAL_RCNT_ATTUNED_DETECT | SN1: AXIAL_RCNT_ATND_DTCT_DTLS | SO1: AXIAL_RCNT_ATND_DTCT_METAL | SP1: AXIAL_RCNT_ATT_DT_METAL_DTLS | SQ1: AXIAL_PREVIOUS_YEAR | SR1: AXIAL_PREV_PROPUL_METHOD | SS1: AXIAL_PREV_ATTUNED_DETECT | ST1: AXIAL_PREV_ATND_DTCT_DTLS | SU1: AXIAL_PREV_ATND_DTCT_METAL | SV1: AXIAL_PREV_ATT_DT_METAL_DTLS | SW1: CIRC_WAVE_RECENT_YEAR | SX1: CIRC_WV_RCNT_PROPUL_METHOD | SY1: CIRC_WV_RCNT_RESOLUTION | SZ1: CIRC_WV_RCNT_RESOLUTION_DTLS | TA1: CIRC_WV_PREVIOUS_YEAR | TB1: CIRC_WV_PREV_PROPUL_METHOD | TC1: CIRC_WV_PREV_RESOLUTION | TD1: CIRC_WV_PREV_RESOLUTION_DTLS | TE1: ULTRASONIC_RECENT_YEAR | TF1: ULTRASONIC_RCNT_PROPUL_METHOD | TG1: ULTRASONIC_RCNT_ATTUNED | TH1: ULTRA_RCNT_ATTUNEDD_DTLS | TI1: UTRA_RCNT_ATT_METL_RESOLUTION | TJ1: UTRA_RCNT_ATT_METL_RES_DTLS | TK1: ULTR_PREVIOUS_YEAR | TL1: ULTRA_PREV_PROPUL_METHOD | TM1: ULTRA_PREV_ATTUNED | TN1: ULTRA_PREV_ATTUNED_DTLS | TO1: UTRA_PREV_ATT_METL_RESOLUTION | TP1: UTRA_PREV_ATT_METL_RES_DTLS | TQ1: GEOMETRY_RECENT_YEAR | TR1: GEOMETRY_RCNT_PROPUL_METHOD | TS1: GEOMETRY_RCNT_RESOLUTION | TT1: GEOMETRY_RCNT_RESOLUTION_DTLS | TU1: GEOMETRT_RCNT_MEASUR_CUPS | TV1: GEOMETRY_PREVIOUS_YEAR | TW1: GEOMETRY_PREV_PROPUL_METHOD | TX1: GEOMETRY_PREV_RESOLUTION | TY1: GEOMETRY_PREV_RESOLUTION_DTLS | TZ1: GEOMETRT_PREV_MEASUR_CUPS | UA1: EMAT_RECENT_YEAR | UB1: EMAT_RCNT_PROPUL_METHOD | UC1: EMAT_PREVIOUS_YEAR | UD1: EMAT_PREV_PROPUL_METHOD | UE1: CPCM_RECENT_YEAR | UF1: CPCM_RCNT_PROPUL_METHOD | UG1: CPCM_PREVIOUS_YEAR | UH1: CPCM_PREV_PROPUL_METHOD | UI1: OTHER_TOOL | UJ1: OTHER_RECENT_YEAR | UK1: OTHER_RCNT_PROPUL_METHOD | UL1: OTHER_PREVIOUS_YEAR | UM1: OTHER_PREV_PROPUL_METHOD | UN1: INSP_COMPL_BEFORE_DAMAGE_IND | UO1: HAS_HYDRTST_CONDUC_BEFORE_IND | UP1: HYDRTST_MOST_RCNT_YEAR | UQ1: HYDRTST_MOST_RCNT_PRESSURE | UR1: DIRECT_ASMNT_CONDUCTED | US1: DIRECT_ASMNT_AT_PNT_ACCDNT_YR | UT1: DIRECT_ASMNT_PNT_NOT_IDNTF_YR | UU1: ASMNT_ECDA_RCNT_IND | UV1: ASMNT_ECDA_RCNT_YEAR | UW1: ASMNT_OTHER_RCNT_IND | UX1: ASMNT_OTHER_TYPE | UY1: ASMNT_OTHER_RCNT_YEAR | UZ1: NON_DESTRUCTIVE_EXAM_IND | VA1: EXM_RADIOGRAPHY_RCNT_YEAR | VB1: EXM_WAVE_ULTRASONIC_RCNT_YEAR | VC1: EXM_HANDL_ULTRASONIC_RCNT_YEAR | VD1: EXM_WET_MGNT_PARTCL_RCNT_YEAR | VE1: EXM_DRY_MGNT_PARTCL_RCNT_YEAR | VF1: EXM_OTHER_TYPE | VG1: EXM_OTHER_RCNT_YEAR | VH1: EXM_RADIOGRAPHY_RCNT_IND | VI1: EXM_WAVE_ULTRASONIC_RCNT_IND | VJ1: EXM_HANDL_ULTRASONIC_RCNT_IND | VK1: EXM_WET_MGNT_PARTCL_RCNT_IND | VL1: EXM_DRY_MGNT_PARTCL_RCNT_IND | VM1: EXM_OTHER_RCNT_IND | VN1: EXTRNL_COR_GALVANIC_IND | VO1: EXTRNL_COR_ATMOSPHERIC_IND | VP1: EXTRNL_COR_STRAY_CURRENT_IND | VQ1: EXTRNL_COR_MICROBIOLOGIC_IND | VR1: EXTRNL_COR_SELECTIVE_SEAM_IND | VS1: INTRNL_COR_CORROSIVE_CMDTY_IND | VT1: INTRNL_COR_WTR_DRPOUT_ACID_IND | VU1: INTRNL_COR_MICROBIOLOGIC_IND | VV1: INTRNL_COR_EROSION_IND | VW1: NF_EARTH_MOVEMENT_IND | VX1: NF_HEAVY_RAINS_IND | VY1: NF_LIGHTNING_IND | VZ1: NF_TEMPERATURE_IND | WA1: NF_HIGH_WINDS_IND | WB1: NF_VEGITATION_ROOT_IND | WC1: EXCVTN_DMG_OPERATOR_IND | WD1: EXCVTN_DMG_OP_CONTRACTOR_IND | WE1: EXCVTN_DMG_THIRD_PARTY_IND | WF1: EXCVTN_DMG_PREVIOUS_DAMAGE_IND | WG1: OSF_NEARBY_INDUSTRIAL_IND | WH1: OSF_VEHICLE_IND | WI1: OSF_BOAT_IND | WJ1: OSF_OTHER_MARITIME_IND | WK1: OSF_ELECTRICAL_ARCING_IND | WL1: OSF_PREVIOUS_MECHANICAL_IND | WM1: OSF_INTENTIONAL_IND | WN1: PWF_DESIGN_IND | WO1: PWF_CONSTRUCTION_IND | WP1: PWF_INSTALLATION_IND | WQ1: PWF_FABRICATION_IND | WR1: PWF_MANUFACTURING_IND | WS1: PWF_ENV_STRESS_CORROSION_IND | WT1: PWF_ENV_SULFIDE_STRESS_IND | WU1: PWF_ENV_HYDROGEN_STRESS_IND | WV1: PWF_ENV_HARD_SPOT_IND | WW1: EQF_CONTROL_RELEAF_IND | WX1: EQF_PUMP_EQUIPMENT_IND | WY1: EQF_THREADED_COUPLING_IND | WZ1: EQF_NON_THREADED_IND | XA1: EQF_DEFECTIVE_FITTING_IND | XB1: EQF_EQUIPMENT_BODY_IND | XC1: IO_DAMAGE_BY_OPERATOR_IND | XD1: IO_TANK_VESSEL_IND | XE1: IO_VALVE_POSITION_IND | XF1: IO_EQUIPMENT_OVERPRESSURE_IND | XG1: IO_NOT_INSTALLED_PROPERLY_IND | XH1: IO_WRONG_EQUIPMENT_IND | XI1: IO_INADEQUATE_PROCEDURE_IND | XJ1: IO_NO_PROCEDURE_IND | XK1: IO_FOLLOW_PROCEDURE_IND | XL1: PREPARER_NAME | XM1: PREPARER_TITLE | XN1: PREPARER_EMAIL | XO1: PREPARER_TELEPHONE | XP1: PREPARER_FAX | XQ1: PREPARED_DATE | XR1: LOCAL_CONTACT_NAME | XS1: LOCAL_CONTACT_EMAIL | XT1: LOCAL_CONTACT_TELEPHONE | XU1: AUTHORIZER_NAME | XV1: AUTHORIZER_TELEPHONE | XW1: AUTHORIZER_TITLE | XX1: AUTHORIZER_EMAIL | XY1: NARRATIVE
A2: 0 | B2: 45838 | C2: 2025 | D2: 20250158 | E2: 41089 | F2: ORIGINAL | G2: 39368 | H2: CRESTWOOD MIDSTREAM PARTNERS LP | I2: 1300 MAIN STREET | J2: HOUSTON | K2: TX | L2: 77002 | M2: 45814.733 | N2: CENTRAL | O2: YES | P2: 47.80288 | Q2: -102.8753 | R2: CRUDE OIL | W2: 0.1 | Y2: 0.1 | Z2: NO | AF2: 0 | AG2: NO | AM2: 0 | AN2: LOCAL OPERATING PERSONNEL, INCLUDING CONTRACTORS | AP2: OPERATOR EMPLOYEE | AQ2: 45814.733 | AR2: ONSHORE PUMP/METER STATION EQUIPMENT AND PIPING | AS2: ONSHORE | AT2: NORMAL OPERATION, INCLUDES PAUSES BETWEEN BATCHES AND DURING MAINTENANCE | AU2: YES | AW2: 45814.733 | AX2: 45815.326 | AZ2: NO | BC2: 45814.733 | BD2: 45814.733 | BE2: 45814.762 | BF2: 1433356 | BG2: 1433488 | BH2: YES | BI2: 45814.733 | BJ2: OPERATOR/CONTRACTOR | BL2: 0.1 | BM2: NO | BV2: YES | BW2: 45814.736 | BX2: NO | CA2: 0 | CB2: ARROW CENTRAL DELIVERY POINT | CC2: 8-INCH 100 LINE | CD2: ND | CE2: 58847 | CF2: Not Within a Municipality | CG2: MCKENZIE | CH2: SURVEY STATION NO. | CI2: 0+00 | CJ2: NO | CK2: TOTALLY CONTAINED ON OPERATOR-CONTROLLED PROPERTY | CL2: ABOVEGROUND | CM2: INSIDE A BUILDING | CP2: NO | DM2: INTRASTATE | DN2: PUMP | EQ2: CENTRIFUGAL | ES2: INJECTION | FK2: 2018 | FL2: 2018 | FM2: CARBON STEEL | FO2: LEAK | FR2: SEAL OR PACKING | FY2: NO | GC2: NO | GD2: NO | GE2: NO | GK2: NO | GT2: NO | GU2: NO | HF2: 0 | HG2: 5 | HH2: 25000 | HI2: 100 | HJ2: 0 | HK2: 0 | HM2: 25105 | HN2: 0 | HO2: 0 | HP2: 0 | HQ2: 0 | HR2: 256 | HS2: 740 | HT2: FOUR HOUR TEST OR OPERATION ß195.406(A)(5) | HV2: 42838 | HW2: NO | HY2: PRESSURE DID NOT EXCEED MOP | HZ2: NO | IS2: > 20% SMYS REGULATED TRANSMISSION | IT2: YES | IU2: YES | IV2: YES | IW2: YES | IX2: NO | IY2: YES | IZ2: YES | JA2: YES | JB2: NO | JC2: NO | JD2: NO, THE OPERATOR DID NOT FIND THAT AN INVESTIGATION OF THE CONTROLLER(S) ACTIONS OR CONTROL ROOM ISSUES WAS NECESSARY DUE TO: (PROVIDE AN EXPLANATION FOR WHY THE OPERATOR DID NOT INVESTIGATE) | JE2: A REVIEW OF THE ACCIDENT DETERMINED THAT THERE WERE NO CONTROL ROOM ACTIONS THAT CONTRIBUTED TO THE EVENT. | JR2: NO | JS2: NO | JX2: OTHER ACCIDENT CAUSE | JY2: UNKNOWN | RY2: UNKNOWN | SA2: STILL UNDER INVESTIGATION, CAUSE OF ACCIDENT TO BE DETERMINED* (*SUPPLEMENTAL REPORT REQUIRED) | XL2: TODD NARDOZZI | XM2: DIRECTOR - DOT COMPLIANCE | XN2: todd.nardozzi@energytransfer.com | XO2: 713-989-7126 | XQ2: 45838 | XU2: TODD NARDOZZI | XV2: 713-989-7126 | XW2: DIRECTOR - DOT COMPLIANCE | XX2: todd.nardozzi@energytransfer.com | XY2: ON 06/06/25 AT APPROXIMATELY 17:35, AN OPERATOR EMPLOYEE DISCOVERED A SMALL FIRE ON PUMP C3 IN THE PUMP ROOM. THE FIRE WAS IMMEDIATELY EXTINGUISHED WITH A FIRE EXTINGUISHER. OPERATIONS DISCOVERED CRUDE OIL LEAKING FROM A SEAL ON THE 8INCH 100 LINE INSIDE ARROW CENTRAL DELIVERY POINT (CDP). APPROXIMATELY 1 GALLON OF CRUDE OIL WAS RELEASED. A SMALL AMOUNT OF PRODUCT WAS CONSUMED BY THE FIRE. THE REMAINING PRODUCT WAS CLEANED-UP BY LOCAL PERSONNEL. THE PUMP WAS REMOVED AND FLANGES BLINDED. THE PUMP HAS BEEN SENT TO A THIRD PARTY FOR ANALYSIS, INSPECTION AND REPAIR. THE LINE WAS RESTARTED ON 06/07/25 AT 07:50. THE CAUSE OF THE ACCIDENT IS STILL UNDER INVESTIGATION BY A THIRD PARTY. A SUPPLEMENTAL REPORT WILL BE SUBMITTED ONCE THE INVESTIGATION IS COMPLETE.
A3: 5 | B3: 45824 | C3: 2025 | D3: 20250148 | E3: 41029 | F3: ORIGINAL | G3: 31476 | H3: ET CRUDE OPERATING LLC | I3: 1300 MAIN STREET | J3: HOUSTON | K3: TX | L3: 77002 | M3: 45800.635 | N3: CENTRAL | O3: YES | P3: 36.0175 | Q3: -96.753889 | R3: CRUDE OIL | W3: 80 | Y3: 80 | Z3: NO | AF3: 0 | AG3: NO | AM3: 0 | AN3: LOCAL OPERATING PERSONNEL, INCLUDING CONTRACTORS | AP3: OPERATOR EMPLOYEE | AQ3: 45800.635 | AR3: ONSHORE TERMINAL/TANK FARM EQUIPMENT AND PIPING | AS3: ONSHORE | AT3: NORMAL OPERATION, INCLUDES PAUSES BETWEEN BATCHES AND DURING MAINTENANCE | AU3: YES | AW3: 45800.635 | AY3: YES | AZ3: NO | BC3: 45800.635 | BD3: 45800.635 | BE3: 45800.665 | BF3: 1432002 | BG3: 1432157 | BH3: NO | BV3: YES | BW3: 45800.635 | BX3: YES | BY3: 45800.639 | BZ3: 45800.705 | CA3: 0 | CB3: CUSHING TANK FARM | CC3: CIMARRON LINE | CD3: OK | CE3: 74023 | CF3: Not Within a Municipality | CG3: PAYNE | CH3: SURVEY STATION NO. | CI3: 0+00 | CJ3: NO | CK3: TOTALLY CONTAINED ON OPERATOR-CONTROLLED PROPERTY | CL3: UNDERGROUND | CM3: UNDER SOIL | CO3: 42 | CP3: NO | DM3: INTERSTATE | DN3: PIPE | DO3: PIPE BODY | DP3: NO | DQ3: 8 | DR3: 0.312 | DS3: 35000 | DT3: GRADE B | DU3: ERW - HIGH FREQUENCY | DW3: UNKNOWN | DX3: FUSION BONDED EPOXY(FBE) | DZ3: NO | FK3: UNKNOWN | FL3: UNKNOWN | FM3: CARBON STEEL | FO3: LEAK | FR3: PINHOLE | FY3: NO | GC3: YES | GD3: NO | GE3: YES | GH3: YES | GK3: NO | GT3: NO | GU3: NO | HF3: 0 | HG3: 50 | HH3: 5000 | HI3: 60000 | HJ3: 30000 | HK3: 0 | HM3: 95050 | HN3: 0 | HO3: 0 | HP3: 0 | HQ3: 0 | HR3: 117 | HS3: 285 | HT3: COMPONENT DESIGN PRESSURE ß195.406(A)(2) | HV3: 42736 | HW3: NO | HY3: PRESSURE DID NOT EXCEED MOP | HZ3: NO | IS3: > 20% SMYS REGULATED TRANSMISSION | IT3: YES | IU3: YES | IV3: YES | IW3: NO | IX3: NO | IY3: NO | JD3: NO, THE OPERATOR DID NOT FIND THAT AN INVESTIGATION OF THE CONTROLLER(S) ACTIONS OR CONTROL ROOM ISSUES WAS NECESSARY DUE TO: (PROVIDE AN EXPLANATION FOR WHY THE OPERATOR DID NOT INVESTIGATE) | JE3: A REVIEW OF THE ACCIDENT DETERMINED THAT THERE WERE NO CONTROL ROOM ACTIONS THAT CONTRIBUTED TO THE EVENT. | JR3: NO | JS3: NO | JX3: OTHER ACCIDENT CAUSE | JY3: UNKNOWN | RY3: UNKNOWN | SA3: STILL UNDER INVESTIGATION, CAUSE OF ACCIDENT TO BE DETERMINED* (*SUPPLEMENTAL REPORT REQUIRED) | XL3: TODD NARDOZZI | XM3: DIRECTOR - DOT COMPLIANCE | XN3: todd.nardozzi@energytransfer.com | XO3: 713-989-7126 | XQ3: 45824 | XU3: TODD NARDOZZI | XV3: 713-989-7126 | XW3: DIRECTOR - DOT COMPLIANCE | XX3: todd.nardozzi@energytransfer.com | XY3: ON 05/23/25 AT 15:15, CRUDE OIL WAS DISCOVERED ON THE GROUND BENEATH STATION PIPING AT TANK 2538 CUSHING TANK FARM. THE LEAK WAS COMING FROM A PINHOLE AT THE 6 O'CLOCK POSITION ON THE CIMARRON 8-INCH LINE. APPROXIMATELY 80 BARRELS OF CRUDE OIL WAS RELEASED ON THE GROUND. CLEANUP CONTRACTORS REMOVED PRODUCT AND CONTAMINATED SOIL. THE LEAK WAS REPAIRED WITH A PLIDCO CLAMP. THE LINE WAS DRAINED, AND THE FAILED SECTION WAS CUT OUT AND SENT TO A THIRD PARTY LAB FOR ANALYSIS. THE LINE REMAINS SHUTDOWN. THE CAUSE OF THE LEAK IS STILL UNDER INVESTIGATION. A SUPPLEMENTAL REPORT WILL BE SUBMITTED ONCE THE LAB REPORT AND INVESTIGATION ARE COMPLETED.
A4: 7 | B4: 45826 | C4: 2025 | D4: 20250151 | E4: 41054 | F4: ORIGINAL | G4: 32099 | H4: ENERGY TRANSFER COMPANY | I4: 1300 MAIN STREET | J4: HOUSTON | K4: TX | L4: 77002 | M4: 45800.332 | N4: CENTRAL | O4: YES | P4: 32.00959 | Q4: -102.03685 | R4: CRUDE OIL | W4: 1 | Y4: 1 | Z4: NO | AF4: 0 | AG4: NO | AM4: 0 | AN4: LOCAL OPERATING PERSONNEL, INCLUDING CONTRACTORS | AP4: OPERATOR EMPLOYEE | AQ4: 45800.332 | AR4: ONSHORE TERMINAL/TANK FARM EQUIPMENT AND PIPING | AS4: ONSHORE | AT4: NORMAL OPERATION, INCLUDES PAUSES BETWEEN BATCHES AND DURING MAINTENANCE | AU4: YES | AW4: 45800.337 | AX4: 45800.626 | AZ4: YES | BA4: OPERATOR | BB4: 45800.383 | BC4: 45800.335 | BD4: 45800.347 | BF4: NRC NOTIFICATION NOT REQUIRED | BH4: NO | BV4: NO | BX4: NO | CA4: 0 | CB4: MIDLAND TANK FARM | CC4: 24INCH MIDLAND MESA C20017 | CD4: TX | CE4: 79706 | CF4: Not Within a Municipality | CG4: MIDLAND | CH4: SURVEY STATION NO. | CI4: 0+00 | CJ4: NO | CK4: TOTALLY CONTAINED ON OPERATOR-CONTROLLED PROPERTY | CL4: ABOVEGROUND | CM4: TYPICAL ABOVEGROUND FACILITY PIPING OR APPURTENANCE | CP4: NO | DM4: INTRASTATE | DN4: FLANGE ASSEMBLY | FK4: 2012 | FL4: 2012 | FM4: CARBON STEEL | FO4: LEAK | FR4: SEAL OR PACKING | FY4: NO | GC4: YES | GD4: NO | GE4: YES | GH4: YES | GK4: NO | GT4: NO | GU4: NO | HF4: 0 | HG4: 33 | HH4: 0 | HI4: 1955 | HJ4: 183 | HK4: 0 | HM4: 2171 | HN4: 0 | HO4: 0 | HP4: 0 | HQ4: 0 | HR4: 420 | HS4: 285 | HT4: COMPONENT DESIGN PRESSURE ß195.406(A)(2) | HV4: 41030 | HW4: NO | HY4: PRESSURE EXCEEDED 110% OF MOP | HZ4: NO | IS4: > 20% SMYS REGULATED TRANSMISSION | IT4: YES | IU4: YES | IV4: YES | IW4: NO | IX4: NO | IY4: NO | JD4: NO, THE OPERATOR DID NOT FIND THAT AN INVESTIGATION OF THE CONTROLLER(S) ACTIONS OR CONTROL ROOM ISSUES WAS NECESSARY DUE TO: (PROVIDE AN EXPLANATION FOR WHY THE OPERATOR DID NOT INVESTIGATE) | JE4: A REVIEW OF THE ACCIDENT DETERMINED THAT THERE WERE NO CONTROL ROOM ACTIONS THAT CONTRIBUTED TO THE EVENT. | JR4: YES | JS4: NO | JT4: 1 | JU4: 0 | JX4: OTHER ACCIDENT CAUSE | JY4: UNKNOWN | RY4: UNKNOWN | SA4: STILL UNDER INVESTIGATION, CAUSE OF ACCIDENT TO BE DETERMINED* (*SUPPLEMENTAL REPORT REQUIRED) | XL4: TODD NARDOZZI | XM4: DIRECTOR - DOT COMPLIANCE | XN4: todd.nardozzi@energytransfer.com | XO4: 713-989-7126 | XQ4: 45826 | XU4: TODD NARDOZZI | XV4: 713-989-7126 | XW4: DIRECTOR - DOT COMPLIANCE | XX4: todd.nardozzi@energytransfer.com | XY4: ON 05/23/25 AT APPROXIMATELY 07:58, A LOCAL OPERATOR EMPLOYEE CLOSED MOV 6001 CAUSING THE 24INCH MIDLAND MESA C20017 LINE TO OVERPRESSURE, WHICH LED TO A RELEASE OF CRUDE OIL ONTO THE GROUND. THE LINE WAS IMMEDIATELY SHUTDOWN AND ISOLATED. THE LEAK WAS DISCOVERED TO BE COMING FROM A FLANGE. FLANGES WERE RETORQUED TO STOP LEAK, THE LINE WAS INSPECTED VISUALLY AND WAS RETURNED TO SERVICE. APPROXIMATELY 1 BARREL OF CRUDE OIL WAS RELEASED. CLEANUP CONTRACTORS REMOVED PRODUCT AND REMEDIATED IMPACTED SOIL. THE CAUSE OF THE ACCIDENT IS STILL UNDER INVESTIGATION. A SUPPLEMENTAL REPORT WILL BE SUBMITTED ONCE COMPLETE.
A5: 10 | B5: 45824 | C5: 2025 | D5: 20250147 | E5: 41028 | F5: ORIGINAL | G5: 32099 | H5: ENERGY TRANSFER COMPANY | I5: 1300 MAIN STREET | J5: HOUSTON | K5: TX | L5: 77002 | M5: 45797.433 | N5: CENTRAL | O5: YES | P5: 32.3066 | Q5: -101.8971 | R5: CRUDE OIL | W5: 1 | Y5: 1 | Z5: NO | AF5: 0 | AG5: NO | AM5: 0 | AN5: LOCAL OPERATING PERSONNEL, INCLUDING CONTRACTORS | AP5: OPERATOR EMPLOYEE | AQ5: 45797.433 | AR5: ONSHORE PUMP/METER STATION EQUIPMENT AND PIPING | AS5: ONSHORE | AT5: NORMAL OPERATION, INCLUDES PAUSES BETWEEN BATCHES AND DURING MAINTENANCE | AU5: NO | AV5: UTILIZED OTHER LACTS TO CONTINUE FLOW | AZ5: YES | BA5: OPERATOR | BB5: 45800.361 | BC5: 45797.433 | BD5: 45797.433 | BF5: NRC NOTIFICATION NOT REQUIRED | BH5: NO | BV5: NO | BX5: NO | CA5: 0 | CB5: RC SMITH STATION | CC5: 23025 - 12INCH RC SMITH TO SUNOCO MIDLAND TERMINAL | CD5: TX | CE5: 79783 | CF5: Not Within a Municipality | CG5: MARTIN | CH5: SURVEY STATION NO. | CI5: 0+00 | CJ5: NO | CK5: TOTALLY CONTAINED ON OPERATOR-CONTROLLED PROPERTY | CL5: ABOVEGROUND | CM5: TYPICAL ABOVEGROUND FACILITY PIPING OR APPURTENANCE | CP5: NO | DM5: INTRASTATE | DN5: OTHER | FJ5: 1 INCH PIPE NIPPLE | FK5: 2013 | FL5: UNKNOWN | FM5: CARBON STEEL | FO5: LEAK | FR5: CRACK | FY5: NO | GC5: YES | GD5: NO | GE5: YES | GH5: YES | GK5: NO | GT5: NO | GU5: NO | HF5: 0 | HG5: 80 | HH5: 3500 | HI5: 180 | HJ5: 1000 | HK5: 0 | HM5: 4760 | HN5: 0 | HO5: 0 | HP5: 0 | HQ5: 0 | HR5: 325 | HS5: 1480 | HT5: COMPONENT DESIGN PRESSURE ß195.406(A)(2) | HV5: 41548 | HW5: NO | HY5: PRESSURE DID NOT EXCEED MOP | HZ5: NO | IS5: > 20% SMYS REGULATED TRANSMISSION | IT5: YES | IU5: YES | IV5: YES | IW5: NO | IX5: NO | IY5: YES | IZ5: YES | JA5: YES | JB5: NO | JC5: NO | JD5: NO, THE OPERATOR DID NOT FIND THAT AN INVESTIGATION OF THE CONTROLLER(S) ACTIONS OR CONTROL ROOM ISSUES WAS NECESSARY DUE TO: (PROVIDE AN EXPLANATION FOR WHY THE OPERATOR DID NOT INVESTIGATE) | JE5: A REVIEW OF THE ACCIDENT DETERMINED THAT THERE WERE NO CONTROL ROOM ACTIONS THAT CONTRIBUTED TO THE EVENT. | JR5: NO | JS5: NO | JX5: OTHER ACCIDENT CAUSE | JY5: UNKNOWN | RY5: UNKNOWN | SA5: STILL UNDER INVESTIGATION, CAUSE OF ACCIDENT TO BE DETERMINED* (*SUPPLEMENTAL REPORT REQUIRED) | XL5: TODD NARDOZZI | XM5: DIRECTOR - DOT COMPLIANCE | XN5: todd.nardozzi@energytransfer.com | XO5: 713-989-7126 | XQ5: 45824 | XU5: TODD NARDOZZI | XV5: 713-989-7126 | XW5: DIRECTOR - DOT COMPLIANCE | XX5: todd.nardozzi@energytransfer.com | XY5: ON 05/20/2025 AT APPROXIMATELY 10:23, A MEASUREMENT SPECIALIST REPORTED A RELEASE AT RC SMITH STATION. DISCOVERED LEAK FROM CRACKED NIPPLE ON THE PUMP SIDE OF 23025 - 12INCH RC SMITH TO SUNOCO MIDLAND TERMINAL. APPROXIMATELY 1 BARREL OF CRUDE OIL WAS RELEASED. CLEANUP CONTRACTORS REMOVED PRODUCT AND REMEDIATED IMPACTED SOIL. REPAIRED LEAK BY REPLACING FAILED NIPPLE. THE CAUSE OF THE ACCIDENT IS STILL UNDER INVESTIGATION. A SUPPLEMENTAL REPORT WILL BE SUBMITTED ONCE THE INVESTIGATION IS COMPLETE.
A6: 18 | B6: 45793 | C6: 2025 | D6: 20250124 | E6: 40896 | F6: ORIGINAL | G6: 10012 | H6: NUSTAR PIPELINE OPERATING PARTNERSHIP L.P. | I6: 8111 WESTCHESTER DRIVE | J6: DALLAS | K6: TX | L6: 75225 | M6: 45785.897 | N6: CENTRAL | O6: YES | P6: 35.0248 | Q6: -91.9321 | R6: HVL OR OTHER FLAMMABLE OR TOXIC FLUID WHICH IS A GAS AT AMBIENT CONDITIONS | S6: ANHYDROUS AMMONIA | W6: 1 | X6: 0 | Y6: 0 | Z6: NO | AF6: 0 | AG6: NO | AM6: 0 | AN6: NOTIFICATION FROM PUBLIC | AQ6: 45785.897 | AR6: ONSHORE PIPELINE, INCLUDING VALVE SITES | AS6: ONSHORE | AT6: NORMAL OPERATION, INCLUDES PAUSES BETWEEN BATCHES AND DURING MAINTENANCE | AU6: YES | AW6: 45785.927 | AX6: 45786.781 | AZ6: NO | BC6: 45785.878 | BD6: 45785.897 | BE6: 45785.93 | BF6: 1430608 | BG6: NO | BH6: NO | BN6: VALVE CLOSURE | BP6: 45785.985 | BQ6: AUTOMATIC | BR6: VALVE CLOSURE | BT6: 45785.987 | BU6: MANUAL | CA6: 0 | CB6: NUSTAR AMMONIA SYSTEM - CABOT STA. TO FLORAL STA. | CC6: CABOT STATION - 10" TO FLORAL STATION | CD6: AR | CE6: 72176 | CF6: Not Within a Municipality | CG6: LONOKE | CH6: MILEPOST | CI6: 146 | CJ6: NO | CK6: PIPELINE RIGHT-OF-WAY | CL6: UNDERGROUND | CM6: UNDER SOIL | CO6: 48 | CP6: NO | DM6: INTERSTATE | DN6: TAP FITTING(STOPPLE, THREAD-O-RING, WELD-O-LET, ETC.) | FK6: 1997 | FL6: UNKNOWN | FM6: CARBON STEEL | FO6: LEAK | FR6: CRACK | FY6: NO | GC6: NO | GD6: NO | GE6: NO | GK6: NO | GT6: YES | GU6: YES | GZ6: YES | HA6: YES | HD6: YES | HE6: YES | HF6: 0 | HG6: 60 | HH6: 10000 | HI6: 0 | HJ6: 0 | HK6: 0 | HM6: 10060 | HN6: 0 | HO6: 0 | HP6: 0 | HQ6: 0 | HR6: 700 | HS6: 1340 | HT6: SUBPART E PRESSURE TEST ß195.406(A)(3) | HV6: 25305 | HW6: NO | HY6: PRESSURE DID NOT EXCEED MOP | HZ6: NO | IC6: 36700 | ID6: YES | IL6: NO | IS6: > 20% SMYS REGULATED TRANSMISSION | IT6: YES | IU6: YES | IV6: YES | IW6: NO | IX6: NO | IY6: YES | IZ6: YES | JA6: YES | JB6: NO | JC6: NO | JD6: NO, THE OPERATOR DID NOT FIND THAT AN INVESTIGATION OF THE CONTROLLER(S) ACTIONS OR CONTROL ROOM ISSUES WAS NECESSARY DUE TO: (PROVIDE AN EXPLANATION FOR WHY THE OPERATOR DID NOT INVESTIGATE) | JE6: THE CRACK IN THE PIPE WAS SMALL ENOUGH IT RENDERED THE LEAK UN-DETECTABLE BY THE CONTROL ROOM (SCADA/CPM). | JR6: NO | JS6: NO | JX6: EQUIPMENT FAILURE | JY6: MALFUNCTION OF CONTROL/RELIEF EQUIPMENT | QB6: MALFUNCTION OF CONTROL/RELIEF EQUIPMENT | QK6: YES | RK6: YES | RL6: SIDE SEAM WELD ON STOPPLE TEE. | XL6: DOUG STUCKY | XM6: MANAGER - PIPELINE SAFETY | XN6: doug.stucky@sunoco.com | XO6: 3162459695 | XQ6: 45793 | XR6: DOUG STUCKY | XS6: doug.stucky@sunoco.com | XT6: 3162459695 | XU6: DOUG STUCKY | XV6: 3162459695 | XW6: MANAGER - PIPELINE SAFETY | XX6: doug.stucky@sunoco.com | XY6: AT APPROXIMATELY 20:00 ON 08MAY25, SUNOCO / NUSTAR LOCAL PERSONNEL RECEIVED A CALL FROM A LANDOWNER THAT THEY SMELLED AMMONIA ANHYDROUS. LOCAL PERSONNEL DISPATCHED TO THE SITE, ARRIVING AT APPROXIMATELY 21:05 TO BEGIN WALKING THE LINE AND LOOKING FOR A LEAK. THE LEAK WAS CONFIRMED AT 21:32 WITH A CALL TO AMMONIA SYSTEM LEADERSHIP. SUNOCO / NUSTAR PIPELINE SAFETY PERSONNEL WERE NOTIFIED OF THE RELEASE AT 22:01 TO BEGIN THE NOTIFICATION PROCESS WITH THE NATIONAL RESPONSE CENTER (NRC). A CALL WAS PLACED AND RECEIVED BY THE NRC AT 22:19. MR. DAVIS TOOK THE CALL AND PROVIDED INCIDENT NUMBER 1430608. A FOLLOW-UP CALL WAS RECEIVED BY REGION 6 EPA AT 23:06 REQUESTING AN UPDATE ON THE INCIDENT AND AN OFFER TO PROVIDE ASSISTANCE, IF NEEDED. A SMALL VAPOR STREAM WAS IDENTIFIED COMING FROM THE UPSTREAM SIDE OF VALVE 3-27. CONTROL CENTER PERSONNEL WERE NOTIFIED OF THE RELEASE AND ASKED TO SHUT DOWN THE PIPELINE (22:15). LOCAL PERSONNEL WERE DISPATCHED TO CLOSE THE UPSTREAM VALVE (3-25) AND THE DOWNSTREAM VALVE (3-27). LOCAL PERSONNEL PROVIDED OVERNIGHT AIR MONITORING OF THE SITE. VISQUEEN WAS USED TO COVER THE LEAK AND KEEP THE VAPORS DOWN. THERE WAS NO DANGER TO LOCAL RESIDENTS AND NO NOTIFICATIONS WERE MADE TO LOCAL AUTHORITIES. SUNOCO / NUSTAR MAINTENANCE PERSONNEL WERE CALLED AND DISPATCHED TO THE SITE FOR REPAIRS. UPON EXCAVATION OF THE VALVE SITE, A SMALL CRACK WAS DISCOVERED ON THE SIDE SEAM WELD OF A STOPPLE TEE. REPAIRS WERE COMPLETED AND THE LINE WAS RETURNED TO SERVICE AT 18:45 ON 09MAY25.
A7: 23 | B7: 45813 | C7: 2025 | D7: 20250139 | E7: 40994 | F7: ORIGINAL | G7: 39596 | H7: PERMIAN EXPRESS PARTNERS LLC | I7: 1300 MAIN STREET | J7: HOUSTON | K7: TX | L7: 77002 | M7: 45782.266 | N7: CENTRAL | O7: YES | P7: 32.728841 | Q7: -97.189752 | R7: CRUDE OIL | W7: 6600 | Y7: 6600 | Z7: NO | AF7: 0 | AG7: NO | AM7: 0 | AN7: SCADA-BASED INFORMATION (SUCH AS ALARM(S), ALERT(S), EVENT(S), AND/OR VOLUME OR PACK CALCULATIONS) | AQ7: 45782.266 | AR7: ONSHORE PIPELINE, INCLUDING VALVE SITES | AS7: ONSHORE | AT7: NORMAL OPERATION, INCLUDES PAUSES BETWEEN BATCHES AND DURING MAINTENANCE | AU7: YES | AW7: 45782.267 | AX7: 45786.917 | AZ7: NO | BC7: 45783.588 | BD7: 45783.59 | BE7: 45783.631 | BF7: 1430396 | BG7: 1430457 | BH7: NO | BN7: VALVE CLOSURE | BP7: 45782.269 | BQ7: REMOTELY CONTROLLED | BR7: VALVE CLOSURE | BT7: 45782.271 | BU7: REMOTELY CONTROLLED | BV7: YES | BW7: 45783.588 | BX7: YES | BY7: 45783.625 | BZ7: 45783.75 | CA7: 0 | CB7: RINGGOLD TO CORSICANA | CC7: 22002.01 - 16INCH CORSICANA TO KELLER | CD7: TX | CE7: 76013 | CF7: ARLINGTON | CG7: TARRANT | CH7: MILEPOST | CI7: 90.82 | CJ7: NO | CK7: PIPELINE RIGHT-OF-WAY | CL7: UNDERGROUND | CM7: UNDER SOIL | CO7: 64 | CP7: NO | DM7: INTERSTATE | DN7: PIPE | DO7: PIPE BODY | DP7: NO | DQ7: 16 | DR7: 0.25 | DS7: 42000 | DT7: API-5L X-42 | DU7: ERW - LOW FREQUENCY | DW7: UNKNOWN | DX7: COAL TAR | DZ7: UNKNOWN | FK7: 1953 | FL7: UNKNOWN | FM7: CARBON STEEL | FO7: LEAK | FR7: OTHER | FS7: STILL UNDER INVESTIGATION | FY7: NO | GC7: YES | GD7: NO | GE7: YES | GH7: YES | GK7: NO | GT7: YES | GU7: YES | GX7: YES | GY7: YES | HF7: 7600000 | HG7: 0 | HH7: 1000000 | HI7: 100000 | HJ7: 2000 | HK7: 0 | HM7: 8702000 | HN7: 0 | HO7: 0 | HP7: 0 | HQ7: 0 | HR7: 773 | HS7: 811 | HT7: SUBPART E PRESSURE TEST ß195.406(A)(3) | HV7: 35796 | HW7: NO | HY7: PRESSURE DID NOT EXCEED MOP | HZ7: NO | IC7: 120331 | ID7: YES | IL7: NO | IS7: > 20% SMYS REGULATED TRANSMISSION | IT7: YES | IU7: YES | IV7: YES | IW7: YES | IX7: YES | IY7: YES | IZ7: YES | JA7: YES | JB7: YES | JC7: YES | JD7: NO, THE OPERATOR DID NOT FIND THAT AN INVESTIGATION OF THE CONTROLLER(S) ACTIONS OR CONTROL ROOM ISSUES WAS NECESSARY DUE TO: (PROVIDE AN EXPLANATION FOR WHY THE OPERATOR DID NOT INVESTIGATE) | JE7: A REVIEW OF THE ACCIDENT DETERMINED THAT THERE WERE NO CONTROL ROOM ACTIONS THAT CONTRIBUTED TO THE EVENT. | JR7: NO | JS7: NO | JX7: OTHER ACCIDENT CAUSE | JY7: UNKNOWN | RY7: UNKNOWN | SA7: STILL UNDER INVESTIGATION, CAUSE OF ACCIDENT TO BE DETERMINED* (*SUPPLEMENTAL REPORT REQUIRED) | XL7: TODD NARDOZZI | XM7: DIRECTOR - DOT COMPLIANCE | XN7: todd.nardozzi@energytransfer.com | XO7: 713-989-7126 | XQ7: 45813 | XU7: TODD NARDOZZI | XV7: 713-989-7126 | XW7: DIRECTOR - DOT COMPLIANCE | XX7: todd.nardozzi@energytransfer.com | XY7: ON 05/05/2025 AT APPROXIMATELY 06:23, THE CONTROL CENTER RECEIVED SCADA INDICATIONS OF A RELEASE ON THE KELLER TO MIDLOTHIAN SEGMENT OF THE 16-INCH RINGGOLD TO CORSICANA SYSTEM. THE LINE WAS SHUTDOWN AND UPSTREAM AND DOWNSTREAM VALVES CLOSED TO ISOLATE THE SEGMENT. OPERATIONS PERSONNEL WERE DISPATCHED AND BEGAN FIELD INVESTIGATIONS TO LOCATE A POTENTIAL RELEASE. ON 05/06/2025 AT APPROXIMATELY 14:10, FIELD PERSONNEL DISCOVERED CRUDE OIL ON THE GROUND NEAR MP 90.82 IN THE ARLINGTON/FT. WORTH AREA. ONCE EXCAVATED, BOTH CRUDE OIL AND SEWER WATER WERE DISCOVERED IN THE EXCAVATION. THE LOCATION OF THE LEAK WAS WHERE A 48-INCH CITY OF FORT WORTH SEWER LINE CROSSED UNDER THE KELLER TO MIDLOTHIAN SEGMENT. INVESTIGATION IN THE DITCH FOUND THE CONCRETE SEWER LINE APPEARED TO HAVE FAILED AND WAS EXPELLING SEWAGE INTO THE THE IMMEDIATE AREA IN AND AROUND THE KELLER TO MIDLOTHIAN PIPELINE. APPROXIMATELY 6,600 BARRELS OF CRUDE OIL WAS RELEASED. THE MAJORITY OF THE RELEASED CRUDE TRAVELED THROUGH THE FAILED SEWER PIPE TO A WATER TREATMENT FACILITY APPROXIMATELY 4 MILES TO THE NORTHEAST. CLEANUP CONTRACTORS WERE MOBILIZED TO CLEANUP PRODUCT AND REMOVE IMPACTED SOIL AT THE FAILURE SITE. PEP COORDINATED CLEANUP EFFORTS AT THE WATER TREATMENT FACILITY WITH THE CITY. THE LINE WAS RESTARTED ON 5/9/25 AT 22:00 BY AFFECTING A STOPPLE AND BYPASS AROUND THE FAILED SECTION. AFTER THE PIPELINE WAS RESTARTED THE FAILED SECTION WAS COLD CUT AND REMOVED FROM THE GROUND, PREPPED AND SHIPPED TO A 3RD PARTY LABORATORY FOR ANALYSIS. THE CAUSE OF THE ACCIDENT IS STILL UNDER INVESTIGATION. A SUPPLEMENTAL REPORT WILL BE SUBMITTED ONCE COMPLETE.
A8: 38 | B8: 45789 | C8: 2025 | D8: 20250119 | E8: 40879 | F8: ORIGINAL | G8: 31476 | H8: ET CRUDE OPERATING LLC | I8: 1300 MAIN STREET | J8: HOUSTON | K8: TX | L8: 77002 | M8: 45762.319 | N8: CENTRAL | O8: YES | P8: 36.017432 | Q8: -96.75399 | R8: CRUDE OIL | W8: 8 | Y8: 8 | Z8: NO | AF8: 0 | AG8: NO | AM8: 0 | AN8: LOCAL OPERATING PERSONNEL, INCLUDING CONTRACTORS | AP8: OPERATOR EMPLOYEE | AQ8: 45762.319 | AR8: ONSHORE TERMINAL/TANK FARM EQUIPMENT AND PIPING | AS8: ONSHORE | AT8: NORMAL OPERATION, INCLUDES PAUSES BETWEEN BATCHES AND DURING MAINTENANCE | AU8: YES | AW8: 45762.319 | AX8: 45762.705 | AZ8: NO | BC8: 45762.319 | BD8: 45762.319 | BF8: NRC NOTIFICATION NOT REQUIRED | BH8: NO | BV8: YES | BW8: 45762.319 | BX8: NO | CA8: 0 | CB8: CUSHING TANK FARM | CC8: CIMARRON LINE | CD8: OK | CE8: 74023 | CF8: Not Within a Municipality | CG8: PAYNE | CH8: SURVEY STATION NO. | CI8: 0+00 | CJ8: NO | CK8: TOTALLY CONTAINED ON OPERATOR-CONTROLLED PROPERTY | CL8: UNDERGROUND | CM8: UNDER SOIL | CO8: 42 | CP8: NO | DM8: INTERSTATE | DN8: PIPE | DO8: PIPE BODY | DP8: NO | DQ8: 8 | DR8: 0.312 | DS8: 35000 | DT8: GRADE B | DU8: ERW - HIGH FREQUENCY | DW8: UNKNOWN | DX8: FUSION BONDED EPOXY(FBE) | DZ8: NO | FK8: UNKNOWN | FL8: UNKNOWN | FM8: CARBON STEEL | FO8: LEAK | FR8: PINHOLE | FY8: NO | GC8: YES | GD8: NO | GE8: YES | GH8: YES | GK8: NO | GT8: NO | GU8: NO | HF8: 0 | HG8: 30 | HH8: 6800 | HI8: 24836 | HJ8: 18036 | HK8: 0 | HM8: 49702 | HN8: 0 | HO8: 0 | HP8: 0 | HQ8: 0 | HR8: 117 | HS8: 285 | HT8: COMPONENT DESIGN PRESSURE ß195.406(A)(2) | HV8: 42736 | HW8: NO | HY8: PRESSURE DID NOT EXCEED MOP | HZ8: NO | IS8: < 20% SMYS REGULATED TRANSMISSION | IT8: YES | IU8: YES | IV8: YES | IW8: NO | IX8: NO | IY8: NO | JD8: NO, THE OPERATOR DID NOT FIND THAT AN INVESTIGATION OF THE CONTROLLER(S) ACTIONS OR CONTROL ROOM ISSUES WAS NECESSARY DUE TO: (PROVIDE AN EXPLANATION FOR WHY THE OPERATOR DID NOT INVESTIGATE) | JE8: A REVIEW OF THE ACCIDENT DETERMINED THAT THERE WERE NO CONTROL ROOM ACTIONS THAT CONTRIBUTED TO THE EVENT. | JR8: NO | JS8: NO | JX8: OTHER ACCIDENT CAUSE | JY8: UNKNOWN | RY8: UNKNOWN | SA8: STILL UNDER INVESTIGATION, CAUSE OF ACCIDENT TO BE DETERMINED* (*SUPPLEMENTAL REPORT REQUIRED) | XL8: TODD NARDOZZI | XM8: DIRECTOR - DOT COMPLIANCE | XN8: todd.nardozzi@energytransfer.com | XO8: 713-989-7126 | XQ8: 45789 | XU8: TODD NARDOZZI | XV8: 713-989-7126 | XW8: DIRECTOR - DOT COMPLIANCE | XX8: todd.nardozzi@energytransfer.com | XY8: ON 04/15/25 AT 07:40, CRUDE OIL WAS DISCOVERED ON THE GROUND BENEATH STATION PIPING AT TANK 2538 CUSHING TANK FARM. THE LEAK WAS COMING FROM A PINHOLE AT THE 6 O'CLOCK POSITION ON THE CIMARRON 8-INCH LINE. APPROXIMATELY 8 BARRELS OF CRUDE OIL WAS RELEASED ON THE GROUND. CLEANUP CONTRACTORS REMOVED PRODUCT AND CONTAMINATED SOIL. THE PIPE WAS TEMPORARILY REPAIRED WITH A PLIDCO CLAMP. THE CAUSE OF THE LEAK IS STILL UNDER INVESTIGATION. A SUPPLEMENTAL REPORT WILL BE SUBMITTED ONCE THE INVESTIGATION IS COMPLETE.
A9: 40 | B9: 45789 | C9: 2025 | D9: 20250120 | E9: 40880 | F9: ORIGINAL | G9: 32099 | H9: ENERGY TRANSFER COMPANY | I9: 1300 MAIN STREET | J9: HOUSTON | K9: TX | L9: 77002 | M9: 45760.351 | N9: CENTRAL | O9: YES | P9: 34.813972 | Q9: -97.711528 | R9: CRUDE OIL | W9: 5 | Y9: 5 | Z9: NO | AF9: 0 | AG9: NO | AM9: 0 | AN9: NOTIFICATION FROM PUBLIC | AQ9: 45760.351 | AR9: ONSHORE PIPELINE, INCLUDING VALVE SITES | AS9: ONSHORE | AT9: NORMAL OPERATION, INCLUDES PAUSES BETWEEN BATCHES AND DURING MAINTENANCE | AU9: YES | AW9: 45760.362 | AX9: 45760.595 | AZ9: NO | BC9: 45760.351 | BD9: 45760.396 | BF9: NRC NOTIFICATION NOT REQUIRED | BH9: NO | BN9: VALVE CLOSURE | BP9: 45760.382 | BQ9: MANUAL | BR9: VALVE CLOSURE | BT9: 45760.396 | BU9: MANUAL | BV9: YES | BW9: 45760.356 | BX9: NO | CA9: 0 | CB9: VELOCITY VLC-3 | CC9: NAPLES TO BRADLEY 8-INCH | CD9: OK | CE9: 73011 | CF9: Not Within a Municipality | CG9: GRADY | CH9: SURVEY STATION NO. | CI9: 1172+10 | CJ9: NO | CK9: PIPELINE RIGHT-OF-WAY | CL9: UNDERGROUND | CM9: UNDER SOIL | CO9: 50 | CP9: NO | DM9: INTRASTATE | DN9: PIPE | DO9: PIPE BODY | DP9: NO | DQ9: 8 | DR9: 0.188 | DS9: 52000 | DT9: API-5L X-52 | DU9: ERW - HIGH FREQUENCY | DW9: TEX-TUBE CO | DX9: FUSION BONDED EPOXY(FBE) | DZ9: NO | FK9: 2015 | FL9: UNKNOWN | FM9: CARBON STEEL | FO9: LEAK | FR9: PINHOLE | FY9: NO | GC9: YES | GD9: NO | GE9: YES | GH9: YES | GK9: NO | GT9: NO | GU9: NO | HF9: 2000 | HG9: 0 | HH9: 2500 | HI9: 5800 | HJ9: 20000 | HK9: 0 | HM9: 30300 | HN9: 0 | HO9: 0 | HP9: 0 | HQ9: 0 | HR9: 20 | HS9: 1440 | HT9: SUBPART E PRESSURE TEST ß195.406(A)(3) | HV9: 42192 | HW9: NO | HY9: PRESSURE DID NOT EXCEED MOP | HZ9: NO | IC9: 54338 | ID9: YES | IL9: NO | IS9: > 20% SMYS REGULATED TRANSMISSION | IT9: YES | IU9: YES | IV9: YES | IW9: NO | IX9: NO | IY9: NO | JD9: NO, THE OPERATOR DID NOT FIND THAT AN INVESTIGATION OF THE CONTROLLER(S) ACTIONS OR CONTROL ROOM ISSUES WAS NECESSARY DUE TO: (PROVIDE AN EXPLANATION FOR WHY THE OPERATOR DID NOT INVESTIGATE) | JE9: A REVIEW OF THE ACCIDENT DETERMINED THAT THERE WERE NO CONTROL ROOM ACTIONS THAT CONTRIBUTED TO THE EVENT. | JR9: NO | JS9: NO | JX9: OTHER ACCIDENT CAUSE | JY9: UNKNOWN | RY9: UNKNOWN | SA9: STILL UNDER INVESTIGATION, CAUSE OF ACCIDENT TO BE DETERMINED* (*SUPPLEMENTAL REPORT REQUIRED) | XL9: TODD NARDOZZI | XM9: DIRECTOR - DOT COMPLIANCE | XN9: todd.nardozzi@energytransfer.com | XO9: 713-989-7126 | XQ9: 45789 | XU9: TODD NARDOZZI | XV9: 713-989-7126 | XW9: DIRECTOR - DOT COMPLIANCE | XX9: todd.nardozzi@energytransfer.com | XY9: ON 04/13/25 AT APPROXIMATELY 08:00, THE ENERGY TRANSFER CONTROL CENTER RECEIVED A CALL FROM A LANDOWNER STATING OIL WAS OBSERVED ON THE ROW NEAR THE VLC-3 NAPLES TO BRADLEY 8-INCH LINE. THE PIPELINE WAS SHUT DOWN AND SECURED. PIPELINE TECHNICIANS WERE DISPATCHED TO CONFIRM THE PIPELINE RELEASE. ONCE THE PIPE WAS EXPOSED, THE LEAK WAS CONFIRMED TO BE COMING FROM A PINHOLE ON THE BOTTOM OF THE VLC-3 NAPLES TO BRADLEY 8-INCH LINE. APPROXIMATELY 5 BARRELS OF CRUDE OIL WAS RELEASED. CONTRACTORS CLEANED UP RELEASED PRODUCT AND CONTAMINATED SOIL. A CLAMP WAS INSTALLED TO PREVENT ANY FURTHER RELEASE. THE ACCIDENT IS STILL UNDER INVESTIGATION. A SUPPLEMENTAL REPORT WILL BE SUBMITTED ONCE THE ROOT CAUSE FAILURE ANALYSIS IS COMPLETED.
A10: 45 | B10: 45782 | C10: 2025 | D10: 20250111 | E10: 40846 | F10: ORIGINAL | G10: 39706 | H10: ENERGY TRANSFER NEDERLAND TERMINAL LLC | I10: 1300 MAIN STREET | J10: HOUSTON | K10: TX | L10: 77002 | M10: 45756.632 | N10: CENTRAL | O10: YES | P10: 30.000608 | Q10: -93.992447 | R10: CRUDE OIL | W10: 60 | Y10: 60 | Z10: NO | AF10: 0 | AG10: NO | AM10: 0 | AN10: LOCAL OPERATING PERSONNEL, INCLUDING CONTRACTORS | AP10: OPERATOR EMPLOYEE | AQ10: 45756.632 | AR10: ONSHORE TERMINAL/TANK FARM EQUIPMENT AND PIPING | AS10: ONSHORE | AT10: NORMAL OPERATION, INCLUDES PAUSES BETWEEN BATCHES AND DURING MAINTENANCE | AU10: YES | AW10: 45756.637 | AX10: 45761.667 | AZ10: NO | BC10: 45756.632 | BD10: 45756.632 | BE10: 45756.662 | BF10: 1428163 | BG10: 1428345 | BH10: NO | BV10: YES | BW10: 45756.633 | BX10: NO | CA10: 0 | CB10: NEDERLAND TERMINAL | CC10: MARSHLAND MANIFOLD | CD10: TX | CE10: 77627 | CF10: NEDERLAND | CG10: JEFFERSON | CH10: SURVEY STATION NO. | CI10: 0+00 | CJ10: NO | CK10: TOTALLY CONTAINED ON OPERATOR-CONTROLLED PROPERTY | CL10: ABOVEGROUND | CM10: TYPICAL ABOVEGROUND FACILITY PIPING OR APPURTENANCE | CP10: NO | DM10: INTERSTATE | DN10: RELIEF LINE AND RELIEF EQUIPMENT | FK10: 2019 | FL10: 2019 | FM10: CARBON STEEL | FO10: LEAK | FR10: CONNECTION FAILURE | FY10: NO | GC10: YES | GD10: NO | GE10: NO | GK10: NO | GT10: YES | GU10: YES | GX10: YES | GY10: YES | HF10: 0 | HG10: 4000 | HH10: 5000 | HI10: 20000 | HJ10: 95000 | HK10: 0 | HM10: 124000 | HN10: 0 | HO10: 0 | HP10: 0 | HQ10: 0 | HR10: 119 | HS10: 285 | HT10: COMPONENT DESIGN PRESSURE ß195.406(A)(2) | HV10: 40179 | HW10: NO | HY10: PRESSURE DID NOT EXCEED MOP | HZ10: NO | IS10: > 20% SMYS REGULATED TRANSMISSION | IT10: YES | IU10: YES | IV10: YES | IW10: NO | IX10: NO | IY10: YES | IZ10: YES | JA10: YES | JB10: NO | JC10: NO | JD10: NO, THE OPERATOR DID NOT FIND THAT AN INVESTIGATION OF THE CONTROLLER(S) ACTIONS OR CONTROL ROOM ISSUES WAS NECESSARY DUE TO: (PROVIDE AN EXPLANATION FOR WHY THE OPERATOR DID NOT INVESTIGATE) | JE10: A REVIEW OF THE ACCIDENT DETERMINED THAT THERE WERE NO CONTROL ROOM ACTIONS THAT CONTRIBUTED TO THE EVENT. | JR10: NO | JS10: NO | JX10: OTHER ACCIDENT CAUSE | JY10: UNKNOWN | RY10: UNKNOWN | SA10: STILL UNDER INVESTIGATION, CAUSE OF ACCIDENT TO BE DETERMINED* (*SUPPLEMENTAL REPORT REQUIRED) | XL10: TODD NARDOZZI | XM10: DIRECTOR - DOT COMPLIANCE | XN10: todd.nardozzi@energytransfer.com | XO10: 713-989-7126 | XQ10: 45782 | XU10: TODD NARDOZZI | XV10: 713-989-7126 | XW10: DIRECTOR - DOT COMPLIANCE | XX10: todd.nardozzi@energytransfer.com | XY10: ON 04/09/25 AT APPROXIMATELY 15:10, AN OPERATOR NOTIFIED MANAGEMENT THAT CRUDE OIL WAS FOUND LEAKING FROM THE #4 SHIP DOCK LINE. THE TRANSFER THROUGH THAT PIPE WAS STOPPED AND THE TRANSFER WAS MOVED TO ANOTHER PIPE TO CONTINUE THE TRANSFER. THE LEAK WAS COMING FROM A 1-INCH PIPE NIPPLE COMING OFF OF THE MAIN HEADER THAT HAD BROKEN OFF APPROXIMATELY 3-INCH ABOVE THE HEADER PIPE AT THE VALVE. APPROXIMATELY 60 BARRELS OF CRUDE OIL WAS RELEASED INTO CONTAINMENT. VACUUM TRUCKS AND CLEANUP PERSONNEL RESPONDED TO THE SITE FOR CLEANUP. ON 04/14/25 THE LEAK WAS REPAIRED BY INSTALLING AND HOT TAPPING NEW TORS WITH NEW 2-INCH VALVES. UTILIZED NEW PIPING AND RECONFIGURED THE LOCATION OF THE PRESSURE RELIEF VALVE WITH NEW SUPPORTS. THE CAUSE OF THE LEAK IS STILL UNDER INVESTIGATION. A SUPPLEMENTAL REPORT WILL BE SUBMITTED ONCE THE INVESTIGATION IS COMPLETE. TO PREVENT REOCCURRENCE, PREPARATIONS IN PROGRESS TO REPLACE 1-INCH O-LETS WITH 2-INCH.
A11: 46 | B11: 45785 | C11: 2025 | D11: 20250114 | E11: 41050 | F11: SUPPLEMENTAL FINAL | G11: 32099 | H11: ENERGY TRANSFER COMPANY | I11: 1300 MAIN STREET | J11: HOUSTON | K11: TX | L11: 77002 | M11: 45755.361 | N11: CENTRAL | O11: YES | P11: 32.001672 | Q11: -102.04588 | R11: CRUDE OIL | W11: 12 | Y11: 12 | Z11: NO | AF11: 0 | AG11: NO | AM11: 0 | AN11: LOCAL OPERATING PERSONNEL, INCLUDING CONTRACTORS | AP11: OPERATOR EMPLOYEE | AQ11: 45755.361 | AR11: ONSHORE TERMINAL/TANK FARM EQUIPMENT AND PIPING | AS11: ONSHORE | AT11: NORMAL OPERATION, INCLUDES PAUSES BETWEEN BATCHES AND DURING MAINTENANCE | AU11: NO | AV11: ISOLATED TANK | AZ11: NO | BC11: 45755.361 | BD11: 45755.361 | BE11: 45755.403 | BF11: 1428027 | BG11: 1428209 | BH11: NO | BV11: YES | BW11: 45755.369 | BX11: NO | CA11: 0 | CB11: MIDLAND TANK FARM | CC11: TANK 1979 16-INCH FILL LINE | CD11: TX | CE11: 79706 | CF11: Not Within a Municipality | CG11: MIDLAND | CH11: SURVEY STATION NO. | CI11: MIDLAND TF | CJ11: NO | CK11: TOTALLY CONTAINED ON OPERATOR-CONTROLLED PROPERTY | CL11: ABOVEGROUND | CM11: TYPICAL ABOVEGROUND FACILITY PIPING OR APPURTENANCE | CP11: NO | DM11: INTRASTATE | DN11: VALVE | EM11: AUXILIARY OR OTHER VALVE | FK11: 2019 | FL11: 2018 | FM11: CARBON STEEL | FO11: LEAK | FR11: PINHOLE | FY11: NO | GC11: YES | GD11: NO | GE11: YES | GH11: YES | GK11: NO | GT11: YES | GU11: NO | HF11: 0 | HG11: 293 | HH11: 19247 | HI11: 4810 | HJ11: 5590 | HK11: 0 | HM11: 29940 | HN11: 0 | HO11: 0 | HP11: 0 | HQ11: 0 | HR11: 8 | HS11: 285 | HT11: COMPONENT DESIGN PRESSURE ß195.406(A)(2) | HV11: 43783 | HW11: NO | HY11: PRESSURE DID NOT EXCEED MOP | HZ11: NO | IS11: > 20% SMYS REGULATED GATHERING | IT11: NO | IY11: NO | JD11: NO, THE FACILITY WAS NOT MONITORED BY A CONTROLLER(S) AT THE TIME OF THE ACCIDENT | JR11: NO | JS11: NO | JX11: CORROSION FAILURE | JY11: INTERNAL CORROSION | JZ11: INTERNAL CORROSION | LD11: LOCALIZED PITTING | LG11: YES | LJ11: YES | LK11: TRACES OF PRODUCED WATER AND DEBRIS IN PRODUCT STREAM | LM11: YES | LS11: YES | LT11: BOTTOM OF VALVE BODY. | LU11: NO | LV11: NO | LW11: NOT APPLICABLE - NOT MAINLINE PIPE | LX11: NOT APPLICABLE - NOT MAINLINE PIPE | XL11: TODD NARDOZZI | XM11: DIRECTOR - DOT COMPLIANCE | XN11: todd.nardozzi@energytransfer.com | XO11: 713-989-7126 | XQ11: 45826 | XU11: TODD NARDOZZI | XV11: 713-989-7126 | XW11: DIRECTOR - DOT COMPLIANCE | XX11: todd.nardozzi@energytransfer.com | XY11: ON 4/8/2025, AT APPROXIMATELY 08:40, AN OPERATOR EMPLOYEE DISCOVERED A LEAK ON THE 16INCH VALVE ON TANK LINE 1979 AT MIDLAND TANK FARM. THE LEAK WAS IMMEDIATELY ISOLATED. APPROXIMATELY 12 BARRELS OF CRUDE OIL WAS RELEASED. CLEANUP CONTRACTORS REMOVED PRODUCT AND REMEDIATED IMPACTED SOIL. THE LEAK WAS REPAIRED BY REPLACING THE VALVE. THE LINE WAS PUT BACK IN SERVICE ON 04/11/2025. THE CAUSE OF THE ACCIDENT IS STILL UNDER INVESTIGATION. A SUPPLEMENTAL REPORT WILL BE SUBMITTED ONCE THE INVESTIGATION IS COMPLETE. SUPPLEMENTAL & FINAL: THE INVESTIGATION DETERMINED THE CAUSE OF THE ACCIDENT WAS DUE TO INTERNAL CORROSION. THE LEAK COINCIDED WITHIN A REGION OF INTERNAL CORROSION LOCATED ALONG THE BOTTOM OF THE VALVE BODY. A PIT IN THE FLANGE MATERIAL ADJACENT TO THE LEAK LOCATION WAS ALSO OBSERVED, WHICH ALIGNED WITH PRE-EXISTING MANUFACTURING VOIDS. ADDITIONALLY, A SECOND PIT WAS IDENTIFIED WITHIN THE ADJACENT FLANGE MATERIAL OF THE VALVE, FURTHER CONTRIBUTING TO THE LOCALIZED CORROSION AND EVENTUAL LEAK. TO PREVENT REOCCURRENCE, NDE EXAMINE ONE OTHER VALVE BY SAME MANUFACTURER WITH SAME APPROXIMATE MANUFACTURED DATE TO ENSURE NO THINNING OF THE BODY WAS OCCURRING.
A12: 74 | B12: 45750 | C12: 2025 | D12: 20250083 | E12: 41000 | F12: SUPPLEMENTAL | G12: 40283 | H12: SUNOCO, LLC | I12: 8111 WESTCHESTER DR. | J12: DALLAS | K12: TX | L12: 75225 | M12: 45720.679 | N12: EASTERN | O12: NO | P12: 36.749647 | Q12: -76.09261 | R12: REFINED AND/OR PETROLEUM PRODUCT (NON-HVL) WHICH IS A LIQUID AT AMBIENT CONDITIONS | S12: DIESEL, FUEL OIL, KEROSENE, JET FUEL | W12: 38 | Y12: 29 | Z12: NO | AF12: 0 | AG12: NO | AM12: 0 | AN12: CPM LEAK DETECTION SYSTEM | AQ12: 45720.719 | AR12: ONSHORE PIPELINE, INCLUDING VALVE SITES | AS12: ONSHORE | AT12: POST-MAINTENANCE/REPAIR | AZ12: YES | BA12: OPERATOR | BB12: 45720.767 | BC12: 45720.719 | BD12: 45720.719 | BE12: 45720.767 | BF12: 1425057 | BG12: 1425144, 1425240 | BH12: NO | BN12: OPERATIONAL CONTROL | BO12: OPERATIONS OPENED MAINLINE VALVE ON PIPELINE TO RELIEVE LINE PRESSURE BACK TO TERMINAL TANK 2001 | BR12: OPERATIONAL CONTROL | BS12: THERE WAS NO FLOW DOWNSTREAM OF THE FAILURE (LINE WAS STATIC) | BV12: YES | BW12: 45720.688 | BX12: YES | BY12: 45720.719 | BZ12: 45720.757 | CA12: 0 | CB12: VIRGINIA BEACH - SUNOCO LLC | CC12: 41002 - 6" VIRGINIA BEACH | CD12: VA | CE12: 23456 | CF12: VIRGINIA BEACH | CG12: Not Within a County or Parish | CH12: MILEPOST | CI12: 2.65 | CJ12: NO | CK12: PIPELINE RIGHT-OF-WAY | CL12: UNDERGROUND | CM12: UNDER SOIL | CO12: 31 | CP12: NO | DM12: INTRASTATE | DN12: PIPE | DO12: PIPE BODY | DP12: NO | DQ12: 6.625 | DR12: 0.188 | DS12: 24000 | DT12: UNKNOWN | DU12: ERW ñ UNKNOWN FREQUENCY | DW12: UNKNOWN | DX12: COAL TAR | DZ12: NO | FK12: 1963 | FL12: 1963 | FM12: CARBON STEEL | FO12: LEAK | FR12: PINHOLE | FY12: NO | GC12: YES | GD12: YES | GE12: YES | GG12: YES | GH12: YES | GK12: YES | GN12: YES | GR12: 4.8 | GS12: GROUNDWATER | GT12: YES | GU12: YES | GZ12: YES | HA12: NO | HF12: 26921 | HG12: 1995 | HH12: 215371 | HI12: 447082 | HJ12: 300000 | HK12: 0 | HM12: 991369 | HN12: 0 | HO12: 0 | HP12: 0 | HQ12: 0 | HR12: 94 | HS12: 575 | HT12: COMPONENT DESIGN PRESSURE ß195.406(A)(2) | HV12: 41242 | HW12: NO | HY12: PRESSURE DID NOT EXCEED MOP | HZ12: NO | ID12: YES | IL12: NO | IS12: > 20% SMYS REGULATED TRANSMISSION | IT12: YES | IU12: YES | IV12: YES | IW12: YES | IX12: YES | IY12: YES | IZ12: YES | JA12: YES | JB12: YES | JC12: YES | JD12: YES, SPECIFY INVESTIGATION RESULT(S): (SELECT ALL THAT APPLY) | JF12: YES | JI12: YES | JJ12: YES | JR12: NO | JS12: NO | JX12: CORROSION FAILURE | JY12: EXTERNAL CORROSION | JZ12: EXTERNAL CORROSION | KA12: LOCALIZED PITTING | KH12: YES | KI12: POLARITY REVERSED ON RECTIFIER | KL12: YES | KN12: YES | KO12: PENDING METALLURGICAL ANALYSIS, ESTIMATED DATE OF COMPLETION 6/30/2025 | KP12: YES | KQ12: YES | KR12: 2000 | KS12: NO | KT12: YES | KU12: YES | KV12: YES | KX12: 2024 | KY12: 2023 | LC12: NO | SC12: YES | SD12: YES | SG12: YES | SK12: 2023 | SL12: FREE SWIMMING | SM12: METAL LOSS | SO12: HIGH RESOLUTION | SQ12: 2018 | SR12: FREE SWIMMING | SS12: METAL LOSS | SU12: HIGH RESOLUTION | TQ12: 2023 | TR12: FREE SWIMMING | TS12: HIGH RESOLUTION | TU12: INSIDE ILI CUPS | TV12: 2018 | TW12: FREE SWIMMING | TX12: HIGH RESOLUTION | TZ12: INSIDE ILI CUPS | UO12: YES | UP12: 2012 | UQ12: 760 | UR12: NO | UZ12: NO | XL12: STEPHEN DOYLE | XM12: MANAGER - ENVIRONMENTAL | XN12: stephen.doyle@sunoco.com | XO12: 8563322424 | XQ12: 45814 | XR12: CLIFF BELL | XS12: clifford.bell@sunoco.com | XT12: 7574271066 | XU12: BRIAN CARLSON | XV12: 6105792045 | XW12: SR. DIRECTOR - TERMINAL OPS | XX12: brian.carlson@sunoco.com | XY12: ON 3/4/2025 AT 17:15, SUNOCO PERSONNEL DISCOVERED A JET FUEL LEAK ON THE PIPELINE BETWEEN VALVE BOX 1 AND VALVE BOX 2. UPON DISCOVERY, SUNOCO IMMEDIATELY CONTACTED THE OSRO. IN RESPONSE TO SUNOCO'S DISCOVERY, THE PRESSURE ON THE PIPELINE WAS RELIEVED TO TERMINAL TANK 2001. ALL MAINLINE VALVES WERE CLOSED AND THE LINE SEGMENT ISOLATED. SUNOCO PERSONNEL REPAIRED THE PIPELINE AND SENT A CUTOUT FOR METALLURGICAL TESTING. AS OF APRIL 3, SUNOCO HAS NOT RECEIVED THOSE RESULTS. AT A LATER DATE, SUNOCO ALSO DETERMINED THAT THE RECTIFIER HAD A REVERSED POLARITY AS REFERENCED IN PART G APPARENT CAUSE OF THIS REPORT. UPDATE: ESTIMATED COST OF OPERATOR'S EMERGENCY RESPONSE INCREASED AS REPORTED IN PART D. PART G UPDATED, PENDING METALLURGICAL ANALYSIS WITH ESTIMATED DATE OF COMPLETION 6/30/2025.
A13: 78 | B13: 45749 | C13: 2025 | D13: 20250079 | E13: 40999 | F13: SUPPLEMENTAL | G13: 40283 | H13: SUNOCO, LLC | I13: 8111 WESTCHESTER DR. | J13: DALLAS | K13: TX | L13: 75225 | M13: 45719.347 | N13: EASTERN | O13: NO | P13: 36.774274 | Q13: -76.093599 | R13: REFINED AND/OR PETROLEUM PRODUCT (NON-HVL) WHICH IS A LIQUID AT AMBIENT CONDITIONS | S13: DIESEL, FUEL OIL, KEROSENE, JET FUEL | W13: 7.14 | Y13: 5.36 | Z13: NO | AF13: 0 | AG13: NO | AM13: 0 | AN13: CPM LEAK DETECTION SYSTEM | AQ13: 45719.49 | AR13: ONSHORE PIPELINE, INCLUDING VALVE SITES | AS13: ONSHORE | AT13: ROUTINE START-UP | AU13: YES | AW13: 45719.423 | AX13: 45786.33 | AZ13: YES | BA13: OPERATOR | BB13: 45719.532 | BC13: 45719.49 | BD13: 45719.49 | BE13: 45719.532 | BF13: 1424936 | BG13: 1425061, 1425543 | BH13: NO | BN13: OPERATIONAL CONTROL | BO13: OPERATIONS OPENED MAINLINE VALVE ON PIPELINE TO RELIEVE LINE PRESSURE BACK TO TERMINAL TANK 2001 | BR13: OPERATIONAL CONTROL | BS13: THERE WAS NO FLOW DOWNSTREAM OF THE FAILURE (LINE WAS STATIC) | BV13: YES | BW13: 45719.469 | BX13: YES | BY13: 45719.502 | BZ13: 45719.569 | CA13: 0 | CB13: VIRGINIA BEACH - SUNOCO LLC | CC13: 41002 - 6" VIRGINIA BEACH | CD13: VA | CE13: 23456 | CF13: VIRGINIA BEACH | CG13: Not Within a County or Parish | CH13: MILEPOST | CI13: 4.5 | CJ13: NO | CK13: PIPELINE RIGHT-OF-WAY | CL13: UNDERGROUND | CM13: IN UNDERGROUND ENCLOSED SPACE (E.G. VAULT) | CO13: 48 | CP13: YES | CU13: YES | CV13: CASED | DM13: INTRASTATE | DN13: PIPE | DO13: PIPE BODY | DP13: NO | DQ13: 6.625 | DR13: 0.25 | DS13: 42000 | DT13: 5L, X42 | DU13: ERW - HIGH FREQUENCY | DW13: UNKNOWN | DX13: FUSION BONDED EPOXY(FBE) | DZ13: NO | FK13: 1997 | FL13: 1997 | FM13: CARBON STEEL | FO13: LEAK | FR13: PINHOLE | FY13: NO | GC13: YES | GD13: YES | GE13: YES | GG13: YES | GH13: YES | GK13: YES | GN13: YES | GR13: 0.9 | GS13: GROUNDWATER | GT13: YES | GU13: YES | GX13: YES | GY13: NO | HF13: 26921 | HG13: 375 | HH13: 215371 | HI13: 447082 | HJ13: 200000 | HK13: 0 | HM13: 889749 | HN13: 0 | HO13: 0 | HP13: 0 | HQ13: 0 | HR13: 92 | HS13: 575 | HT13: COMPONENT DESIGN PRESSURE ß195.406(A)(2) | HV13: 41242 | HW13: NO | HY13: PRESSURE DID NOT EXCEED MOP | HZ13: NO | ID13: YES | IL13: NO | IS13: > 20% SMYS REGULATED TRANSMISSION | IT13: YES | IU13: YES | IV13: YES | IW13: YES | IX13: YES | IY13: YES | IZ13: YES | JA13: YES | JB13: YES | JC13: YES | JD13: YES, SPECIFY INVESTIGATION RESULT(S): (SELECT ALL THAT APPLY) | JF13: YES | JI13: YES | JJ13: YES | JR13: NO | JS13: NO | JX13: CORROSION FAILURE | JY13: EXTERNAL CORROSION | JZ13: EXTERNAL CORROSION | KA13: LOCALIZED PITTING | KH13: YES | KI13: POLARITY REVERSED ON RECTIFIER | KL13: YES | KN13: YES | KO13: PENDING METALLURGICAL ANALYSIS, ESTIMATED DATE OF COMPLETION 6/30/2025 | KP13: YES | KQ13: YES | KR13: 2000 | KS13: NO | KT13: YES | KU13: YES | KV13: YES | KX13: 2024 | KY13: 2023 | LC13: YES | SC13: YES | SD13: YES | SG13: YES | SK13: 2023 | SL13: FREE SWIMMING | SM13: METAL LOSS | SO13: HIGH RESOLUTION | SQ13: 2018 | SR13: FREE SWIMMING | SS13: METAL LOSS | SU13: HIGH RESOLUTION | TQ13: 2023 | TR13: FREE SWIMMING | TS13: HIGH RESOLUTION | TU13: INSIDE ILI CUPS | TV13: 2018 | TW13: FREE SWIMMING | TX13: HIGH RESOLUTION | TZ13: INSIDE ILI CUPS | UO13: YES | UP13: 2012 | UQ13: 760 | UR13: NO | UZ13: NO | WZ13: YES | XL13: STEPHEN DOYLE | XM13: MANAGER - ENVIRONMENTAL | XN13: stephen.doyle@sunoco.com | XO13: 8563322424 | XQ13: 45814 | XR13: CLIFF BELL | XS13: cliff.bell@sunoco.com | XT13: 757-427-1066 | XU13: BRIAN CARLSON | XV13: 610-579-2045 | XW13: SR. DIRECTOR - TERMINAL OPS | XX13: brian.carlson@sunoco.com | XY13: ON 3/3/2025, SUNOCO PERSONNEL DISCOVERED A JET FUEL LEAK AT MAINLINE VALVE BOX #2 AT 11:45 EST, WHICH WAS INITIALLY ESTIMATED TO BE 70 GALLONS. IN RESPONSE TO SUNOCO'S DISCOVERY, THE PRESSURE ON THE PIPELINE WAS RELIEVED TO TANK 2001. ALL MAINLINE VALVES WERE CLOSED AND THE LINE SEGMENT ISOLATED. SUNOCO CONTACTED THE OSRO (HEPACO) AT 12:03 EST. THE PRELIMINARY LEAK INVESTIGATION SUGGESTED THAT THE GASKET ON THE FLANGE WITHIN VALVE BOX #2 MAY HAVE CAUSED THE DISCOVERED RELEASE. UPON REPLACING THAT VALVE, HOWEVER, SUNOCO PERSONNEL STILL OBSERVED PRODUCT NORTH OF VALVE BOX #2 AND, AS SUCH, COMPLETED AN INVESTIGATION ON THE PIPE UNDERNEATH DAM NECK ROAD. AT A LATER DATE, SUNOCO ALSO DETERMINED THAT THE RECTIFIER HAD A REVERSED POLARITY. SUNOCO CONSEQUENTLY DETERMINED THAT THE PIPELINE SEGMENT UNDERNEATH THE ROAD MAY INCLUDE SOME CORROSION ABNORMALITIES AND, AS SUCH, SENT IT FOR METALLURGICAL TESTING. AS OF APRIL 2, SUNOCO HAS NOT RECEIVED THOSE RESULTS. UPDATE: PIPELINE HAS BEEN RESTARTED AS REPORTED IN PART A. ESTIMATED COST OF OPERATOR'S EMERGENCY RESPONSE INCREASED AS REPORTED IN PART D. PART G UPDATED, PENDING METALLURGICAL ANALYSIS WITH ESTIMATED DATE OF COMPLETION 6/30/2025.
A14: 81 | B14: 45744 | C14: 2025 | D14: 20250074 | E14: 40694 | F14: ORIGINAL FINAL | G14: 22442 | H14: WEST TEXAS GULF PIPELINE CO | I14: 1300 MAIN STREET | J14: HOUSTON | K14: TX | L14: 77002 | M14: 45716.719 | N14: CENTRAL | O14: NO | P14: 32.152658 | Q14: -97.374423 | R14: CRUDE OIL | W14: 10 | Y14: 10 | Z14: NO | AF14: 0 | AG14: NO | AM14: 0 | AN14: CONTROLLER | AP14: OPERATOR EMPLOYEE | AQ14: 45716.719 | AR14: ONSHORE PUMP/METER STATION EQUIPMENT AND PIPING | AS14: ONSHORE | AT14: NORMAL OPERATION, INCLUDES PAUSES BETWEEN BATCHES AND DURING MAINTENANCE | AU14: YES | AW14: 45716.728 | AX14: 45716.875 | AZ14: NO | BC14: 45716.765 | BD14: 45716.774 | BF14: NRC NOTIFICATION NOT REQUIRED | BH14: NO | BV14: YES | BW14: 45716.722 | BX14: NO | CA14: 0 | CB14: BLUM STATION | CC14: 23010.04 - 26-INCH BLUM TO WORTHAM | CD14: TX | CE14: 76627 | CF14: Not Within a Municipality | CG14: HILL | CH14: SURVEY STATION NO. | CI14: 0+00 | CJ14: NO | CK14: ORIGINATED ON OPERATOR-CONTROLLED PROPERTY, BUT THEN FLOWED OR MIGRATED OFF THE PROPERTY | CL14: ABOVEGROUND | CM14: TYPICAL ABOVEGROUND FACILITY PIPING OR APPURTENANCE | CP14: NO | DM14: INTERSTATE | DN14: SUMP | FK14: 2018 | FL14: 2018 | FM14: CARBON STEEL | FO14: OVERFILL OR OVERFLOW | FY14: NO | GC14: YES | GD14: NO | GE14: YES | GH14: YES | GK14: NO | GT14: NO | GU14: NO | HF14: 0 | HG14: 146 | HH14: 0 | HI14: 5000 | HJ14: 7000 | HK14: 0 | HM14: 12146 | HN14: 0 | HO14: 0 | HP14: 0 | HQ14: 0 | HR14: 576 | HS14: 750 | HT14: SUBPART E PRESSURE TEST ß195.406(A)(3) | HV14: 44847 | HW14: NO | HY14: PRESSURE DID NOT EXCEED MOP | HZ14: NO | IS14: > 20% SMYS REGULATED TRANSMISSION | IT14: YES | IU14: YES | IV14: YES | IW14: YES | IX14: YES | IY14: YES | IZ14: YES | JA14: YES | JB14: YES | JC14: YES | JD14: YES, SPECIFY INVESTIGATION RESULT(S): (SELECT ALL THAT APPLY) | JF14: YES | JM14: YES | JR14: NO | JS14: NO | JX14: INCORRECT OPERATION | JY14: TANK, VESSEL, OR SUMP/SEPARATOR ALLOWED OR CAUSED TO OVERFILL OR OVERFLOW | RM14: TANK, VESSEL, OR SUMP/SEPARATOR ALLOWED OR CAUSED TO OVERFILL OR OVERFLOW | RN14: OTHER | RO14: INADEQUATE STATION SHUTDOWN PROCEDURE. | RQ14: YES | RV14: NORMAL OPERATING CONDITIONS | RW14: YES | RX14: YES, THEY WERE QUALIFIED FOR THE TASK(S) | XL14: TODD NARDOZZI | XM14: DIRECTOR - DOT COMPLIANCE | XN14: todd.nardozzi@energytransfer.com | XO14: 713-989-7126 | XQ14: 45744 | XU14: TODD NARDOZZI | XV14: 713-989-7126 | XW14: DIRECTOR - DOT COMPLIANCE | XX14: todd.nardozzi@energytransfer.com | XY14: ON 02/28/2025 AT 17:16, THE CONTROL CENTER SHUT DOWN THE WTG BLUM TO WORTHAM SEGMENT. BLUM STATION WAS BLOCKED IN FROM THE MAIN LINE AND THERMAL PRESSURE BUILT ON ABOVE GRADE PIPING. THERMAL RELIEF SYSTEM REACTED AS DESIGNED AND BEGAN RELIEVING TO THE STATION SUMP. THE THERMAL RELIEFS CONTINUED TO REMAIN ACTIVE FOR AN EXTENDED PERIOD WHICH RESULTED IN AN OVERFILL OF THE SUMP. APPROXIMATELY, 10 BARRELS OF CRUDE OIL WAS RELEASED. ALL FREE PRODUCT WAS PICKED UP AND CONTAMINATED SOIL WAS CLEANED UP. THE CAUSE OF THE ACCIDENT WAS DUE TO INCORRECT SHUTDOWN SEQUENCE. TO PREVENT REOCCURRENCE A PROCEDURE CHANGE HAS BEEN IMPLEMENTED THAT WILL PREVENT THIS SITUATION.
A15: 83 | B15: 45744 | C15: 2025 | D15: 20250073 | E15: 40693 | F15: ORIGINAL FINAL | G15: 39596 | H15: PERMIAN EXPRESS PARTNERS LLC | I15: 1300 MAIN STREET | J15: HOUSTON | K15: TX | L15: 77002 | M15: 45715.667 | N15: CENTRAL | O15: NO | P15: 33.86404 | Q15: -97.954054 | R15: CRUDE OIL | W15: 1 | Y15: 1 | Z15: NO | AF15: 0 | AG15: NO | AM15: 0 | AN15: LOCAL OPERATING PERSONNEL, INCLUDING CONTRACTORS | AP15: OPERATOR EMPLOYEE | AQ15: 45715.667 | AR15: ONSHORE PUMP/METER STATION EQUIPMENT AND PIPING | AS15: ONSHORE | AT15: NORMAL OPERATION, INCLUDES PAUSES BETWEEN BATCHES AND DURING MAINTENANCE | AU15: NO | AV15: LINE IS NOT IN ACTIVE SERVICE. OPERATIONAL DEAD-LEG. | AZ15: NO | BC15: 45715.667 | BD15: 45715.667 | BF15: NRC NOTIFICATION NOT REQUIRED | BH15: NO | BV15: YES | BW15: 45715.688 | BX15: NO | CA15: 0 | CB15: RINGGOLD STATION | CC15: WICHITA FALLS TANK 12-INCH FILL LINE | CD15: TX | CE15: 76255 | CF15: Not Within a Municipality | CG15: MONTAGUE | CH15: SURVEY STATION NO. | CI15: 0+00 | CJ15: NO | CK15: TOTALLY CONTAINED ON OPERATOR-CONTROLLED PROPERTY | CL15: ABOVEGROUND | CM15: TYPICAL ABOVEGROUND FACILITY PIPING OR APPURTENANCE | CP15: NO | DM15: INTERSTATE | DN15: PIPE | DO15: PIPE BODY | DP15: NO | DQ15: 12 | DR15: 0.625 | DS15: 42000 | DT15: UNKNOWN | DU15: ERW ñ UNKNOWN FREQUENCY | DW15: UNKNOWN | DX15: PAINT | DZ15: YES | FK15: 2012 | FL15: UNKNOWN | FM15: CARBON STEEL | FO15: LEAK | FR15: PINHOLE | FY15: NO | GC15: YES | GD15: NO | GE15: YES | GH15: YES | GK15: NO | GT15: NO | GU15: NO | HF15: 0 | HG15: 0 | HH15: 0 | HI15: 1300 | HJ15: 0 | HK15: 0 | HM15: 1300 | HN15: 0 | HO15: 0 | HP15: 0 | HQ15: 0 | HR15: 25 | HS15: 285 | HT15: COMPONENT DESIGN PRESSURE ß195.406(A)(2) | HV15: 41183 | HW15: NO | HY15: PRESSURE DID NOT EXCEED MOP | HZ15: NO | IS15: > 20% SMYS REGULATED TRANSMISSION | IT15: YES | IU15: YES | IV15: YES | IW15: NO | IX15: NO | IY15: NO | JD15: NO, THE OPERATOR DID NOT FIND THAT AN INVESTIGATION OF THE CONTROLLER(S) ACTIONS OR CONTROL ROOM ISSUES WAS NECESSARY DUE TO: (PROVIDE AN EXPLANATION FOR WHY THE OPERATOR DID NOT INVESTIGATE) | JE15: A REVIEW OF THE ACCIDENT DETERMINED THAT THERE WERE NO CONTROL ROOM ACTIONS THAT CONTRIBUTED TO THE EVENT. | JR15: NO | JS15: NO | JX15: CORROSION FAILURE | JY15: INTERNAL CORROSION | JZ15: INTERNAL CORROSION | LD15: GENERAL CORROSION | LG15: YES | LL15: YES | LP15: YES | LR15: YES | LU15: YES | LV15: NO | LW15: NOT APPLICABLE - NOT MAINLINE PIPE | LX15: NOT APPLICABLE - NOT MAINLINE PIPE | SC15: NO | UO15: NO | UR15: NO | UZ15: NO | XL15: TODD NARDOZZI | XM15: DIRECTOR - DOT COMPLIANCE | XN15: todd.nardozzi@energytransfer.com | XO15: 713-989-7126 | XQ15: 45744 | XU15: TODD NARDOZZI | XV15: 713-989-7126 | XW15: DIRECTOR - DOT COMPLIANCE | XX15: todd.nardozzi@energytransfer.com | XY15: ON 02/27/2025 AT APPROXIMATELY 16:00, AS EMPLOYEES AND CONTRACTORS WERE WORKING IN THE AREA THEY NOTICED A LEAK FROM A PINHOLE AT THE 6 O'CLOCK POSITION ON THE WICHITA FALLS TANK 12-INCH FILL LINE. THIS LINE IS AN OPERATIONAL DEAD-LEG. APPROXIMATELY 1 BARREL OF CRUDE OIL WAS RELEASED TO THE GROUND. CONTRACTORS CLEANED-UP THE PRODUCT AND REMOVED IMPACTED SOIL. THE CAUSE OF THE LEAK WAS DETERMINED TO BE INTERNAL CORROSION. THE LINE WAS REPAIRED WITH A MECHANICAL CLAMP. TO PREVENT REOCCURRENCE, THIS LINE WILL BE PERMANENTLY REMOVED.
A16: 97 | B16: 45782 | C16: 2025 | D16: 20250110 | E16: 41059 | F16: SUPPLEMENTAL FINAL | G16: 39706 | H16: ENERGY TRANSFER NEDERLAND TERMINAL LLC | I16: 1300 MAIN STREET | J16: HOUSTON | K16: TX | L16: 77002 | M16: 45698.569 | N16: CENTRAL | O16: NO | P16: 30.003982 | Q16: -93.989769 | R16: CRUDE OIL | W16: 0.3 | Y16: 0.3 | Z16: NO | AF16: 0 | AG16: NO | AM16: 0 | AN16: LOCAL OPERATING PERSONNEL, INCLUDING CONTRACTORS | AP16: OPERATOR EMPLOYEE | AQ16: 45698.569 | AR16: ONSHORE BREAKOUT TANK OR STORAGE VESSEL, INCLUDING ATTACHED APPURTENANCES | AS16: ONSHORE | AT16: NORMAL OPERATION, INCLUDES PAUSES BETWEEN BATCHES AND DURING MAINTENANCE | AU16: NO | AV16: TANK ISOLATED | AZ16: NO | BC16: 45698.569 | BD16: 45698.569 | BF16: NRC NOTIFICATION NOT REQUIRED | BH16: NO | BV16: YES | BW16: 45698.571 | BX16: NO | CA16: 0 | CB16: NEDERLAND TERMINAL | CC16: TANK 1570 | CD16: TX | CE16: 77627 | CF16: NEDERLAND | CG16: JEFFERSON | CH16: SURVEY STATION NO. | CI16: 0+00 | CJ16: NO | CK16: TOTALLY CONTAINED ON OPERATOR-CONTROLLED PROPERTY | CL16: TANK, INCLUDING ATTACHED APPURTENANCES | CP16: NO | DM16: INTERSTATE | DN16: TANK/VESSEL | EW16: MIXER | EY16: ATMOSPHERIC | FD16: 56.8 | FE16: NO | FF16: 2011 | FH16: 2021 | FK16: 2011 | FL16: 2011 | FM16: CARBON STEEL | FO16: LEAK | FR16: SEAL OR PACKING | FY16: NO | GC16: YES | GD16: NO | GE16: YES | GH16: YES | GK16: NO | GT16: YES | GU16: YES | GX16: YES | GY16: YES | HF16: 0 | HG16: 1000 | HH16: 3000 | HI16: 2500 | HJ16: 1000 | HK16: 0 | HM16: 7500 | HN16: 0 | HO16: 0 | HP16: 0 | HQ16: 0 | HR16: 14.7 | HZ16: NO | IS16: > 20% SMYS REGULATED TRANSMISSION | IT16: YES | IU16: YES | IV16: YES | IW16: NO | IX16: NO | IY16: NO | JD16: NO, THE OPERATOR DID NOT FIND THAT AN INVESTIGATION OF THE CONTROLLER(S) ACTIONS OR CONTROL ROOM ISSUES WAS NECESSARY DUE TO: (PROVIDE AN EXPLANATION FOR WHY THE OPERATOR DID NOT INVESTIGATE) | JE16: A REVIEW OF THE ACCIDENT DETERMINED THAT THERE WERE NO CONTROL ROOM ACTIONS THAT CONTRIBUTED TO THE EVENT. | JR16: NO | JS16: NO | JX16: EQUIPMENT FAILURE | JY16: NON-THREADED CONNECTION FAILURE | QB16: NON-THREADED CONNECTION FAILURE | QS16: SEAL (NOT PUMP SEAL) OR PACKING | RK16: YES | RL16: SEAL MATERIAL WEAR | XL16: TODD NARDOZZI | XM16: DIRECTOR - DOT COMPLIANCE | XN16: todd.nardozzi@energytransfer.com | XO16: 713-989-7126 | XQ16: 45827 | XU16: TODD NARDOZZI | XV16: 713-989-7126 | XW16: DIRECTOR - DOT COMPLIANCE | XX16: todd.nardozzi@energytransfer.com | XY16: ON 02/10/2025 AT APPROXIMATELY 13:40, CRUDE OIL WAS DISCOVERED LEAKING FROM TANK MIXER "D" ON TANK 1570. THE LEAK WAS IMMEDIATELY REPORTED, MIXER ISOLATED, AND LEAKED STOPPED. THE LEAK WAS COMING FROM A FAILED TANK MIXER SEAL. APPROXIMATELY 0.3 BARRELS (12 GALLONS) OF CRUDE OIL WAS RELEASED WITHIN SECONDARY CONTAINMENT. CONTRACTORS CLEANED UP REMAINING PRODUCT AND REMOVED CONTAMINATED SOIL. THE FAILED SEAL WAS REPLACED AND TANK OPERATIONS RESUMED. SUPPLEMENTAL & FINAL: THE MIXER ASSEMBLY WAS EXAMINED AND NO ABNORMALITIES NOTED. THE CAUSE OF THE ACCIDENT WAS DUE TO A NON-THREADED CONNECTION FAILURE. THE TANK MIXER SEAL FAILED FROM ROUTINE WEAR.
A17: 104 | B17: 45718 | C17: 2025 | D17: 20250051 | E17: 40629 | F17: SUPPLEMENTAL | G17: 18718 | H17: SUNOCO PIPELINE L.P. | I17: 1300 MAIN STREET | J17: HOUSTON | K17: TX | L17: 77002 | M17: 45688.688 | N17: EASTERN | O17: NO | P17: 40.271237 | Q17: -74.876208 | R17: REFINED AND/OR PETROLEUM PRODUCT (NON-HVL) WHICH IS A LIQUID AT AMBIENT CONDITIONS | S17: DIESEL, FUEL OIL, KEROSENE, JET FUEL | W17: 156 | Y17: 16.9 | Z17: NO | AF17: 0 | AG17: NO | AM17: 0 | AN17: NOTIFICATION FROM PUBLIC | AQ17: 45688.688 | AR17: ONSHORE PIPELINE, INCLUDING VALVE SITES | AS17: ONSHORE | AT17: NORMAL OPERATION, INCLUDES PAUSES BETWEEN BATCHES AND DURING MAINTENANCE | AU17: NO | AV17: LINE WAS DOWN ON SCHEDULE AT TIME OF RELEASE CONFIRMED DISCOVERY | AZ17: YES | BA17: OPERATOR | BB17: 45688.712 | BC17: 45688.688 | BD17: 45688.688 | BE17: 45688.704 | BF17: 1422422 | BG17: 1422562 | BH17: NO | BN17: VALVE CLOSURE | BP17: 45686.718 | BQ17: REMOTELY CONTROLLED | BR17: VALVE CLOSURE | BT17: 45687.382 | BU17: MANUAL | BV17: YES | BW17: 45688.688 | BX17: YES | BY17: 45688.708 | BZ17: 45688.75 | CA17: 0 | CB17: 11010 - 14-INCH TWIN OAKS-NEWARK | CC17: 11010 - 14-INCH TWIN OAKS-NEWARK | CD17: PA | CE17: 18977 | CF17: UPPER MAKEFIELD TWP. | CG17: BUCKS | CH17: SURVEY STATION NO. | CI17: 2788+05 | CJ17: NO | CK17: PIPELINE RIGHT-OF-WAY | CL17: UNDERGROUND | CM17: UNDER SOIL | CO17: 60 | CP17: NO | DM17: INTERSTATE | DN17: PIPE | DO17: PIPE BODY | DP17: NO | DQ17: 14 | DR17: 0.25 | DS17: 52000 | DT17: API-5LX | DU17: SEAMLESS | DW17: NATIONAL TUBE SUPPLY CO | DX17: COLD APPLIED TAPE | DZ17: YES | FK17: 1956 | FL17: UNKNOWN | FM17: CARBON STEEL | FO17: LEAK | FR17: CRACK | FY17: NO | GC17: YES | GD17: YES | GE17: YES | GG17: YES | GH17: YES | GK17: YES | GN17: YES | GO17: YES | GP17: YES | GR17: 1.6 | GS17: UNKNOWN | GT17: YES | GU17: YES | GX17: YES | GY17: YES | HB17: YES | HC17: YES | HF17: 50000 | HG17: 14040 | HH17: 125000 | HI17: 84300 | HJ17: 15000000 | HK17: 0 | HM17: 15273340 | HN17: 0 | HO17: 0 | HP17: 0 | HQ17: 0 | HR17: 320 | HS17: 1200 | HT17: SUBPART E PRESSURE TEST ß195.406(A)(3) | HV17: 42509 | HW17: NO | HY17: PRESSURE DID NOT EXCEED MOP | HZ17: NO | IC17: 32155 | ID17: YES | IL17: NO | IS17: > 20% SMYS REGULATED TRANSMISSION | IT17: YES | IU17: YES | IV17: YES | IW17: NO | IX17: NO | IY17: YES | IZ17: YES | JA17: YES | JB17: NO | JC17: NO | JD17: NO, THE OPERATOR DID NOT FIND THAT AN INVESTIGATION OF THE CONTROLLER(S) ACTIONS OR CONTROL ROOM ISSUES WAS NECESSARY DUE TO: (PROVIDE AN EXPLANATION FOR WHY THE OPERATOR DID NOT INVESTIGATE) | JE17: A REVIEW OF THE ACCIDENT DETERMINED THAT THERE WERE NO CONTROL ROOM ACTIONS THAT CONTRIBUTED TO THE EVENT. | JR17: NO | JS17: NO | JX17: MATERIAL FAILURE OF PIPE OR WELD | JY17: ENVIRONMENTAL CRACKING-RELATED | PC17: YES | PG17: ENVIRONMENTAL CRACKING-RELATED | PN17: STRESS CORROSION CRACKING | PP17: YES | PT17: YES | SC17: YES | SD17: YES | SE17: YES | SF17: YES | SG17: YES | SK17: 2022 | SL17: FREE SWIMMING | SM17: METAL LOSS | SO17: HIGH RESOLUTION | SQ17: 2019 | SR17: FREE SWIMMING | SS17: METAL LOSS | SU17: HIGH RESOLUTION | SW17: 2022 | SX17: FREE SWIMMING | SY17: HIGH RESOLUTION | TA17: 2019 | TB17: FREE SWIMMING | TC17: HIGH RESOLUTION | TE17: 2017 | TF17: FREE SWIMMING | TG17: CRACK | TK17: 2006 | TL17: FREE SWIMMING | TM17: WALL MEASUREMENT | TO17: STANDARD RESOLUTION | TQ17: 2022 | TR17: FREE SWIMMING | TS17: HIGH RESOLUTION | TU17: NO CUPS | TV17: 2019 | TW17: FREE SWIMMING | TX17: HIGH RESOLUTION | TZ17: NO CUPS | UO17: YES | UP17: 2016 | UQ17: 1555 | UR17: NO | UZ17: NO | XL17: TODD NARDOZZI | XM17: DIRECTOR - DOT COMPLIANCE | XN17: todd.nardozzi@energytransfer.com | XO17: 713-989-7126 | XQ17: 45730 | XU17: TODD NARDOZZI | XV17: 713-989-7126 | XW17: DIRECTOR - DOT COMPLIANCE | XX17: todd.nardozzi@energytransfer.com | XY17: ON 01/31/2025 AT APPROXIMATELY 16:30, OPERATIONS PERSONNEL INVESTIGATING A COMPLAINT OF A PETROLEUM ODOR DISCOVERED A LEAK AT A HISTORIC A SLEEVE REPAIR ON THE 11010 - 14-INCH TWIN OAKS-NEWARK LINE. THE FAILED SECTION OF PIPE WAS PREVIOUSLY REPAIRED BY A TYPE A SLEEVE. THAT SECTION OF PIPE INCLUDING THE SLEEVE WAS CUT OUT AND REPLACED. THE CUTOUT HAS BEEN SENT TO 3RD PARTY LABORATORY FOR ANALYSIS. A SUPPLEMENTAL REPORT WILL BE SUBMITTED ONCE THE INVESTIGATION IS COMPLETE. OTHER SIMILAR REPAIR SLEEVES ON THE PIPELINE WERE EITHER EXCAVATED AND ASSESSED OR PROBED AND SURVEYED FOR PRESENCE OF HYDROCARBON INDICATORS TO DETERMINE IF ANY CONDITIONS SIMILAR TO THAT OF THE FAILURE POINT WERE PRESENT. NONE WERE FOUND. ON SITE REMEDIATION AND PRODUCT RECOVERY EFFORTS CONTINUE. SUPPLEMENTAL: THE METALLURGICAL ANALYSIS INDICATED THAT THE PIPE LEAKED AT AN AREA OF EXTERNAL CRACKING LOCATED AT A BOTTOM SIDE DENT IN A REGION OF NOTABLE EXTERNAL CORROSION. THE MECHANISM OF CRACKING IS LIKELY NEAR-NEUTRAL PH STRESS CORROSION CRACKING.
A18: 107 | B18: 45714 | C18: 2025 | D18: 20250049 | E18: 40555 | F18: ORIGINAL FINAL | G18: 10012 | H18: NUSTAR PIPELINE OPERATING PARTNERSHIP L.P. | I18: 8111 WESTCHESTER DRIVE | J18: DALLAS | K18: TX | L18: 75225 | M18: 45687.51 | N18: CENTRAL | O18: NO | P18: 44.01146 | Q18: -98.18275 | R18: REFINED AND/OR PETROLEUM PRODUCT (NON-HVL) WHICH IS A LIQUID AT AMBIENT CONDITIONS | S18: GASOLINE (NON-ETHANOL) | W18: 1.8 | Y18: 1 | Z18: NO | AF18: 0 | AG18: NO | AM18: 0 | AN18: LOCAL OPERATING PERSONNEL, INCLUDING CONTRACTORS | AP18: OPERATOR EMPLOYEE | AQ18: 45687.51 | AR18: ONSHORE PIPELINE, INCLUDING VALVE SITES | AS18: ONSHORE | AT18: NORMAL OPERATION, INCLUDES PAUSES BETWEEN BATCHES AND DURING MAINTENANCE | AU18: NO | AV18: OPERATOR PERSONNEL WERE ABLE TO ISOLATE LEAKING RELIEF VALVE. | AZ18: NO | BC18: 45687.51 | BD18: 45687.51 | BE18: 45687.547 | BF18: 1422298 | BG18: 1422474 | BH18: NO | BN18: OPERATIONAL CONTROL | BO18: LEAKING RELIEF VALVE WAS ISOLATED. DID NOT IMPACT CONTINUED NORMAL OPERATIONS. | BR18: OPERATIONAL CONTROL | BS18: LEAKING RELIEF VALVE WAS ISOLATED. DID NOT IMPACT CONTINUED NORMAL OPERATIONS. | BV18: YES | BW18: 45687.51 | BX18: NO | CA18: 0 | CB18: LINE 5 - YANKTON, SD TO WOLSEY, SD | CC18: MILEPOST 90 - PIG TRAP SITE | CD18: SD | CE18: 57314 | CF18: Not Within a Municipality | CG18: SANBORN | CH18: MILEPOST | CI18: 90 | CJ18: NO | CK18: ORIGINATED ON OPERATOR-CONTROLLED PROPERTY, BUT THEN FLOWED OR MIGRATED OFF THE PROPERTY | CL18: ABOVEGROUND | CM18: TYPICAL ABOVEGROUND FACILITY PIPING OR APPURTENANCE | CP18: NO | DM18: INTERSTATE | DN18: RELIEF LINE AND RELIEF EQUIPMENT | FK18: 2020 | FL18: 2019 | FM18: CARBON STEEL | FO18: LEAK | FR18: SEAL OR PACKING | FY18: NO | GC18: YES | GD18: YES | GE18: YES | GH18: YES | GI18: YES | GK18: NO | GT18: NO | GU18: NO | HF18: 0 | HG18: 250 | HH18: 2000 | HI18: 18700 | HJ18: 51000 | HK18: 0 | HM18: 71950 | HN18: 0 | HO18: 0 | HP18: 0 | HQ18: 0 | HR18: 623.7 | HS18: 1313 | HT18: INTERNAL DESIGN PRESSURE ß195.406(A)(1) | HV18: 30457 | HW18: NO | HY18: PRESSURE DID NOT EXCEED MOP | HZ18: NO | ID18: YES | IL18: NO | IS18: > 20% SMYS REGULATED TRANSMISSION | IT18: YES | IU18: YES | IV18: YES | IW18: NO | IX18: NO | IY18: YES | IZ18: YES | JA18: YES | JB18: NO | JC18: NO | JD18: NO, THE OPERATOR DID NOT FIND THAT AN INVESTIGATION OF THE CONTROLLER(S) ACTIONS OR CONTROL ROOM ISSUES WAS NECESSARY DUE TO: (PROVIDE AN EXPLANATION FOR WHY THE OPERATOR DID NOT INVESTIGATE) | JE18: FAILED RELIEF VALVE WAS ON TRAP BARREL THAT RELIEVES BACK TO THE MAIN LINE. NOT UNDER SCADA CONTROL OR MONITORING. | JR18: NO | JS18: NO | JX18: EQUIPMENT FAILURE | JY18: MALFUNCTION OF CONTROL/RELIEF EQUIPMENT | QB18: MALFUNCTION OF CONTROL/RELIEF EQUIPMENT | QI18: YES | RI18: YES | WW18: YES | XL18: DOUG A. STUCKY | XM18: MANAGER - PIPELINE SAFETY | XN18: doug.stucky@sunoco.com | XO18: 3167217036 | XQ18: 45714 | XR18: MIKE OSWEILER | XS18: mike.osweiler@sunoco.com | XT18: 4023792620 | XU18: DOUG A. STUCKY | XV18: 3167217036 | XW18: MANAGER - PIPELINE SAFETY | XX18: doug.stucky@sunoco.com | XY18: AT APPROXIMATELY 12:15PM ON 30JAN25 WHILE SUNOCO LOCAL OPERATIONS PERSONNEL WERE MAKING THEIR ROUNDS, IT WAS DISCOVERED AT THE MP90 - PIG TRAP SITE THAT A RELIEF VALVE WAS LEAKING. THE SPILL WAS CONFIRMED AT 12:15PM. THE RELIEF VALVE WAS ISOLATED IMMEDIATELY, AND NOTIFICATIONS WERE MADE TO SUNOCO MANAGEMENT IN THE WICHITA OFFICE AT 12:43PM. ADDITIONAL LOCAL SUNOCO PERSONNEL WERE MOBILIZED TO THE SITE TO BEGIN CLEANUP OPERATIONS. SORBENT PADS, TRASH PUMPS, AND DRUMS WERE USED FOR INITIAL COLLECTION OF FREE PRODUCT ON TOP OF THE GROUND. THE SUNOCO MAINTENANCE CREW WAS NOTIFIED AND MOBILIZED TO THE SITE ON THE MORNING OF 31JAN25 WITH A VAC TRUCK AND EXCAVATOR TO CONTINUE CLEANUP OPERATIONS. AT THE TIME OF THE INCIDENT, IT WAS OVERCAST AND 46 DEGREES F. THE GROUND WAS FROZEN AND THERE WAS MINIMAL WIND. AN INITIAL ESTIMATE OF 75 GALLONS OF GASOLINE WAS RELEASED. A FAILED RELIEF VALVE WAS IDENTIFIED AS THE CAUSE OF RELEASE. PIG TRAP SITE IS RURAL, AND THE RELEASE IMPACTED SOIL AROUND THE SITE. THERE WAS NO IMPACT TO WATER, WILDLIFE, OR PUBLIC. NOTIFICATIONS MADE TO STATE AND FEDERAL AGENCIES (NRC, SOUTH DAKOTA DANR, PHMSA, ONE-CALL). SOUTH DAKOTA DANR ARRIVED ON SITE AT APPROXIMATELY 5:00PM, TO ACCESS DAMAGES AND CLEAN-UP ACTIVITIES. NO ADDITIONAL CONCERNS IDENTIFIED. SUNOCO CONTACTED PINNACLE ENGINEERING TO LEAD THE CLEAN-UP / REMEDIATION EFFORTS. THE PINNACLE CONSULTANT ARRIVED ON SITE AT APPROXIMATELY 8:20AM ON THE MORNING OF 31JAN25. INITIAL CLEAN-UP AND REMEDIATION EFFORTS ARE COMPLETE. CONTINUED REMEDIATION WILL BE DETERMINED BASED ON FURTHER ASSESSMENT TO BE COMPLETED BY 11MAR25. THE SUNOCO ENGINEERING TEAM IS REVIEWING NEW DESIGN OPTIONS TO REPLACE THE FAILED RELIEF VALVE.
A19: 113 | B19: 45709 | C19: 2025 | D19: 20250046 | E19: 40532 | F19: ORIGINAL FINAL | G19: 39462 | H19: BAYOU BRIDGE PIPELINE, LLC | I19: 1300 MAIN STREET | J19: HOUSTON | K19: TX | L19: 77002 | M19: 45681.74 | N19: CENTRAL | O19: NO | P19: 30.008087 | Q19: -93.971785 | R19: CRUDE OIL | W19: 10 | Y19: 10 | Z19: NO | AF19: 0 | AG19: NO | AM19: 0 | AN19: OTHER | AO19: THIRD PARTY OPERATOR | AQ19: 45681.74 | AR19: ONSHORE PUMP/METER STATION EQUIPMENT AND PIPING | AS19: ONSHORE | AT19: NORMAL OPERATION, INCLUDES PAUSES BETWEEN BATCHES AND DURING MAINTENANCE | AU19: YES | AW19: 45681.745 | AX19: 45681.942 | AZ19: NO | BC19: 45681.767 | BD19: 45681.767 | BF19: NRC NOTIFICATION NOT REQUIRED | BH19: NO | BV19: YES | BW19: 45681.767 | BX19: NO | CA19: 0 | CB19: NECHES STATION | CC19: 21062 - 30-INCH NEDERLAND TO LAKE CHARLES | CD19: TX | CE19: 77627 | CF19: Not Within a Municipality | CG19: JEFFERSON | CH19: MILEPOST | CI19: 0+00 | CJ19: NO | CK19: TOTALLY CONTAINED ON OPERATOR-CONTROLLED PROPERTY | CL19: ABOVEGROUND | CM19: TYPICAL ABOVEGROUND FACILITY PIPING OR APPURTENANCE | CP19: NO | DM19: INTERSTATE | DN19: VALVE | EM19: AUXILIARY OR OTHER VALVE | FK19: 2016 | FL19: 2015 | FM19: CARBON STEEL | FO19: LEAK | FR19: CONNECTION FAILURE | FY19: NO | GC19: YES | GD19: NO | GE19: YES | GH19: YES | GK19: NO | GT19: YES | GU19: YES | GX19: YES | GY19: YES | HF19: 0 | HG19: 75 | HH19: 5 | HI19: 45000 | HJ19: 2000 | HK19: 0 | HM19: 47080 | HN19: 0 | HO19: 0 | HP19: 0 | HQ19: 0 | HR19: 125 | HS19: 285 | HT19: COMPONENT DESIGN PRESSURE ß195.406(A)(2) | HV19: 42461 | HW19: NO | HY19: PRESSURE DID NOT EXCEED MOP | HZ19: NO | IS19: > 20% SMYS REGULATED TRANSMISSION | IT19: YES | IU19: YES | IV19: YES | IW19: NO | IX19: NO | IY19: YES | IZ19: YES | JA19: YES | JB19: NO | JC19: NO | JD19: NO, THE OPERATOR DID NOT FIND THAT AN INVESTIGATION OF THE CONTROLLER(S) ACTIONS OR CONTROL ROOM ISSUES WAS NECESSARY DUE TO: (PROVIDE AN EXPLANATION FOR WHY THE OPERATOR DID NOT INVESTIGATE) | JE19: A REVIEW OF THE ACCIDENT DETERMINED THAT THERE WERE NO CONTROL ROOM ACTIONS THAT CONTRIBUTED TO THE EVENT. | JR19: NO | JS19: NO | JX19: EQUIPMENT FAILURE | JY19: THREADED CONNECTION/COUPLING FAILURE | QB19: THREADED CONNECTION/COUPLING FAILURE | QQ19: THREADED FITTING | RH19: YES | RK19: YES | RL19: PLUG WAS POSSIBLY CROSS THREADED ON INSTALLATION. | XG19: YES | XL19: TODD NARDOZZI | XM19: DIRECTOR - DOT COMPLIANCE | XN19: todd.nardozzi@energytransfer.com | XO19: 713-989-7126 | XQ19: 45709 | XU19: TODD NARDOZZI | XV19: 713-989-7126 | XW19: DIRECTOR - DOT COMPLIANCE | XX19: todd.nardozzi@energytransfer.com | XY19: ON 01/24/2025 AT APPROXIMATELY 17:45, THE OPS MANAGER WAS CONTACTED BY P66 FIELD PERSONNEL ABOUT A POSSIBLE RELEASE AT NECHES STATION. THE CONTROL CENTER WAS NOTIFIED AND IMMEDIATELY SHUTDOWN 21062 NEDERLAND TO LAKE CHARLES 30-INCH LINE. PIPELINE TECHS ARRIVED ON SITE AND CONFIRMED THE RELEASE WAS ON THE METER SKID DRAIN VALVE 3/8 PLUG. THE METER WAS ISOLATED AND THE VALVE PLUG REPAIRED. APPROXIMATELY 10 BARRELS OF CRUDE OIL WAS RELEASED. ALL FREE PRODUCT WAS PICKED UP AND CONTAMINATED SOIL WAS CLEANED UP. THE CAUSE OF THE RELEASE WAS DUE TO A THREADED FITTING FAILURE POSSIBLY DUE TO CROSS THREADING ON INSTALLATION. PRESSURE SIDE'S DRAIN ISOLATION VALVE BLEW OUT. THREADS ON VALVE WERE INSPECTED AND CLEANED USING A 3/8 TAP. PLUG WAS REPLACED AND PRESSURE TESTED. TO PREVENT REOCCURRENCE, THE COMPLETE VALVE WAS REPLACED ON 01/27/2025. ADDITIONALLY, ALL OTHER DRAIN VALVE PLUGS IN NECHES STATION WERE INSPECTED.
A20: 128 | B20: 45686 | C20: 2024 | D20: 20250027 | E20: 40458 | F20: ORIGINAL FINAL | G20: 39205 | H20: DAPL-ETCO OPERATIONS MANAGEMENT, LLC | I20: 1300 MAIN STREET | J20: HOUSTON | K20: TX | L20: 77002 | M20: 45656.568 | N20: CENTRAL | O20: NO | P20: 48.295173 | Q20: -102.91761 | R20: CRUDE OIL | W20: 2.4 | Y20: 2.4 | Z20: NO | AF20: 0 | AG20: NO | AM20: 0 | AN20: LOCAL OPERATING PERSONNEL, INCLUDING CONTRACTORS | AP20: OPERATOR EMPLOYEE | AQ20: 45656.568 | AR20: ONSHORE PUMP/METER STATION EQUIPMENT AND PIPING | AS20: ONSHORE | AT20: NORMAL OPERATION, INCLUDES PAUSES BETWEEN BATCHES AND DURING MAINTENANCE | AU20: YES | AW20: 45656.57 | AX20: 45656.578 | AZ20: NO | BC20: 45656.568 | BD20: 45656.568 | BF20: NRC NOTIFICATION NOT REQUIRED | BH20: NO | BV20: NO | BX20: NO | CA20: 0 | CB20: RAMBERG STATION | CC20: 12-INCH STANLEY TO RAMBERG | CD20: ND | CE20: 58852 | CF20: Not Within a Municipality | CG20: WILLIAMS | CH20: SURVEY STATION NO. | CI20: 0+00 | CJ20: NO | CK20: TOTALLY CONTAINED ON OPERATOR-CONTROLLED PROPERTY | CL20: ABOVEGROUND | CM20: INSIDE A BUILDING | CP20: NO | DM20: INTERSTATE | DN20: INSTRUMENTATION | FK20: 2016 | FL20: 2016 | FM20: MATERIAL OTHER THAN CARBON STEEL | FN20: SITE GLASS | FO20: LEAK | FR20: CRACK | FY20: NO | GC20: NO | GD20: NO | GE20: NO | GK20: NO | GT20: NO | GU20: NO | HF20: 0 | HG20: 0 | HH20: 150 | HI20: 1350 | HJ20: 500 | HK20: 0 | HM20: 2000 | HN20: 0 | HO20: 0 | HP20: 0 | HQ20: 0 | HR20: 71 | HS20: 285 | HT20: COMPONENT DESIGN PRESSURE ß195.406(A)(2) | HV20: 42675 | HW20: NO | HY20: PRESSURE DID NOT EXCEED MOP | HZ20: NO | IS20: > 20% SMYS REGULATED TRANSMISSION | IT20: YES | IU20: YES | IV20: YES | IW20: YES | IX20: YES | IY20: YES | IZ20: YES | JA20: YES | JB20: NO | JC20: NO | JD20: NO, THE OPERATOR DID NOT FIND THAT AN INVESTIGATION OF THE CONTROLLER(S) ACTIONS OR CONTROL ROOM ISSUES WAS NECESSARY DUE TO: (PROVIDE AN EXPLANATION FOR WHY THE OPERATOR DID NOT INVESTIGATE) | JE20: A REVIEW OF THE ACCIDENT DETERMINED THAT THERE WERE NO CONTROL ROOM ACTIONS THAT CONTRIBUTED TO THE EVENT. | JR20: NO | JS20: NO | JX20: EQUIPMENT FAILURE | JY20: OTHER EQUIPMENT FAILURE | QB20: OTHER EQUIPMENT FAILURE | QU20: RVP ANALYZER SITE GLASS | RK20: YES | RL20: FATIGUE | XL20: TODD NARDOZZI | XM20: DIRECTOR - DOT COMPLIANCE | XN20: todd.nardozzi@energytransfer.com | XO20: 713-989-7126 | XQ20: 45686 | XU20: TODD NARDOZZI | XV20: 713-989-7126 | XW20: DIRECTOR - DOT COMPLIANCE | XX20: todd.nardozzi@energytransfer.com | XY20: ON 12/30/24 AT APPROXIMATELY 13:38, A PIPELINE TECH DISCOVERED CRUDE OIL INSIDE THE METER BUILDING AT RAMBERG STATION. THE CONTROL CENTER WAS IMMEDIATELY NOTIFIED TO SHUT DOWN THE STATION. THE STATION LEL DETECTOR ALARMED AND LOCKED OUT THE STATION AT 13:41 BUT SHUTDOWN WAS ALREADY IN PROCESS. THE LEAK WAS COMING FROM CRACKED SITE GLASS ON THE KOBOLD FLOW METER RVP ANALYZER INSIDE THE ANALYZER CABINET. APPROXIMATELY 2.4 BARRELS OF CRUDE OIL WAS RELEASED INSIDE BUILDING ONTO CONCRETE. OPERATING PERSONNEL CLEANED UP ALL RELEASED PRODUCT. THE CAUSE OF THE ACCIDENT WAS DETERMINED TO BE FROM FAILURE OF THE RVP ANALYZER SITE GLASS. TO PREVENT REOCCURRENCE ALL SITE GLASS IN ALL RVP ANALYZERS IN THE SYSTEM WERE REPLACED WITH STAINLESS STEEL.
A21: 129 | B21: 45681 | C21: 2024 | D21: 20250026 | E21: 40445 | F21: ORIGINAL | G21: 39706 | H21: ENERGY TRANSFER NEDERLAND TERMINAL LLC | I21: 1300 MAIN STREET | J21: HOUSTON | K21: TX | L21: 77002 | M21: 45655.427 | N21: CENTRAL | O21: NO | P21: 29.9976 | Q21: -93.992767 | R21: CRUDE OIL | W21: 3 | Y21: 3 | Z21: NO | AF21: 0 | AG21: NO | AM21: 0 | AN21: LOCAL OPERATING PERSONNEL, INCLUDING CONTRACTORS | AP21: OPERATOR EMPLOYEE | AQ21: 45655.427 | AR21: ONSHORE TERMINAL/TANK FARM EQUIPMENT AND PIPING | AS21: ONSHORE | AT21: NORMAL OPERATION, INCLUDES PAUSES BETWEEN BATCHES AND DURING MAINTENANCE | AU21: NO | AV21: LINE WAS ISOLATED AND OPERATIONS TRANSFERRED TO ANOTHER LINE. | AZ21: NO | BC21: 45655.427 | BD21: 45655.427 | BF21: NRC NOTIFICATION NOT REQUIRED | BH21: NO | BV21: YES | BW21: 45655.427 | BX21: NO | CA21: 0 | CB21: NEDERLAND TERMINAL | CC21: 28-16G 16-INCH | CD21: TX | CE21: 77627 | CF21: NEDERLAND | CG21: JEFFERSON | CH21: SURVEY STATION NO. | CI21: 0+00 | CJ21: NO | CK21: TOTALLY CONTAINED ON OPERATOR-CONTROLLED PROPERTY | CL21: UNDERGROUND | CM21: UNDER SOIL | CO21: 48 | CP21: NO | DM21: INTERSTATE | DN21: PIPE | DO21: PIPE BODY | DP21: NO | DQ21: 16 | DR21: 0.375 | DS21: 42000 | DT21: X42 | DU21: SEAMLESS | DW21: UNKNOWN | DX21: FUSION BONDED EPOXY(FBE) | DZ21: NO | FK21: UNKNOWN | FL21: UNKNOWN | FM21: CARBON STEEL | FO21: LEAK | FR21: PINHOLE | FY21: NO | GC21: YES | GD21: NO | GE21: YES | GH21: YES | GK21: NO | GT21: YES | GU21: YES | GX21: YES | GY21: YES | HF21: 0 | HG21: 300 | HH21: 3500 | HI21: 15000 | HJ21: 2500 | HK21: 0 | HM21: 21300 | HN21: 0 | HO21: 0 | HP21: 0 | HQ21: 0 | HR21: 85 | HS21: 275 | HT21: SUBPART E PRESSURE TEST ß195.406(A)(3) | HV21: 44060 | HW21: BI-DIRECTIONAL | HY21: PRESSURE DID NOT EXCEED MOP | HZ21: NO | IS21: > 20% SMYS REGULATED TRANSMISSION | IT21: YES | IU21: YES | IV21: YES | IW21: NO | IX21: NO | IY21: YES | IZ21: YES | JA21: YES | JB21: NO | JC21: NO | JD21: NO, THE OPERATOR DID NOT FIND THAT AN INVESTIGATION OF THE CONTROLLER(S) ACTIONS OR CONTROL ROOM ISSUES WAS NECESSARY DUE TO: (PROVIDE AN EXPLANATION FOR WHY THE OPERATOR DID NOT INVESTIGATE) | JE21: A REVIEW OF THE ACCIDENT DETERMINED THAT THERE WERE NO CONTROL ROOM ACTIONS THAT CONTRIBUTED TO THE EVENT. | JR21: NO | JS21: NO | JX21: OTHER ACCIDENT CAUSE | JY21: UNKNOWN | RY21: UNKNOWN | SA21: STILL UNDER INVESTIGATION, CAUSE OF ACCIDENT TO BE DETERMINED* (*SUPPLEMENTAL REPORT REQUIRED) | XL21: TODD NARDOZZI | XM21: DIRECTOR - DOT COMPLIANCE | XN21: todd.nardozzi@energytransfer.com | XO21: 713-989-7126 | XQ21: 45681 | XU21: TODD NARDOZZI | XV21: 713-989-7126 | XW21: DIRECTOR - DOT COMPLIANCE | XX21: todd.nardozzi@energytransfer.com | XY21: ON 12/29/24 AT APPROXIMATELY 10:15 A LEAK WAS DISCOVERED INSIDE OF THE TANK 1546 CONTAINMENT DIKE INVOLVING THE 28-16"G LINE. THE LEAK OCCURRED UNDERGROUND AND ONCE DISCOVERED, THE OPERATORS CHANGED THE LINE UP AND CEASED THE TRANSFER OF OIL THROUGH THE 28-16"G LINE. THE LEAK WAS COMING FROM A PINHOLE. APPROXIMATELY 3 BARRELS OF CRUDE OIL WAS RELEASED. ON SITE CLEANUP CREW REMOVED FREE PRODUCT AND REMEDIATED CONTAMINATED SOIL. THE PIPE WAS TEMPORARILY REPAIRED WITH A CLAMP. THE CAUSE OF THE LEAK IS STILL UNDER INVESTIGATION. A SUPPLEMENTAL REPORT WILL BE SUBMITTED ONCE THE INVESTIGATION IS COMPLETE.
A22: 130 | B22: 45681 | C22: 2024 | D22: 20250023 | E22: 41005 | F22: SUPPLEMENTAL FINAL | G22: 22830 | H22: WOLVERINE PIPELINE CO | I22: 8075 CREEKSIDE DR., STE. 210 | J22: PORTAGE | K22: MI | L22: 49024-6303 | M22: 45653.771 | N22: EASTERN | O22: YES | P22: 42.32199 | Q22: -84.64886 | R22: REFINED AND/OR PETROLEUM PRODUCT (NON-HVL) WHICH IS A LIQUID AT AMBIENT CONDITIONS | S22: DIESEL, FUEL OIL, KEROSENE, JET FUEL | W22: 60.85 | Y22: 60.85 | Z22: NO | AF22: 0 | AG22: NO | AM22: 0 | AN22: NOTIFICATION FROM PUBLIC | AQ22: 45653.81 | AR22: ONSHORE PIPELINE, INCLUDING VALVE SITES | AS22: ONSHORE | AT22: NORMAL OPERATION, INCLUDES PAUSES BETWEEN BATCHES AND DURING MAINTENANCE | AU22: YES | AW22: 45653.771 | AX22: 45667.356 | AZ22: YES | BA22: OPERATOR | BB22: 45653.844 | BC22: 45653.81 | BD22: 45653.81 | BE22: 45653.84 | BF22: 1419975 | BG22: 1420033, 1420075 | BH22: NO | BN22: VALVE CLOSURE | BP22: 45653.822 | BQ22: MANUAL | BR22: VALVE CLOSURE | BT22: 45653.823 | BU22: MANUAL | BV22: YES | BW22: 45653.799 | BX22: YES | BY22: 45653.844 | BZ22: 45653.917 | CA22: 0 | CB22: LAPAUGH TO ALMA | CC22: LAPAUGH TO ALMA | CD22: MI | CE22: 48847 | CF22: ITHACA | CG22: GRATIOT | CH22: MILEPOST | CI22: 23.48 | CJ22: NO | CK22: PIPELINE RIGHT-OF-WAY | CL22: UNDERGROUND | CM22: UNDER SOIL | CO22: 6 | CP22: YES | CW22: YES | CX22: UNCASED | CY22: NEWARK -ARCADA DRAIN | CZ22: 2 | DA22: BELOW WATER, PIPE BURIED BELOW BOTTOM (NOT IN BORED/DRILLED CROSSING) | DB22: NO | DM22: INTERSTATE | DN22: PIPE | DO22: PIPE BODY | DP22: NO | DQ22: 6.625 | DR22: 0.25 | DS22: 42000 | DT22: API 5L X-42 | DU22: ERW - LOW FREQUENCY | DW22: UNKNOWN | DX22: OTHER | DY22: WAX, PARAFIN BASED | DZ22: YES | FK22: 1957 | FL22: UNKNOWN | FM22: CARBON STEEL | FO22: LEAK | FR22: PINHOLE | FY22: NO | GC22: YES | GD22: NO | GE22: NO | GK22: YES | GM22: YES | GR22: 60.84 | GS22: NEWARK-ARCADA COUNTY DRAIN | GT22: NO | GU22: NO | HF22: 12000 | HG22: 4250 | HH22: 733921 | HI22: 911509 | HJ22: 73258 | HK22: 66502 | HL22: MEALS/LODGING FOR EMPLOYEES, SMALL CLAIMS/DAMAGE SETTLEMENTS WITH LANDOWNERS | HM22: 1801440 | HN22: 0 | HO22: 0 | HP22: 0 | HQ22: 0 | HR22: 341 | HS22: 1440 | HT22: INTERNAL DESIGN PRESSURE ß195.406(A)(1) | HV22: 33309 | HW22: NO | HY22: PRESSURE DID NOT EXCEED MOP | HZ22: NO | IC22: 34400 | ID22: YES | IL22: NO | IS22: > 20% SMYS REGULATED TRANSMISSION | IT22: YES | IU22: YES | IV22: YES | IW22: NO | IX22: NO | IY22: NO | JD22: NO, THE OPERATOR DID NOT FIND THAT AN INVESTIGATION OF THE CONTROLLER(S) ACTIONS OR CONTROL ROOM ISSUES WAS NECESSARY DUE TO: (PROVIDE AN EXPLANATION FOR WHY THE OPERATOR DID NOT INVESTIGATE) | JE22: EARLY ANALYSIS OF SCADA DATA DID NOT INDICATE OPERATOR ACTIONS CONTRIBUTED TO INCIDENT. | JR22: YES | JS22: NO | JT22: 1 | JU22: 0 | JX22: EXCAVATION DAMAGE | JY22: PREVIOUS DAMAGE DUE TO EXCAVATION ACTIVITY | MK22: PREVIOUS DAMAGE DUE TO EXCAVATION ACTIVITY | ML22: NO | MQ22: NO | MV22: YES | MY22: YES | MZ22: PRIVATE LANDOWNER | NA22: YES | NG22: NO | NH22: NO | NI22: < 18î | NK22: UNKNOWN/OTHER | NL22: UNKNOWN/OTHER | NM22: UNKNOWN/OTHER | NN22: NO | NR22: UNKNOWN/OTHER | NS22: NO | NT22: YES | NU22: 325 | NV22: NOTIFICATION ISSUE | NW22: NO NOTIFICATION MADE TO THE ONE-CALL CENTER/811 | SC22: YES | SD22: YES | SG22: YES | SK22: 2023 | SL22: FREE SWIMMING | SM22: METAL LOSS | SO22: HIGH RESOLUTION | SQ22: 2018 | SR22: FREE SWIMMING | SS22: METAL LOSS | SU22: HIGH RESOLUTION | TQ22: 2023 | TR22: FREE SWIMMING | TS22: HIGH RESOLUTION | TU22: NO CUPS | TV22: 2018 | TW22: FREE SWIMMING | TX22: HIGH RESOLUTION | TZ22: NO CUPS | UN22: YES | UO22: NO | UR22: NO | UZ22: NO | XL22: SPENCER | XM22: SHE SUPERVISOR | XN22: spencer_welling@wplco.com | XO22: 269-548-9865 | XQ22: 45772 | XR22: SPENCER WELLING | XS22: spencer_welling@wplco.com | XT22: 269-548-9865 | XU22: CHRIS NEELY | XV22: 269-491-0411 | XW22: VICE PRESIDENT AND MANAGER | XX22: chris_neely@wplco.com | XY22: WOLVERINE PIPE LINE (WPL) OCC RECEIVED A CALL FROM THE GRATIOT COUNTY DRAIN COMMISSIONER INDICATING THAT THERE WAS A POTENTIAL LEAK. OCC IMMEDIATELY SHUT DOWN THE AFFECTED LINE SEGMENT AND DISPATCHED PERSONNEL TO INVESTIGATE. UPON ARRIVING ON SITE, WPL PERSONNEL CONFIRMED THE RELEASE AND THE UPSTREAM AND DOWNSTREAM BLOCK VALVES WERE CLOSED. PRODUCT APPEARED TO BE LEAKING OUT OF THE PIPELINE DIRECTLY INTO THE WATERS OF THE NEWARK-ARCADA DRAIN. AFTER EXCAVATING, IT WAS APPARENT THAT THE PIPELINE WAS DAMAGED BY A THID PARTY EXCAVATOR. THIS AREA OF DAMAGE CONTAINED A DENT WITH GOUGING WITHIN THE DENT. THE LEAK ORIGINATED FROM A CRACK WITHIN THIS GOUGE.THE DENT MEASURED APPROXIMATELY 20-INCHES LONG CONTAINING THE APPROXIMATELY 1-INCH-WIDE GOUGE WITHIN THE DENT. THE MECHANICAL DAMAGE WAS IDENTIFIED ALONG THE 9:00 O'CLOCK SIDE. THE CRACK ASSOCIATED MEASURED APPROXIMATELY 2.5-INCHES LONG X 0.053-INCH DEEP. NEW PIPING WAS INSTALLED UNDERNEATH THE NEWARK-ARCADA DRAIN AT A DEPTH OF 32", PRESSURE TESTED, AND THE PIPELINE RESUMED NORMAL OPERATIONS. WOLVERINE IS WORKING WITH THE MICHIGAN PUBLIC SERVICE COMMISSION AND THE GRATIOT COUNTY DRAIN COMMISSION TO DETERMINE THE INVOLVED THIRD PARTY.
A23: 139 | B23: 45673 | C23: 2024 | D23: 20250016 | E23: 40416 | F23: ORIGINAL | G23: 39596 | H23: PERMIAN EXPRESS PARTNERS LLC | I23: 1300 MAIN STREET | J23: HOUSTON | K23: TX | L23: 77002 | M23: 45644.639 | N23: CENTRAL | O23: NO | P23: 32.352845 | Q23: -93.677745 | R23: CRUDE OIL | W23: 5 | Y23: 5 | Z23: NO | AF23: 0 | AG23: NO | AM23: 0 | AN23: LOCAL OPERATING PERSONNEL, INCLUDING CONTRACTORS | AP23: OPERATOR EMPLOYEE | AQ23: 45644.639 | AR23: ONSHORE PUMP/METER STATION EQUIPMENT AND PIPING | AS23: ONSHORE | AT23: NORMAL OPERATION, INCLUDES PAUSES BETWEEN BATCHES AND DURING MAINTENANCE | AU23: YES | AW23: 45644.64 | AX23: 45645.052 | AZ23: NO | BC23: 45644.639 | BD23: 45644.639 | BF23: NRC NOTIFICATION NOT REQUIRED | BH23: NO | BV23: YES | BW23: 45644.639 | BX23: NO | CA23: 0 | CB23: FINNEY STATION | CC23: 26010.02-18 INCH LONGVIEW TO FINNEY | CD23: LA | CE23: 71115 | CF23: Not Within a Municipality | CG23: CADDO | CH23: MILEPOST | CI23: 68 | CJ23: NO | CK23: TOTALLY CONTAINED ON OPERATOR-CONTROLLED PROPERTY | CL23: ABOVEGROUND | CM23: TYPICAL ABOVEGROUND FACILITY PIPING OR APPURTENANCE | CP23: NO | DM23: INTERSTATE | DN23: METER/PROVER | FK23: 2023 | FL23: UNKNOWN | FM23: CARBON STEEL | FO23: LEAK | FR23: PINHOLE | FY23: NO | GC23: YES | GD23: NO | GE23: YES | GH23: YES | GK23: NO | GT23: NO | GU23: NO | HF23: 0 | HG23: 10 | HH23: 15000 | HI23: 5000 | HJ23: 1000 | HK23: 0 | HM23: 21010 | HN23: 0 | HO23: 0 | HP23: 0 | HQ23: 0 | HR23: 390 | HS23: 982 | HT23: SUBPART E PRESSURE TEST ß195.406(A)(3) | HV23: 44707 | HW23: NO | HY23: PRESSURE DID NOT EXCEED MOP | HZ23: NO | IS23: > 20% SMYS REGULATED TRANSMISSION | IT23: YES | IU23: YES | IV23: YES | IW23: YES | IX23: YES | IY23: YES | IZ23: YES | JA23: YES | JB23: NO | JC23: NO | JD23: NO, THE OPERATOR DID NOT FIND THAT AN INVESTIGATION OF THE CONTROLLER(S) ACTIONS OR CONTROL ROOM ISSUES WAS NECESSARY DUE TO: (PROVIDE AN EXPLANATION FOR WHY THE OPERATOR DID NOT INVESTIGATE) | JE23: A REVIEW OF THE ACCIDENT DETERMINED THAT THERE WERE NO CONTROL ROOM ACTIONS THAT CONTRIBUTED TO THE EVENT. | JR23: NO | JS23: NO | JX23: OTHER ACCIDENT CAUSE | JY23: UNKNOWN | RY23: UNKNOWN | SA23: STILL UNDER INVESTIGATION, CAUSE OF ACCIDENT TO BE DETERMINED* (*SUPPLEMENTAL REPORT REQUIRED) | XL23: TODD NARDOZZI | XM23: DIRECTOR - DOT COMPLIANCE | XN23: todd.nardozzi@energytransfer.com | XO23: 713-989-7126 | XQ23: 45673 | XU23: TODD NARDOZZI | XV23: 713-989-7126 | XW23: DIRECTOR - DOT COMPLIANCE | XX23: todd.nardozzi@energytransfer.com | XY23: ON 12/18/2024 AT APPROXIMATELY 15:20, A PIPELINE TECHNICIAN DISCOVERED OIL ON THE GROUND AROUND FINNEY STATION METER PIPING DURING A ROUTINE STATION CHECK. THE STATION WAS SHUTDOWN AND 26010.02 LONGVIEW TO FINNEY 18-INCH LINE WAS BLOCKED IN. APPROXIMATELY 5 BARRELS OF CRUDE OIL WAS RELEASED ONTO THE GROUND. CONTRACTORS CLEANED-UP THE PRODUCT AND REMOVED IMPACTED SOIL. THE LINE WAS REPAIRED WITH A CLAMP AND RESTARTED. AN NDE SCAN WAS PERFORMED AT THE ACCIDENT LOCATION AND NO OTHER ANOMALIES WERE FOUND. THE CAUSE OF THE ACCIDENT IS UNDER INVESTIGATION. THE FAILED SECTION IS PLANNED TO BE CUT OUT AND SENT TO A THIRD-PARTY LAB FOR ANALYSIS. A SUPPLEMENTAL REPORT WILL BE SUBMITTED ONCE THE INVESTIGATION IS COMPLETE.
A24: 144 | B24: 45663 | C24: 2024 | D24: 20250005 | E24: 40380 | F24: ORIGINAL FINAL | G24: 39706 | H24: ENERGY TRANSFER NEDERLAND TERMINAL LLC | I24: 1300 MAIN STREET | J24: HOUSTON | K24: TX | L24: 77002 | M24: 45635.583 | N24: CENTRAL | O24: NO | P24: 29.994522 | Q24: -93.991514 | R24: CRUDE OIL | W24: 10 | Y24: 10 | Z24: NO | AF24: 0 | AG24: NO | AM24: 0 | AN24: LOCAL OPERATING PERSONNEL, INCLUDING CONTRACTORS | AP24: CONTRACTOR WORKING FOR THE OPERATOR | AQ24: 45635.583 | AR24: ONSHORE TERMINAL/TANK FARM EQUIPMENT AND PIPING | AS24: ONSHORE | AT24: NORMAL OPERATION, INCLUDES PAUSES BETWEEN BATCHES AND DURING MAINTENANCE | AU24: NO | AV24: LINE ALREADY DOWN FOR MAINTENANCE | AZ24: NO | BC24: 45635.583 | BD24: 45635.583 | BF24: NRC NOTIFICATION NOT REQUIRED | BH24: NO | BV24: YES | BW24: 45635.583 | BX24: NO | CA24: 0 | CB24: NEDERLAND TERMINAL | CC24: 28-24C WTG 24INCH | CD24: TX | CE24: 77627 | CF24: NEDERLAND | CG24: JEFFERSON | CH24: SURVEY STATION NO. | CI24: 0+00 | CJ24: NO | CK24: TOTALLY CONTAINED ON OPERATOR-CONTROLLED PROPERTY | CL24: ABOVEGROUND | CM24: TYPICAL ABOVEGROUND FACILITY PIPING OR APPURTENANCE | CP24: NO | DM24: INTERSTATE | DN24: FLANGE ASSEMBLY | FK24: 2024 | FL24: 2024 | FM24: MATERIAL OTHER THAN CARBON STEEL | FN24: GARLOCK FIBEROUS | FO24: LEAK | FR24: CONNECTION FAILURE | FY24: NO | GC24: YES | GD24: NO | GE24: YES | GH24: YES | GK24: NO | GT24: YES | GU24: YES | GX24: YES | GY24: YES | HF24: 0 | HG24: 700 | HH24: 7500 | HI24: 8200 | HJ24: 1500 | HK24: 0 | HM24: 17900 | HN24: 0 | HO24: 0 | HP24: 0 | HQ24: 0 | HR24: 1100 | HS24: 1440 | HT24: INTERNAL DESIGN PRESSURE ß195.406(A)(1) | HV24: 36526 | HW24: NO | HY24: PRESSURE DID NOT EXCEED MOP | HZ24: NO | IS24: > 20% SMYS REGULATED TRANSMISSION | IT24: NO | IY24: NO | JD24: NO, THE OPERATOR DID NOT FIND THAT AN INVESTIGATION OF THE CONTROLLER(S) ACTIONS OR CONTROL ROOM ISSUES WAS NECESSARY DUE TO: (PROVIDE AN EXPLANATION FOR WHY THE OPERATOR DID NOT INVESTIGATE) | JE24: A REVIEW OF THE ACCIDENT DETERMINED THAT THERE WERE NO CONTROL ROOM ACTIONS THAT CONTRIBUTED TO THE EVENT. | JR24: NO | JS24: NO | JX24: EQUIPMENT FAILURE | JY24: NON-THREADED CONNECTION FAILURE | QB24: NON-THREADED CONNECTION FAILURE | QS24: GASKET | QY24: YES | XL24: TODD NARDOZZI | XM24: DIRECTOR - DOT COMPLIANCE | XN24: todd.nardozzi@energytransfer.com | XO24: 713-989-7126 | XQ24: 45663 | XU24: TODD NARDOZZI | XV24: 713-989-7126 | XW24: DIRECTOR - DOT COMPLIANCE | XX24: todd.nardozzi@energytransfer.com | XY24: ON 12/09/24 AT APPROXIMATELY 13:59, A GASKET FAILURE OCCURRED DURING PRESSURE CHECK ON 28-24C WTG 24INCH LINE, PRIOR TO HYDRO TESTING. THIS GASKET WAS INSTALLED PRIOR WHILE WORKING TO GET THE LINE PREPARED FOR HYDRO TESTING. PRESSURE WAS IMMEDIATELY DROPPED TO STOP THE RELEASE. APPROXIMATELY 10 BBLS OF CRUDE OIL WAS RELEASED. ON SITE CLEANUP CREW REMOVED FREE PRODUCT AND REMEDIATED CONTAMINATED SOIL. THE CAUSE OF THE ACCIDENT WAS DUE TO A NON-THREADED CONNECTION FAILURE. RECENTLY INSTALLED GASKETS WILL BE REPLACED TO PREVENT REOCCURRENCE.
A25: 148 | B25: 45665 | C25: 2024 | D25: 20250009 | E25: 40695 | F25: SUPPLEMENTAL FINAL | G25: 32099 | H25: ENERGY TRANSFER COMPANY | I25: 1300 MAIN STREET | J25: HOUSTON | K25: TX | L25: 77002 | M25: 45635.438 | N25: CENTRAL | O25: NO | P25: 30.045552 | Q25: -94.230316 | R25: CRUDE OIL | W25: 1 | Y25: 1 | Z25: NO | AF25: 0 | AG25: NO | AM25: 0 | AN25: NOTIFICATION FROM PUBLIC | AQ25: 45635.438 | AR25: ONSHORE PIPELINE, INCLUDING VALVE SITES | AS25: ONSHORE | AT25: NORMAL OPERATION, INCLUDES PAUSES BETWEEN BATCHES AND DURING MAINTENANCE | AU25: NO | AV25: ALREADY SHUTDOWN AND BLOCKED IN FOR FIELD WORK | AZ25: NO | BC25: 45635.458 | BD25: 45635.469 | BF25: NRC NOTIFICATION NOT REQUIRED | BH25: NO | BN25: OPERATIONAL CONTROL | BO25: CLOSED MANUAL BLOCK VALVE | BR25: OPERATIONAL CONTROL | BS25: CLOSED MANUAL BLOCK VALVE | BV25: YES | BW25: 45635.458 | BX25: NO | CA25: 0 | CB25: EAST TEXAS 10-INCH | CC25: 21003.01 - 10-INCH NEDERLAND TO SOUR LAKE | CD25: TX | CE25: 77713 | CF25: Not Within a Municipality | CG25: JEFFERSON | CH25: SURVEY STATION NO. | CI25: 559+07.8 | CJ25: NO | CK25: PIPELINE RIGHT-OF-WAY | CL25: UNDERGROUND | CM25: UNDER SOIL | CO25: 60 | CP25: NO | DM25: INTRASTATE | DN25: PIPE | DO25: PIPE BODY | DP25: NO | DQ25: 10 | DR25: 0.219 | DS25: 52000 | DT25: API 5L GRADE B | DU25: ERW - HIGH FREQUENCY | DW25: UNKNOWN | DX25: FUSION BONDED EPOXY(FBE) | DZ25: YES | FK25: UNKNOWN | FL25: UNKNOWN | FM25: CARBON STEEL | FO25: LEAK | FR25: PINHOLE | FY25: NO | GC25: YES | GD25: NO | GE25: YES | GH25: YES | GK25: NO | GT25: YES | GU25: NO | HF25: 10000 | HG25: 70 | HH25: 2000 | HI25: 10000 | HJ25: 25000 | HK25: 0 | HM25: 47070 | HN25: 0 | HO25: 0 | HP25: 0 | HQ25: 0 | HR25: 8 | HS25: 1000 | HT25: SUBPART E PRESSURE TEST ß195.406(A)(3) | HV25: 36340 | HW25: BI-DIRECTIONAL | HY25: PRESSURE DID NOT EXCEED MOP | HZ25: NO | ID25: YES | IL25: NO | IS25: > 20% SMYS REGULATED TRANSMISSION | IT25: YES | IU25: YES | IV25: YES | IW25: NO | IX25: NO | IY25: YES | IZ25: YES | JA25: YES | JB25: NO | JC25: NO | JD25: NO, THE OPERATOR DID NOT FIND THAT AN INVESTIGATION OF THE CONTROLLER(S) ACTIONS OR CONTROL ROOM ISSUES WAS NECESSARY DUE TO: (PROVIDE AN EXPLANATION FOR WHY THE OPERATOR DID NOT INVESTIGATE) | JE25: A REVIEW OF THE ACCIDENT DETERMINED THAT THERE WERE NO CONTROL ROOM ACTIONS THAT CONTRIBUTED TO THE EVENT. | JR25: NO | JS25: NO | JX25: CORROSION FAILURE | JY25: INTERNAL CORROSION | JZ25: INTERNAL CORROSION | LD25: LOCALIZED PITTING | LH25: YES | LM25: YES | LP25: YES | LU25: YES | LV25: NO | LW25: YES | LX25: YES | SC25: YES | SD25: YES | SE25: YES | SG25: YES | SK25: 2024 | SL25: FREE SWIMMING | SM25: METAL LOSS | SO25: HIGH RESOLUTION | SQ25: 2019 | SR25: FREE SWIMMING | SS25: METAL LOSS | SU25: HIGH RESOLUTION | SW25: 2024 | SX25: FREE SWIMMING | SY25: HIGH RESOLUTION | TA25: 2019 | TB25: FREE SWIMMING | TC25: HIGH RESOLUTION | TQ25: 2024 | TR25: FREE SWIMMING | TS25: HIGH RESOLUTION | TU25: INSIDE ILI CUPS | TV25: 2019 | TW25: FREE SWIMMING | TX25: HIGH RESOLUTION | TZ25: INSIDE ILI CUPS | UO25: YES | UP25: 1999 | UQ25: 1252 | UR25: NO | UZ25: NO | XL25: TODD NARDOZZI | XM25: DIRECTOR - DOT COMPLIANCE | XN25: todd.nardozzi@energytransfer.com | XO25: 713-989-7126 | XQ25: 45744 | XU25: TODD NARDOZZI | XV25: 713-989-7126 | XW25: DIRECTOR - DOT COMPLIANCE | XX25: todd.nardozzi@energytransfer.com | XY25: ON 12/09/24 AT APPROXIMATELY 10:30, A LEAK WAS DISCOVERED ON THE 21003.01 10-INCH NEDERLAND TO SOUR LAKE LINE ON A LANDOWNER'S PROPERTY. THE LINE WAS ALREADY SHUTDOWN AND BLOCKED IN PER SCHEDULE. MANUAL BLOCK VALVES BETWEEN SOUR LAKE AND NEDERLAND WERE CLOSED OFF TO FURTHER ISOLATE THE SEGMENT. ONCE THE LINE WAS EXCAVATED IT WAS DISCOVERED THE LEAK WAS COMING FROM A PINHOLE. THE LINE WAS TEMPORARILY CLAMPED TO STOP THE LEAK. APPROXIMATELY 1 BARREL OF CRUDE OIL WAS RELEASED INTO THE GROUND. CLEANUP CONTRACTOR REMOVED FREE PRODUCT AND CONTAMINATED SOIL. THE FAILED PIPE WAS CUTOUT AND REPLACED. THE CAUSE OF THE LEAK IS STILL UNDER INVESTIGATION. THE FAILED SECTION HAS BEEN CUT OUT AND SENT TO 3RD PARTY LABORATORY FOR ANALYSIS. A SUPPLEMENTAL REPORT WILL BE SUBMITTED ONCE THE INVESTIGATION IS COMPLETE. SUPPLEMENTAL & FINAL: THE INVESTIGATION DETERMINED THE ACCIDENT WAS CAUSED BY INTERNAL CORROSION. THE ISOLATED INTERNAL CORROSION CONTAINED TUNNELING AND PITS-IN-PITS, CONSISTENT WITH MICROBIAL INFLUENCED CORROSION (MIC), WHICH CAUSED A PINHOLE AT THE 7 OCLOCK POSITION. TO PREVENT REOCCURRENCE, BIOCIDE INJECTION LOCATIONS, AND TREATMENT CHEMICAL AND QUANTITY ARE BEING REVIEWED FOR SUFFICIENCY.
A26: 152 | B26: 45645 | C26: 2024 | D26: 20240293 | E26: 40344 | F26: ORIGINAL FINAL | G26: 18718 | H26: SUNOCO PIPELINE L.P. | I26: 1300 MAIN STREET | J26: HOUSTON | K26: TX | L26: 77002 | M26: 45629.478 | N26: EASTERN | O26: NO | P26: 40.316053 | Q26: -76.038183 | R26: REFINED AND/OR PETROLEUM PRODUCT (NON-HVL) WHICH IS A LIQUID AT AMBIENT CONDITIONS | S26: DIESEL, FUEL OIL, KEROSENE, JET FUEL | W26: 30 | Y26: 30 | Z26: NO | AF26: 0 | AG26: NO | AM26: 0 | AN26: LOCAL OPERATING PERSONNEL, INCLUDING CONTRACTORS | AP26: OPERATOR EMPLOYEE | AQ26: 45629.478 | AR26: ONSHORE PUMP/METER STATION EQUIPMENT AND PIPING | AS26: ONSHORE | AT26: NORMAL OPERATION, INCLUDES PAUSES BETWEEN BATCHES AND DURING MAINTENANCE | AU26: NO | AV26: LINE ALREADY DOWN FOR MAINTENACE | AZ26: NO | BC26: 45629.478 | BD26: 45629.478 | BE26: 45629.693 | BF26: 1417894 | BG26: 1418050 | BH26: NO | BV26: YES | BW26: 45629.478 | BX26: YES | BY26: 45629.507 | BZ26: 45629.583 | CA26: 0 | CB26: MONTELLO PUMP STATION | CC26: 600 MANIFOLD PIPING | CD26: PA | CE26: 19608 | CF26: SPRING TOWNSHIP | CG26: BERKS | CH26: SURVEY STATION NO. | CI26: 0+00 | CJ26: NO | CK26: TOTALLY CONTAINED ON OPERATOR-CONTROLLED PROPERTY | CL26: ABOVEGROUND | CM26: TYPICAL ABOVEGROUND FACILITY PIPING OR APPURTENANCE | CP26: NO | DM26: INTERSTATE | DN26: FLANGE ASSEMBLY | FK26: UNKNOWN | FL26: UNKNOWN | FM26: CARBON STEEL | FO26: OTHER | FX26: PRODUCT RELEASED AFTER SPOOL PIECE REMOVED DURING HYDROTEST PREPARATION. | FY26: NO | GC26: YES | GD26: NO | GE26: YES | GH26: YES | GK26: NO | GT26: YES | GU26: YES | GX26: YES | GY26: YES | HB26: YES | HC26: YES | HF26: 0 | HG26: 100 | HH26: 0 | HI26: 20000 | HJ26: 45000 | HK26: 0 | HM26: 65100 | HN26: 0 | HO26: 0 | HP26: 0 | HQ26: 0 | HR26: 0 | HS26: 280 | HT26: SUBPART E PRESSURE TEST ß195.406(A)(3) | HV26: 43231 | HW26: NO | HY26: PRESSURE DID NOT EXCEED MOP | HZ26: NO | IS26: > 20% SMYS REGULATED TRANSMISSION | IT26: YES | IU26: YES | IV26: YES | IW26: NO | IX26: NO | IY26: NO | JD26: NO, THE OPERATOR DID NOT FIND THAT AN INVESTIGATION OF THE CONTROLLER(S) ACTIONS OR CONTROL ROOM ISSUES WAS NECESSARY DUE TO: (PROVIDE AN EXPLANATION FOR WHY THE OPERATOR DID NOT INVESTIGATE) | JE26: A REVIEW OF THE ACCIDENT DETERMINED THAT THERE WERE NO CONTROL ROOM ACTIONS THAT CONTRIBUTED TO THE EVENT. | JR26: NO | JS26: YES | JV26: 1 | JW26: 0 | JX26: INCORRECT OPERATION | JY26: OTHER INCORRECT OPERATION | RM26: OTHER INCORRECT OPERATION | RP26: CONTRACTOR FAILED TO DRAIN DOWN LINE COMPLETELY PRIOR TO HYRDO-TEST. | RS26: YES | RV26: OTHER MAINTENANCE | RW26: YES | RX26: YES, THEY WERE QUALIFIED FOR THE TASK(S) | XL26: TODD NARDOZZI | XM26: DIRECTOR - DOT COMPLIANCE | XN26: todd.nardozzi@energytransfer.com | XO26: 713-989-7126 | XQ26: 45645 | XU26: TODD NARDOZZI | XV26: 713-989-7126 | XW26: DIRECTOR - DOT COMPLIANCE | XX26: todd.nardozzi@energytransfer.com | XY26: ON 12/03/24 AT APPROXIMATELY 11:28, A DIESEL FUEL LEAK WAS DISCOVERED AT MONTELLO PUMP STATION DURING MAINTENANCE ACTIVITIES. WHILE READYING LINE 6 AND LINE 9 FOR HYDRO-TEST, CONTRACTORS OPENED THE FIRST FLANGE, INTRODUCING AIR INTO THE PIPE, WHICH RESULTED IN PRODUCT FLOWING OUT OF THE OPEN 10-INCH PIPE IN THE 600 MANIFOLD AREA. PRODUCT FLOW WAS REDUCED SO A 10-INCH BLIND FLANGE COULD BE INSTALLED. THE BLIND STOPPED THE FLOW AND ISOLATED THE LINE. APPROXIMATELY 30 BBLS OF DIESEL FUEL WAS RELEASED. AN ONSITE VACUUM TRUCK RESPONDED TO COLLECT FREE PRODUCT. AN OSRO WAS MOBILIZED FOR ADDITIONAL CLEAN-UP. THE INVESTIGATION DETERMINED THAT THE LEAK OCCURRED DUE TO THE LINE NOT BEING VENTED AT THE HIGH POINT. TO PREVENT REOCCURRENCE IN SIMILAR SITUATIONS, AN INSPECTOR OR COMPANY REPRESENTATIVE WILL VERIFY THE DRAINED VOLUME VS LINE FILL COMPARISON PRIOR TO COMPLETION OF THE DRAIN DOWN.
A27: 169 | B27: 45623 | C27: 2024 | D27: 20240281 | E27: 40260 | F27: ORIGINAL FINAL | G27: 32099 | H27: ENERGY TRANSFER COMPANY | I27: 1300 MAIN STREET | J27: HOUSTON | K27: TX | L27: 77002 | M27: 45596.625 | N27: CENTRAL | O27: YES | P27: 30.140718 | Q27: -94.398944 | R27: CRUDE OIL | W27: 2 | Y27: 2 | Z27: NO | AF27: 0 | AG27: NO | AM27: 0 | AN27: LOCAL OPERATING PERSONNEL, INCLUDING CONTRACTORS | AP27: OPERATOR EMPLOYEE | AQ27: 45596.625 | AR27: ONSHORE PUMP/METER STATION EQUIPMENT AND PIPING | AS27: ONSHORE | AT27: NORMAL OPERATION, INCLUDES PAUSES BETWEEN BATCHES AND DURING MAINTENANCE | AU27: YES | AW27: 45596.625 | AX27: 45597.167 | AZ27: YES | BA27: OPERATOR | BB27: 45596.668 | BC27: 45596.625 | BD27: 45596.625 | BF27: NRC NOTIFICATION NOT REQUIRED | BH27: NO | BV27: YES | BW27: 45596.628 | BX27: NO | CA27: 0 | CB27: SOUR LAKE STATION | CC27: 12-INCH STATION PIPING | CD27: TX | CE27: 77659 | CF27: SOUR LAKE | CG27: HARDIN | CH27: SURVEY STATION NO. | CI27: 0+00 | CJ27: NO | CK27: TOTALLY CONTAINED ON OPERATOR-CONTROLLED PROPERTY | CL27: UNDERGROUND | CM27: UNDER SOIL | CO27: 24 | CP27: NO | DM27: INTRASTATE | DN27: PIPE | DO27: PIPE BODY | DP27: NO | DQ27: 12 | DR27: 0.25 | DS27: 35000 | DT27: GRADE B | DU27: SEAMLESS | DW27: UNKNOWN | DX27: COLD APPLIED TAPE | DZ27: UNKNOWN | FK27: 1931 | FL27: UNKNOWN | FM27: CARBON STEEL | FO27: LEAK | FR27: PINHOLE | FY27: NO | GC27: YES | GD27: NO | GE27: YES | GH27: YES | GK27: NO | GT27: YES | GU27: NO | HF27: 0 | HG27: 0 | HH27: 11500 | HI27: 5000 | HJ27: 4000 | HK27: 0 | HM27: 20500 | HN27: 0 | HO27: 0 | HP27: 0 | HQ27: 0 | HR27: 13 | HS27: 285 | HT27: INTERNAL DESIGN PRESSURE ß195.406(A)(1) | HV27: 27395 | HW27: BI-DIRECTIONAL | HY27: PRESSURE DID NOT EXCEED MOP | HZ27: NO | IS27: > 20% SMYS REGULATED TRANSMISSION | IT27: YES | IU27: YES | IV27: YES | IW27: NO | IX27: NO | IY27: YES | IZ27: YES | JA27: YES | JB27: NO | JC27: NO | JD27: NO, THE OPERATOR DID NOT FIND THAT AN INVESTIGATION OF THE CONTROLLER(S) ACTIONS OR CONTROL ROOM ISSUES WAS NECESSARY DUE TO: (PROVIDE AN EXPLANATION FOR WHY THE OPERATOR DID NOT INVESTIGATE) | JE27: A REVIEW OF THE ACCIDENT DETERMINED THAT THERE WERE NO CONTROL ROOM ACTIONS THAT CONTRIBUTED TO THE EVENT. | JR27: NO | JS27: NO | JX27: CORROSION FAILURE | JY27: INTERNAL CORROSION | JZ27: INTERNAL CORROSION | LD27: LOCALIZED PITTING | LG27: YES | LL27: YES | LR27: YES | LU27: YES | LV27: NO | LW27: NOT APPLICABLE - NOT MAINLINE PIPE | LX27: YES | SC27: NO | UO27: NO | UR27: NO | UZ27: NO | XL27: TODD NARDOZZI | XM27: DIRECTOR - DOT COMPLIANCE | XN27: todd.nardozzi@energytransfer.com | XO27: 713-989-7126 | XQ27: 45623 | XU27: TODD NARDOZZI | XV27: 713-989-7126 | XW27: DIRECTOR - DOT COMPLIANCE | XX27: todd.nardozzi@energytransfer.com | XY27: ON 10/31/24 AT APPROXIMATELY 15:00, A MEASUREMENT TECH NOTICED A CRUDE SMELL AT THE SOUR LAKE STATION, PERFORMED AN AREA WALK THROUGH AND DISCOVERED CRUDE OIL ON THE SURFACE ABOVE THE PIPING IN THE AREA OF TANK 721. THE LINE WAS SHUT IN AND ISOLATED. THE AREA WAS EXCAVATED AND IT WAS IDENTIFIED THAT THE FAILURE OCCURRED ON A SECTION OF "DEAD LEG" PIPING. THE LEAK WAS COMING FROM A PINHOLE AT THE 6 O'CLOCK POSITION. THE SEGMENT WAS DRAINED AND TWO SKILLET BLINDS WERE INSTALLED. 2 BARRELS OF CRUDE OIL WAS RELEASED. CONTRACTORS CLEANED UP FREE PRODUCT AND REMEDIATED IMPACTED SOIL. THE CAUSE OF THE ACCIDENT WAS DETERMINED TO BE FROM INTERNAL CORROSION. TO PREVENT REOCCURRENCE, THE LINE SEGMENT WAS DE-INVENTORIED AND REMAINS ISOLATED INDEFINITELY. PIPING MODIFICATIONS TO THE MANIFOLD ARE PLANNED TO PERMANENTLY REMOVE THE DEAD LEG.
A28: 176 | B28: 45617 | C28: 2024 | D28: 20240273 | E28: 40236 | F28: ORIGINAL FINAL | G28: 39706 | H28: ENERGY TRANSFER NEDERLAND TERMINAL LLC | I28: 1300 MAIN STREET | J28: HOUSTON | K28: TX | L28: 77002 | M28: 45588.917 | N28: CENTRAL | O28: YES | P28: 30.001456 | Q28: -93.990056 | R28: CRUDE OIL | W28: 10 | Y28: 10 | Z28: NO | AF28: 0 | AG28: NO | AM28: 0 | AN28: LOCAL OPERATING PERSONNEL, INCLUDING CONTRACTORS | AP28: OPERATOR EMPLOYEE | AQ28: 45588.917 | AR28: ONSHORE BREAKOUT TANK OR STORAGE VESSEL, INCLUDING ATTACHED APPURTENANCES | AS28: ONSHORE | AT28: NORMAL OPERATION, INCLUDES PAUSES BETWEEN BATCHES AND DURING MAINTENANCE | AU28: NO | AV28: TANK ISOLATED | AZ28: NO | BC28: 45588.917 | BD28: 45588.917 | BF28: NRC NOTIFICATION NOT REQUIRED | BH28: NO | BV28: YES | BW28: 45588.924 | BX28: NO | CA28: 0 | CB28: NEDERLAND TERMINAL | CC28: TANK 1583 | CD28: TX | CE28: 77627 | CF28: NEDERLAND | CG28: JEFFERSON | CH28: SURVEY STATION NO. | CI28: 0+00 | CJ28: NO | CK28: TOTALLY CONTAINED ON OPERATOR-CONTROLLED PROPERTY | CL28: TANK, INCLUDING ATTACHED APPURTENANCES | CP28: NO | DM28: INTERSTATE | DN28: TANK/VESSEL | EW28: MIXER | EY28: ATMOSPHERIC | FD28: 58 | FE28: NO | FF28: 2016 | FH28: 2021 | FK28: UNKNOWN | FL28: UNKNOWN | FM28: CARBON STEEL | FO28: LEAK | FR28: SEAL OR PACKING | FY28: NO | GC28: YES | GD28: NO | GE28: YES | GH28: YES | GK28: NO | GT28: YES | GU28: YES | GX28: YES | GY28: YES | HF28: 0 | HG28: 0 | HH28: 13000 | HI28: 0 | HJ28: 16500 | HK28: 0 | HM28: 29500 | HN28: 0 | HO28: 0 | HP28: 0 | HQ28: 0 | HR28: 14.7 | HZ28: NO | IS28: > 20% SMYS REGULATED TRANSMISSION | IT28: YES | IU28: YES | IV28: YES | IW28: NO | IX28: NO | IY28: NO | JD28: NO, THE OPERATOR DID NOT FIND THAT AN INVESTIGATION OF THE CONTROLLER(S) ACTIONS OR CONTROL ROOM ISSUES WAS NECESSARY DUE TO: (PROVIDE AN EXPLANATION FOR WHY THE OPERATOR DID NOT INVESTIGATE) | JE28: A REVIEW OF THE ACCIDENT DETERMINED THAT THERE WERE NO CONTROL ROOM ACTIONS THAT CONTRIBUTED TO THE EVENT. | JR28: NO | JS28: NO | JX28: EQUIPMENT FAILURE | JY28: NON-THREADED CONNECTION FAILURE | QB28: NON-THREADED CONNECTION FAILURE | QS28: SEAL (NOT PUMP SEAL) OR PACKING | RK28: YES | RL28: ROUTINE WEAR | XL28: TODD NARDOZZI | XM28: DIRECTOR - DOT COMPLIANCE | XN28: todd.nardozzi@energytransfer.com | XO28: 713-989-7126 | XQ28: 45617 | XU28: TODD NARDOZZI | XV28: 713-989-7126 | XW28: DIRECTOR - DOT COMPLIANCE | XX28: todd.nardozzi@energytransfer.com | XY28: ON 10/23/2024 AT APPROXIMATELY 22:00, CRUDE OIL WAS DISCOVERED WITHIN THE DIKE CONTAINMENT OF TANK 1583. THE LEAK WAS IMMEDIATELY REPORTED, TANK WAS ISOLATED, AND LEAKED STOPPED. OPERATIONS TRANSFERRED THE OIL FROM TANK 1583 TO ANOTHER TANK. THE LEAK WAS COMING FROM A FAILED TANK MIXER SEAL. APPROXIMATELY 10 BARRELS OF CRUDE OIL WAS RELEASED WITHIN THE TANK DIKE. AN ON-SITE VACUUM TRUCK RESPONDED TO COLLECT ANY FREE PRODUCT. CONTRACTORS CLEANED UP REMAINING PRODUCT AND REMOVED CONTAMINATED SOIL. THE INVESTIGATION DETERMINED THE CAUSE OF THE LEAK WAS DUE TO A FAILURE OF THE MIXER BEARING SEAL. THE MIXER HAS BEEN LOCKED OUT SEALING THE LEAK AND TANK 1583 WAS RETURNED TO SERVICE.
A29: 177 | B29: 45617 | C29: 2024 | D29: 20240274 | E29: 40936 | F29: SUPPLEMENTAL FINAL | G29: 32099 | H29: ENERGY TRANSFER COMPANY | I29: 1300 MAIN STREET | J29: HOUSTON | K29: TX | L29: 77002 | M29: 45588.623 | N29: CENTRAL | O29: YES | P29: 34.296335 | Q29: -100.24264 | R29: CRUDE OIL | W29: 350 | Y29: 275 | Z29: NO | AF29: 0 | AG29: NO | AM29: 0 | AN29: LOCAL OPERATING PERSONNEL, INCLUDING CONTRACTORS | AP29: OPERATOR EMPLOYEE | AQ29: 45588.623 | AR29: ONSHORE PIPELINE, INCLUDING VALVE SITES | AS29: ONSHORE | AT29: NORMAL OPERATION, INCLUDES PAUSES BETWEEN BATCHES AND DURING MAINTENANCE | AU29: YES | AW29: 45588.625 | AX29: 45591.667 | AZ29: YES | BA29: OPERATOR | BB29: 45588.779 | BC29: 45588.635 | BD29: 45588.766 | BE29: 45589.645 | BF29: 1414672 | BG29: 1414818 | BH29: NO | BN29: VALVE CLOSURE | BP29: 45588.649 | BQ29: MANUAL | BR29: VALVE CLOSURE | BT29: 45588.646 | BU29: REMOTELY CONTROLLED | BV29: YES | BW29: 45588.625 | BX29: NO | CA29: 0 | CB29: TEXAS PLAINS PIPELINE | CC29: 23002.04 - 10-INCH TRUSCOTT TO CHILDRESS | CD29: TX | CE29: 79248 | CF29: Not Within a Municipality | CG29: COTTLE | CH29: SURVEY STATION NO. | CI29: 320+76 | CJ29: NO | CK29: PIPELINE RIGHT-OF-WAY | CL29: UNDERGROUND | CM29: UNDER SOIL | CO29: 66 | CP29: NO | DM29: INTRASTATE | DN29: PIPE | DO29: PIPE BODY | DP29: NO | DQ29: 10 | DR29: 0.365 | DS29: 30000 | DT29: UNKNOWN | DU29: LAP WELDED | DW29: UNKNOWN | DX29: COAL TAR | DZ29: YES | FK29: 1927 | FL29: UNKNOWN | FM29: CARBON STEEL | FO29: LEAK | FR29: PINHOLE | FY29: NO | GC29: YES | GD29: NO | GE29: YES | GH29: YES | GK29: NO | GT29: NO | GU29: NO | HF29: 23500 | HG29: 6225 | HH29: 200000 | HI29: 25000 | HJ29: 400000 | HK29: 0 | HM29: 654725 | HN29: 0 | HO29: 0 | HP29: 0 | HQ29: 0 | HR29: 180 | HS29: 705 | HT29: SUBPART E PRESSURE TEST ß195.406(A)(3) | HV29: 27848 | HW29: NO | HY29: PRESSURE DID NOT EXCEED MOP | HZ29: NO | IC29: 31680 | ID29: YES | IL29: NO | IS29: > 20% SMYS REGULATED TRANSMISSION | IT29: YES | IU29: YES | IV29: YES | IW29: NO | IX29: NO | IY29: YES | IZ29: YES | JA29: YES | JB29: NO | JC29: NO | JD29: NO, THE OPERATOR DID NOT FIND THAT AN INVESTIGATION OF THE CONTROLLER(S) ACTIONS OR CONTROL ROOM ISSUES WAS NECESSARY DUE TO: (PROVIDE AN EXPLANATION FOR WHY THE OPERATOR DID NOT INVESTIGATE) | JE29: A REVIEW OF THE ACCIDENT DETERMINED THAT THERE WERE NO CONTROL ROOM ACTIONS THAT CONTRIBUTED TO THE EVENT. | JR29: NO | JS29: NO | JX29: CORROSION FAILURE | JY29: EXTERNAL CORROSION | JZ29: EXTERNAL CORROSION | KA29: LOCALIZED PITTING | KC29: YES | KL29: YES | KN29: YES | KO29: NDE METHODS UT-0, WCAMT, AND CREAFORM | KP29: YES | KQ29: YES | KR29: 1985 | KS29: YES | KT29: YES | KU29: YES | KV29: YES | KW29: YES | KX29: 2024 | KY29: 2020 | KZ29: 2022 | LA29: ACI | LC29: YES | SC29: YES | SD29: YES | SG29: YES | SK29: 2022 | SL29: FREE SWIMMING | SM29: METAL LOSS | SO29: HIGH RESOLUTION | SQ29: 2019 | SR29: FREE SWIMMING | SS29: METAL LOSS | SU29: HIGH RESOLUTION | TQ29: 2022 | TR29: FREE SWIMMING | TS29: STANDARD RESOLUTION | TU29: NO CUPS | TV29: 2019 | TW29: FREE SWIMMING | TX29: STANDARD RESOLUTION | TZ29: NO CUPS | UO29: YES | UP29: 1976 | UQ29: 870 | UR29: NO | UZ29: NO | XL29: TODD NARDOZZI | XM29: DIRECTOR - DOT COMPLIANCE | XN29: todd.nardozzi@energytransfer.com | XO29: 713-989-7126 | XQ29: 45800 | XU29: TODD NARDOZZI | XV29: 713-989-7126 | XW29: DIRECTOR - DOT COMPLIANCE | XX29: todd.nardozzi@energytransfer.com | XY29: ON 10/23/24 AT 14:57, OPERATIONS WAS DRIVING THE ROW AND NOTICED CRUDE OIL ON THE GROUND NEAR 23002.04 - TRUSCOTT TO CHILDRESS 10-INCH LINE. THE CONTROL CENTER WAS NOTIFIED AND THE LINE WAS SHUTDOWN AND SEGMENT ISOLATED. ONCE THE LINE WAS EXCAVATED IT WAS DISCOVERED THE LEAK WAS COMING FROM A PINHOLE. THE LINE WAS TEMPORARILY CLAMPED TO STOP THE LEAK. APPROXIMATELY 248 BARRELS OF CRUDE OIL WAS RELEASED INTO THE GROUND. CLEAN-UP CONTRACTORS REMOVED PRODUCT AND CONTAMINATED SOIL. THE INVESTIGATION DETERMINED THE LEAK WAS CAUSED BY EXTERNAL CORROSION. DUE TO THE EXTENT OF THE CORROSION, THE SECTION WAS CUTOUT AND REPLACED BEFORE RETURNING TO SERVICE ON 10/26/24 AT 16:00.
A30: 186 | B30: 45610 | C30: 2024 | D30: 20240267 | E30: 40221 | F30: ORIGINAL FINAL | G30: 32099 | H30: ENERGY TRANSFER COMPANY | I30: 1300 MAIN STREET | J30: HOUSTON | K30: TX | L30: 77002 | M30: 45580.726 | N30: CENTRAL | O30: YES | P30: 30.080835 | Q30: -95.072743 | R30: CRUDE OIL | W30: 472 | Y30: 472 | Z30: NO | AF30: 0 | AG30: NO | AM30: 0 | AN30: OTHER | AO30: SECOND PARTY ROW MOWER | AQ30: 45580.726 | AR30: ONSHORE PIPELINE, INCLUDING VALVE SITES | AS30: ONSHORE | AT30: NORMAL OPERATION, INCLUDES PAUSES BETWEEN BATCHES AND DURING MAINTENANCE | AU30: YES | AW30: 45580.733 | AX30: 45581.647 | AZ30: NO | BC30: 45580.731 | BD30: 45580.726 | BE30: 45580.806 | BF30: 1413821 | BG30: 141400 | BH30: NO | BN30: VALVE CLOSURE | BP30: 45580.733 | BQ30: REMOTELY CONTROLLED | BR30: VALVE CLOSURE | BT30: 45580.733 | BU30: REMOTELY CONTROLLED | BV30: YES | BW30: 45580.727 | BX30: YES | BY30: 45580.753 | BZ30: 45580.772 | CA30: 0 | CB30: KILGORE 10-INCH | CC30: 21004.04 - 10-INCH GOODRICH TO HOUSTON TERMINAL | CD30: TX | CE30: 77346 | CF30: HUFFMAN | CG30: HARRIS | CH30: SURVEY STATION NO. | CI30: 8721+80 | CJ30: NO | CK30: PIPELINE RIGHT-OF-WAY | CL30: UNDERGROUND | CM30: EXPOSED DUE TO LOSS OF COVER | CO30: UNKNOWN | CP30: NO | DM30: INTERSTATE | DN30: PIPE | DO30: PIPE BODY | DP30: NO | DQ30: 10 | DR30: 0.25 | DS30: 35000 | DT30: GRADE B | DU30: SEAMLESS | DW30: JONES AND LAUGHLIN STEEL COMPANY | DX30: OTHER | DY30: ARMOR PLATE | DZ30: YES | FK30: 1931 | FL30: UNKNOWN | FM30: CARBON STEEL | FO30: MECHANICAL PUNCTURE | FP30: 12 | FQ30: 2.4 | FY30: NO | GC30: YES | GD30: NO | GE30: YES | GH30: YES | GK30: NO | GT30: NO | GU30: YES | HB30: YES | HC30: YES | HF30: 30836 | HG30: 1650 | HH30: 100000 | HI30: 450000 | HJ30: 120000 | HK30: 0 | HM30: 702486 | HN30: 0 | HO30: 0 | HP30: 0 | HQ30: 0 | HR30: 119 | HS30: 800 | HT30: SUBPART E PRESSURE TEST ß195.406(A)(3) | HV30: 37381 | HW30: NO | HY30: PRESSURE DID NOT EXCEED MOP | HZ30: NO | IC30: 173949 | ID30: YES | IL30: NO | IS30: > 20% SMYS REGULATED TRANSMISSION | IT30: YES | IU30: YES | IV30: YES | IW30: YES | IX30: YES | IY30: YES | IZ30: YES | JA30: YES | JB30: NO | JC30: NO | JD30: NO, THE OPERATOR DID NOT FIND THAT AN INVESTIGATION OF THE CONTROLLER(S) ACTIONS OR CONTROL ROOM ISSUES WAS NECESSARY DUE TO: (PROVIDE AN EXPLANATION FOR WHY THE OPERATOR DID NOT INVESTIGATE) | JE30: A REVIEW OF THE ACCIDENT DETERMINED THAT THERE WERE NO CONTROL ROOM ACTIONS THAT CONTRIBUTED TO THE EVENT. | JR30: NO | JS30: NO | JX30: OTHER OUTSIDE FORCE DAMAGE | JY30: DAMAGE BY CAR, TRUCK, OR OTHER MOTORIZED VEHICLE/EQUIPMENT NOT ENGAGED IN EXCAVATION | NY30: DAMAGE BY CAR, TRUCK, OR OTHER MOTORIZED VEHICLE/EQUIPMENT NOT ENGAGED IN EXCAVATION | NZ30: OPERATOR'S CONTRACTOR | OJ30: NO | OP30: YES | OQ30: 5 | OS30: MOTORCYCLE/ATV | OT30: OFF-ROAD | OU30: 0 | OV30: NO | XL30: TODD NARDOZZI | XM30: DIRECTOR - DOT COMPLIANCE | XN30: todd.nardozzi@energytransfer.com | XO30: 713-989-7126 | XQ30: 45610 | XU30: TODD NARDOZZI | XV30: 713-989-7126 | XW30: DIRECTOR - DOT COMPLIANCE | XX30: todd.nardozzi@energytransfer.com | XY30: ON 10/15/24 AT APPROXIMATELY 17:25, A 2ND PARTY ROW MOWING CONTRACTOR STRUCK THE 21004.04 - GOODRICH TO HOUSTON TERMINAL 10-INCH LINE. THE CONTROL CENTER IMMEDIATELY SHUT DOWN THE ORIGIN PUMP AND REMOTE OPERATED VALVES, WHILE FIELD PERSONNEL CLOSED THE UPSTREAM AND DOWNSTREAM MANUAL VALVES. FIELD PERSONNEL STARTED DIGGING TRENCHES, BUILDING DAMS AND PUTTING ABSORBENT BOOM OUT TO SLOW DOWN THE RELEASE UNTIL MORE RESOURCES ARRIVED. APPROXIMATELY 472 BARRELS OF CRUDE OIL WAS RELEASED. COMPANY PERSONNEL AND OSRO WERE MOBILIZED TO CONTAIN AND RECOVER RELEASED PRODUCT. ON 10/16/14 AT APPROXIMATELY 14:15, A PLIDCO CLAMP WAS INSTALLED AND AT 15:32, THE LINE WAS RESTARTED.
A31: 187 | B31: 45610 | C31: 2024 | D31: 20240268 | E31: 40222 | F31: ORIGINAL FINAL | G31: 32099 | H31: ENERGY TRANSFER COMPANY | I31: 1300 MAIN STREET | J31: HOUSTON | K31: TX | L31: 77002 | M31: 45580.128 | N31: CENTRAL | O31: YES | P31: 30.14057 | Q31: -94.396295 | R31: CRUDE OIL | W31: 2 | Y31: 2 | Z31: NO | AF31: 0 | AG31: NO | AM31: 0 | AN31: LOCAL OPERATING PERSONNEL, INCLUDING CONTRACTORS | AP31: OPERATOR EMPLOYEE | AQ31: 45580.128 | AR31: ONSHORE PUMP/METER STATION EQUIPMENT AND PIPING | AS31: ONSHORE | AT31: NORMAL OPERATION, INCLUDES PAUSES BETWEEN BATCHES AND DURING MAINTENANCE | AU31: YES | AW31: 45580.167 | AX31: 45580.699 | AZ31: YES | BA31: OPERATOR | BB31: 45580.289 | BC31: 45580.128 | BD31: 45580.349 | BF31: NRC NOTIFICATION NOT REQUIRED | BH31: NO | BV31: YES | BW31: 45580.137 | BX31: NO | CA31: 0 | CB31: SOUR LAKE STATION | CC31: 21003.02 - 10-INCH SOUR LAKE TO WARREN | CD31: TX | CE31: 77659 | CF31: SOUR LAKE | CG31: HARDIN | CH31: SURVEY STATION NO. | CI31: 0+00 | CJ31: NO | CK31: TOTALLY CONTAINED ON OPERATOR-CONTROLLED PROPERTY | CL31: UNDERGROUND | CM31: UNDER SOIL | CO31: 60 | CP31: NO | DM31: INTRASTATE | DN31: PIPE | DO31: PIPE BODY | DP31: NO | DQ31: 10 | DR31: 0.365 | DS31: 35000 | DT31: GRADE B | DU31: SEAMLESS | DW31: UNKNOWN | DX31: COAL TAR | DZ31: NO | FK31: 1931 | FL31: UNKNOWN | FM31: CARBON STEEL | FO31: LEAK | FR31: PINHOLE | FY31: NO | GC31: YES | GD31: NO | GE31: YES | GH31: YES | GK31: NO | GT31: NO | GU31: NO | HF31: 0 | HG31: 27 | HH31: 7700 | HI31: 3000 | HJ31: 0 | HK31: 0 | HM31: 10727 | HN31: 0 | HO31: 0 | HP31: 0 | HQ31: 0 | HR31: 173 | HS31: 1000 | HT31: INTERNAL DESIGN PRESSURE ß195.406(A)(1) | HV31: 45041 | HW31: BI-DIRECTIONAL | HY31: PRESSURE DID NOT EXCEED MOP | HZ31: NO | IS31: > 20% SMYS REGULATED TRANSMISSION | IT31: YES | IU31: YES | IV31: YES | IW31: YES | IX31: YES | IY31: YES | IZ31: YES | JA31: YES | JB31: NO | JC31: YES | JD31: NO, THE OPERATOR DID NOT FIND THAT AN INVESTIGATION OF THE CONTROLLER(S) ACTIONS OR CONTROL ROOM ISSUES WAS NECESSARY DUE TO: (PROVIDE AN EXPLANATION FOR WHY THE OPERATOR DID NOT INVESTIGATE) | JE31: A REVIEW OF THE ACCIDENT DETERMINED THAT THERE WERE NO CONTROL ROOM ACTIONS THAT CONTRIBUTED TO THE EVENT. | JR31: NO | JS31: NO | JX31: CORROSION FAILURE | JY31: INTERNAL CORROSION | JZ31: INTERNAL CORROSION | LD31: LOCALIZED PITTING | LG31: YES | LL31: YES | LP31: YES | LU31: YES | LV31: NO | LW31: YES | LX31: YES | SC31: YES | SD31: YES | SG31: YES | SK31: 2021 | SL31: FREE SWIMMING | SM31: METAL LOSS | SO31: HIGH RESOLUTION | SQ31: 2016 | SR31: FREE SWIMMING | SS31: METAL LOSS | SU31: HIGH RESOLUTION | TQ31: 2021 | TR31: FREE SWIMMING | TS31: HIGH RESOLUTION | TU31: INSIDE ILI CUPS | TV31: 2016 | TW31: FREE SWIMMING | TX31: HIGH RESOLUTION | TZ31: INSIDE ILI CUPS | UO31: YES | UP31: 1999 | UQ31: 1094 | UR31: NO | UZ31: NO | XL31: TODD NARDOZZI | XM31: DIRECTOR - DOT COMPLIANCE | XN31: todd.nardozzi@energytransfer.com | XO31: 713-989-7126 | XQ31: 45610 | XU31: TODD NARDOZZI | XV31: 713-989-7126 | XW31: DIRECTOR - DOT COMPLIANCE | XX31: todd.nardozzi@energytransfer.com | XY31: ON 10/15/2024 AT APPROXIMATELY 03:05, A PIPELINE TECH FOUND A CRUDE OIL LEAK AT SOUR LAKE STATION NEAR THE EAST TEXAS 10-INCH SCRAPER TRAP. THE LINE WAS SHUT DOWN AND THE SEGMENT ISOLATED. THE AREA WAS EXCAVATED, AND THE LEAK WAS IDENTIFIED COMING FROM A PIN HOLE AT THE 6 O'CLOCK POSITION ON 21003.02 10-INCH SOUR LAKE TO WARREN LINE. APPROXIMATELY 2 BARRELS OF CRUDE OIL WAS RELEASED INTO THE GROUND. CLEANUP CONTRACTOR REMOVED FREE PRODUCT AND CONTAMINATED SOIL. THE LINE WAS REPAIRED WITH A CLAMP, PRESSURE TESTED AND RESTARTED. PLANNING TO ELIMINATE THE FAILED PIPE SEGMENT TO PREVENT REOCCURRENCE.
A32: 189 | B32: 45594 | C32: 2024 | D32: 20240259 | E32: 40280 | F32: SUPPLEMENTAL FINAL | G32: 12470 | H32: MID - VALLEY PIPELINE CO | I32: 1300 MAIN STREET | J32: HOUSTON | K32: TX | L32: 77002 | M32: 45569.75 | N32: EASTERN | O32: YES | P32: 40.70502 | Q32: -84.12333 | R32: CRUDE OIL | W32: 0.1 | Y32: 0.1 | Z32: NO | AF32: 0 | AG32: NO | AM32: 0 | AN32: LOCAL OPERATING PERSONNEL, INCLUDING CONTRACTORS | AP32: CONTRACTOR WORKING FOR THE OPERATOR | AQ32: 45569.75 | AR32: ONSHORE TERMINAL/TANK FARM EQUIPMENT AND PIPING | AS32: ONSHORE | AT32: NORMAL OPERATION, INCLUDES PAUSES BETWEEN BATCHES AND DURING MAINTENANCE | AU32: NO | AV32: ALREADY SHUTDOWN | AZ32: NO | BC32: 45569.75 | BD32: 45569.75 | BE32: 45569.843 | BF32: 1412849 | BG32: 1412985 | BH32: YES | BI32: 45569.75 | BJ32: ALLOWED TO BURN OUT | BL32: 0.1 | BM32: NO | BV32: YES | BW32: 45569.76 | BX32: NO | CA32: 0 | CB32: LIMA STATION | CC32: 28008 - 20-INCH ASHLAND SPUR LINE | CD32: OH | CE32: 45804 | CF32: Not Within a Municipality | CG32: ALLEN | CH32: SURVEY STATION NO. | CI32: 0+00 | CJ32: NO | CK32: TOTALLY CONTAINED ON OPERATOR-CONTROLLED PROPERTY | CL32: ABOVEGROUND | CM32: TYPICAL ABOVEGROUND FACILITY PIPING OR APPURTENANCE | CP32: NO | DM32: INTERSTATE | DN32: OTHER | FJ32: ISOLATION MUD PLUG | FK32: 2024 | FL32: UNKNOWN | FM32: MATERIAL OTHER THAN CARBON STEEL | FN32: BENTONITE MUD PLUG | FO32: OTHER | FX32: FLASH FIRE DUE TO HYDROCARBON VAPORS PASSING BY ISOLATION MUD PLUG | FY32: NO | GC32: NO | GD32: NO | GE32: NO | GK32: NO | GT32: YES | GU32: YES | GX32: YES | GY32: YES | HF32: 0 | HG32: 1 | HH32: 0 | HI32: 1000 | HJ32: 0 | HK32: 0 | HM32: 1001 | HN32: 0 | HO32: 0 | HP32: 0 | HQ32: 0 | HR32: 0 | HS32: 275 | HT32: COMPONENT DESIGN PRESSURE ß195.406(A)(2) | HV32: 31365 | HW32: NO | HY32: PRESSURE DID NOT EXCEED MOP | HZ32: NO | IS32: > 20% SMYS REGULATED TRANSMISSION | IT32: YES | IU32: YES | IV32: YES | IW32: NO | IX32: NO | IY32: YES | IZ32: YES | JA32: YES | JB32: NO | JC32: NO | JD32: NO, THE OPERATOR DID NOT FIND THAT AN INVESTIGATION OF THE CONTROLLER(S) ACTIONS OR CONTROL ROOM ISSUES WAS NECESSARY DUE TO: (PROVIDE AN EXPLANATION FOR WHY THE OPERATOR DID NOT INVESTIGATE) | JE32: A REVIEW OF THE ACCIDENT DETERMINED THAT THERE WERE NO CONTROL ROOM ACTIONS THAT CONTRIBUTED TO THE EVENT. | JR32: NO | JS32: YES | JV32: 5 | JW32: 0 | JX32: INCORRECT OPERATION | JY32: EQUIPMENT NOT INSTALLED PROPERLY | RM32: EQUIPMENT NOT INSTALLED PROPERLY | RS32: YES | RV32: OTHER MAINTENANCE | RW32: YES | RX32: YES, THEY WERE QUALIFIED FOR THE TASK(S) | XL32: TODD NARDOZZI | XM32: DIRECTOR - DOT COMPLIANCE | XN32: todd.nardozzi@energytransfer.com | XO32: 713-989-7126 | XQ32: 45630 | XU32: TODD NARDOZZI | XV32: 713-989-7126 | XW32: DIRECTOR - DOT COMPLIANCE | XX32: todd.nardozzi@energytransfer.com | XY32: ON 10/04/24 AT APPROXIMATELY 18:00, A SMALL FLASH FIRE OCCURRED AT LIMA MVPL TERMINAL WHILE WELDING TO INSTALL A FABRICATED ASSEMBLY IN ORDER TO AFFECT A PRESSURE TEST THE 20-INCH ASHLAND SPUR LINE. TACK WELDS WERE COMPLETED ON THE ASSEMBLY AND AS CONTRACT CREW WAS BEGINNING THE WELD ROOT PASS A SMALL FLASH OCCURRED DUE TO VAPORS PASSING MUD PLUG. LINE IS NON-PIGGABLE AND DEPENDENT ON DRAIN UP TO EVACUATE LINE. OPERATIONS HELD A SAFETY STAND DOWN AFTER THE FLASHFIRE. COLD CUT TACK WELDS TO REMOVE FABRICATED ASSEMBLY FOR INSPECTION AND ALSO, INSPECTED THE 20-INCH SPUR LINE. AFTER SATISFACTORY INSPECTION, PROCEEDED WITH INSTALLATION OF FABRICATED ASSEMBLY AND PRESSURE TEST. THE INVESTIGATION DETERMINED THAT THE MUD PLUG FAILED LIKELY DUE TO BEING INSTALLED TOO FAR IN ADVANCE OF THE WELDING ACTIVITIES WHICH MAY HAVE ALLOWED IT TO DRY TO AN EXTENT THAT THE SEALING CAPABILITIES WERE COMPROMISED AND THE PLUG WAS MADE WITH INSUFFICIENT THICKNESS FOR THE DIAMETER OF PIPE. THE CONTRACTORS QUALIFICATIONS WERE REMOVED AND INVOLVED INDIVIDUALS ARE BEING RETRAINED.
A33: 192 | B33: 45597 | C33: 2024 | D33: 20240261 | E33: 40267 | F33: SUPPLEMENTAL FINAL | G33: 31454 | H33: NUSTAR LOGISTICS, L.P. | I33: 8111 WESTCHESTER DRIVE | J33: DALLAS | K33: TX | L33: 75225 | M33: 45568.406 | N33: CENTRAL | O33: YES | P33: 28.63158 | Q33: -98.79009 | R33: CRUDE OIL | W33: 1.78 | Y33: 0.89 | Z33: NO | AF33: 0 | AG33: NO | AM33: 0 | AN33: LOCAL OPERATING PERSONNEL, INCLUDING CONTRACTORS | AP33: OPERATOR EMPLOYEE | AQ33: 45568.406 | AR33: ONSHORE TERMINAL/TANK FARM EQUIPMENT AND PIPING | AS33: ONSHORE | AT33: NORMAL OPERATION, INCLUDES PAUSES BETWEEN BATCHES AND DURING MAINTENANCE | AU33: YES | AW33: 45568.424 | AX33: 45568.776 | AZ33: NO | BC33: 45568.424 | BD33: 45568.406 | BF33: NRC NOTIFICATION NOT REQUIRED | BH33: NO | BV33: YES | BW33: 45568.406 | BX33: NO | CA33: 0 | CB33: 70P CHOKE CANYON PIPELINE SYSTEM | CC33: HWY 97 TERMINAL | CD33: TX | CE33: 78072 | CF33: Not Within a Municipality | CG33: MCMULLEN | CH33: SURVEY STATION NO. | CI33: 0+00 | CJ33: NO | CK33: TOTALLY CONTAINED ON OPERATOR-CONTROLLED PROPERTY | CL33: ABOVEGROUND | CM33: TYPICAL ABOVEGROUND FACILITY PIPING OR APPURTENANCE | CP33: NO | DM33: INTRASTATE | DN33: FILTER/STRAINER/SEPARATOR | FK33: UNKNOWN | FL33: UNKNOWN | FM33: CARBON STEEL | FO33: LEAK | FR33: PINHOLE | FY33: NO | GC33: YES | GD33: NO | GE33: YES | GH33: YES | GK33: NO | GT33: NO | GU33: NO | HF33: 0 | HG33: 66 | HH33: 12217 | HI33: 2538 | HJ33: 1500 | HK33: 0 | HM33: 16321 | HN33: 0 | HO33: 0 | HP33: 0 | HQ33: 0 | HR33: 115 | HS33: 285 | HT33: COMPONENT DESIGN PRESSURE ß195.406(A)(2) | HV33: 41709 | HW33: NO | HY33: PRESSURE DID NOT EXCEED MOP | HZ33: NO | IS33: > 20% SMYS REGULATED TRANSMISSION | IT33: YES | IU33: YES | IV33: YES | IW33: NO | IX33: NO | IY33: YES | IZ33: YES | JA33: YES | JB33: NO | JC33: NO | JD33: NO, THE OPERATOR DID NOT FIND THAT AN INVESTIGATION OF THE CONTROLLER(S) ACTIONS OR CONTROL ROOM ISSUES WAS NECESSARY DUE TO: (PROVIDE AN EXPLANATION FOR WHY THE OPERATOR DID NOT INVESTIGATE) | JE33: NEITHER CONTROLLER NOR CONTROL ROOM ISSUES CONTRIBUTED TO THE ACCIDENT. | JR33: NO | JS33: NO | JX33: CORROSION FAILURE | JY33: INTERNAL CORROSION | JZ33: INTERNAL CORROSION | LD33: LOCALIZED PITTING | LH33: YES | LL33: YES | LP33: YES | LU33: YES | LV33: NO | LW33: NOT APPLICABLE - NOT MAINLINE PIPE | LX33: NOT APPLICABLE - NOT MAINLINE PIPE | XL33: RUSSELL PESEK | XM33: SUPERVISOR PIPELINE SAFETY | XN33: russell.pesek@sunoco.com | XO33: 361-249-9417 | XP33: 210-918-7117 | XQ33: 45628 | XU33: WES GORE | XV33: 361-249-9402 | XW33: GENERAL MANAGER | XX33: wes.gore@sunoco.com | XY33: WHILE PERFORMING A ROUTINE MAINTENANCE INSPECTION, COMPANY OPERATIONS PERSONNEL DISCOVERED A CRUDE OIL LEAK INSIDE NUSTAR'S HWY 97 TERMINAL TANK FARM. THE LEAK ORIGINATED AT THE 6 O'CLOCK POSITION OF A STRAINER/FILTER VESSEL LOCATED UPSTREAM OF BOOSTER PUMP 404 AND WITHIN TANK 403'S CONTAINMENT. NUSTAR'S 70P CHOKE CANYON PIPELINE SYSTEM WAS SHUT DOWN, AND BOTH SUCTION AND DISCHARGE VALVES WERE USED TO ISOLATE THE BOOSTER PUMP STATION. UPDATE - THE LEAK OCCURRED ON THE BOTTOM HEAD OF THE STRAINER AT A THROUGH-WALL INTERNAL CORROSION PIT. THE CAUSE OF THE LEAK IS INTERNAL CORROSION OF THE COMPONENT SURFACE DUE TO MICROBIOLOGICALLY INFLUENCED CORROSION.
A34: 203 | B34: 45580 | C34: 2024 | D34: 20240245 | E34: 40111 | F34: ORIGINAL | G34: 32099 | H34: ENERGY TRANSFER COMPANY | I34: 1300 MAIN STREET | J34: HOUSTON | K34: TX | L34: 77002 | M34: 45551.422 | N34: CENTRAL | O34: YES | P34: 29.663823 | Q34: -95.10192 | R34: HVL OR OTHER FLAMMABLE OR TOXIC FLUID WHICH IS A GAS AT AMBIENT CONDITIONS | S34: LPG (LIQUEFIED PETROLEUM GAS) / NGL (NATURAL GAS LIQUID) | W34: 38793 | X34: 398 | Y34: 0 | Z34: YES | AA34: 0 | AB34: 0 | AC34: 0 | AD34: 0 | AE34: 1 | AF34: 1 | AG34: NO | AM34: 0 | AN34: CPM LEAK DETECTION SYSTEM | AQ34: 45551.422 | AR34: ONSHORE PIPELINE, INCLUDING VALVE SITES | AS34: ONSHORE | AT34: NORMAL OPERATION, INCLUDES PAUSES BETWEEN BATCHES AND DURING MAINTENANCE | AU34: YES | AW34: 45551.424 | AX34: 45557.078 | AZ34: YES | BA34: OPERATOR | BB34: 45551.446 | BC34: 45551.446 | BD34: 45551.453 | BE34: 45551.479 | BF34: 1410978 | BG34: 1411188 | BH34: YES | BI34: 45551.422 | BJ34: ALLOWED TO BURN OUT | BL34: 38793 | BM34: YES | BN34: VALVE CLOSURE | BP34: 45551.473 | BQ34: REMOTELY CONTROLLED | BR34: VALVE CLOSURE | BT34: 45551.473 | BU34: REMOTELY CONTROLLED | CA34: 1500 | CB34: S512.03 JUSTICE 20_20IN WOLFE AIR PARK TO HOUSTON | CC34: JUSTICE 20IN JACKSON TO HOUSTON | CD34: TX | CE34: 77571 | CF34: LAPORTE | CG34: HARRIS | CH34: SURVEY STATION NO. | CI34: 5555+71 | CJ34: NO | CK34: PIPELINE RIGHT-OF-WAY | CL34: ABOVEGROUND | CM34: TYPICAL ABOVEGROUND FACILITY PIPING OR APPURTENANCE | CP34: NO | DM34: INTRASTATE | DN34: PIPE | DO34: PIPE BODY | DP34: NO | DQ34: 3.5 | DR34: 0.3 | DS34: 35000 | DT34: API 5L | DU34: ERW - HIGH FREQUENCY | DW34: UNITED STATES STEEL | DX34: PAINT | DZ34: YES | FK34: 2012 | FL34: 2012 | FM34: CARBON STEEL | FO34: OTHER | FX34: A THIRD-PARTY VEHICLE CRASHED INTO A 3' BLOWDOWN ON THE JUSTICE 20' PIPELINE NEAR SPENCER HWY, RESULTING IN THE RUPTURE OF THE LINE AND THE FATALITY OF THE DRIVER. DETAILS OF THIS THIRD-PARTY CRASH ARE UNDER CRIMINAL INVESTIGATION. | FY34: NO | GC34: NO | GD34: NO | GE34: NO | GK34: NO | GT34: YES | GU34: YES | GV34: YES | GW34: YES | GX34: YES | GY34: YES | GZ34: YES | HA34: YES | HB34: YES | HC34: YES | HD34: YES | HE34: YES | HF34: 850000 | HG34: 802782 | HH34: 1322185 | HI34: 301795 | HJ34: 0 | HK34: 0 | HM34: 3276762 | HN34: 0 | HO34: 0 | HP34: 1465 | HQ34: 30 | HR34: 893 | HS34: 1440 | HT34: SUBPART E PRESSURE TEST ß195.406(A)(3) | HV34: 41082 | HW34: NO | HY34: PRESSURE DID NOT EXCEED MOP | HZ34: NO | IC34: 76273 | ID34: YES | IL34: NO | IS34: > 20% SMYS REGULATED TRANSMISSION | IT34: YES | IU34: YES | IV34: YES | IW34: YES | IX34: NO | IY34: YES | IZ34: YES | JA34: YES | JB34: YES | JC34: NO | JD34: NO, THE OPERATOR DID NOT FIND THAT AN INVESTIGATION OF THE CONTROLLER(S) ACTIONS OR CONTROL ROOM ISSUES WAS NECESSARY DUE TO: (PROVIDE AN EXPLANATION FOR WHY THE OPERATOR DID NOT INVESTIGATE) | JE34: A THIRD-PARTY VEHICLE CRASHED INTO A 3' BLOWDOWN ON THE JUSTICE 20' PIPELINE NEAR SPENCER HWY, RESULTING IN THE RUPTURE OF THE LINE AND THE FATALITY OF THE DRIVER. DETAILS OF THIS THIRD-PARTY CRASH ARE UNDER CRIMINAL INVESTIGATION. | JR34: YES | JS34: NO | JT34: 1 | JU34: 0 | JX34: OTHER OUTSIDE FORCE DAMAGE | JY34: DAMAGE BY CAR, TRUCK, OR OTHER MOTORIZED VEHICLE/EQUIPMENT NOT ENGAGED IN EXCAVATION | NY34: DAMAGE BY CAR, TRUCK, OR OTHER MOTORIZED VEHICLE/EQUIPMENT NOT ENGAGED IN EXCAVATION | NZ34: THIRD PARTY | OJ34: UNKNOWN | OP34: UNKNOWN | OR34: YES | OS34: PASSENGER CAR | OT34: PARKING LOT | OU34: 492 | OV34: YES | OX34: YES | XL34: JOSEPH STOVER | XN34: joseph.stover@energytransfer.com | XO34: 832-324-1027 | XQ34: 45580 | XU34: JUSTIN DAVIDSON | XV34: 713-989-5231 | XW34: MANAGER - DOT COMPLIANCE | XX34: justin.davidson@energytransfer.com | XY34: ON 09/16/2024 AT 10:08AM, THE ENERGY TRANSFER (ET) CONTROL ROOM RECEIVED A LEAK DETECTION RUPTURE ALARM. THEY ACKNOWLEDGED THE ALARM AND THEN CALLED THE JACKSON PLANT TO PREPARE FOR A SHUTDOWN OF THE S512.03 JUSTICE 20_20IN WOLFE AIR PARK TO HOUSTON LINE AT 10:14AM. THE CONTROL ROOM MANAGER THEN CALLED OPERATIONS TO NOTIFY THEM OF A SUSPECTED ISSUE NEAR SPENCER HWY. OPERATIONS THEN DISPATCHED PERSONNEL AND ARRIVED ON SITE AT 10:42 AM WHERE FIRE AND EMERGENCY RESPONDERS WERE ALREADY ON THE SCENE. ET PERSONNEL CONFIRMED DISCOVERY AT 10:52 AM. THE CONTROL ROOM CONTINUED PREPARING FOR A SHUTDOWN AND RECEIVED CONFIRMATION AT 11:21 AM THAT THE MLV UPSTREAM AND DOWNSTREAM WERE CLOSED AND THAT THE LINE WAS ISOLATED. STOPPLE FITTINGS WERE THEN INSTALLED TO REDUCE BLOWDOWN VOLUME. ET AND EMERGENCY RESPONDERS MONITORED THE FIRE ONSITE UNTIL 6:37PM ON 09/19/2024 WHEN THE FIRE WAS DEPLETED. ET THEN BEGAN REMEDIATING THE DAMAGE AND THE LINE WAS PUT BACK INTO SERVICE ON 1:52 AM ON 9/22/2024. THE INVESTIGATION IS STILL ONGOING AND WAITING ON THE DEER PARK POLICE REPORT. IN REFERENCE TO A.10, A THIRD-PARTY VEHICLE CRASHED INTO A 3' BLOWDOWN ON THE JUSTICE 20' PIPELINE NEAR SPENCER HWY, RESULTING IN THE RUPTURE OF THE LINE AND THE FATALITY OF THE DRIVER. DETAILS OF THIS THIRD-PARTY CRASH ARE UNDER CRIMINAL INVESTIGATION.
A35: 204 | B35: 45576 | C35: 2024 | D35: 20240244 | E35: 40099 | F35: ORIGINAL | G35: 12470 | H35: MID - VALLEY PIPELINE CO | I35: 1300 MAIN STREET | J35: HOUSTON | K35: TX | L35: 77002 | M35: 45550.228 | N35: EASTERN | O35: YES | P35: 40.707241 | Q35: -84.11808 | R35: CRUDE OIL | W35: 2 | Y35: 2 | Z35: NO | AF35: 0 | AG35: NO | AM35: 0 | AN35: NOTIFICATION FROM PUBLIC | AQ35: 45550.228 | AR35: ONSHORE TERMINAL/TANK FARM EQUIPMENT AND PIPING | AS35: ONSHORE | AT35: NORMAL OPERATION, INCLUDES PAUSES BETWEEN BATCHES AND DURING MAINTENANCE | AU35: YES | AW35: 45550.278 | AX35: 45550.534 | AZ35: NO | BC35: 45550.262 | BD35: 45550.267 | BF35: NRC NOTIFICATION NOT REQUIRED | BH35: NO | BV35: YES | BW35: 45550.234 | BX35: YES | BY35: 45550.267 | BZ35: 45550.438 | CA35: 0 | CB35: LIMA STATION | CC35: TANK 90 16-INCH TANK LINE | CD35: OH | CE35: 45804 | CF35: LIMA | CG35: ALLEN | CH35: SURVEY STATION NO. | CI35: 0+00 | CJ35: NO | CK35: TOTALLY CONTAINED ON OPERATOR-CONTROLLED PROPERTY | CL35: UNDERGROUND | CM35: UNDER SOIL | CO35: 48 | CP35: NO | DM35: INTERSTATE | DN35: PIPE | DO35: PIPE BODY | DP35: NO | DQ35: 16 | DR35: 0.25 | DS35: 35000 | DT35: API 5L | DU35: SEAMLESS | DW35: UNKNOWN | DX35: COAL TAR | DZ35: UNKNOWN | FK35: UNKNOWN | FL35: UNKNOWN | FM35: CARBON STEEL | FO35: LEAK | FR35: PINHOLE | FY35: NO | GC35: YES | GD35: NO | GE35: YES | GH35: YES | GK35: NO | GT35: YES | GU35: YES | GX35: YES | GY35: YES | HF35: 0 | HG35: 27 | HH35: 10000 | HI35: 12000 | HJ35: 9000 | HK35: 0 | HM35: 31027 | HN35: 0 | HO35: 0 | HP35: 0 | HQ35: 0 | HR35: 50 | HS35: 275 | HT35: COMPONENT DESIGN PRESSURE ß195.406(A)(2) | HV35: 42457 | HW35: NO | HY35: PRESSURE DID NOT EXCEED MOP | HZ35: NO | IS35: > 20% SMYS REGULATED TRANSMISSION | IT35: YES | IU35: YES | IV35: YES | IW35: NO | IX35: NO | IY35: YES | IZ35: YES | JA35: YES | JB35: NO | JC35: NO | JD35: NO, THE OPERATOR DID NOT FIND THAT AN INVESTIGATION OF THE CONTROLLER(S) ACTIONS OR CONTROL ROOM ISSUES WAS NECESSARY DUE TO: (PROVIDE AN EXPLANATION FOR WHY THE OPERATOR DID NOT INVESTIGATE) | JE35: A REVIEW OF THE ACCIDENT DETERMINED THAT THERE WERE NO CONTROL ROOM ACTIONS THAT CONTRIBUTED TO THE EVENT. | JR35: NO | JS35: NO | JX35: OTHER ACCIDENT CAUSE | JY35: UNKNOWN | RY35: UNKNOWN | SA35: STILL UNDER INVESTIGATION, CAUSE OF ACCIDENT TO BE DETERMINED* (*SUPPLEMENTAL REPORT REQUIRED) | XL35: TODD NARDOZZI | XM35: DIRECTOR - DOT COMPLIANCE | XN35: todd.nardozzi@energytransfer.com | XO35: 713-989-7126 | XQ35: 45576 | XU35: TODD NARDOZZI | XV35: 713-989-7126 | XW35: DIRECTOR - DOT COMPLIANCE | XX35: todd.nardozzi@energytransfer.com | XY35: ON 09/15/2024 AT 05:29, AN OPERATIONS SUPERVISOR RECEIVED REPORTS OF A CRUDE OIL SMELL COMING FROM THE AREA AROUND MVPL LIMA STATION. A LEAK WAS DISCOVERED INSIDE OF TANK 90 DIKE ON THE MVPL FILL LINE IN THE EAST TANK FARM AT LIMA STATION. THE STATION WAS SHUTDOWN, AND VALVES 7290A AND THE HOV WERE CLOSED. THE LINE WAS EXCAVATED AND A PINHOLE ON THE BOTTOM SIDE OF THE PIPE WAS IDENTIFIED. APPROXIMATELY 2 BARRELS OF CRUDE OIL WAS RELEASED INTO THE TANK DIKE AREA. RELEASED PRODUCT WAS CLEANED UP AND IMPACTED SOIL REMEDIATED. THE LINE WAS REPAIRED BY INSTALLING A 16-INCH PLIDCO MECHANICAL CLAMP AND THE LINE WAS RESTARTED AT 12:49. THE CAUSE OF THE ACCIDENT IS UNDER INVESTIGATION. THE FAILED SECTION IS PLANNED TO BE CUT OUT AND SENT TO A THIRD-PARTY LAB FOR ANALYSIS. A SUPPLEMENTAL REPORT WILL BE SUBMITTED ONCE THE INVESTIGATION IS COMPLETE.
A36: 209 | B36: 45576 | C36: 2024 | D36: 20240242 | E36: 40439 | F36: SUPPLEMENTAL FINAL | G36: 22442 | H36: WEST TEXAS GULF PIPELINE CO | I36: 1300 MAIN STREET | J36: HOUSTON | K36: TX | L36: 77002 | M36: 45546.51 | N36: CENTRAL | O36: YES | P36: 32.48341 | Q36: -94.83916 | R36: CRUDE OIL | W36: 30 | Y36: 30 | Z36: NO | AF36: 0 | AG36: NO | AM36: 0 | AN36: LOCAL OPERATING PERSONNEL, INCLUDING CONTRACTORS | AP36: CONTRACTOR WORKING FOR THE OPERATOR | AQ36: 45546.51 | AR36: ONSHORE PUMP/METER STATION EQUIPMENT AND PIPING | AS36: ONSHORE | AT36: NORMAL OPERATION, INCLUDES PAUSES BETWEEN BATCHES AND DURING MAINTENANCE | AU36: YES | AW36: 45546.525 | AX36: 45546.854 | AZ36: NO | BC36: 45546.562 | BD36: 45546.854 | BF36: NRC NOTIFICATION NOT REQUIRED | BH36: NO | BV36: YES | BW36: 45546.51 | BX36: NO | CA36: 0 | CB36: TEXOMA STATION | CC36: WTG 12-INCH RELIEF LINE | CD36: TX | CE36: 75604 | CF36: LONGVIEW | CG36: GREGG | CH36: SURVEY STATION NO. | CI36: 0+00 | CJ36: NO | CK36: TOTALLY CONTAINED ON OPERATOR-CONTROLLED PROPERTY | CL36: UNDERGROUND | CM36: UNDER SOIL | CO36: 132 | CP36: NO | DM36: INTERSTATE | DN36: PIPE | DO36: PIPE BODY | DP36: NO | DQ36: 12 | DR36: 0.4 | DS36: 35000 | DT36: API 5L | DU36: ERW - HIGH FREQUENCY | DW36: MARUICHI SUN STEEL JOINT STOCK COMPANY | DX36: FUSION BONDED EPOXY(FBE) | DZ36: NO | FK36: 2016 | FL36: 2014 | FM36: CARBON STEEL | FO36: LEAK | FR36: PINHOLE | FY36: NO | GC36: YES | GD36: NO | GE36: YES | GH36: YES | GK36: NO | GT36: NO | GU36: NO | HF36: 0 | HG36: 0 | HH36: 500 | HI36: 15000 | HJ36: 15000 | HK36: 0 | HM36: 30500 | HN36: 0 | HO36: 0 | HP36: 0 | HQ36: 0 | HR36: 20 | HS36: 285 | HT36: COMPONENT DESIGN PRESSURE ß195.406(A)(2) | HV36: 42488 | HW36: NO | HY36: PRESSURE DID NOT EXCEED MOP | HZ36: NO | IS36: > 20% SMYS REGULATED TRANSMISSION | IT36: YES | IU36: YES | IV36: YES | IW36: NO | IX36: NO | IY36: YES | IZ36: YES | JA36: YES | JB36: NO | JC36: NO | JD36: NO, THE OPERATOR DID NOT FIND THAT AN INVESTIGATION OF THE CONTROLLER(S) ACTIONS OR CONTROL ROOM ISSUES WAS NECESSARY DUE TO: (PROVIDE AN EXPLANATION FOR WHY THE OPERATOR DID NOT INVESTIGATE) | JE36: A REVIEW OF THE ACCIDENT DETERMINED THAT THERE WERE NO CONTROL ROOM ACTIONS THAT CONTRIBUTED TO THE EVENT. | JR36: NO | JS36: NO | JX36: CORROSION FAILURE | JY36: INTERNAL CORROSION | JZ36: INTERNAL CORROSION | LD36: LOCALIZED PITTING | LH36: YES | LM36: YES | LP36: YES | LU36: NO | LV36: NO | LW36: NOT APPLICABLE - NOT MAINLINE PIPE | LX36: NOT APPLICABLE - NOT MAINLINE PIPE | SC36: NO | UO36: NO | UR36: NO | UZ36: NO | XL36: TODD NARDOZZI | XM36: DIRECTOR - DOT COMPLIANCE | XN36: todd.nardozzi@energytransfer.com | XO36: 713-989-7126 | XQ36: 45681 | XU36: TODD NARDOZZI | XV36: 713-989-7126 | XW36: DIRECTOR - DOT COMPLIANCE | XX36: todd.nardozzi@energytransfer.com | XY36: ON 09/11/24 AT APPROXIMATELY 12:15, A THIRD-PARTY CONTRACTOR CALLED LOCAL OPERATIONS ABOUT CRUDE OIL ON THE GROUND AT TEXOMA STATION. THE CONTROL CENTER WAS CALLED TO BEGIN SHUTTING DOWN AND ISOLATING THE LINE. THE WTG 12-INCH RELIEF LINE WAS BELIEVED TO BE THE SOURCE OF THE RELEASE AND WAS EXCAVATED. AFTER EXCAVATION OF THE RELIEF LINE TWO CORROSION PINHOLES WERE DISCOVERED AT THE 6 O'CLOCK POSITION. APPROXIMATELY 30 BARRELS OF CRUDE OIL WAS RELEASED. CLEAN-UP CONTRACTORS REMOVED FREE PRODUCT AND IMPACTED SOIL IS BEING REMEDIATED. THE LEAK WAS REPAIRED BY CUTTING OUT AND REPLACING THE PIPE. THE FAILED SECTION CUT OUT WAS SENT TO A THIRD-PARTY LAB FOR ANALYSIS. THE CAUSE OF THE ACCIDENT WAS DETERMINED TO BE DUE TO MICROBIOLOGICALLY INDUCED INTERNAL CORROSION. TO PREVENT REOCCURRENCE, THE RELIEF LINE WAS RELOCATED ABOVE GRADE TO ELIMINATE LOW POINT/SETTLEMENT ISSUES.
A37: 210 | B37: 45576 | C37: 2024 | D37: 20240241 | E37: 40278 | F37: SUPPLEMENTAL FINAL | G37: 31888 | H37: CENTURION PIPELINE L.P. | I37: 1300 MAIN STREET | J37: HOUSTON | K37: TX | L37: 77002 | M37: 45546.448 | N37: CENTRAL | O37: YES | P37: 31.754959 | Q37: -103.06514 | R37: CRUDE OIL | W37: 1.6 | Y37: 1.6 | Z37: NO | AF37: 0 | AG37: NO | AM37: 0 | AN37: LOCAL OPERATING PERSONNEL, INCLUDING CONTRACTORS | AP37: OPERATOR EMPLOYEE | AQ37: 45546.448 | AR37: ONSHORE PUMP/METER STATION EQUIPMENT AND PIPING | AS37: ONSHORE | AT37: NORMAL OPERATION, INCLUDES PAUSES BETWEEN BATCHES AND DURING MAINTENANCE | AU37: YES | AW37: 45546.457 | AX37: 45546.5 | AZ37: YES | BA37: OPERATOR | BB37: 45546.485 | BC37: 45546.457 | BD37: 45546.457 | BF37: NRC NOTIFICATION NOT REQUIRED | BH37: NO | BV37: NO | BX37: NO | CA37: 0 | CB37: HALLEY STATION | CC37: C20010 - HALLEY TO WINK | CD37: TX | CE37: 79745 | CF37: Not Within a Municipality | CG37: WINKLER | CH37: MILEPOST | CI37: 0+00 | CJ37: NO | CK37: TOTALLY CONTAINED ON OPERATOR-CONTROLLED PROPERTY | CL37: ABOVEGROUND | CM37: TYPICAL ABOVEGROUND FACILITY PIPING OR APPURTENANCE | CP37: NO | DM37: INTRASTATE | DN37: RELIEF LINE AND RELIEF EQUIPMENT | FK37: UNKNOWN | FL37: UNKNOWN | FM37: CARBON STEEL | FO37: OVERFILL OR OVERFLOW | FY37: NO | GC37: YES | GD37: NO | GE37: YES | GH37: YES | GK37: NO | GT37: NO | GU37: NO | HF37: 0 | HG37: 150 | HH37: 200 | HI37: 800 | HJ37: 10000 | HK37: 0 | HM37: 11150 | HN37: 0 | HO37: 0 | HP37: 0 | HQ37: 0 | HR37: 5 | HS37: 285 | HT37: INTERNAL DESIGN PRESSURE ß195.406(A)(1) | HV37: 42640 | HW37: NO | HY37: PRESSURE DID NOT EXCEED MOP | HZ37: NO | IS37: > 20% SMYS REGULATED TRANSMISSION | IT37: NO | IY37: NO | JD37: NO, THE FACILITY WAS NOT MONITORED BY A CONTROLLER(S) AT THE TIME OF THE ACCIDENT | JR37: NO | JS37: NO | JX37: EQUIPMENT FAILURE | JY37: MALFUNCTION OF CONTROL/RELIEF EQUIPMENT | QB37: MALFUNCTION OF CONTROL/RELIEF EQUIPMENT | QH37: YES | RK37: YES | RL37: AGE AND WEAR RELATED FAILURE OF CHECK VALVE. | XL37: TODD NARDOZZI | XM37: DIRECTOR - DOT COMPLIANCE | XN37: todd.nardozzi@energytransfer.com | XO37: 713-989-7126 | XQ37: 45630 | XU37: TODD NARDOZZI | XV37: 713-989-7126 | XW37: DIRECTOR - DOT COMPLIANCE | XX37: todd.nardozzi@energytransfer.com | XY37: ON 09/11/24 AT APPROXIMATELY 10:45 AM, CRUDE OIL WAS DISCOVERED AT THE METER SKID LOCATED INSIDE OF THE CENTURION HALLEY STATION. THE METER SKID WAS ISOLATED AND C20010 - HALLEY TO WINK 10-INCH LINE WAS SHUT DOWN. LEAK WAS DETERMINED TO BE COMING FROM METER SKID DRAIN LINE DUE TO A FAULTY CHECK VALVE. APPROXIMATELY 1.6 BARRELS OF CRUDE OIL WAS RELEASED. RELEASED PRODUCT WAS CLEANED UP AND IMPACTED SOIL WAS REMEDIATED. TO PREVENT IMMEDIATE REOCCURRENCE THE 2-INCH METER VALVE AND 2-INCH CHECK VALVE WERE REPLACED. AN ADDITIONAL REDUNDANT VALVE WILL BE INSTALLED ON THE METER SKID TO ALIGN WITH CURRENT COMPANY DESIGN STANDARDS AND PREVENT FUTURE REOCCURRENCE.
A38: 211 | B38: 45576 | C38: 2024 | D38: 20240243 | E38: 40098 | F38: SUPPLEMENTAL FINAL | G38: 39706 | H38: ENERGY TRANSFER NEDERLAND TERMINAL LLC | I38: 1300 MAIN STREET | J38: HOUSTON | K38: TX | L38: 77002 | M38: 45546.208 | N38: CENTRAL | O38: YES | P38: 30.001325 | Q38: -93.992525 | R38: CRUDE OIL | W38: 100 | Y38: 100 | Z38: NO | AF38: 0 | AG38: NO | AM38: 0 | AN38: LOCAL OPERATING PERSONNEL, INCLUDING CONTRACTORS | AP38: CONTRACTOR WORKING FOR THE OPERATOR | AQ38: 45546.208 | AR38: ONSHORE TERMINAL/TANK FARM EQUIPMENT AND PIPING | AS38: ONSHORE | AT38: NORMAL OPERATION, INCLUDES PAUSES BETWEEN BATCHES AND DURING MAINTENANCE | AU38: YES | AW38: 45546.208 | AX38: 45546.25 | AZ38: NO | BC38: 45546.208 | BD38: 45546.208 | BE38: 45546.308 | BF38: 1410452 | BG38: 1411792 | BH38: NO | BV38: YES | BW38: 45546.217 | BX38: NO | CA38: 0 | CB38: NEDERLAND TERMINAL | CC38: MARSHLAND MANIFOLD | CD38: TX | CE38: 77627 | CF38: NEDERLAND | CG38: JEFFERSON | CH38: SURVEY STATION NO. | CI38: 0+00 | CJ38: NO | CK38: TOTALLY CONTAINED ON OPERATOR-CONTROLLED PROPERTY | CL38: ABOVEGROUND | CM38: TYPICAL ABOVEGROUND FACILITY PIPING OR APPURTENANCE | CP38: NO | DM38: INTERSTATE | DN38: RELIEF LINE AND RELIEF EQUIPMENT | FK38: 2016 | FL38: 2016 | FM38: CARBON STEEL | FO38: LEAK | FR38: CRACK | FY38: NO | GC38: YES | GD38: NO | GE38: YES | GH38: YES | GK38: NO | GT38: YES | GU38: YES | GX38: YES | GY38: YES | HF38: 0 | HG38: 10000 | HH38: 6500 | HI38: 7000 | HJ38: 300000 | HK38: 0 | HM38: 323500 | HN38: 0 | HO38: 0 | HP38: 0 | HQ38: 0 | HR38: 147 | HS38: 290 | HT38: SUBPART E PRESSURE TEST ß195.406(A)(3) | HV38: 42726 | HW38: NO | HY38: PRESSURE DID NOT EXCEED MOP | HZ38: NO | IS38: > 20% SMYS REGULATED TRANSMISSION | IT38: YES | IU38: YES | IV38: YES | IW38: NO | IX38: NO | IY38: YES | IZ38: YES | JA38: YES | JB38: NO | JC38: NO | JD38: NO, THE OPERATOR DID NOT FIND THAT AN INVESTIGATION OF THE CONTROLLER(S) ACTIONS OR CONTROL ROOM ISSUES WAS NECESSARY DUE TO: (PROVIDE AN EXPLANATION FOR WHY THE OPERATOR DID NOT INVESTIGATE) | JE38: A REVIEW OF THE ACCIDENT DETERMINED THAT THERE WERE NO CONTROL ROOM ACTIONS THAT CONTRIBUTED TO THE EVENT. | JR38: NO | JS38: NO | JX38: EQUIPMENT FAILURE | JY38: MALFUNCTION OF CONTROL/RELIEF EQUIPMENT | QB38: MALFUNCTION OF CONTROL/RELIEF EQUIPMENT | QI38: YES | RK38: YES | RL38: HARMONIC DISTORTION | XH38: YES | XL38: TODD NARDOZZI | XM38: DIRECTOR - DOT COMPLIANCE | XN38: todd.nardozzi@energytransfer.com | XO38: 713-989-7126 | XQ38: 45576 | XU38: TODD NARDOZZI | XV38: 713-989-7126 | XW38: DIRECTOR - DOT COMPLIANCE | XX38: todd.nardozzi@energytransfer.com | XY38: ON 9/11/2024 AT APPROXIMATELY 05:00, A CONTRACTOR DISCOVERED A RELEASE OF CRUDE OIL AT THE MARSHLAND MANIFOLD ON INLET PIPING ASSOCIATED WITH #2 BOOSTER. THE BOOSTER PUMP WAS SHUT DOWN AND THE PRESSURE RELIEF VALVE WAS ISOLATED WHICH STOPPED THE LEAK. THE LEAK WAS DETERMINED TO BE COMING FROM A CRACK IN THE 1.5-INCH PRESSURE RELIEF LINE FROM THE BOOSTER DISCHARGE LINE. APPROXIMATELY 100 BARRELS OF CRUDE OIL WAS RELEASED INTO CONTAINMENT. CLEANUP CREWS REMOVED FREE PRODUCT AND REMEDIATED CONTAMINATED SOIL. THE 48HR NRC REPORT WAS MADE AS SOON AS POSSIBLE AFTER IT WAS DISCOVERED THAT IT HAD NOT BEEN MADE W/IN 48 HOURS OF THE ORIGINAL NRC REPORT. AN INVESTIGATION WAS COMPLETED, AND IT WAS DETERMINED THAT A THERMAL PRESSURE SAFETY VALVE (PSV) HAD SETPOINT LEVEL TOO CLOSE TO THE FACILITY LINE NORMAL OPERATING PRESSURE WHICH ALLOWED ACTIVATION OF THE PSV DURING ROUTINE STARTUPS OF THE ASSOCIATED BOOSTER PUMP. THE PSV FAILED TO RESEAT WHICH CAUSED VIBRATION DURING THE CONTINUED FLOW THROUGH THE PSV AND LED TO A CRACK IN THE SCHEDULE 80 PIPE ASSOCIATED WITH THE PSV LEADING TO THE RELEASE. TO PREVENT REOCCURRENCE, THE PSV AND ASSOCIATED PIPING HAS BEEN REPLACED. THE NEW PSV HAS AN INCREASED SETPOINT TO ENSURE IT WILL NOT ACTIVATE UNDER NORMAL OPERATING CONDITIONS BUT WILL STILL PROTECT THE PIPING FROM THERMAL OVERPRESSURE.
A39: 212 | B39: 45569 | C39: 2024 | D39: 20240235 | E39: 40070 | F39: SUPPLEMENTAL | G39: 31888 | H39: CENTURION PIPELINE L.P. | I39: 1300 MAIN STREET | J39: HOUSTON | K39: TX | L39: 77002 | M39: 45541.292 | N39: CENTRAL | O39: YES | P39: 32.68873 | Q39: -102.64766 | R39: CRUDE OIL | W39: 2 | Y39: 2 | Z39: NO | AF39: 0 | AG39: NO | AM39: 0 | AN39: LOCAL OPERATING PERSONNEL, INCLUDING CONTRACTORS | AP39: OPERATOR EMPLOYEE | AQ39: 45541.327 | AR39: ONSHORE PUMP/METER STATION EQUIPMENT AND PIPING | AS39: ONSHORE | AT39: NORMAL OPERATION, INCLUDES PAUSES BETWEEN BATCHES AND DURING MAINTENANCE | AU39: YES | AW39: 45541.327 | AX39: 45541.625 | AZ39: YES | BA39: OPERATOR | BB39: 45541.347 | BC39: 45541.327 | BD39: 45541.327 | BF39: NRC NOTIFICATION NOT REQUIRED | BH39: NO | BV39: YES | BW39: 45541.333 | BX39: NO | CA39: 0 | CB39: SEMINOLE STATION | CC39: SP-0001 2-INCH DISCHARGE LINE | CD39: TX | CE39: 79360 | CF39: SEMINOLE | CG39: GAINES | CH39: MILEPOST | CI39: 0+00 | CJ39: NO | CK39: TOTALLY CONTAINED ON OPERATOR-CONTROLLED PROPERTY | CL39: UNDERGROUND | CM39: UNDER SOIL | CO39: 20 | CP39: NO | DM39: INTRASTATE | DN39: SUMP | FK39: UNKNOWN | FL39: UNKNOWN | FM39: CARBON STEEL | FO39: LEAK | FR39: PINHOLE | FY39: NO | GC39: YES | GD39: NO | GE39: YES | GH39: YES | GK39: NO | GT39: NO | GU39: NO | HF39: 0 | HG39: 0 | HH39: 2000 | HI39: 2000 | HJ39: 1000 | HK39: 0 | HM39: 5000 | HN39: 0 | HO39: 0 | HP39: 0 | HQ39: 0 | HR39: 40 | HS39: 275 | HT39: COMPONENT DESIGN PRESSURE ß195.406(A)(2) | HV39: 41407 | HW39: NO | HY39: PRESSURE DID NOT EXCEED MOP | HZ39: NO | IS39: < 20% SMYS REGULATED TRANSMISSION | IT39: YES | IU39: YES | IV39: YES | IW39: NO | IX39: NO | IY39: NO | JD39: NO, THE OPERATOR DID NOT FIND THAT AN INVESTIGATION OF THE CONTROLLER(S) ACTIONS OR CONTROL ROOM ISSUES WAS NECESSARY DUE TO: (PROVIDE AN EXPLANATION FOR WHY THE OPERATOR DID NOT INVESTIGATE) | JE39: A REVIEW OF THE ACCIDENT DETERMINED THAT THERE WERE NO CONTROL ROOM ACTIONS THAT CONTRIBUTED TO THE EVENT. | JR39: NO | JS39: NO | JX39: OTHER ACCIDENT CAUSE | JY39: UNKNOWN | RY39: UNKNOWN | SA39: STILL UNDER INVESTIGATION, CAUSE OF ACCIDENT TO BE DETERMINED* (*SUPPLEMENTAL REPORT REQUIRED) | XL39: TODD NARDOZZI | XM39: DIRECTOR - DOT COMPLIANCE | XN39: todd.nardozzi@energytransfer.com | XO39: 713-989-7126 | XQ39: 45569 | XU39: TODD NARDOZZI | XV39: 713-989-7126 | XW39: DIRECTOR - DOT COMPLIANCE | XX39: todd.nardozzi@energytransfer.com | XY39: ON 09/06/24 AT APPROXIMATELY 07:00, OPERATIONS DISCOVERED CRUDE OIL ON THE GROUND AT THE OUTGOING METER SKID WITHIN SEMINOLE STATION. THE RELEASE WAS COMING FROM A PINHOLE ON THE 2-INCH SUMP (SP-0001) DISCHARGE LINE. ISOLATED AND SHUT DOWN SUMP. CLOSED DISCHARGE VALVE ON SUMP & TIE-IN VALVE TO LINE. APPROXIMATELY 2 BARRELS OF CRUDE OIL WAS RELEASED ONTO THE GROUND. CLEANUP CREWS REMOVED PRODUCT AND REMEDIATED IMPACTED SOIL. A CLAMP WAS INSTALLED TO REPAIR THE LEAK AND THE SUMP WAS RETURNED TO SERVICE. A SUPPLEMENTAL REPORT WILL BE SUBMITTED ONCE THE INVESTIGATION IS COMPLETE.
A40: 218 | B40: 45561 | C40: 2024 | D40: 20240229 | E40: 40040 | F40: ORIGINAL | G40: 32099 | H40: ENERGY TRANSFER COMPANY | I40: 1300 MAIN STREET | J40: HOUSTON | K40: TX | L40: 77002 | M40: 45533.865 | N40: CENTRAL | O40: YES | P40: 31.584061 | Q40: -94.815932 | R40: CRUDE OIL | W40: 1.9 | Y40: 1.9 | Z40: NO | AF40: 0 | AG40: NO | AM40: 0 | AN40: NOTIFICATION FROM PUBLIC | AQ40: 45533.865 | AR40: ONSHORE PIPELINE, INCLUDING VALVE SITES | AS40: ONSHORE | AT40: NORMAL OPERATION, INCLUDES PAUSES BETWEEN BATCHES AND DURING MAINTENANCE | AU40: YES | AW40: 45533.869 | AX40: 45534.75 | AZ40: YES | BA40: OPERATOR | BB40: 45534.34 | BC40: 45533.896 | BD40: 45534.021 | BE40: 45534.049 | BF40: 1409437 | BG40: 1409548 | BH40: NO | BN40: VALVE CLOSURE | BP40: 45533.87 | BQ40: REMOTELY CONTROLLED | BR40: VALVE CLOSURE | BT40: 45533.873 | BU40: REMOTELY CONTROLLED | BV40: YES | BW40: 45533.869 | BX40: YES | BY40: 45533.938 | BZ40: 45534.021 | CA40: 0 | CB40: EAST TEXAS 10-INCH | CC40: 21003.04 - 10-INCH DIBOLL TO DOUGLAS | CD40: TX | CE40: 75964 | CF40: NACOGDOCHES | CG40: NACOGDOCHES | CH40: MILEPOST | CI40: 130.04 | CJ40: NO | CK40: PIPELINE RIGHT-OF-WAY | CL40: UNDERGROUND | CM40: UNDER SOIL | CO40: 24 | CP40: NO | DM40: INTRASTATE | DN40: WELD, INCLUDING HEAT-AFFECTED ZONE | DQ40: 10 | DR40: 0.307 | DS40: 35000 | DT40: GRADE B | DU40: SEAMLESS | DW40: UNKNOWN | DX40: COAL TAR | DZ40: YES | EA40: PIPE GIRTH WELD | EC40: NO | FK40: 1931 | FL40: UNKNOWN | FM40: CARBON STEEL | FO40: LEAK | FR40: PINHOLE | FY40: NO | GC40: YES | GD40: NO | GE40: YES | GF40: YES | GH40: YES | GK40: YES | GM40: YES | GR40: 1.9 | GS40: UNNAMED CREEK | GT40: NO | GU40: NO | HF40: 3000 | HG40: 138 | HH40: 12000 | HI40: 40000 | HJ40: 1500 | HK40: 0 | HM40: 56638 | HN40: 0 | HO40: 0 | HP40: 0 | HQ40: 0 | HR40: 320 | HS40: 1000 | HT40: SUBPART E PRESSURE TEST ß195.406(A)(3) | HV40: 45051 | HW40: NO | HY40: PRESSURE DID NOT EXCEED MOP | HZ40: NO | IC40: 31152 | ID40: YES | IL40: NO | IS40: > 20% SMYS REGULATED TRANSMISSION | IT40: YES | IU40: YES | IV40: YES | IW40: NO | IX40: NO | IY40: YES | IZ40: YES | JA40: YES | JB40: NO | JC40: NO | JD40: NO, THE OPERATOR DID NOT FIND THAT AN INVESTIGATION OF THE CONTROLLER(S) ACTIONS OR CONTROL ROOM ISSUES WAS NECESSARY DUE TO: (PROVIDE AN EXPLANATION FOR WHY THE OPERATOR DID NOT INVESTIGATE) | JE40: A REVIEW OF THE ACCIDENT DETERMINED THAT THERE WERE NO CONTROL ROOM ACTIONS THAT CONTRIBUTED TO THE EVENT. | JR40: NO | JS40: NO | JX40: OTHER ACCIDENT CAUSE | JY40: UNKNOWN | RY40: UNKNOWN | SA40: STILL UNDER INVESTIGATION, CAUSE OF ACCIDENT TO BE DETERMINED* (*SUPPLEMENTAL REPORT REQUIRED) | XL40: TODD NARDOZZI | XM40: DIRECTOR - DOT COMPLIANCE | XN40: todd.nardozzi@energytransfer.com | XO40: 713-989-7126 | XQ40: 45561 | XU40: TODD NARDOZZI | XV40: 713-989-7126 | XW40: DIRECTOR - DOT COMPLIANCE | XX40: todd.nardozzi@energytransfer.com | XY40: ON 08/29/24 AT APPROXIMATELY 20:45, A LAND OWNER CALLED THE CONTROL CENTER ABOUT A POTENTIAL CRUDE OIL LEAK ON PIPELINE ROW OF 21003.04 10-INCH DIBOLL TO DOUGLAS LINE. THE LINE WAS SHUT DOWN AND THE SEGMENT ISOLATED. THE LEAK WAS IDENTIFIED COMING FROM A PIN HOLE AT THE 6 O'CLOCK POSITION. APPROXIMATELY 1.9 BARRELS OF CRUDE OIL WAS RELEASED AND MIGRATED TO A NEARBY UNNAMED CREEK. OSRO REMOVED FREE PRODUCT AND CONTAMINATED SOIL. ON 08/30/34, A CLAMP WAS INSTALLED AND THE LINE WAS RESTARTED. THE PIPE WILL BE CUT OUT AND SENT TO A 3RD PARTY LABORATORY FOR ANALYSIS. A SUPPLEMENTAL REPORT WILL BE SUBMITTED ONCE THE ANALYSIS AND INVESTIGATION IS COMPLETE.
A41: 219 | B41: 45561 | C41: 2024 | D41: 20240230 | E41: 40443 | F41: SUPPLEMENTAL FINAL | G41: 32099 | H41: ENERGY TRANSFER COMPANY | I41: 1300 MAIN STREET | J41: HOUSTON | K41: TX | L41: 77002 | M41: 45533.771 | N41: CENTRAL | O41: YES | P41: 31.790902 | Q41: -100.0637 | R41: CRUDE OIL | W41: 225 | Y41: 225 | Z41: NO | AF41: 0 | AG41: NO | AM41: 0 | AN41: NOTIFICATION FROM PUBLIC | AQ41: 45533.771 | AR41: ONSHORE PIPELINE, INCLUDING VALVE SITES | AS41: ONSHORE | AT41: NORMAL OPERATION, INCLUDES PAUSES BETWEEN BATCHES AND DURING MAINTENANCE | AU41: YES | AW41: 45533.781 | AX41: 45534.542 | AZ41: NO | BC41: 45533.792 | BD41: 45533.854 | BE41: 45533.96 | BF41: 1409432 | BG41: 1409569 | BH41: NO | BN41: VALVE CLOSURE | BP41: 45533.782 | BQ41: REMOTELY CONTROLLED | BR41: VALVE CLOSURE | BT41: 45533.783 | BU41: REMOTELY CONTROLLED | BV41: YES | BW41: 45533.78 | BX41: NO | CA41: 0 | CB41: AMDEL PIPELINE | CC41: 21001.09 10-INCH BRONTE TO TALPA | CD41: TX | CE41: 76821 | CF41: BALLINGER | CG41: RUNNELS | CH41: SURVEY STATION NO. | CI41: 79450.4 | CJ41: NO | CK41: PIPELINE RIGHT-OF-WAY | CL41: UNDERGROUND | CM41: UNDER SOIL | CO41: 48 | CP41: NO | DM41: INTERSTATE | DN41: PIPE | DO41: PIPE BODY | DP41: NO | DQ41: 10 | DR41: 0.307 | DS41: 35000 | DT41: API 5L GRADE B | DU41: SEAMLESS | DW41: UNKNOWN | DX41: COLD APPLIED TAPE | DZ41: YES | FK41: 1928 | FL41: UNKNOWN | FM41: CARBON STEEL | FO41: LEAK | FR41: PINHOLE | FY41: NO | GC41: YES | GD41: NO | GE41: YES | GH41: YES | GK41: NO | GT41: NO | GU41: NO | HF41: 10000 | HG41: 16875 | HH41: 123643 | HI41: 22000 | HJ41: 150000 | HK41: 0 | HM41: 322518 | HN41: 0 | HO41: 0 | HP41: 0 | HQ41: 0 | HR41: 573 | HS41: 1067 | HT41: SUBPART E PRESSURE TEST ß195.406(A)(3) | HV41: 32444 | HW41: NO | HY41: PRESSURE DID NOT EXCEED MOP | HZ41: NO | IC41: 212203 | ID41: YES | IL41: NO | IS41: > 20% SMYS REGULATED TRANSMISSION | IT41: YES | IU41: YES | IV41: YES | IW41: NO | IX41: NO | IY41: YES | IZ41: YES | JA41: YES | JB41: NO | JC41: NO | JD41: NO, THE OPERATOR DID NOT FIND THAT AN INVESTIGATION OF THE CONTROLLER(S) ACTIONS OR CONTROL ROOM ISSUES WAS NECESSARY DUE TO: (PROVIDE AN EXPLANATION FOR WHY THE OPERATOR DID NOT INVESTIGATE) | JE41: A REVIEW OF THE ACCIDENT DETERMINED THAT THERE WERE NO CONTROL ROOM ACTIONS THAT CONTRIBUTED TO THE EVENT. | JR41: NO | JS41: NO | JX41: CORROSION FAILURE | JY41: EXTERNAL CORROSION | JZ41: EXTERNAL CORROSION | KA41: LOCALIZED PITTING | KC41: YES | KM41: YES | KP41: YES | KQ41: YES | KR41: 1950 | KS41: YES | KT41: YES | KU41: YES | KV41: YES | KX41: 2024 | KY41: 2024 | LC41: YES | SC41: YES | SD41: YES | SG41: YES | SK41: 2023 | SL41: FREE SWIMMING | SM41: METAL LOSS | SO41: HIGH RESOLUTION | SQ41: 2016 | SR41: FREE SWIMMING | SS41: METAL LOSS | SU41: HIGH RESOLUTION | TQ41: 2023 | TR41: FREE SWIMMING | TS41: STANDARD RESOLUTION | TU41: NO CUPS | TV41: 2016 | TW41: FREE SWIMMING | TX41: STANDARD RESOLUTION | TZ41: NO CUPS | UO41: YES | UP41: 1988 | UQ41: 1335 | UR41: NO | UZ41: NO | XL41: TODD NARDOZZI | XM41: DIRECTOR - DOT COMPLIANCE | XN41: todd.nardozzi@energytransfer.com | XO41: 713-989-7126 | XQ41: 45681 | XU41: TODD NARDOZZI | XV41: 713-989-7126 | XW41: DIRECTOR - DOT COMPLIANCE | XX41: todd.nardozzi@energytransfer.com | XY41: ON 08/29/24 AT APPROXIMATELY 18:30, A LANDOWNER NOTIFIED OPERATIONS ABOUT OIL ON THE GROUND AT MP 79450.4 OF THE 21001.09 10-INCH BRONTE TO TALPA (AMDEL SYSTEM). THE LINE WAS IMMEDIATELY SHUTDOWN AND THE SEGMENT ISOLATED. THE LINE WAS EXCAVATED AND A THROUGH-WALL PINHOLE WAS FOUND AT THE 05:10 O'CLOCK POSITION. APPROXIMATELY 225 BARRELS OF CRUDE OIL WAS RELEASED. CLEAN-UP CONTRACTORS REMOVED FREE PRODUCT AND IMPACTED SOIL IS BEING REMEDIATED. ON 08/30/24, A PLIDCO CLAMP WAS INSTALLED TO TEMPORARILY REPAIR THE LEAK WHILE THE LINE WAS RETURNED TO SERVICE. THE FAILED SECTION OF PIPE WAS CUT OUT AND REPLACED. THE FAILED SECTION WAS SENT TO A LABORATORY FOR EXAMINATION. THE INVESTIGATION DETERMINED THE CAUSE OF THE ACCIDENT WAS DUE TO EXTERNAL CORROSION.
A42: 224 | B42: 45559 | C42: 2024 | D42: 20240225 | E42: 40028 | F42: ORIGINAL | G42: 31888 | H42: CENTURION PIPELINE L.P. | I42: 1300 MAIN STREET | J42: HOUSTON | K42: TX | L42: 77002 | M42: 45529.521 | N42: CENTRAL | O42: YES | P42: 32.223061 | Q42: -103.70565 | R42: CRUDE OIL | W42: 2.5 | Y42: 2.5 | Z42: NO | AF42: 0 | AG42: NO | AM42: 0 | AN42: LOCAL OPERATING PERSONNEL, INCLUDING CONTRACTORS | AP42: OPERATOR EMPLOYEE | AQ42: 45529.521 | AR42: ONSHORE BREAKOUT TANK OR STORAGE VESSEL, INCLUDING ATTACHED APPURTENANCES | AS42: ONSHORE | AT42: NORMAL OPERATION, INCLUDES PAUSES BETWEEN BATCHES AND DURING MAINTENANCE | AU42: NO | AV42: TANK 7302 WAS ISOLATED. | AZ42: NO | BC42: 45529.521 | BD42: 45529.521 | BF42: NRC NOTIFICATION NOT REQUIRED | BH42: NO | BV42: YES | BW42: 45529.545 | BX42: NO | CA42: 0 | CB42: JAL STATION | CC42: TANK 7302 | CD42: NM | CE42: 88252 | CF42: JAL | CG42: LEA | CH42: SURVEY STATION NO. | CI42: 0+00 | CJ42: NO | CK42: TOTALLY CONTAINED ON OPERATOR-CONTROLLED PROPERTY | CL42: TANK, INCLUDING ATTACHED APPURTENANCES | CP42: NO | DM42: INTERSTATE | DN42: TANK/VESSEL | EW42: ROOF DRAIN SYSTEM | EY42: ATMOSPHERIC | FD42: 40 | FE42: NO | FG42: YES | FH42: 2022 | FK42: 2017 | FL42: 2017 | FM42: CARBON STEEL | FO42: LEAK | FR42: OTHER | FS42: UNDER INVESTIGATION | FY42: NO | GC42: YES | GD42: NO | GE42: YES | GH42: YES | GK42: NO | GT42: NO | GU42: NO | HF42: 0 | HG42: 200 | HH42: 0 | HI42: 200 | HJ42: 11000 | HK42: 0 | HM42: 11400 | HN42: 0 | HO42: 0 | HP42: 0 | HQ42: 0 | HR42: 14.7 | HZ42: NO | IS42: > 20% SMYS REGULATED TRANSMISSION | IT42: YES | IU42: YES | IV42: YES | IW42: NO | IX42: NO | IY42: NO | JD42: NO, THE OPERATOR DID NOT FIND THAT AN INVESTIGATION OF THE CONTROLLER(S) ACTIONS OR CONTROL ROOM ISSUES WAS NECESSARY DUE TO: (PROVIDE AN EXPLANATION FOR WHY THE OPERATOR DID NOT INVESTIGATE) | JE42: A REVIEW OF THE ACCIDENT DETERMINED THAT THERE WERE NO CONTROL ROOM ACTIONS THAT CONTRIBUTED TO THE EVENT. | JR42: NO | JS42: NO | JX42: OTHER ACCIDENT CAUSE | JY42: UNKNOWN | RY42: UNKNOWN | SA42: STILL UNDER INVESTIGATION, CAUSE OF ACCIDENT TO BE DETERMINED* (*SUPPLEMENTAL REPORT REQUIRED) | XL42: TODD NARDOZZI | XM42: DIRECTOR - DOT COMPLIANCE | XN42: todd.nardozzi@energytransfer.com | XO42: 713-989-7126 | XQ42: 45559 | XU42: TODD NARDOZZI | XV42: 713-989-7126 | XW42: DIRECTOR - DOT COMPLIANCE | XX42: todd.nardozzi@energytransfer.com | XY42: ON 08/25/24 AT 12:30, CRUDE OIL WAS DISCOVERED ON THE GROUND AT JAL STATION. CRUDE OIL WAS ALSO FOUND ON TOP OF THE EXTERNAL FLOATING ROOF. IT WAS DETERMINED THE CRUDE OIL WAS COMING FROM THE ROOF DRAIN LINE OF TANK 7302. TANK'S ROOF DRAIN WAS CLOSED AND THE TANK WAS ISOLATED. APPROXIMATELY 2.5 BARRELS OF CRUDE OIL WAS RELEASED INTO CONTAINMENT. CLEANUP CREWS REMOVED PRODUCT AND REMEDIATED CONTAMINATED SOIL. THE CAUSE OF THE ACCIDENT IS PENDING AN ONGOING INVESTIGATION. A SUPPLEMENTAL REPORT WILL BE SUBMITTED ONCE COMPLETED.
A43: 226 | B43: 45553 | C43: 2024 | D43: 20240219 | E43: 40008 | F43: ORIGINAL | G43: 32099 | H43: ENERGY TRANSFER COMPANY | I43: 1300 MAIN STREET | J43: HOUSTON | K43: TX | L43: 77002 | M43: 45524.373 | N43: EASTERN | O43: YES | P43: 42.384495 | Q43: -83.353622 | R43: CRUDE OIL | W43: 5 | Y43: 5 | Z43: NO | AF43: 0 | AG43: NO | AM43: 0 | AN43: NOTIFICATION FROM PUBLIC | AQ43: 45524.373 | AR43: ONSHORE PIPELINE, INCLUDING VALVE SITES | AS43: ONSHORE | AT43: NORMAL OPERATION, INCLUDES PAUSES BETWEEN BATCHES AND DURING MAINTENANCE | AU43: YES | AW43: 45524.376 | AX43: 45528.406 | AZ43: NO | BC43: 45524.383 | BD43: 45524.383 | BE43: 45524.502 | BF43: 1408478 | BG43: 1408663 | BH43: NO | BN43: VALVE CLOSURE | BP43: 45524.381 | BQ43: MANUAL | BR43: VALVE CLOSURE | BT43: 45524.381 | BU43: MANUAL | BV43: YES | BW43: 45524.38 | BX43: YES | BY43: 45524.449 | BZ43: 45524.507 | CA43: 0 | CB43: MARYSVILLE TO TOLEDO | CC43: 13002 CMAR-CTOL-16INCH | CD43: MI | CE43: 48154 | CF43: LIVONIA | CG43: WAYNE | CH43: SURVEY STATION NO. | CI43: 344498.8 | CJ43: NO | CK43: PIPELINE RIGHT-OF-WAY | CL43: UNDERGROUND | CM43: UNDER SOIL | CO43: 42 | CP43: NO | DM43: INTERSTATE | DN43: PIPE | DO43: PIPE BODY | DP43: NO | DQ43: 16 | DR43: 0.25 | DS43: 60000 | DT43: X-60 | DU43: ERW - HIGH FREQUENCY | DW43: REPUBLIC STEEL | DX43: COAL TAR | DZ43: YES | FK43: 1967 | FL43: 1967 | FM43: CARBON STEEL | FO43: OTHER | FX43: STILL UNDER INVESTIGATION | FY43: NO | GC43: YES | GD43: NO | GE43: YES | GH43: YES | GK43: NO | GT43: YES | GU43: YES | GX43: YES | GY43: YES | HF43: 18000 | HG43: 360 | HH43: 225580 | HI43: 155995 | HJ43: 275000 | HK43: 0 | HM43: 674935 | HN43: 0 | HO43: 0 | HP43: 0 | HQ43: 0 | HR43: 1205 | HS43: 1300 | HT43: SUBPART E PRESSURE TEST ß195.406(A)(3) | HV43: 31888 | HW43: NO | HY43: PRESSURE DID NOT EXCEED MOP | HZ43: NO | IC43: 55986 | ID43: YES | IL43: NO | IS43: > 20% SMYS REGULATED TRANSMISSION | IT43: YES | IU43: YES | IV43: YES | IW43: NO | IX43: NO | IY43: YES | IZ43: YES | JA43: YES | JB43: NO | JC43: NO | JD43: NO, THE OPERATOR DID NOT FIND THAT AN INVESTIGATION OF THE CONTROLLER(S) ACTIONS OR CONTROL ROOM ISSUES WAS NECESSARY DUE TO: (PROVIDE AN EXPLANATION FOR WHY THE OPERATOR DID NOT INVESTIGATE) | JE43: A REVIEW OF THE ACCIDENT DETERMINED THAT THERE WERE NO CONTROL ROOM ACTIONS THAT CONTRIBUTED TO THE EVENT. | JR43: NO | JS43: NO | JX43: OTHER ACCIDENT CAUSE | JY43: UNKNOWN | RY43: UNKNOWN | SA43: STILL UNDER INVESTIGATION, CAUSE OF ACCIDENT TO BE DETERMINED* (*SUPPLEMENTAL REPORT REQUIRED) | XL43: TODD NARDOZZI | XM43: DIRECTOR - DOT COMPLIANCE | XN43: todd.nardozzi@energytransfer.com | XO43: 713-989-7126 | XQ43: 45553 | XU43: TODD NARDOZZI | XV43: 713-989-7126 | XW43: DIRECTOR - DOT COMPLIANCE | XX43: todd.nardozzi@energytransfer.com | XY43: ON 8/20/2024 AT 08:57, OPERATIONS RECEIVED A NOTIFICATION CONCERNING VISIBLE PRODUCT LEAKING FROM A SIDEWALK ON 13002 CMAR-CTOL-16INCH LINE. LINE WAS IMMEDIATELY SHUTDOWN AND ISOLATED. APPROXIMATELY 5 BARRELS OF CRUDE OIL WAS RELEASED. AN OSRO WAS MOBILIZED TO CLEANUP FREE PRODUCT AND CONTAMINATED SOIL. THE FAILED PIPE WAS CUTOUT AND REPLACED. THE LINE WAS RESTARTED ON 8/24/2024 AT 09:45. THE CAUSE OF THE LEAK IS STILL UNDER INVESTIGATION. A SUPPLEMENTAL REPORT WILL BE SUBMITTED ONCE THE INVESTIGATION IS COMPLETE.
A44: 233 | B44: 45546 | C44: 2024 | D44: 20240216 | E44: 40223 | F44: SUPPLEMENTAL FINAL | G44: 31888 | H44: CENTURION PIPELINE L.P. | I44: 1300 MAIN STREET | J44: HOUSTON | K44: TX | L44: 77002 | M44: 45516.021 | N44: CENTRAL | O44: YES | P44: 35.511293 | Q44: -97.884654 | R44: CRUDE OIL | W44: 5 | Y44: 5 | Z44: NO | AF44: 0 | AG44: NO | AM44: 0 | AN44: LOCAL OPERATING PERSONNEL, INCLUDING CONTRACTORS | AP44: OPERATOR EMPLOYEE | AQ44: 45516.021 | AR44: ONSHORE PUMP/METER STATION EQUIPMENT AND PIPING | AS44: ONSHORE | AT44: NORMAL OPERATION, INCLUDES PAUSES BETWEEN BATCHES AND DURING MAINTENANCE | AU44: YES | AW44: 45516.045 | AX44: 45516.069 | AZ44: NO | BC44: 45516.021 | BD44: 45516.03 | BF44: NRC NOTIFICATION NOT REQUIRED | BH44: NO | BV44: YES | BW44: 45516.021 | BX44: NO | CA44: 0 | CB44: EL RENO STATION | CC44: EL RENO TO CUSHING SYSTEM #2 16-INCH | CD44: OK | CE44: 73036 | CF44: EL RENO | CG44: CANADIAN | CH44: MILEPOST | CI44: 0+00 | CJ44: NO | CK44: TOTALLY CONTAINED ON OPERATOR-CONTROLLED PROPERTY | CL44: UNDERGROUND | CM44: UNDER SOIL | CO44: 28 | CP44: NO | DM44: INTERSTATE | DN44: TUBING | EU44: STAINLESS STEEL | EV44: RIGID | FK44: UNKNOWN | FL44: UNKNOWN | FM44: MATERIAL OTHER THAN CARBON STEEL | FN44: STAINLESS STEEL | FO44: LEAK | FR44: CRACK | FY44: NO | GC44: YES | GD44: NO | GE44: YES | GH44: YES | GK44: NO | GT44: YES | GU44: YES | GZ44: YES | HA44: YES | HF44: 0 | HG44: 0 | HH44: 100 | HI44: 20000 | HJ44: 20000 | HK44: 0 | HM44: 40100 | HN44: 0 | HO44: 0 | HP44: 0 | HQ44: 0 | HR44: 258 | HS44: 740 | HT44: SUBPART E PRESSURE TEST ß195.406(A)(3) | HV44: 42684 | HW44: NO | HY44: PRESSURE DID NOT EXCEED MOP | HZ44: NO | IS44: > 20% SMYS REGULATED TRANSMISSION | IT44: YES | IU44: YES | IV44: YES | IW44: NO | IX44: NO | IY44: YES | IZ44: YES | JA44: YES | JB44: NO | JC44: NO | JD44: NO, THE OPERATOR DID NOT FIND THAT AN INVESTIGATION OF THE CONTROLLER(S) ACTIONS OR CONTROL ROOM ISSUES WAS NECESSARY DUE TO: (PROVIDE AN EXPLANATION FOR WHY THE OPERATOR DID NOT INVESTIGATE) | JE44: A REVIEW OF THE ACCIDENT DETERMINED THAT THERE WERE NO CONTROL ROOM ACTIONS THAT CONTRIBUTED TO THE EVENT. | JR44: NO | JS44: NO | JX44: NATURAL FORCE DAMAGE | JY44: HEAVY RAINS/FLOODS | LY44: HEAVY RAINS/FLOODS | MA44: OTHER | MD44: INCREASED EARTH SETTLING FROM EXTREME DRY WEATHER TO SUDDEN RAINFALL. | ME44: NO | XL44: TODD NARDOZZI | XM44: DIRECTOR - DOT COMPLIANCE | XN44: todd.nardozzi@energytransfer.com | XO44: 713-989-7126 | XQ44: 45610 | XU44: TODD NARDOZZI | XV44: 713-989-7126 | XW44: DIRECTOR - DOT COMPLIANCE | XX44: todd.nardozzi@energytransfer.com | XY44: ON 8/11/24 AT 23:30, A LEAK WAS DISCOVERED IN THE MAINLINE PUMP STRAINER AREA OF THE EL RENO TO CUSHING SYSTEM #2 LINE AT EL RENO STATION. THE AREA WAS ISOLATED AND THE LINE SHUTDOWN. THE INVESTIGATION DETERMINED THE LEAK WAS COMING FROM A THREADED 1/2-INCH PVIT FITTING. APPROXIMATELY 5 BARRELS OF CRUDE OIL WAS RELEASED TO THE GROUND. RELEASED PRODUCT WAS CLEANED UP AND IMPACTED SOIL REMEDIATED. FAILED FITTING WAS REPLACED AND LINE RESTARTED. THE CAUSE OF THE LEAK IS STILL UNDER INVESTIGATION. A SUPPLEMENTAL REPORT WILL BE SUBMITTED ONCE THE INVESTIGATION IS COMPLETE. SUPPLEMENTAL REPORT FILED ON NOVEMBER 15, 2024: DURING THE ACCIDENT INVESTIGATION, IT WAS DETERMINED THAT SUDDEN HEAVY RAINFALL CAUSE INCREASED SETTLING OF THE SOIL IN THE AREA OF THE FITTING. PRIOR TO THE LEAK, THE GROUND HAD PREVIOUSLY BEEN EXCAVATED AND BACKFILLED. WEATHER CONDITIONS WERE IN DROUGHT PRIOR TO THE RAINFALL. WITH THE AGE OF THE FITTING AND THE SUDDEN RAINFALL CAUSING SETTLING, THE FITTING LEAKED. THE THREADED FITTING WAS REPLACED WITH A SINGLE STAINLESS STEEL LINE TO PREVENT FUTURE REOCCURRENCE. THE SINGLE STAINLESS STEEL LINE WILL PREVENT MULTIPLE CONNECTION POINTS THAT COULD SERVE AS POTENTIAL LEAK POINTS.
A45: 235 | B45: 45540 | C45: 2024 | D45: 20240213 | E45: 39973 | F45: ORIGINAL | G45: 18718 | H45: SUNOCO PIPELINE L.P. | I45: 1300 MAIN STREET | J45: HOUSTON | K45: TX | L45: 77002 | M45: 45513.323 | N45: EASTERN | O45: YES | P45: 39.851131 | Q45: -75.41527 | R45: REFINED AND/OR PETROLEUM PRODUCT (NON-HVL) WHICH IS A LIQUID AT AMBIENT CONDITIONS | S45: GASOLINE (NON-ETHANOL) | W45: 1342 | Y45: 1342 | Z45: NO | AF45: 0 | AG45: NO | AM45: 0 | AN45: LOCAL OPERATING PERSONNEL, INCLUDING CONTRACTORS | AP45: OPERATOR EMPLOYEE | AQ45: 45513.323 | AR45: ONSHORE BREAKOUT TANK OR STORAGE VESSEL, INCLUDING ATTACHED APPURTENANCES | AS45: ONSHORE | AT45: NORMAL OPERATION, INCLUDES PAUSES BETWEEN BATCHES AND DURING MAINTENANCE | AU45: YES | AW45: 45513.325 | AY45: YES | AZ45: YES | BA45: OPERATOR | BB45: 45513.448 | BC45: 45513.354 | BD45: 45513.358 | BE45: 45513.448 | BF45: 1407384 | BG45: 1407549 | BH45: NO | BV45: YES | BW45: 45513.375 | BX45: YES | BY45: 45513.358 | BZ45: 45513.358 | CA45: 0 | CB45: MARCUS HOOK TANK FARM | CC45: TANK 327 | CD45: PA | CE45: 19014 | CF45: ASTON | CG45: DELAWARE | CH45: SURVEY STATION NO. | CI45: 0+00 | CJ45: NO | CK45: TOTALLY CONTAINED ON OPERATOR-CONTROLLED PROPERTY | CL45: TANK, INCLUDING ATTACHED APPURTENANCES | CP45: NO | DM45: INTERSTATE | DN45: TANK/VESSEL | EW45: CHIME | EY45: ATMOSPHERIC | FD45: 48 | FE45: NO | FF45: 2016 | FH45: 2021 | FK45: 1951 | FL45: 1951 | FM45: CARBON STEEL | FO45: OTHER | FX45: UNDER INVESTIGATION | FY45: NO | GC45: YES | GD45: YES | GE45: YES | GG45: YES | GH45: YES | GK45: YES | GN45: YES | GR45: 0.2 | GS45: MW35 | GT45: YES | GU45: YES | GX45: YES | GY45: YES | HF45: 0 | HG45: 18900 | HH45: 2750000 | HI45: 250000 | HJ45: 75000 | HK45: 0 | HM45: 3093900 | HN45: 0 | HO45: 0 | HP45: 0 | HQ45: 0 | HR45: 14.7 | HZ45: NO | IS45: > 20% SMYS REGULATED TRANSMISSION | IT45: YES | IU45: YES | IV45: YES | IW45: NO | IX45: NO | IY45: YES | IZ45: YES | JA45: YES | JB45: NO | JC45: NO | JD45: NO, THE OPERATOR DID NOT FIND THAT AN INVESTIGATION OF THE CONTROLLER(S) ACTIONS OR CONTROL ROOM ISSUES WAS NECESSARY DUE TO: (PROVIDE AN EXPLANATION FOR WHY THE OPERATOR DID NOT INVESTIGATE) | JE45: A REVIEW OF THE ACCIDENT DETERMINED THAT THERE WERE NO CONTROL ROOM ACTIONS THAT CONTRIBUTED TO THE EVENT. | JR45: NO | JS45: NO | JX45: OTHER ACCIDENT CAUSE | JY45: UNKNOWN | RY45: UNKNOWN | SA45: STILL UNDER INVESTIGATION, CAUSE OF ACCIDENT TO BE DETERMINED* (*SUPPLEMENTAL REPORT REQUIRED) | XL45: TODD NARDOZZI | XM45: DIRECTOR - DOT COMPLIANCE | XN45: todd.nardozzi@energytransfer.com | XO45: 713-989-7126 | XQ45: 45540 | XU45: TODD NARDOZZI | XV45: 713-989-7126 | XW45: DIRECTOR - DOT COMPLIANCE | XX45: todd.nardozzi@energytransfer.com | XY45: ON 8/9/24 AT 07:45, BUBBLING AROUND CHIME OF TANK 327 WAS OBSERVED DURING ROUNDS AT MARCUS HOOK TANK FARM. APPROXIMATELY 1,342 BBLS OF GASOLINE WAS RELEASED INTO CONTAINMENT. REMAINING PRODUCT FROM TANK 327 WAS TRANSFERRED TO AN ADJACENT TANK. FREE PRODUCT WAS RECOVERED FROM TANK DIKE AREA. TANK MANWAYS REMOVED. THE CAUSE OF THE ACCIDENT IS STILL UNDER INVESTIGATION. A SUPPLEMENTAL REPORT WILL BE SUBMITTED ONCE THE INVESTIGATION IS COMPLETED.
A46: 236 | B46: 45532 | C46: 2024 | D46: 20240201 | E46: 40833 | F46: SUPPLEMENTAL FINAL | G46: 32099 | H46: ENERGY TRANSFER COMPANY | I46: 1300 MAIN STREET | J46: HOUSTON | K46: TX | L46: 77002 | M46: 45512.5 | N46: CENTRAL | O46: YES | P46: 35.485621 | Q46: -100.93968 | R46: CRUDE OIL | W46: 50 | Y46: 50 | Z46: NO | AF46: 0 | AG46: NO | AM46: 0 | AN46: LOCAL OPERATING PERSONNEL, INCLUDING CONTRACTORS | AP46: OPERATOR EMPLOYEE | AQ46: 45512.5 | AR46: ONSHORE PUMP/METER STATION EQUIPMENT AND PIPING | AS46: ONSHORE | AT46: NORMAL OPERATION, INCLUDES PAUSES BETWEEN BATCHES AND DURING MAINTENANCE | AU46: YES | AW46: 45512.508 | AX46: 45540.708 | AZ46: YES | BA46: OPERATOR | BB46: 45512.628 | BC46: 45512.573 | BD46: 45512.583 | BE46: 45512.626 | BF46: 1407325 | BG46: 1407520 | BH46: NO | BV46: YES | BW46: 45512.542 | BX46: NO | CA46: 0 | CB46: MERTEN STATION | CC46: 23002 8-INCH MCCLELLAN TO MERTEN | CD46: TX | CE46: 79065 | CF46: PAMPA | CG46: GRAY | CH46: SURVEY STATION NO. | CI46: 0+00 | CJ46: NO | CK46: TOTALLY CONTAINED ON OPERATOR-CONTROLLED PROPERTY | CL46: ABOVEGROUND | CM46: TYPICAL ABOVEGROUND FACILITY PIPING OR APPURTENANCE | CP46: NO | DM46: INTRASTATE | DN46: VALVE | EM46: MAINLINE | EN46: CHECK | EP46: UNKNOWN | FK46: UNKNOWN | FL46: UNKNOWN | FM46: CARBON STEEL | FO46: LEAK | FR46: SEAL OR PACKING | FY46: NO | GC46: YES | GD46: NO | GE46: YES | GH46: YES | GK46: NO | GT46: NO | GU46: NO | HF46: 0 | HG46: 395 | HH46: 25000 | HI46: 2500 | HJ46: 40000 | HK46: 0 | HM46: 67895 | HN46: 0 | HO46: 0 | HP46: 0 | HQ46: 0 | HR46: 55 | HS46: 580 | HT46: FOUR HOUR TEST OR OPERATION ß195.406(A)(5) | HV46: 41275 | HW46: NO | HY46: PRESSURE DID NOT EXCEED MOP | HZ46: NO | IS46: > 20% SMYS REGULATED TRANSMISSION | IT46: YES | IU46: YES | IV46: YES | IW46: NO | IX46: NO | IY46: YES | IZ46: YES | JA46: YES | JB46: NO | JC46: NO | JD46: NO, THE OPERATOR DID NOT FIND THAT AN INVESTIGATION OF THE CONTROLLER(S) ACTIONS OR CONTROL ROOM ISSUES WAS NECESSARY DUE TO: (PROVIDE AN EXPLANATION FOR WHY THE OPERATOR DID NOT INVESTIGATE) | JE46: A REVIEW OF THE ACCIDENT DETERMINED THAT THERE WERE NO CONTROL ROOM ACTIONS THAT CONTRIBUTED TO THE EVENT. | JR46: NO | JS46: NO | JX46: EQUIPMENT FAILURE | JY46: MALFUNCTION OF CONTROL/RELIEF EQUIPMENT | QB46: MALFUNCTION OF CONTROL/RELIEF EQUIPMENT | QH46: YES | RK46: YES | RL46: INTERNAL PIN DRIPPED ALLOWING EXTERNAL HANDLE TO COME OUTSIDE OF THE PACKINGING | XL46: TODD NARDOZZI | XM46: DIRECTOR - DOT COMPLIANCE | XN46: todd.nardozzi@energytransfer.com | XO46: 713-989-7126 | XQ46: 45779 | XU46: TODD NARDOZZI | XV46: 713-989-7126 | XW46: DIRECTOR - DOT COMPLIANCE | XX46: todd.nardozzi@energytransfer.com | XY46: ON 8/8/24 AT APPROXIMATELY 12:00, A COMPANY EMPLOYEE DISCOVERED A CRUDE OIL RELEASE AT MERTEN STATION. THE CONTROL CENTER WAS NOTIFIED AND IMMEDIATELY SHUTDOWN AND BLOCKED OFF THE TRUCKING LACTS INTO THE TANK, THE TANK INJECTION PUMP AND THE MAIN LINE. OPERATIONS ISOLATED THE ONSITE VALVE AND VERIFIED THE LEAK WAS COMING FROM A CHECK VALVE ON THE 23002 8-INCH MCCLELLAN TO MERTEN LINE. APPROXIMATELY 50 BARRELS OF CRUDE OIL WAS RELEASED. RELEASED PRODUCT WAS CLEANED UP AND IMPACTED SOIL REMEDIATED. THE INVESTIGATION DISCOVERED THE INTERNAL PIN OF THE CHECK VALVE DROPPED ALLOWING EXTERNAL HANDLE TO COME OUTSIDE OF THE PACKING AND RELEASE CRUDE OIL. THE STATION IS CURRENTLY BEING BYPASSED WHILE VALVE REPLACEMENT IS PENDING. A SUPPLEMENTAL REPORT WILL BE SUBMITTED ONCE THE REPAIR HAS BEEN MADE AND THE STATION IS RESTARTED. SUPPLEMENTAL & FINAL: THE CHECK VALVE WAS REPLACED WITH A SPRING ASSISTED CHECK VALVE AND THE LINE WAS RETURNED TO SERVICE.
A47: 237 | B47: 45538 | C47: 2024 | D47: 20240210 | E47: 40616 | F47: SUPPLEMENTAL FINAL | G47: 12470 | H47: MID - VALLEY PIPELINE CO | I47: 1300 MAIN STREET | J47: HOUSTON | K47: TX | L47: 77002 | M47: 45512.292 | N47: CENTRAL | O47: YES | P47: 32.876169 | Q47: -91.052988 | R47: CRUDE OIL | W47: 0.4 | Y47: 0.4 | Z47: NO | AF47: 0 | AG47: NO | AM47: 0 | AN47: LOCAL OPERATING PERSONNEL, INCLUDING CONTRACTORS | AP47: OPERATOR EMPLOYEE | AQ47: 45512.302 | AR47: ONSHORE PUMP/METER STATION EQUIPMENT AND PIPING | AS47: ONSHORE | AT47: NORMAL OPERATION, INCLUDES PAUSES BETWEEN BATCHES AND DURING MAINTENANCE | AU47: NO | AV47: LINE WAS ALREADY SHUTDOWN | AZ47: YES | BA47: OPERATOR | BB47: 45512.512 | BC47: 45512.312 | BD47: 45512.312 | BF47: NRC NOTIFICATION NOT REQUIRED | BH47: NO | BV47: YES | BW47: 45512.304 | BX47: NO | CA47: 0 | CB47: MAYERSVILLE STATION | CC47: 16-INCH STRAINER BYPASS LINE | CD47: MS | CE47: 39111 | CF47: MAYERSVILLE | CG47: ISSAQUENA | CH47: MILEPOST | CI47: 227 | CJ47: NO | CK47: TOTALLY CONTAINED ON OPERATOR-CONTROLLED PROPERTY | CL47: ABOVEGROUND | CM47: TYPICAL ABOVEGROUND FACILITY PIPING OR APPURTENANCE | CP47: NO | DM47: INTERSTATE | DN47: PIPE | DO47: PIPE BODY | DP47: NO | DQ47: 16 | DR47: 0.375 | DS47: 42000 | DT47: X52 | DU47: SEAMLESS | DW47: UNKNOWN | DX47: COLD APPLIED TAPE | DZ47: YES | FK47: 1950 | FL47: 1948 | FM47: CARBON STEEL | FO47: LEAK | FR47: PINHOLE | FY47: NO | GC47: YES | GD47: NO | GE47: YES | GH47: YES | GK47: NO | GT47: YES | GU47: NO | HF47: 0 | HG47: 0 | HH47: 11029 | HI47: 5329 | HJ47: 1800 | HK47: 0 | HM47: 18158 | HN47: 0 | HO47: 0 | HP47: 0 | HQ47: 0 | HR47: 200 | HS47: 250 | HT47: COMPONENT DESIGN PRESSURE ß195.406(A)(2) | HV47: 44459 | HW47: NO | HY47: PRESSURE DID NOT EXCEED MOP | HZ47: NO | IS47: > 20% SMYS REGULATED TRANSMISSION | IT47: YES | IU47: YES | IV47: YES | IW47: NO | IX47: NO | IY47: NO | JD47: NO, THE OPERATOR DID NOT FIND THAT AN INVESTIGATION OF THE CONTROLLER(S) ACTIONS OR CONTROL ROOM ISSUES WAS NECESSARY DUE TO: (PROVIDE AN EXPLANATION FOR WHY THE OPERATOR DID NOT INVESTIGATE) | JE47: A REVIEW OF THE ACCIDENT DETERMINED THAT THERE WERE NO CONTROL ROOM ACTIONS THAT CONTRIBUTED TO THE EVENT. | JR47: NO | JS47: NO | JX47: CORROSION FAILURE | JY47: INTERNAL CORROSION | JZ47: INTERNAL CORROSION | LD47: LOCALIZED PITTING | LG47: YES | LH47: YES | LL47: YES | LM47: YES | LP47: YES | LR47: YES | LU47: YES | LV47: NO | LW47: NOT APPLICABLE - NOT MAINLINE PIPE | LX47: NOT APPLICABLE - NOT MAINLINE PIPE | SC47: NO | UO47: NO | UR47: NO | UZ47: NO | XL47: TODD NARDOZZI | XM47: DIRECTOR - DOT COMPLIANCE | XN47: todd.nardozzi@energytransfer.com | XO47: 713-989-7126 | XQ47: 45728 | XU47: TODD NARDOZZI | XV47: 713-989-7126 | XW47: DIRECTOR - DOT COMPLIANCE | XX47: todd.nardozzi@energytransfer.com | XY47: ON 08/08/24 AT APPROXIMATELY 07:15, DURING THE MORNING WALKTHROUGH, A LOCAL OPERATOR EMPLOYEE DISCOVERED A LEAK ON THE 16-INCH STRAINER BYPASS PIPING AT MAYERSVILLE PUMP STATION. THE CONTROL CENTER WAS IMMEDIATELY NOTIFIED AND THE STATION WAS ISOLATED ALTHOUGH AT THE TIME OF DISCOVERY THE PIPELINE WAS DOWN ON NORMAL SCHEDULE. THE LEAK AREA WAS FURTHER ISOLATED AND AN INVESTIGATION DETERMINED THE LEAK WAS COMING FROM A PINHOLE LEAK AT THE 6 OCLOCK POSITION ON THE STRAINER BYPASS PIPING. THE LEAK POINT WAS REPAIRED USING A 16-INCH MECHANICAL CLAMP. APPROXIMATELY 15 GALLONS (0.4 BBLS.) OF CRUDE OIL WAS RELEASED. CLEANUP CONTRACTORS REMOVED PRODUCT AND REMEDIATED IMPACTED SOIL. THE FAILED SECTION HAS BEEN CUT OUT AND REPLACED AND SENT TO A LABORATORY FOR EXAMINATION. SUPPLEMENTAL & FINAL: THE LAB ANALYSIS DETERMINED THE CAUSE OF THE ACCIDENT WAS DUE TO INTERNAL CORROSION. TO PREVENT REOCCURRENCE, CONTINUOUS TREATMENTS UPSTREAM OF THIS STATION HAVE BEEN IMPLEMENTED AND THE VOLUME OF PRODUCT TO FLUSH THE LINE WAS INCREASED.
A48: 248 | B48: 45530 | C48: 2024 | D48: 20240199 | E48: 40934 | F48: SUPPLEMENTAL FINAL | G48: 22442 | H48: WEST TEXAS GULF PIPELINE CO | I48: 1300 MAIN STREET | J48: HOUSTON | K48: TX | L48: 77002 | M48: 45501.625 | N48: CENTRAL | O48: YES | P48: 32.53155 | Q48: -100.8306 | R48: CRUDE OIL | W48: 3.07 | Y48: 3.07 | Z48: NO | AF48: 0 | AG48: NO | AM48: 0 | AN48: LOCAL OPERATING PERSONNEL, INCLUDING CONTRACTORS | AP48: OPERATOR EMPLOYEE | AQ48: 45501.625 | AR48: ONSHORE PUMP/METER STATION EQUIPMENT AND PIPING | AS48: ONSHORE | AT48: IDLE | AZ48: NO | BC48: 45501.729 | BD48: 45501.729 | BF48: NRC NOTIFICATION NOT REQUIRED | BH48: NO | BV48: YES | BW48: 45501.729 | BX48: NO | CA48: 0 | CB48: COLORADO CITY WTG | CC48: BOOSTER PUMP 3111 | CD48: TX | CE48: 79526 | CF48: HERMLEIGH | CG48: SCURRY | CH48: SURVEY STATION NO. | CI48: 0+00 | CJ48: NO | CK48: TOTALLY CONTAINED ON OPERATOR-CONTROLLED PROPERTY | CL48: ABOVEGROUND | CM48: TYPICAL ABOVEGROUND FACILITY PIPING OR APPURTENANCE | CP48: NO | DM48: INTERSTATE | DN48: PUMP | EQ48: CENTRIFUGAL | ES48: INJECTION | FK48: 1951 | FL48: UNKNOWN | FM48: CARBON STEEL | FO48: LEAK | FR48: PINHOLE | FY48: NO | GC48: YES | GD48: NO | GE48: YES | GH48: YES | GK48: NO | GT48: NO | GU48: NO | HF48: 0 | HG48: 0 | HH48: 200 | HI48: 8000 | HJ48: 0 | HK48: 0 | HM48: 8200 | HN48: 0 | HO48: 0 | HP48: 0 | HQ48: 0 | HR48: 75 | HS48: 285 | HT48: COMPONENT DESIGN PRESSURE ß195.406(A)(2) | HV48: 19395 | HW48: NO | HY48: PRESSURE DID NOT EXCEED MOP | HZ48: NO | IS48: > 20% SMYS REGULATED TRANSMISSION | IT48: NO | IY48: NO | JD48: NO, THE OPERATOR DID NOT FIND THAT AN INVESTIGATION OF THE CONTROLLER(S) ACTIONS OR CONTROL ROOM ISSUES WAS NECESSARY DUE TO: (PROVIDE AN EXPLANATION FOR WHY THE OPERATOR DID NOT INVESTIGATE) | JE48: A REVIEW OF THE ACCIDENT DETERMINED THAT THERE WERE NO CONTROL ROOM ACTIONS THAT CONTRIBUTED TO THE EVENT. | JR48: NO | JS48: NO | JX48: CORROSION FAILURE | JY48: INTERNAL CORROSION | JZ48: INTERNAL CORROSION | LD48: LOCALIZED PITTING | LG48: YES | LH48: YES | LL48: YES | LP48: YES | LR48: YES | LU48: NO | LV48: NO | LW48: NOT APPLICABLE - NOT MAINLINE PIPE | LX48: NO | XL48: TODD NARDOZZI | XM48: DIRECTOR - DOT COMPLIANCE | XN48: todd.nardozzi@energytransfer.com | XO48: 713-989-7126 | XQ48: 45800 | XU48: TODD NARDOZZI | XV48: 713-989-7126 | XW48: DIRECTOR - DOT COMPLIANCE | XX48: todd.nardozzi@energytransfer.com | XY48: ON 7/28/24 AT APPROXIMATELY 15:00, A LEAK WAS DISCOVERED ON THE BOOSTER PUMP 3111 DRAIN LINE ON THE 20-INCH COLORADO CITY WTG LINE. THE BOOSTER PUMP WAS OUT OF SERVICE AND ISOLATED WITH GATE VALVES AT THE TIME OF THE LEAK. COLORADO CITY WTG DELIVERIES WERE STOPPED AND THE DRAIN DOWN LINE WAS ISOLATED. TECHNICIANS INSTALLED SKILLETS TO FURTHER ISOLATE DEAD LEG DISCHARGE AND SUCTION PIPING TO BOOSTER PUMP 3111. 3.07 BARRELS OF CRUDE OIL WAS RELEASED. RELEASED PRODUCT WAS CLEANED UP AND IMPACTED SOIL REMEDIATED. AN INVESTIGATION DETERMINED THE CAUSE OF THE LEAK WAS DUE TO INTERNAL CORROSION ON THE DRAIN LINE WELD. THE GATE VALVES UTILIZED FOR ISOLATION MAY HAVE LEAKED BY ALLOWING A SMALL AMOUNT OF PRODUCT TO ACCUMULATE OVER TIME. TO PREVENT REOCCURRENCE, BOOSTER PUMP 3111 HAS BEEN ISOLATED AND DRAINED FROM MAINLINE PIPING, AND THE DEAD LEG REMOVED.
A49: 257 | B49: 45516 | C49: 2024 | D49: 20240188 | E49: 39882 | F49: ORIGINAL FINAL | G49: 32683 | H49: INLAND CORPORATION | I49: 1300 MAIN STREET | J49: HOUSTON | K49: TX | L49: 77002 | M49: 45486.75 | N49: EASTERN | O49: YES | P49: 40.70948 | Q49: -84.13095 | R49: REFINED AND/OR PETROLEUM PRODUCT (NON-HVL) WHICH IS A LIQUID AT AMBIENT CONDITIONS | S49: DIESEL, FUEL OIL, KEROSENE, JET FUEL | W49: 13 | Y49: 13 | Z49: NO | AF49: 0 | AG49: NO | AM49: 0 | AN49: LOCAL OPERATING PERSONNEL, INCLUDING CONTRACTORS | AP49: OPERATOR EMPLOYEE | AQ49: 45486.75 | AR49: ONSHORE PUMP/METER STATION EQUIPMENT AND PIPING | AS49: ONSHORE | AT49: NORMAL OPERATION, INCLUDES PAUSES BETWEEN BATCHES AND DURING MAINTENANCE | AU49: YES | AW49: 45486.812 | AX49: 45486.979 | AZ49: YES | BA49: OPERATOR | BB49: 45486.914 | BC49: 45486.75 | BD49: 45486.854 | BE49: 45486.915 | BF49: 1404694 | BG49: 1404851 | BH49: NO | BV49: YES | BW49: 45486.771 | BX49: NO | CA49: 0 | CB49: LIMA STATION | CC49: 13212 LIME-COLUMBUS NORTH-SL10 10-INCH | CD49: OH | CE49: 45804 | CF49: LIMA | CG49: ALLEN | CH49: SURVEY STATION NO. | CI49: 1+13.5 | CJ49: NO | CK49: TOTALLY CONTAINED ON OPERATOR-CONTROLLED PROPERTY | CL49: UNDERGROUND | CM49: UNDER SOIL | CO49: 36 | CP49: NO | DM49: INTERSTATE | DN49: VALVE | EM49: AUXILIARY OR OTHER VALVE | FK49: UNKNOWN | FL49: UNKNOWN | FM49: CARBON STEEL | FO49: LEAK | FR49: CONNECTION FAILURE | FY49: NO | GC49: YES | GD49: NO | GE49: YES | GH49: YES | GK49: NO | GT49: YES | GU49: YES | GX49: YES | GY49: YES | HF49: 0 | HG49: 1289 | HH49: 25 | HI49: 10000 | HJ49: 65000 | HK49: 0 | HM49: 76314 | HN49: 0 | HO49: 0 | HP49: 0 | HQ49: 0 | HR49: 29 | HS49: 1200 | HT49: COMPONENT DESIGN PRESSURE ß195.406(A)(2) | HV49: 43748 | HW49: NO | HY49: PRESSURE DID NOT EXCEED MOP | HZ49: NO | IS49: > 20% SMYS REGULATED TRANSMISSION | IT49: YES | IU49: YES | IV49: YES | IW49: NO | IX49: NO | IY49: YES | IZ49: YES | JA49: YES | JB49: NO | JC49: NO | JD49: NO, THE OPERATOR DID NOT FIND THAT AN INVESTIGATION OF THE CONTROLLER(S) ACTIONS OR CONTROL ROOM ISSUES WAS NECESSARY DUE TO: (PROVIDE AN EXPLANATION FOR WHY THE OPERATOR DID NOT INVESTIGATE) | JE49: A REVIEW OF THE EVENT DETERMINED THERE WERE NO CONTROL ROOM ACTIONS THAT LED TO OR CONTRIBUTED TO THE FAILURE. | JR49: NO | JS49: NO | JX49: EQUIPMENT FAILURE | JY49: THREADED CONNECTION/COUPLING FAILURE | QB49: THREADED CONNECTION/COUPLING FAILURE | QQ49: VALVE THREADS | RK49: YES | RL49: UNKNOWN UNDERGROUND CONNECTION AND WAS NOT MAINTAINED. | XL49: TODD NARDOZZI | XM49: DIRECTOR - DOT COMPLIANCE | XN49: todd.nardozzi@energytransfer.com | XO49: 713-989-7126 | XQ49: 45516 | XU49: TODD NARDOZZI | XV49: 713-989-7126 | XW49: DIRECTOR - DOT COMPLIANCE | XX49: todd.nardozzi@energytransfer.com | XY49: ON 7/13/2024 AT 18:00, A LEAK OF DIESEL FUEL WAS DISCOVERED AT LIMA STATION ON THE 13212 LIMA-COLUMBUS NORTH-SL10 10-INCH LINE. STATION WAS SHUTDOWN WHILE INVESTIGATION INTO SOURCE OF THE LEAK WAS COMPLETED. AFTER EXCAVATION THE LEAK WAS DETERMINED TO HAVE BEEN COMING FROM AN UNKNOWN 2-INCH THREAD-O-LET AND VALVE ASSOCIATED WITH SMALL DIAMETER PIPING. THE LEAK WAS CONTROLLED AND REPAIRED BY REMOVING THE VALVE AND PLUGGING THIS CONNECTION. APPROXIMATELY 13 BARRELS OF DIESEL WAS RELEASED. RELEASED PRODUCT WAS CLEANED UP AND IMPACTED SOIL REMEDIATED. TO PREVENT REOCCURRENCE, OPERATIONS IDENTIFIED AND VERIFIED THE STATUS OF OTHER 2-INCH VALVES WITHIN LIMA STATION.
